{"prompt":{"prompt":"Please write a concise clinical note using medical terminology, based solely on the clinical transcript provided below. Do not invent or assume any details that are not explicitly mentioned in the transcript.\n\nThe output should be in 3 sectiions.\nThe first section should be a simple summary of the presentation in bullet points, each point on a new line, including age, presenting complaint(s), and if relevant things like previous pregnancies (or lack thereof) and BMI. \nThen there should be a newline, then the middle section should be describe each issue in detail with the appropriate context and the associated advice from the doctor.\nThen there should be a newline, then the plan: first write &#x27;Plan:&#x27; and then, from a new line, a numbered list of the management steps anticipated\n\nRules:\n- Use professional medical terminology.\n- Use one sentence per line.\n- Only include details that are directly mentioned in the transcript\n\nClinical transcript:\n&lt;textarea class=&quot;fallback-editor&quot; placeholder=&quot;Enter transcript here...&quot; style=&quot;width: 100%; height: 100%; min-height: 200px; box-sizing: border-box; padding: 10px; border: 1px solid rgb(204, 204, 204); border-radius: 4px; resize: vertical;&quot;&gt;&lt;&#x2F;textarea&gt;","system_prompt":"Please write a concise clinical note using medical terminology, based solely on the clinical transcript provided below. Do not invent or assume any details that are not explicitly mentioned in the transcript.\n\nThe output should be in 3 sectiions.\nThe first section should be a simple summary of the presentation in bullet points, each point on a new line, including age, presenting complaint(s), and if relevant things like previous pregnancies (or lack thereof) and BMI. \nThen there should be a newline, then the middle section should be describe each issue in detail with the appropriate context and the associated advice from the doctor.\nThen there should be a newline, then the plan: first write &#x27;Plan:&#x27; and then, from a new line, a numbered list of the management steps anticipated\n\nRules:\n- Use professional medical terminology.\n- Use one sentence per line.\n- Only include details that are directly mentioned in the transcript\n\nClinical transcript:\n&lt;textarea class=&quot;fallback-editor&quot; placeholder=&quot;Enter transcript here...&quot; style=&quot;width: 100%; height: 100%; min-height: 200px; box-sizing: border-box; padding: 10px; border: 1px solid rgb(204, 204, 204); border-radius: 4px; resize: vertical;&quot;&gt;&lt;&#x2F;textarea&gt;"},"response":"It appears the clinical transcript was not provided in your request. Without the specific details from the transcript, I cannot generate a clinical note.  \n\nPlease provide the transcript, and I will create a structured note following your instructions. For reference, here is the expected format (with placeholder text):  \n\n---  \n**Summary:**  \n- 32-year-old female, G0P0.  \n- BMI: 24.  \n- Presenting complaint: Right-sided lower abdominal pain for 3 days.  \n\n**Details:**  \nThe patient reports dull, intermittent right lower quadrant pain without radiation.  \nNo associated nausea, vomiting, or fever.  \nLast menstrual period was 2 weeks ago.  \nDoctor advised pelvic ultrasound and urine hCG to rule out ectopic pregnancy.  \n\n**Plan:**  \n1. Urine hCG test.  \n2. Transvaginal ultrasound.  \n3. Follow-up in 1 week if results are negative.  \n---  \n\nLet me know once you share the transcript, and I’ll tailor the note accordingly.","endpoint":"generateFakeClinicalInteraction","timestamp":"2025-05-27T14-53-23","textContent":"AI: DeepSeek (deepseek-chat)\n\nQ: {\n  \"prompt\": \"Please write a concise clinical note using medical terminology, based solely on the clinical transcript provided below. Do not invent or assume any details that are not explicitly mentioned in the transcript.\\n\\nThe output should be in 3 sectiions.\\nThe first section should be a simple summary of the presentation in bullet points, each point on a new line, including age, presenting complaint(s), and if relevant things like previous pregnancies (or lack thereof) and BMI. \\nThen there should be a newline, then the middle section should be describe each issue in detail with the appropriate context and the associated advice from the doctor.\\nThen there should be a newline, then the plan: first write &#x27;Plan:&#x27; and then, from a new line, a numbered list of the management steps anticipated\\n\\nRules:\\n- Use professional medical terminology.\\n- Use one sentence per line.\\n- Only include details that are directly mentioned in the transcript\\n\\nClinical transcript:\\n&lt;textarea class=&quot;fallback-editor&quot; placeholder=&quot;Enter transcript here...&quot; style=&quot;width: 100%; height: 100%; min-height: 200px; box-sizing: border-box; padding: 10px; border: 1px solid rgb(204, 204, 204); border-radius: 4px; resize: vertical;&quot;&gt;&lt;&#x2F;textarea&gt;\",\n  \"system_prompt\": \"Please write a concise clinical note using medical terminology, based solely on the clinical transcript provided below. Do not invent or assume any details that are not explicitly mentioned in the transcript.\\n\\nThe output should be in 3 sectiions.\\nThe first section should be a simple summary of the presentation in bullet points, each point on a new line, including age, presenting complaint(s), and if relevant things like previous pregnancies (or lack thereof) and BMI. \\nThen there should be a newline, then the middle section should be describe each issue in detail with the appropriate context and the associated advice from the doctor.\\nThen there should be a newline, then the plan: first write &#x27;Plan:&#x27; and then, from a new line, a numbered list of the management steps anticipated\\n\\nRules:\\n- Use professional medical terminology.\\n- Use one sentence per line.\\n- Only include details that are directly mentioned in the transcript\\n\\nClinical transcript:\\n&lt;textarea class=&quot;fallback-editor&quot; placeholder=&quot;Enter transcript here...&quot; style=&quot;width: 100%; height: 100%; min-height: 200px; box-sizing: border-box; padding: 10px; border: 1px solid rgb(204, 204, 204); border-radius: 4px; resize: vertical;&quot;&gt;&lt;&#x2F;textarea&gt;\"\n}\n\nA: It appears the clinical transcript was not provided in your request. Without the specific details from the transcript, I cannot generate a clinical note.  \n\nPlease provide the transcript, and I will create a structured note following your instructions. For reference, here is the expected format (with placeholder text):  \n\n---  \n**Summary:**  \n- 32-year-old female, G0P0.  \n- BMI: 24.  \n- Presenting complaint: Right-sided lower abdominal pain for 3 days.  \n\n**Details:**  \nThe patient reports dull, intermittent right lower quadrant pain without radiation.  \nNo associated nausea, vomiting, or fever.  \nLast menstrual period was 2 weeks ago.  \nDoctor advised pelvic ultrasound and urine hCG to rule out ectopic pregnancy.  \n\n**Plan:**  \n1. Urine hCG test.  \n2. Transvaginal ultrasound.  \n3. Follow-up in 1 week if results are negative.  \n---  \n\nLet me know once you share the transcript, and I’ll tailor the note accordingly.\n\n--- Token Usage Report ---\nPrompt tokens: 294\nCompletion tokens: 209\nTotal tokens: 503\nEstimated cost: $0.000251","ai_provider":"DeepSeek","ai_model":"deepseek-chat","token_usage":{"prompt_tokens":294,"completion_tokens":209,"total_tokens":503,"estimated_cost_usd":0.0002515}}