{"prompt":{"prompt":"Create a fictional dictation of a clinical interaction between a healthcare professional and a patient. \nThis dictation is for testing purposes only and should include various topics that might be discussed in a healthcare setting. \nPlease ensure the material is entirely fictional and does not provide any real medical advice or information. \nPlease ensure variables such as age, weight and history are varied.\nThe clinician should ensure the history and examination findings are incomplete, leaving out some pertinent questions.\nIn response to their history and examination findings, the clinician should  provide management advice and guidance.\nThe clinical scenario should be the following: \n\nMake the age 37, the BMI 35.4 and the number of prior pregnancies 5\n\nBase the clinical scenario on the following gynecology issue: Abnormal uterine bleeding","system_prompt":"Create a fictional dictation of a clinical interaction between a healthcare professional and a patient. \nThis dictation is for testing purposes only and should include various topics that might be discussed in a healthcare setting. \nPlease ensure the material is entirely fictional and does not provide any real medical advice or information. \nPlease ensure variables such as age, weight and history are varied.\nThe clinician should ensure the history and examination findings are incomplete, leaving out some pertinent questions.\nIn response to their history and examination findings, the clinician should  provide management advice and guidance.\nThe clinical scenario should be the following: \n\nMake the age 37, the BMI 35.4 and the number of prior pregnancies 5\n\nBase the clinical scenario on the following gynecology issue: Abnormal uterine bleeding"},"response":"**Dictation: Clinical Interaction – Abnormal Uterine Bleeding**  \n\n**Patient Details:**  \n- Name: Jane Doe (fictional)  \n- Age: 37  \n- BMI: 35.4  \n- Gravida: 5, Para: 4, Abortions: 1 (spontaneous)  \n- Last Menstrual Period (LMP): 2 weeks ago (reports prolonged bleeding)  \n\n**History of Presenting Complaint:**  \nMs. Doe presents with a 6-month history of abnormal uterine bleeding (AUB), characterized by heavy menstrual flow (soaking through pads every 2 hours) and intermittent spotting between cycles. She reports occasional cramping but denies fever, dizziness, or syncope. She has not recently traveled or had any known bleeding disorders in the family.  \n\n**Past Medical History:**  \n- Hypertension (on lisinopril)  \n- Type 2 diabetes (poorly controlled, last HbA1c 8.2%)  \n- No prior surgeries  \n- No known allergies  \n\n**Medications:**  \n- Lisinopril 10mg daily  \n- Metformin 1000mg BID  \n- Occasional ibuprofen for pain (not regularly)  \n\n**Social History:**  \n- Smokes ½ pack per day  \n- Rare alcohol use  \n- Works as a teacher, reports high stress  \n\n**Examination Findings:**  \n- General: Obese, no pallor or signs of acute distress  \n- Abdomen: Soft, non-tender, no palpable masses  \n- Pelvic exam (limited): Cervix appears normal, no active bleeding at time of exam  \n- No speculum or bimanual exam performed today due to patient discomfort  \n\n**Incomplete Aspects of History/Exam:**  \n- No detailed menstrual cycle history (cycle length, regularity prior to changes)  \n- No assessment for signs of anemia (e.g., fatigue, pallor, tachycardia)  \n- No transvaginal ultrasound or endometrial biopsy performed  \n- Sexual history and contraception use not explored  \n- Family history of gynecologic cancers not obtained  \n\n**Impression:**  \n37-year-old female with obesity, hypertension, and poorly controlled diabetes presenting with AUB (likely secondary to anovulation or structural etiology such as fibroids/polyps, though malignancy not ruled out).  \n\n**Management Plan:**  \n1. **Initial Workup:**  \n   - CBC to assess for anemia  \n   - TSH to evaluate thyroid dysfunction  \n   - Pelvic ultrasound (transvaginal preferred if tolerated) to assess for structural abnormalities  \n   - Consider endometrial biopsy if persistent bleeding or risk factors for hyperplasia  \n\n2. **Symptomatic Management:**  \n   - Trial of progestin therapy (e.g., norethindrone) to regulate bleeding  \n   - Iron supplementation if anemia present  \n\n3. **Lifestyle & Comorbidity Optimization:**  \n   - Strongly encourage smoking cessation  \n   - Referral to diabetes educator for glycemic control  \n   - Weight loss counseling given BMI 35.4  \n\n4. **Follow-Up:**  \n   - Return in 4 weeks for reassessment and review of imaging/labs  \n   - Urgent follow-up if bleeding worsens (e.g., syncope, severe anemia)  \n\n**Note:** This dictation is for testing purposes only. No real medical advice is implied. Further evaluation required for definitive diagnosis.  \n\n**Dictated by:** Dr. Smith (fictional)  \n**Date:** [Fictional date]","endpoint":"generateFakeClinicalInteraction","timestamp":"2025-05-27T14-16-14","textContent":"AI: DeepSeek (deepseek-chat)\n\nQ: {\n  \"prompt\": \"Create a fictional dictation of a clinical interaction between a healthcare professional and a patient. \\nThis dictation is for testing purposes only and should include various topics that might be discussed in a healthcare setting. \\nPlease ensure the material is entirely fictional and does not provide any real medical advice or information. \\nPlease ensure variables such as age, weight and history are varied.\\nThe clinician should ensure the history and examination findings are incomplete, leaving out some pertinent questions.\\nIn response to their history and examination findings, the clinician should  provide management advice and guidance.\\nThe clinical scenario should be the following: \\n\\nMake the age 37, the BMI 35.4 and the number of prior pregnancies 5\\n\\nBase the clinical scenario on the following gynecology issue: Abnormal uterine bleeding\",\n  \"system_prompt\": \"Create a fictional dictation of a clinical interaction between a healthcare professional and a patient. \\nThis dictation is for testing purposes only and should include various topics that might be discussed in a healthcare setting. \\nPlease ensure the material is entirely fictional and does not provide any real medical advice or information. \\nPlease ensure variables such as age, weight and history are varied.\\nThe clinician should ensure the history and examination findings are incomplete, leaving out some pertinent questions.\\nIn response to their history and examination findings, the clinician should  provide management advice and guidance.\\nThe clinical scenario should be the following: \\n\\nMake the age 37, the BMI 35.4 and the number of prior pregnancies 5\\n\\nBase the clinical scenario on the following gynecology issue: Abnormal uterine bleeding\"\n}\n\nA: **Dictation: Clinical Interaction – Abnormal Uterine Bleeding**  \n\n**Patient Details:**  \n- Name: Jane Doe (fictional)  \n- Age: 37  \n- BMI: 35.4  \n- Gravida: 5, Para: 4, Abortions: 1 (spontaneous)  \n- Last Menstrual Period (LMP): 2 weeks ago (reports prolonged bleeding)  \n\n**History of Presenting Complaint:**  \nMs. Doe presents with a 6-month history of abnormal uterine bleeding (AUB), characterized by heavy menstrual flow (soaking through pads every 2 hours) and intermittent spotting between cycles. She reports occasional cramping but denies fever, dizziness, or syncope. She has not recently traveled or had any known bleeding disorders in the family.  \n\n**Past Medical History:**  \n- Hypertension (on lisinopril)  \n- Type 2 diabetes (poorly controlled, last HbA1c 8.2%)  \n- No prior surgeries  \n- No known allergies  \n\n**Medications:**  \n- Lisinopril 10mg daily  \n- Metformin 1000mg BID  \n- Occasional ibuprofen for pain (not regularly)  \n\n**Social History:**  \n- Smokes ½ pack per day  \n- Rare alcohol use  \n- Works as a teacher, reports high stress  \n\n**Examination Findings:**  \n- General: Obese, no pallor or signs of acute distress  \n- Abdomen: Soft, non-tender, no palpable masses  \n- Pelvic exam (limited): Cervix appears normal, no active bleeding at time of exam  \n- No speculum or bimanual exam performed today due to patient discomfort  \n\n**Incomplete Aspects of History/Exam:**  \n- No detailed menstrual cycle history (cycle length, regularity prior to changes)  \n- No assessment for signs of anemia (e.g., fatigue, pallor, tachycardia)  \n- No transvaginal ultrasound or endometrial biopsy performed  \n- Sexual history and contraception use not explored  \n- Family history of gynecologic cancers not obtained  \n\n**Impression:**  \n37-year-old female with obesity, hypertension, and poorly controlled diabetes presenting with AUB (likely secondary to anovulation or structural etiology such as fibroids/polyps, though malignancy not ruled out).  \n\n**Management Plan:**  \n1. **Initial Workup:**  \n   - CBC to assess for anemia  \n   - TSH to evaluate thyroid dysfunction  \n   - Pelvic ultrasound (transvaginal preferred if tolerated) to assess for structural abnormalities  \n   - Consider endometrial biopsy if persistent bleeding or risk factors for hyperplasia  \n\n2. **Symptomatic Management:**  \n   - Trial of progestin therapy (e.g., norethindrone) to regulate bleeding  \n   - Iron supplementation if anemia present  \n\n3. **Lifestyle & Comorbidity Optimization:**  \n   - Strongly encourage smoking cessation  \n   - Referral to diabetes educator for glycemic control  \n   - Weight loss counseling given BMI 35.4  \n\n4. **Follow-Up:**  \n   - Return in 4 weeks for reassessment and review of imaging/labs  \n   - Urgent follow-up if bleeding worsens (e.g., syncope, severe anemia)  \n\n**Note:** This dictation is for testing purposes only. No real medical advice is implied. Further evaluation required for definitive diagnosis.  \n\n**Dictated by:** Dr. Smith (fictional)  \n**Date:** [Fictional date]\n\n--- Token Usage Report ---\nPrompt tokens: 158\nCompletion tokens: 708\nTotal tokens: 866\nEstimated cost: $0.000433","ai_provider":"DeepSeek","ai_model":"deepseek-chat","token_usage":{"prompt_tokens":158,"completion_tokens":708,"total_tokens":866,"estimated_cost_usd":0.000433}}