{"prompt":{"prompt":"Please write a concise clinical note using medical terminology, based solely on the clinical transcript provided below. Do not invent or assume any details that are not explicitly mentioned in the transcript.\n\nThe output should be in 3 sectiions.\nThe first section should be a simple summary of the presentation in bullet points, each point on a new line, including age, presenting complaint(s), and if relevant things like previous pregnancies (or lack thereof) and BMI. \nThen there should be a newline, then the middle section should be describe each issue in detail with the appropriate context and the associated advice from the doctor.\nThen there should be a newline, then the plan: first write &#x27;Plan:&#x27; and then, from a new line, a numbered list of the management steps anticipated\n\nRules:\n- Use professional medical terminology.\n- Use one sentence per line.\n- Only include details that are directly mentioned in the transcript\n\nClinical transcript:\n**Dictation: Clinical Interaction – Abnormal Uterine Bleeding**  \n*For testing purposes only. Fictional scenario. Not for clinical use.*  \n\n**Patient Details:**  \n- Name: Jane Doe (fictional)  \n- Age: 42  \n- Gender: Female  \n- Weight: 78 kg  \n- Occupation: Office administrator  \n- Referral: Self-referred for evaluation of abnormal uterine bleeding  \n\n**History of Presenting Complaint:**  \nMs. Doe reports a 4-month history of irregular, heavy menstrual bleeding. She describes episodes of bleeding lasting up to 10 days, with flooding requiring frequent pad changes (every 1–2 hours). She denies intermenstrual bleeding but reports occasional post-coital spotting. She has associated fatigue but denies dizziness, syncope, or significant pain. No history of clotting disorders or bleeding diatheses.  \n\n*Incomplete aspects:*  \n- No detailed menstrual history (e.g., age of menarche, prior regularity).  \n- Contraceptive history not explored (e.g., current or past hormonal use).  \n- Family history of gynecological conditions (e.g., fibroids, endometrial cancer) not elicited.  \n\n**Past Medical History:**  \n- Hypothyroidism (on levothyroxine 75 mcg daily).  \n- No known diabetes or hypertension.  \n- No prior surgeries.  \n\n**Medications:**  \n- Levothyroxine 75 mcg daily.  \n- Occasional ibuprofen for headaches.  \n\n**Examination Findings:**  \n- General: Pale conjunctiva (possible anemia), BMI 28.  \n- Abdominal: Soft, non-tender, no palpable masses.  \n- Pelvic: *Deferred at this visit due to patient preference.*  \n\n*Incomplete aspects:*  \n- No speculum or bimanual exam performed.  \n- Thyroid exam not documented despite history of hypothyroidism.  \n\n**Assessment:**  \n1. **Abnormal uterine bleeding (AUB)** – Likely secondary to ovulatory dysfunction (given age, weight, and thyroid history), though structural causes (e.g., fibroids, polyps) cannot be excluded.  \n2. **Possible iron-deficiency anemia** – Given fatigue and pallor.  \n\n**Management Plan:**  \n1. **Investigations:**  \n   - Full blood count (FBC), ferritin, TSH (given hypothyroidism).  \n   - Pelvic ultrasound to assess for structural pathology.  \n   - *Endometrial biopsy not yet arranged – to consider if ultrasound abnormal or if bleeding persists.*  \n2. **Symptomatic Management:**  \n   - Start tranexamic acid 1 g TDS during heavy bleeding days.  \n   - Consider trial of cyclical progestogens (e.g., norethisterone) if bleeding pattern suggests anovulation.  \n3. **Follow-up:**  \n   - Review in 4 weeks with investigation results.  \n   - Counsel about red flags (e.g., worsening anemia, persistent bleeding).  \n   - *Hormonal contraception options not discussed – to address at next visit.*  \n\n**Clinician’s Note:**  \nIncomplete history and examination limit full assessment. Urgent investigations prioritized. Patient advised to return sooner if symptoms worsen.  \n\n---  \n*End of dictation. This is a fictional example for testing purposes only. No real patient data or medical advice is implied.*","system_prompt":"Please write a concise clinical note using medical terminology, based solely on the clinical transcript provided below. Do not invent or assume any details that are not explicitly mentioned in the transcript.\n\nThe output should be in 3 sectiions.\nThe first section should be a simple summary of the presentation in bullet points, each point on a new line, including age, presenting complaint(s), and if relevant things like previous pregnancies (or lack thereof) and BMI. \nThen there should be a newline, then the middle section should be describe each issue in detail with the appropriate context and the associated advice from the doctor.\nThen there should be a newline, then the plan: first write &#x27;Plan:&#x27; and then, from a new line, a numbered list of the management steps anticipated\n\nRules:\n- Use professional medical terminology.\n- Use one sentence per line.\n- Only include details that are directly mentioned in the transcript\n\nClinical transcript:\n**Dictation: Clinical Interaction – Abnormal Uterine Bleeding**  \n*For testing purposes only. Fictional scenario. Not for clinical use.*  \n\n**Patient Details:**  \n- Name: Jane Doe (fictional)  \n- Age: 42  \n- Gender: Female  \n- Weight: 78 kg  \n- Occupation: Office administrator  \n- Referral: Self-referred for evaluation of abnormal uterine bleeding  \n\n**History of Presenting Complaint:**  \nMs. Doe reports a 4-month history of irregular, heavy menstrual bleeding. She describes episodes of bleeding lasting up to 10 days, with flooding requiring frequent pad changes (every 1–2 hours). She denies intermenstrual bleeding but reports occasional post-coital spotting. She has associated fatigue but denies dizziness, syncope, or significant pain. No history of clotting disorders or bleeding diatheses.  \n\n*Incomplete aspects:*  \n- No detailed menstrual history (e.g., age of menarche, prior regularity).  \n- Contraceptive history not explored (e.g., current or past hormonal use).  \n- Family history of gynecological conditions (e.g., fibroids, endometrial cancer) not elicited.  \n\n**Past Medical History:**  \n- Hypothyroidism (on levothyroxine 75 mcg daily).  \n- No known diabetes or hypertension.  \n- No prior surgeries.  \n\n**Medications:**  \n- Levothyroxine 75 mcg daily.  \n- Occasional ibuprofen for headaches.  \n\n**Examination Findings:**  \n- General: Pale conjunctiva (possible anemia), BMI 28.  \n- Abdominal: Soft, non-tender, no palpable masses.  \n- Pelvic: *Deferred at this visit due to patient preference.*  \n\n*Incomplete aspects:*  \n- No speculum or bimanual exam performed.  \n- Thyroid exam not documented despite history of hypothyroidism.  \n\n**Assessment:**  \n1. **Abnormal uterine bleeding (AUB)** – Likely secondary to ovulatory dysfunction (given age, weight, and thyroid history), though structural causes (e.g., fibroids, polyps) cannot be excluded.  \n2. **Possible iron-deficiency anemia** – Given fatigue and pallor.  \n\n**Management Plan:**  \n1. **Investigations:**  \n   - Full blood count (FBC), ferritin, TSH (given hypothyroidism).  \n   - Pelvic ultrasound to assess for structural pathology.  \n   - *Endometrial biopsy not yet arranged – to consider if ultrasound abnormal or if bleeding persists.*  \n2. **Symptomatic Management:**  \n   - Start tranexamic acid 1 g TDS during heavy bleeding days.  \n   - Consider trial of cyclical progestogens (e.g., norethisterone) if bleeding pattern suggests anovulation.  \n3. **Follow-up:**  \n   - Review in 4 weeks with investigation results.  \n   - Counsel about red flags (e.g., worsening anemia, persistent bleeding).  \n   - *Hormonal contraception options not discussed – to address at next visit.*  \n\n**Clinician’s Note:**  \nIncomplete history and examination limit full assessment. Urgent investigations prioritized. Patient advised to return sooner if symptoms worsen.  \n\n---  \n*End of dictation. This is a fictional example for testing purposes only. No real patient data or medical advice is implied.*"},"response":"### Summary:  \n- Age: 42  \n- BMI: 28  \n- Presenting complaint: 4-month history of irregular, heavy menstrual bleeding with flooding (pad changes every 1–2 hours), occasional post-coital spotting, and associated fatigue.  \n- No history of clotting disorders or bleeding diatheses.  \n- Past medical history: Hypothyroidism (on levothyroxine 75 mcg daily).  \n- No prior pregnancies mentioned.  \n- Examination findings: Pale conjunctiva (possible anemia), soft/non-tender abdomen, no palpable masses. Pelvic exam deferred.  \n\n### Details:  \n- Abnormal uterine bleeding (AUB) is likely secondary to ovulatory dysfunction, given age, weight, and thyroid history, though structural causes (e.g., fibroids, polyps) cannot be excluded.  \n- Possible iron-deficiency anemia is suspected due to fatigue and pallor.  \n- Investigations advised include FBC, ferritin, TSH, and pelvic ultrasound to assess for structural pathology.  \n- Endometrial biopsy may be considered if ultrasound is abnormal or bleeding persists.  \n- Symptomatic management includes tranexamic acid 1 g TDS during heavy bleeding days and a potential trial of cyclical progestogens (e.g., norethisterone) if anovulation is confirmed.  \n\n### Plan:  \n1. Investigations:  \n   - FBC, ferritin, TSH.  \n   - Pelvic ultrasound.  \n   - Consider endometrial biopsy if indicated.  \n2. Symptomatic management:  \n   - Tranexamic acid 1 g TDS during heavy bleeding.  \n   - Trial of cyclical progestogens if anovulation is suspected.  \n3. Follow-up:  \n   - Review in 4 weeks with investigation results.  \n   - Counsel on red flags (worsening anemia, persistent bleeding).  \n   - Address hormonal contraception options at next visit.","endpoint":"generateFakeClinicalInteraction","timestamp":"2025-05-26T15-40-00","textContent":"AI: DeepSeek (deepseek-chat)\n\nQ: {\n  \"prompt\": \"Please write a concise clinical note using medical terminology, based solely on the clinical transcript provided below. Do not invent or assume any details that are not explicitly mentioned in the transcript.\\n\\nThe output should be in 3 sectiions.\\nThe first section should be a simple summary of the presentation in bullet points, each point on a new line, including age, presenting complaint(s), and if relevant things like previous pregnancies (or lack thereof) and BMI. \\nThen there should be a newline, then the middle section should be describe each issue in detail with the appropriate context and the associated advice from the doctor.\\nThen there should be a newline, then the plan: first write &#x27;Plan:&#x27; and then, from a new line, a numbered list of the management steps anticipated\\n\\nRules:\\n- Use professional medical terminology.\\n- Use one sentence per line.\\n- Only include details that are directly mentioned in the transcript\\n\\nClinical transcript:\\n**Dictation: Clinical Interaction – Abnormal Uterine Bleeding**  \\n*For testing purposes only. Fictional scenario. Not for clinical use.*  \\n\\n**Patient Details:**  \\n- Name: Jane Doe (fictional)  \\n- Age: 42  \\n- Gender: Female  \\n- Weight: 78 kg  \\n- Occupation: Office administrator  \\n- Referral: Self-referred for evaluation of abnormal uterine bleeding  \\n\\n**History of Presenting Complaint:**  \\nMs. Doe reports a 4-month history of irregular, heavy menstrual bleeding. She describes episodes of bleeding lasting up to 10 days, with flooding requiring frequent pad changes (every 1–2 hours). She denies intermenstrual bleeding but reports occasional post-coital spotting. She has associated fatigue but denies dizziness, syncope, or significant pain. No history of clotting disorders or bleeding diatheses.  \\n\\n*Incomplete aspects:*  \\n- No detailed menstrual history (e.g., age of menarche, prior regularity).  \\n- Contraceptive history not explored (e.g., current or past hormonal use).  \\n- Family history of gynecological conditions (e.g., fibroids, endometrial cancer) not elicited.  \\n\\n**Past Medical History:**  \\n- Hypothyroidism (on levothyroxine 75 mcg daily).  \\n- No known diabetes or hypertension.  \\n- No prior surgeries.  \\n\\n**Medications:**  \\n- Levothyroxine 75 mcg daily.  \\n- Occasional ibuprofen for headaches.  \\n\\n**Examination Findings:**  \\n- General: Pale conjunctiva (possible anemia), BMI 28.  \\n- Abdominal: Soft, non-tender, no palpable masses.  \\n- Pelvic: *Deferred at this visit due to patient preference.*  \\n\\n*Incomplete aspects:*  \\n- No speculum or bimanual exam performed.  \\n- Thyroid exam not documented despite history of hypothyroidism.  \\n\\n**Assessment:**  \\n1. **Abnormal uterine bleeding (AUB)** – Likely secondary to ovulatory dysfunction (given age, weight, and thyroid history), though structural causes (e.g., fibroids, polyps) cannot be excluded.  \\n2. **Possible iron-deficiency anemia** – Given fatigue and pallor.  \\n\\n**Management Plan:**  \\n1. **Investigations:**  \\n   - Full blood count (FBC), ferritin, TSH (given hypothyroidism).  \\n   - Pelvic ultrasound to assess for structural pathology.  \\n   - *Endometrial biopsy not yet arranged – to consider if ultrasound abnormal or if bleeding persists.*  \\n2. **Symptomatic Management:**  \\n   - Start tranexamic acid 1 g TDS during heavy bleeding days.  \\n   - Consider trial of cyclical progestogens (e.g., norethisterone) if bleeding pattern suggests anovulation.  \\n3. **Follow-up:**  \\n   - Review in 4 weeks with investigation results.  \\n   - Counsel about red flags (e.g., worsening anemia, persistent bleeding).  \\n   - *Hormonal contraception options not discussed – to address at next visit.*  \\n\\n**Clinician’s Note:**  \\nIncomplete history and examination limit full assessment. Urgent investigations prioritized. Patient advised to return sooner if symptoms worsen.  \\n\\n---  \\n*End of dictation. This is a fictional example for testing purposes only. No real patient data or medical advice is implied.*\",\n  \"system_prompt\": \"Please write a concise clinical note using medical terminology, based solely on the clinical transcript provided below. Do not invent or assume any details that are not explicitly mentioned in the transcript.\\n\\nThe output should be in 3 sectiions.\\nThe first section should be a simple summary of the presentation in bullet points, each point on a new line, including age, presenting complaint(s), and if relevant things like previous pregnancies (or lack thereof) and BMI. \\nThen there should be a newline, then the middle section should be describe each issue in detail with the appropriate context and the associated advice from the doctor.\\nThen there should be a newline, then the plan: first write &#x27;Plan:&#x27; and then, from a new line, a numbered list of the management steps anticipated\\n\\nRules:\\n- Use professional medical terminology.\\n- Use one sentence per line.\\n- Only include details that are directly mentioned in the transcript\\n\\nClinical transcript:\\n**Dictation: Clinical Interaction – Abnormal Uterine Bleeding**  \\n*For testing purposes only. Fictional scenario. Not for clinical use.*  \\n\\n**Patient Details:**  \\n- Name: Jane Doe (fictional)  \\n- Age: 42  \\n- Gender: Female  \\n- Weight: 78 kg  \\n- Occupation: Office administrator  \\n- Referral: Self-referred for evaluation of abnormal uterine bleeding  \\n\\n**History of Presenting Complaint:**  \\nMs. Doe reports a 4-month history of irregular, heavy menstrual bleeding. She describes episodes of bleeding lasting up to 10 days, with flooding requiring frequent pad changes (every 1–2 hours). She denies intermenstrual bleeding but reports occasional post-coital spotting. She has associated fatigue but denies dizziness, syncope, or significant pain. No history of clotting disorders or bleeding diatheses.  \\n\\n*Incomplete aspects:*  \\n- No detailed menstrual history (e.g., age of menarche, prior regularity).  \\n- Contraceptive history not explored (e.g., current or past hormonal use).  \\n- Family history of gynecological conditions (e.g., fibroids, endometrial cancer) not elicited.  \\n\\n**Past Medical History:**  \\n- Hypothyroidism (on levothyroxine 75 mcg daily).  \\n- No known diabetes or hypertension.  \\n- No prior surgeries.  \\n\\n**Medications:**  \\n- Levothyroxine 75 mcg daily.  \\n- Occasional ibuprofen for headaches.  \\n\\n**Examination Findings:**  \\n- General: Pale conjunctiva (possible anemia), BMI 28.  \\n- Abdominal: Soft, non-tender, no palpable masses.  \\n- Pelvic: *Deferred at this visit due to patient preference.*  \\n\\n*Incomplete aspects:*  \\n- No speculum or bimanual exam performed.  \\n- Thyroid exam not documented despite history of hypothyroidism.  \\n\\n**Assessment:**  \\n1. **Abnormal uterine bleeding (AUB)** – Likely secondary to ovulatory dysfunction (given age, weight, and thyroid history), though structural causes (e.g., fibroids, polyps) cannot be excluded.  \\n2. **Possible iron-deficiency anemia** – Given fatigue and pallor.  \\n\\n**Management Plan:**  \\n1. **Investigations:**  \\n   - Full blood count (FBC), ferritin, TSH (given hypothyroidism).  \\n   - Pelvic ultrasound to assess for structural pathology.  \\n   - *Endometrial biopsy not yet arranged – to consider if ultrasound abnormal or if bleeding persists.*  \\n2. **Symptomatic Management:**  \\n   - Start tranexamic acid 1 g TDS during heavy bleeding days.  \\n   - Consider trial of cyclical progestogens (e.g., norethisterone) if bleeding pattern suggests anovulation.  \\n3. **Follow-up:**  \\n   - Review in 4 weeks with investigation results.  \\n   - Counsel about red flags (e.g., worsening anemia, persistent bleeding).  \\n   - *Hormonal contraception options not discussed – to address at next visit.*  \\n\\n**Clinician’s Note:**  \\nIncomplete history and examination limit full assessment. Urgent investigations prioritized. Patient advised to return sooner if symptoms worsen.  \\n\\n---  \\n*End of dictation. This is a fictional example for testing purposes only. No real patient data or medical advice is implied.*\"\n}\n\nA: ### Summary:  \n- Age: 42  \n- BMI: 28  \n- Presenting complaint: 4-month history of irregular, heavy menstrual bleeding with flooding (pad changes every 1–2 hours), occasional post-coital spotting, and associated fatigue.  \n- No history of clotting disorders or bleeding diatheses.  \n- Past medical history: Hypothyroidism (on levothyroxine 75 mcg daily).  \n- No prior pregnancies mentioned.  \n- Examination findings: Pale conjunctiva (possible anemia), soft/non-tender abdomen, no palpable masses. Pelvic exam deferred.  \n\n### Details:  \n- Abnormal uterine bleeding (AUB) is likely secondary to ovulatory dysfunction, given age, weight, and thyroid history, though structural causes (e.g., fibroids, polyps) cannot be excluded.  \n- Possible iron-deficiency anemia is suspected due to fatigue and pallor.  \n- Investigations advised include FBC, ferritin, TSH, and pelvic ultrasound to assess for structural pathology.  \n- Endometrial biopsy may be considered if ultrasound is abnormal or bleeding persists.  \n- Symptomatic management includes tranexamic acid 1 g TDS during heavy bleeding days and a potential trial of cyclical progestogens (e.g., norethisterone) if anovulation is confirmed.  \n\n### Plan:  \n1. Investigations:  \n   - FBC, ferritin, TSH.  \n   - Pelvic ultrasound.  \n   - Consider endometrial biopsy if indicated.  \n2. Symptomatic management:  \n   - Tranexamic acid 1 g TDS during heavy bleeding.  \n   - Trial of cyclical progestogens if anovulation is suspected.  \n3. Follow-up:  \n   - Review in 4 weeks with investigation results.  \n   - Counsel on red flags (worsening anemia, persistent bleeding).  \n   - Address hormonal contraception options at next visit.\n\n--- Token Usage Report ---\nPrompt tokens: 879\nCompletion tokens: 387\nTotal tokens: 1266\nEstimated cost: $0.000633","ai_provider":"DeepSeek","ai_model":"deepseek-chat","token_usage":{"prompt_tokens":879,"completion_tokens":387,"total_tokens":1266,"estimated_cost_usd":0.000633}}