{"prompt":{"prompt":"Create a fictional dictation of a clinical interaction between a healthcare professional and a patient. \nThis dictation is for testing purposes only and should include various topics that might be discussed in a healthcare setting. \nPlease ensure the material is entirely fictional and does not provide any real medical advice or information. \nPlease ensure variables such as age, weight and history are varied.\nThe clinician should ensure the history and examination findings are incomplete, leaving out some pertinent questions.\nIn response to their history and examination findings, the clinician should  provide management advice and guidance.\nThe clinical scenario should be the following: \n\nMake the age 63, the BMI 24.5 and the number of prior pregnancies 2\n\nBase the clinical scenario on the following obstetrics issue: Intrapartum fetal heart rate concerns","system_prompt":"Create a fictional dictation of a clinical interaction between a healthcare professional and a patient. \nThis dictation is for testing purposes only and should include various topics that might be discussed in a healthcare setting. \nPlease ensure the material is entirely fictional and does not provide any real medical advice or information. \nPlease ensure variables such as age, weight and history are varied.\nThe clinician should ensure the history and examination findings are incomplete, leaving out some pertinent questions.\nIn response to their history and examination findings, the clinician should  provide management advice and guidance.\nThe clinical scenario should be the following: \n\nMake the age 63, the BMI 24.5 and the number of prior pregnancies 2\n\nBase the clinical scenario on the following obstetrics issue: Intrapartum fetal heart rate concerns"},"response":"**Dictation: Clinical Interaction – Intrapartum Fetal Heart Rate Concerns**  \n*For testing purposes only. Fictional scenario. No real medical advice.*  \n\n**Patient Details:**  \n- Name: Jane Doe (fictional)  \n- Age: 63  \n- BMI: 24.5  \n- Gravida: 2, Para: 2 (prior pregnancies)  \n- Gestational Age: 39 weeks + 3 days (current pregnancy)  \n\n**History of Presenting Complaint:**  \nMrs. Doe presents to the labor and delivery unit in active labor at 39+3 weeks gestation. She reports regular contractions every 3 minutes, lasting 60 seconds, with moderate intensity. Rupture of membranes occurred 2 hours prior, with clear amniotic fluid noted.  \n\n*Incomplete history:*  \n- No documentation of fetal movement patterns prior to admission.  \n- Maternal fever or recent infections not asked.  \n- Prior delivery history (e.g., vaginal vs. cesarean, complications) not clarified.  \n\n**Fetal Heart Rate (FHR) Monitoring Findings:**  \n- Baseline FHR: 150 bpm (normal).  \n- Recurrent late decelerations noted over the past 30 minutes, with minimal variability.  \n- No accelerations documented.  \n- *Incomplete examination:* Tocodynamometer placement not confirmed; uterine activity pattern not quantified.  \n\n**Management Plan:**  \n1. **Immediate Actions:**  \n   - Reposition patient to left lateral tilt.  \n   - Administer IV fluids (normal saline bolus).  \n   - Supplemental oxygen via non-rebreather mask at 10L/min.  \n   - Discontinue oxytocin if infusing (not documented if in use).  \n\n2. **Further Assessment:**  \n   - Perform scalp stimulation for fetal response (not yet done).  \n   - Consider fetal blood sampling if decelerations persist (equipment availability not checked).  \n\n3. **Consultation:**  \n   - Notify obstetrician and anesthesia team for potential urgent delivery.  \n   - *Omission:* No discussion of patient’s preferences for intervention (e.g., cesarean vs. operative vaginal delivery).  \n\n4. **Monitoring:**  \n   - Continuous FHR monitoring; reassess in 15 minutes.  \n   - *Incomplete:* Maternal vital signs (e.g., blood pressure, temperature) not repeated since admission.  \n\n**Follow-Up:**  \nPlan for urgent delivery if FHR abnormalities persist or worsen. Documented consent for procedures not yet obtained.  \n\n*Dictated by: Dr. A. Smith (fictional)*  \n*Date: [Fictional]*  \n\n**Notes for Testing:**  \n- Intentional gaps in history/exam to simulate real-world documentation inconsistencies.  \n- Management reflects reactive steps; lacks anticipatory guidance (e.g., contingency planning for neonatal resuscitation).  \n- No reference to maternal comorbidities (e.g., hypertension, diabetes) or medications.","endpoint":"newFunctionName","timestamp":"2025-04-22T19-38-33","textContent":"AI: DeepSeek (deepseek-chat)\n\nQ: {\n  \"prompt\": \"Create a fictional dictation of a clinical interaction between a healthcare professional and a patient. \\nThis dictation is for testing purposes only and should include various topics that might be discussed in a healthcare setting. \\nPlease ensure the material is entirely fictional and does not provide any real medical advice or information. \\nPlease ensure variables such as age, weight and history are varied.\\nThe clinician should ensure the history and examination findings are incomplete, leaving out some pertinent questions.\\nIn response to their history and examination findings, the clinician should  provide management advice and guidance.\\nThe clinical scenario should be the following: \\n\\nMake the age 63, the BMI 24.5 and the number of prior pregnancies 2\\n\\nBase the clinical scenario on the following obstetrics issue: Intrapartum fetal heart rate concerns\",\n  \"system_prompt\": \"Create a fictional dictation of a clinical interaction between a healthcare professional and a patient. \\nThis dictation is for testing purposes only and should include various topics that might be discussed in a healthcare setting. \\nPlease ensure the material is entirely fictional and does not provide any real medical advice or information. \\nPlease ensure variables such as age, weight and history are varied.\\nThe clinician should ensure the history and examination findings are incomplete, leaving out some pertinent questions.\\nIn response to their history and examination findings, the clinician should  provide management advice and guidance.\\nThe clinical scenario should be the following: \\n\\nMake the age 63, the BMI 24.5 and the number of prior pregnancies 2\\n\\nBase the clinical scenario on the following obstetrics issue: Intrapartum fetal heart rate concerns\"\n}\n\nA: **Dictation: Clinical Interaction – Intrapartum Fetal Heart Rate Concerns**  \n*For testing purposes only. Fictional scenario. No real medical advice.*  \n\n**Patient Details:**  \n- Name: Jane Doe (fictional)  \n- Age: 63  \n- BMI: 24.5  \n- Gravida: 2, Para: 2 (prior pregnancies)  \n- Gestational Age: 39 weeks + 3 days (current pregnancy)  \n\n**History of Presenting Complaint:**  \nMrs. Doe presents to the labor and delivery unit in active labor at 39+3 weeks gestation. She reports regular contractions every 3 minutes, lasting 60 seconds, with moderate intensity. Rupture of membranes occurred 2 hours prior, with clear amniotic fluid noted.  \n\n*Incomplete history:*  \n- No documentation of fetal movement patterns prior to admission.  \n- Maternal fever or recent infections not asked.  \n- Prior delivery history (e.g., vaginal vs. cesarean, complications) not clarified.  \n\n**Fetal Heart Rate (FHR) Monitoring Findings:**  \n- Baseline FHR: 150 bpm (normal).  \n- Recurrent late decelerations noted over the past 30 minutes, with minimal variability.  \n- No accelerations documented.  \n- *Incomplete examination:* Tocodynamometer placement not confirmed; uterine activity pattern not quantified.  \n\n**Management Plan:**  \n1. **Immediate Actions:**  \n   - Reposition patient to left lateral tilt.  \n   - Administer IV fluids (normal saline bolus).  \n   - Supplemental oxygen via non-rebreather mask at 10L/min.  \n   - Discontinue oxytocin if infusing (not documented if in use).  \n\n2. **Further Assessment:**  \n   - Perform scalp stimulation for fetal response (not yet done).  \n   - Consider fetal blood sampling if decelerations persist (equipment availability not checked).  \n\n3. **Consultation:**  \n   - Notify obstetrician and anesthesia team for potential urgent delivery.  \n   - *Omission:* No discussion of patient’s preferences for intervention (e.g., cesarean vs. operative vaginal delivery).  \n\n4. **Monitoring:**  \n   - Continuous FHR monitoring; reassess in 15 minutes.  \n   - *Incomplete:* Maternal vital signs (e.g., blood pressure, temperature) not repeated since admission.  \n\n**Follow-Up:**  \nPlan for urgent delivery if FHR abnormalities persist or worsen. Documented consent for procedures not yet obtained.  \n\n*Dictated by: Dr. A. Smith (fictional)*  \n*Date: [Fictional]*  \n\n**Notes for Testing:**  \n- Intentional gaps in history/exam to simulate real-world documentation inconsistencies.  \n- Management reflects reactive steps; lacks anticipatory guidance (e.g., contingency planning for neonatal resuscitation).  \n- No reference to maternal comorbidities (e.g., hypertension, diabetes) or medications.\n\n--- Token Usage Report ---\nPrompt tokens: 162\nCompletion tokens: 600\nTotal tokens: 762\nEstimated cost: $0.000381","ai_provider":"DeepSeek","ai_model":"deepseek-chat","token_usage":{"prompt_tokens":162,"completion_tokens":600,"total_tokens":762,"estimated_cost_usd":0.000381}}