{"prompt":{"prompt":"Create a fictional dictation of a clinical interaction between a healthcare professional and a patient. \nThis dictation is for testing purposes only and should include various topics that might be discussed in a healthcare setting. \nPlease ensure the material is entirely fictional and does not provide any real medical advice or information. \nPlease ensure variables such as age, weight and history are varied.\nThe clinician should ensure the history and examination findings are incomplete, leaving out some pertinent questions.\nIn response to their history and examination findings, the clinician should  provide management advice and guidance.\nThe clinical scenario should be the following: \n\nMake the age 65, the BMI 31.6 and the number of prior pregnancies 3\n\nBase the clinical scenario on the following gynecology issue: Abnormal uterine bleeding","system_prompt":"Create a fictional dictation of a clinical interaction between a healthcare professional and a patient. \nThis dictation is for testing purposes only and should include various topics that might be discussed in a healthcare setting. \nPlease ensure the material is entirely fictional and does not provide any real medical advice or information. \nPlease ensure variables such as age, weight and history are varied.\nThe clinician should ensure the history and examination findings are incomplete, leaving out some pertinent questions.\nIn response to their history and examination findings, the clinician should  provide management advice and guidance.\nThe clinical scenario should be the following: \n\nMake the age 65, the BMI 31.6 and the number of prior pregnancies 3\n\nBase the clinical scenario on the following gynecology issue: Abnormal uterine bleeding"},"response":"**Dictation: Clinical Interaction – Abnormal Uterine Bleeding**  \n\n**Patient Details:**  \n- Name: Jane Doe (fictional)  \n- Age: 65  \n- BMI: 31.6  \n- Gravida: 3, Para: 3  \n- Last Menstrual Period: Approximately 12 months ago (self-reported menopause)  \n- Chief Complaint: Recurrent vaginal bleeding for the past 3 months  \n\n**History of Present Illness:**  \nMs. Doe reports intermittent postmenopausal bleeding over the last three months, described as light to moderate in flow, occurring approximately every 2–3 weeks. She denies associated pain, fever, or foul discharge. She reports no recent trauma, changes in bowel/bladder habits, or weight loss. She has not used hormonal therapies or anticoagulants. She has a history of hypertension (well-controlled on lisinopril) and type 2 diabetes (diet-controlled).  \n\n*Missing Pertinent Information:*  \n- Family history of gynecologic cancers (not asked)  \n- Prior abnormal Pap smears or HPV status (not documented)  \n- Sexual activity history (not explored)  \n- Use of over-the-counter supplements/herbal remedies (not discussed)  \n\n**Examination Findings:**  \n- General: Well-appearing, no acute distress  \n- Vital Signs: BP 128/78, HR 72, RR 14, SpO2 98%  \n- Abdomen: Soft, non-tender, no palpable masses  \n- Pelvic Exam: External genitalia normal; speculum exam reveals scant blood in vaginal vault; cervix appears atrophic with no visible lesions. Bimanual exam: uterus slightly enlarged, no adnexal tenderness or masses noted.  \n\n*Missing Pertinent Exam Elements:*  \n- No documentation of cervical motion tenderness  \n- No rectal exam performed  \n- No description of uterine mobility/fixation  \n\n**Assessment:**  \nPostmenopausal bleeding in a 65-year-old with obesity and a history of three prior pregnancies. Differential includes:  \n1. Endometrial atrophy (most common)  \n2. Endometrial hyperplasia/polyp  \n3. Endometrial carcinoma (must rule out)  \n4. Cervical pathology (less likely given exam)  \n\n**Plan:**  \n1. **Diagnostics:**  \n   - Transvaginal ultrasound to assess endometrial thickness  \n   - Endometrial biopsy (office-based) to evaluate for hyperplasia/malignancy  \n   - Consider referral for hysteroscopy if biopsy is inconclusive  \n2. **Lifestyle:** Encourage weight management given BMI 31.6 and association with endometrial cancer risk.  \n3. **Follow-Up:**  \n   - Schedule biopsy within 1–2 weeks  \n   - Return for results and further management  \n   - If bleeding worsens or becomes heavy, advise ED evaluation  \n\n*Missing Management Elements:*  \n- No discussion of diabetes/hypertension optimization for surgical risk (if needed)  \n- No counseling on potential next steps (e.g., hysterectomy if malignancy found)  \n- No mention of anemia screening despite recurrent bleeding  \n\n**Impression:**  \nUrgent evaluation warranted for postmenopausal bleeding. Patient counseled on concerning nature of symptoms and importance of follow-up.  \n\n---  \n*Note: This is a fictional dictation for testing purposes only. No real medical advice is implied or provided.*","endpoint":"newFunctionName","timestamp":"2025-05-11T06-25-16","textContent":"AI: DeepSeek (deepseek-chat)\n\nQ: {\n  \"prompt\": \"Create a fictional dictation of a clinical interaction between a healthcare professional and a patient. \\nThis dictation is for testing purposes only and should include various topics that might be discussed in a healthcare setting. \\nPlease ensure the material is entirely fictional and does not provide any real medical advice or information. \\nPlease ensure variables such as age, weight and history are varied.\\nThe clinician should ensure the history and examination findings are incomplete, leaving out some pertinent questions.\\nIn response to their history and examination findings, the clinician should  provide management advice and guidance.\\nThe clinical scenario should be the following: \\n\\nMake the age 65, the BMI 31.6 and the number of prior pregnancies 3\\n\\nBase the clinical scenario on the following gynecology issue: Abnormal uterine bleeding\",\n  \"system_prompt\": \"Create a fictional dictation of a clinical interaction between a healthcare professional and a patient. \\nThis dictation is for testing purposes only and should include various topics that might be discussed in a healthcare setting. \\nPlease ensure the material is entirely fictional and does not provide any real medical advice or information. \\nPlease ensure variables such as age, weight and history are varied.\\nThe clinician should ensure the history and examination findings are incomplete, leaving out some pertinent questions.\\nIn response to their history and examination findings, the clinician should  provide management advice and guidance.\\nThe clinical scenario should be the following: \\n\\nMake the age 65, the BMI 31.6 and the number of prior pregnancies 3\\n\\nBase the clinical scenario on the following gynecology issue: Abnormal uterine bleeding\"\n}\n\nA: **Dictation: Clinical Interaction – Abnormal Uterine Bleeding**  \n\n**Patient Details:**  \n- Name: Jane Doe (fictional)  \n- Age: 65  \n- BMI: 31.6  \n- Gravida: 3, Para: 3  \n- Last Menstrual Period: Approximately 12 months ago (self-reported menopause)  \n- Chief Complaint: Recurrent vaginal bleeding for the past 3 months  \n\n**History of Present Illness:**  \nMs. Doe reports intermittent postmenopausal bleeding over the last three months, described as light to moderate in flow, occurring approximately every 2–3 weeks. She denies associated pain, fever, or foul discharge. She reports no recent trauma, changes in bowel/bladder habits, or weight loss. She has not used hormonal therapies or anticoagulants. She has a history of hypertension (well-controlled on lisinopril) and type 2 diabetes (diet-controlled).  \n\n*Missing Pertinent Information:*  \n- Family history of gynecologic cancers (not asked)  \n- Prior abnormal Pap smears or HPV status (not documented)  \n- Sexual activity history (not explored)  \n- Use of over-the-counter supplements/herbal remedies (not discussed)  \n\n**Examination Findings:**  \n- General: Well-appearing, no acute distress  \n- Vital Signs: BP 128/78, HR 72, RR 14, SpO2 98%  \n- Abdomen: Soft, non-tender, no palpable masses  \n- Pelvic Exam: External genitalia normal; speculum exam reveals scant blood in vaginal vault; cervix appears atrophic with no visible lesions. Bimanual exam: uterus slightly enlarged, no adnexal tenderness or masses noted.  \n\n*Missing Pertinent Exam Elements:*  \n- No documentation of cervical motion tenderness  \n- No rectal exam performed  \n- No description of uterine mobility/fixation  \n\n**Assessment:**  \nPostmenopausal bleeding in a 65-year-old with obesity and a history of three prior pregnancies. Differential includes:  \n1. Endometrial atrophy (most common)  \n2. Endometrial hyperplasia/polyp  \n3. Endometrial carcinoma (must rule out)  \n4. Cervical pathology (less likely given exam)  \n\n**Plan:**  \n1. **Diagnostics:**  \n   - Transvaginal ultrasound to assess endometrial thickness  \n   - Endometrial biopsy (office-based) to evaluate for hyperplasia/malignancy  \n   - Consider referral for hysteroscopy if biopsy is inconclusive  \n2. **Lifestyle:** Encourage weight management given BMI 31.6 and association with endometrial cancer risk.  \n3. **Follow-Up:**  \n   - Schedule biopsy within 1–2 weeks  \n   - Return for results and further management  \n   - If bleeding worsens or becomes heavy, advise ED evaluation  \n\n*Missing Management Elements:*  \n- No discussion of diabetes/hypertension optimization for surgical risk (if needed)  \n- No counseling on potential next steps (e.g., hysterectomy if malignancy found)  \n- No mention of anemia screening despite recurrent bleeding  \n\n**Impression:**  \nUrgent evaluation warranted for postmenopausal bleeding. Patient counseled on concerning nature of symptoms and importance of follow-up.  \n\n---  \n*Note: This is a fictional dictation for testing purposes only. No real medical advice is implied or provided.*\n\n--- Token Usage Report ---\nPrompt tokens: 158\nCompletion tokens: 679\nTotal tokens: 837\nEstimated cost: $0.000419","ai_provider":"DeepSeek","ai_model":"deepseek-chat","token_usage":{"prompt_tokens":158,"completion_tokens":679,"total_tokens":837,"estimated_cost_usd":0.00041850000000000004}}