{"prompt":{"prompt":"Create a fictional dictation of a clinical interaction between a healthcare professional and a patient. \nThis dictation is for testing purposes only and should include various topics that might be discussed in a healthcare setting. \nPlease ensure the material is entirely fictional and does not provide any real medical advice or information. \nPlease ensure variables such as age, weight and history are varied.\nThe clinician should ensure the history and examination findings are incomplete, leaving out some pertinent questions.\nIn response to their history and examination findings, the clinician should  provide management advice and guidance.\nThe clinical scenario should be the following:  \n            \nThe clinical scenario should focus on a patient with Abnormal uterine bleeding.","system_prompt":"Create a fictional dictation of a clinical interaction between a healthcare professional and a patient. \nThis dictation is for testing purposes only and should include various topics that might be discussed in a healthcare setting. \nPlease ensure the material is entirely fictional and does not provide any real medical advice or information. \nPlease ensure variables such as age, weight and history are varied.\nThe clinician should ensure the history and examination findings are incomplete, leaving out some pertinent questions.\nIn response to their history and examination findings, the clinician should  provide management advice and guidance.\nThe clinical scenario should be the following:  \n            \nThe clinical scenario should focus on a patient with Abnormal uterine bleeding."},"response":"**Fictional Clinical Dictation: Abnormal Uterine Bleeding**  \n\n**Patient Name:** Jane Doe  \n**Age:** 42 years  \n**Gender:** Female  \n**Date of Visit:** October 10, 2023  \n**Clinician:** Dr. Smith  \n\n### **History of Present Illness:**  \nMs. Doe presents today reporting a 4-month history of abnormal uterine bleeding. She describes her periods as \"very heavy,\" requiring her to change pads every 2 hours on the heaviest days. She also reports intermittent spotting between periods. She denies associated fever, dizziness, or syncope but notes mild fatigue. She has no history of bleeding disorders or prior gynecologic surgeries.  \n\n*[Missing Pertinent Information: Duration of bleeding episodes, presence of clots, associated pain, sexual activity history, contraceptive use, family history of gynecologic cancers.]*  \n\n### **Past Medical History:**  \n- Hypertension (well-controlled on lisinopril)  \n- Obesity (BMI 32)  \n- No known diabetes or thyroid disorders  \n\n### **Medications:**  \n- Lisinopril 10 mg daily  \n- Multivitamin  \n\n### **Allergies:**  \n- NKDA  \n\n### **Social History:**  \n- Non-smoker  \n- Occasional alcohol use  \n- Works as a teacher  \n- Married, monogamous  \n\n*[Missing Pertinent Information: Exercise habits, diet, stress levels, prior Pap smear results.]*  \n\n### **Family History:**  \n- Mother with hypertension  \n- No known history of gynecologic cancers  \n\n### **Review of Systems:**  \n- **General:** Mild fatigue, no weight changes  \n- **Cardiovascular:** No chest pain or palpitations  \n- **Gastrointestinal:** No nausea, vomiting, or changes in bowel habits  \n- **Genitourinary:** No dysuria or urinary frequency  \n\n*[Missing Pertinent Information: Breast tenderness, hirsutism, acne, or other signs of hormonal imbalance.]*  \n\n### **Physical Examination:**  \n- **Vitals:** BP 128/82, HR 78, Temp 98.4°F, Weight 185 lbs  \n- **General:** Well-appearing, no acute distress  \n- **Abdomen:** Soft, non-tender, no palpable masses  \n- **Pelvic Exam:** External genitalia normal, cervix appears normal, no active bleeding at time of exam  \n- **Bimanual Exam:** Uterus slightly enlarged, no adnexal tenderness  \n\n*[Missing Pertinent Information: Speculum exam findings, assessment for cervical motion tenderness, evaluation for uterine prolapse.]*  \n\n### **Assessment:**  \n42-year-old female with abnormal uterine bleeding, likely secondary to perimenopausal hormonal changes or possible fibroids. Other differentials include endometrial hyperplasia or polyps.  \n\n### **Plan:**  \n1. **Diagnostics:**  \n   - Pelvic ultrasound to assess for fibroids, polyps, or endometrial thickening  \n   - CBC to evaluate for anemia  \n   - TSH to rule out thyroid dysfunction  \n   - *[Missing: Endometrial biopsy given age >40, consideration of STI screening.]*  \n\n2. **Management:**  \n   - Start tranexamic acid for heavy bleeding as needed  \n   - Consider trial of combined oral contraceptives if no contraindications  \n   - Iron supplementation if anemia is confirmed  \n\n3. **Follow-Up:**  \n   - Return in 4 weeks for review of lab results and ultrasound findings  \n   - If bleeding worsens or new symptoms arise, seek urgent evaluation  \n\n*[Missing: Discussion of surgical options (e.g., hysterectomy, ablation) if medical management fails, counseling on weight loss impact on hormonal balance.]*  \n\n**Impression:** Abnormal uterine bleeding, etiology to be determined.  \n\n**Dictated by:** Dr. Smith  \n**Date:** October 10, 2023  \n\n---  \n*This dictation is for fictional testing purposes only and does not constitute real medical advice.*","endpoint":"generateFakeClinicalInteraction","timestamp":"2025-05-26T16-25-00","textContent":"AI: DeepSeek (deepseek-chat)\n\nQ: {\n  \"prompt\": \"Create a fictional dictation of a clinical interaction between a healthcare professional and a patient. \\nThis dictation is for testing purposes only and should include various topics that might be discussed in a healthcare setting. \\nPlease ensure the material is entirely fictional and does not provide any real medical advice or information. \\nPlease ensure variables such as age, weight and history are varied.\\nThe clinician should ensure the history and examination findings are incomplete, leaving out some pertinent questions.\\nIn response to their history and examination findings, the clinician should  provide management advice and guidance.\\nThe clinical scenario should be the following:  \\n            \\nThe clinical scenario should focus on a patient with Abnormal uterine bleeding.\",\n  \"system_prompt\": \"Create a fictional dictation of a clinical interaction between a healthcare professional and a patient. \\nThis dictation is for testing purposes only and should include various topics that might be discussed in a healthcare setting. \\nPlease ensure the material is entirely fictional and does not provide any real medical advice or information. \\nPlease ensure variables such as age, weight and history are varied.\\nThe clinician should ensure the history and examination findings are incomplete, leaving out some pertinent questions.\\nIn response to their history and examination findings, the clinician should  provide management advice and guidance.\\nThe clinical scenario should be the following:  \\n            \\nThe clinical scenario should focus on a patient with Abnormal uterine bleeding.\"\n}\n\nA: **Fictional Clinical Dictation: Abnormal Uterine Bleeding**  \n\n**Patient Name:** Jane Doe  \n**Age:** 42 years  \n**Gender:** Female  \n**Date of Visit:** October 10, 2023  \n**Clinician:** Dr. Smith  \n\n### **History of Present Illness:**  \nMs. Doe presents today reporting a 4-month history of abnormal uterine bleeding. She describes her periods as \"very heavy,\" requiring her to change pads every 2 hours on the heaviest days. She also reports intermittent spotting between periods. She denies associated fever, dizziness, or syncope but notes mild fatigue. She has no history of bleeding disorders or prior gynecologic surgeries.  \n\n*[Missing Pertinent Information: Duration of bleeding episodes, presence of clots, associated pain, sexual activity history, contraceptive use, family history of gynecologic cancers.]*  \n\n### **Past Medical History:**  \n- Hypertension (well-controlled on lisinopril)  \n- Obesity (BMI 32)  \n- No known diabetes or thyroid disorders  \n\n### **Medications:**  \n- Lisinopril 10 mg daily  \n- Multivitamin  \n\n### **Allergies:**  \n- NKDA  \n\n### **Social History:**  \n- Non-smoker  \n- Occasional alcohol use  \n- Works as a teacher  \n- Married, monogamous  \n\n*[Missing Pertinent Information: Exercise habits, diet, stress levels, prior Pap smear results.]*  \n\n### **Family History:**  \n- Mother with hypertension  \n- No known history of gynecologic cancers  \n\n### **Review of Systems:**  \n- **General:** Mild fatigue, no weight changes  \n- **Cardiovascular:** No chest pain or palpitations  \n- **Gastrointestinal:** No nausea, vomiting, or changes in bowel habits  \n- **Genitourinary:** No dysuria or urinary frequency  \n\n*[Missing Pertinent Information: Breast tenderness, hirsutism, acne, or other signs of hormonal imbalance.]*  \n\n### **Physical Examination:**  \n- **Vitals:** BP 128/82, HR 78, Temp 98.4°F, Weight 185 lbs  \n- **General:** Well-appearing, no acute distress  \n- **Abdomen:** Soft, non-tender, no palpable masses  \n- **Pelvic Exam:** External genitalia normal, cervix appears normal, no active bleeding at time of exam  \n- **Bimanual Exam:** Uterus slightly enlarged, no adnexal tenderness  \n\n*[Missing Pertinent Information: Speculum exam findings, assessment for cervical motion tenderness, evaluation for uterine prolapse.]*  \n\n### **Assessment:**  \n42-year-old female with abnormal uterine bleeding, likely secondary to perimenopausal hormonal changes or possible fibroids. Other differentials include endometrial hyperplasia or polyps.  \n\n### **Plan:**  \n1. **Diagnostics:**  \n   - Pelvic ultrasound to assess for fibroids, polyps, or endometrial thickening  \n   - CBC to evaluate for anemia  \n   - TSH to rule out thyroid dysfunction  \n   - *[Missing: Endometrial biopsy given age >40, consideration of STI screening.]*  \n\n2. **Management:**  \n   - Start tranexamic acid for heavy bleeding as needed  \n   - Consider trial of combined oral contraceptives if no contraindications  \n   - Iron supplementation if anemia is confirmed  \n\n3. **Follow-Up:**  \n   - Return in 4 weeks for review of lab results and ultrasound findings  \n   - If bleeding worsens or new symptoms arise, seek urgent evaluation  \n\n*[Missing: Discussion of surgical options (e.g., hysterectomy, ablation) if medical management fails, counseling on weight loss impact on hormonal balance.]*  \n\n**Impression:** Abnormal uterine bleeding, etiology to be determined.  \n\n**Dictated by:** Dr. Smith  \n**Date:** October 10, 2023  \n\n---  \n*This dictation is for fictional testing purposes only and does not constitute real medical advice.*\n\n--- Token Usage Report ---\nPrompt tokens: 136\nCompletion tokens: 809\nTotal tokens: 945\nEstimated cost: $0.000473","ai_provider":"DeepSeek","ai_model":"deepseek-chat","token_usage":{"prompt_tokens":136,"completion_tokens":809,"total_tokens":945,"estimated_cost_usd":0.00047250000000000005}}