{"prompt":{"prompt":"Create a fictional dictation of a clinical interaction between a healthcare professional and a patient. \nThis dictation is for testing purposes only and should include various topics that might be discussed in a healthcare setting. \nPlease ensure the material is entirely fictional and does not provide any real medical advice or information. \nPlease ensure variables such as age, weight and history are varied.\nThe clinician should ensure the history and examination findings are incomplete, leaving out some pertinent questions.\nIn response to their history and examination findings, the clinician should  provide management advice and guidance.\nThe clinical scenario should be the following: Abnormal uterine bleeding","system_prompt":"Create a fictional dictation of a clinical interaction between a healthcare professional and a patient. \nThis dictation is for testing purposes only and should include various topics that might be discussed in a healthcare setting. \nPlease ensure the material is entirely fictional and does not provide any real medical advice or information. \nPlease ensure variables such as age, weight and history are varied.\nThe clinician should ensure the history and examination findings are incomplete, leaving out some pertinent questions.\nIn response to their history and examination findings, the clinician should  provide management advice and guidance.\nThe clinical scenario should be the following: Abnormal uterine bleeding"},"response":"**Clinical Dictation: Fictional Patient Encounter**  \n**Patient Name:** Jane Doe  \n**Age:** 42  \n**Date of Visit:** October 10, 2023  \n**Clinician:** Dr. Smith  \n**Specialty:** Gynecology  \n\n---\n\n### **Subjective:**  \nMs. Doe presents today reporting a 4-month history of abnormal uterine bleeding. She describes episodes of heavy menstrual bleeding lasting 8–10 days, with passage of clots, occurring every 2–3 weeks. She denies intermenstrual bleeding but reports occasional spotting. She notes associated fatigue but denies dizziness, syncope, or severe pelvic pain.  \n\n**Relevant History:**  \n- Gravida 3, Para 3 (last delivery 10 years ago, vaginal).  \n- No history of gynecologic surgeries.  \n- No known bleeding disorders or anticoagulant use.  \n- Family history: Mother with fibroids (no further details obtained).  \n- Medications: Over-the-counter iron supplements (self-initiated).  \n- Allergies: NKDA.  \n\n**Social History:**  \n- Smokes 5 cigarettes/day (10 pack-year history).  \n- Occasional alcohol use.  \n- No recreational drug use.  \n\n**Review of Systems (Incomplete):**  \n- No weight changes, fever, or night sweats.  \n- No breast changes or galactorrhea.  \n- No dyspareunia or postcoital bleeding.  \n- Thyroid, clotting history, and recent Pap smear status not asked.  \n\n---\n\n### **Objective:**  \n**Vitals:**  \n- BP: 128/82 mmHg | HR: 78 bpm | BMI: 29 (weight 170 lbs)  \n\n**Physical Exam (Limited):**  \n- Abdomen: Soft, non-tender; no masses palpated.  \n- Pelvic Exam: Cervix appears normal; uterus slightly enlarged, mobile, non-tender. Adnexa not palpated. No active bleeding at time of exam.  \n- Breasts: No masses or discharge.  \n\n**No Further Workup:**  \n- No labs (CBC, TSH, coagulation studies) or imaging (ultrasound) ordered today.  \n\n---\n\n### **Assessment:**  \n**Working Diagnosis:**  \nAbnormal uterine bleeding (AUB), likely secondary to fibroids or ovulatory dysfunction. Other etiologies (e.g., endometrial hyperplasia, coagulopathy) not yet ruled out.  \n\n**Missed Questions:**  \n- Last menstrual period (LMP) not documented.  \n- Contraceptive use/history not explored.  \n- No assessment for anemia symptoms (e.g., pallor, tachycardia).  \n\n---\n\n### **Plan:**  \n1. **Diagnostics (Deferred):**  \n   - Recommend outpatient pelvic ultrasound and CBC/ferritin to assess for fibroids/anemia.  \n   - Consider endometrial biopsy if ultrasound abnormal (not discussed with patient today).  \n\n2. **Symptomatic Management:**  \n   - Start tranexamic acid 1300 mg TID during heavy bleeding (no contraindications reviewed).  \n   - Continue iron supplementation.  \n\n3. **Lifestyle:**  \n   - Counsel on smoking cessation (brief discussion only).  \n\n4. **Follow-Up:**  \n   - Return in 4 weeks for review of imaging/labs (not yet ordered). If bleeding worsens, advise ED referral.  \n\n**Patient Instructions:**  \n- Keep a bleeding diary.  \n- Seek care if lightheadedness or soaking >1 pad/hour.  \n\n**Note:** This dictation is for fictional testing purposes only. No real medical advice is implied.  \n\n---  \n**End of Note**  \n\n*[Intentional gaps: No LMP, incomplete ROS, deferred diagnostics, limited counseling.]*","endpoint":"generateFakeClinicalInteraction","timestamp":"2025-05-27T12-02-08","textContent":"AI: DeepSeek (deepseek-chat)\n\nQ: {\n  \"prompt\": \"Create a fictional dictation of a clinical interaction between a healthcare professional and a patient. \\nThis dictation is for testing purposes only and should include various topics that might be discussed in a healthcare setting. \\nPlease ensure the material is entirely fictional and does not provide any real medical advice or information. \\nPlease ensure variables such as age, weight and history are varied.\\nThe clinician should ensure the history and examination findings are incomplete, leaving out some pertinent questions.\\nIn response to their history and examination findings, the clinician should  provide management advice and guidance.\\nThe clinical scenario should be the following: Abnormal uterine bleeding\",\n  \"system_prompt\": \"Create a fictional dictation of a clinical interaction between a healthcare professional and a patient. \\nThis dictation is for testing purposes only and should include various topics that might be discussed in a healthcare setting. \\nPlease ensure the material is entirely fictional and does not provide any real medical advice or information. \\nPlease ensure variables such as age, weight and history are varied.\\nThe clinician should ensure the history and examination findings are incomplete, leaving out some pertinent questions.\\nIn response to their history and examination findings, the clinician should  provide management advice and guidance.\\nThe clinical scenario should be the following: Abnormal uterine bleeding\"\n}\n\nA: **Clinical Dictation: Fictional Patient Encounter**  \n**Patient Name:** Jane Doe  \n**Age:** 42  \n**Date of Visit:** October 10, 2023  \n**Clinician:** Dr. Smith  \n**Specialty:** Gynecology  \n\n---\n\n### **Subjective:**  \nMs. Doe presents today reporting a 4-month history of abnormal uterine bleeding. She describes episodes of heavy menstrual bleeding lasting 8–10 days, with passage of clots, occurring every 2–3 weeks. She denies intermenstrual bleeding but reports occasional spotting. She notes associated fatigue but denies dizziness, syncope, or severe pelvic pain.  \n\n**Relevant History:**  \n- Gravida 3, Para 3 (last delivery 10 years ago, vaginal).  \n- No history of gynecologic surgeries.  \n- No known bleeding disorders or anticoagulant use.  \n- Family history: Mother with fibroids (no further details obtained).  \n- Medications: Over-the-counter iron supplements (self-initiated).  \n- Allergies: NKDA.  \n\n**Social History:**  \n- Smokes 5 cigarettes/day (10 pack-year history).  \n- Occasional alcohol use.  \n- No recreational drug use.  \n\n**Review of Systems (Incomplete):**  \n- No weight changes, fever, or night sweats.  \n- No breast changes or galactorrhea.  \n- No dyspareunia or postcoital bleeding.  \n- Thyroid, clotting history, and recent Pap smear status not asked.  \n\n---\n\n### **Objective:**  \n**Vitals:**  \n- BP: 128/82 mmHg | HR: 78 bpm | BMI: 29 (weight 170 lbs)  \n\n**Physical Exam (Limited):**  \n- Abdomen: Soft, non-tender; no masses palpated.  \n- Pelvic Exam: Cervix appears normal; uterus slightly enlarged, mobile, non-tender. Adnexa not palpated. No active bleeding at time of exam.  \n- Breasts: No masses or discharge.  \n\n**No Further Workup:**  \n- No labs (CBC, TSH, coagulation studies) or imaging (ultrasound) ordered today.  \n\n---\n\n### **Assessment:**  \n**Working Diagnosis:**  \nAbnormal uterine bleeding (AUB), likely secondary to fibroids or ovulatory dysfunction. Other etiologies (e.g., endometrial hyperplasia, coagulopathy) not yet ruled out.  \n\n**Missed Questions:**  \n- Last menstrual period (LMP) not documented.  \n- Contraceptive use/history not explored.  \n- No assessment for anemia symptoms (e.g., pallor, tachycardia).  \n\n---\n\n### **Plan:**  \n1. **Diagnostics (Deferred):**  \n   - Recommend outpatient pelvic ultrasound and CBC/ferritin to assess for fibroids/anemia.  \n   - Consider endometrial biopsy if ultrasound abnormal (not discussed with patient today).  \n\n2. **Symptomatic Management:**  \n   - Start tranexamic acid 1300 mg TID during heavy bleeding (no contraindications reviewed).  \n   - Continue iron supplementation.  \n\n3. **Lifestyle:**  \n   - Counsel on smoking cessation (brief discussion only).  \n\n4. **Follow-Up:**  \n   - Return in 4 weeks for review of imaging/labs (not yet ordered). If bleeding worsens, advise ED referral.  \n\n**Patient Instructions:**  \n- Keep a bleeding diary.  \n- Seek care if lightheadedness or soaking >1 pad/hour.  \n\n**Note:** This dictation is for fictional testing purposes only. No real medical advice is implied.  \n\n---  \n**End of Note**  \n\n*[Intentional gaps: No LMP, incomplete ROS, deferred diagnostics, limited counseling.]*\n\n--- Token Usage Report ---\nPrompt tokens: 124\nCompletion tokens: 764\nTotal tokens: 888\nEstimated cost: $0.000444","ai_provider":"DeepSeek","ai_model":"deepseek-chat","token_usage":{"prompt_tokens":124,"completion_tokens":764,"total_tokens":888,"estimated_cost_usd":0.000444}}