{"prompt":{"prompt":"Create a fictional dictation of a clinical interaction between a healthcare professional and a patient. \nThis dictation is for testing purposes only and should include various topics that might be discussed in a healthcare setting. \nPlease ensure the material is entirely fictional and does not provide any real medical advice or information. \nPlease ensure variables such as age, weight and history are varied.\nThe clinician should ensure the history and examination findings are incomplete, leaving out some pertinent questions.\nIn response to their history and examination findings, the clinician should  provide management advice and guidance.\nThe clinical scenario should be the following: \n\nMake the age 35, the BMI 39.6 and the number of prior pregnancies 5\n\nBase the clinical scenario on the following issue: Abnormal uterine bleeding","system_prompt":"Create a fictional dictation of a clinical interaction between a healthcare professional and a patient. \nThis dictation is for testing purposes only and should include various topics that might be discussed in a healthcare setting. \nPlease ensure the material is entirely fictional and does not provide any real medical advice or information. \nPlease ensure variables such as age, weight and history are varied.\nThe clinician should ensure the history and examination findings are incomplete, leaving out some pertinent questions.\nIn response to their history and examination findings, the clinician should  provide management advice and guidance.\nThe clinical scenario should be the following: \n\nMake the age 35, the BMI 39.6 and the number of prior pregnancies 5\n\nBase the clinical scenario on the following issue: Abnormal uterine bleeding"},"response":"**Clinical Dictation – Fictional for Testing Purposes Only**  \n\n**Patient Name:** Jane Doe  \n**Age:** 35  \n**BMI:** 39.6  \n**Gravida:** 5, Para: 3 (prior pregnancies: 3 live births, 1 miscarriage, 1 elective termination)  \n**Date of Encounter:** [Fictional Date]  \n**Clinician:** Dr. Smith  \n\n### **History of Present Illness:**  \nMs. Doe presents today reporting abnormal uterine bleeding for the past 6 months. She describes her periods as heavy, lasting 7–10 days, with passage of clots. She reports intermittent spotting between cycles. She denies associated fever, dizziness, or syncope but notes occasional fatigue. She has no history of bleeding disorders. She is sexually active with one partner and uses condoms inconsistently for contraception. She has not had a recent Pap smear.  \n\n*Missing Pertinent Questions:*  \n- Family history of gynecologic malignancies or bleeding disorders  \n- Exact menstrual pattern prior to onset of symptoms (e.g., regularity, previous flow)  \n- Medications (e.g., NSAIDs, anticoagulants)  \n- Symptoms of thyroid dysfunction (fatigue, weight changes, hair loss)  \n- Recent weight changes or signs of hyperandrogenism (hirsutism, acne)  \n\n### **Past Medical/Surgical History:**  \n- Obesity (BMI 39.6)  \n- Gestational diabetes (last pregnancy)  \n- No prior surgeries  \n\n### **Social History:**  \n- Smokes ½ pack per day  \n- Occasional alcohol use  \n- No recreational drug use  \n\n### **Review of Systems:**  \n- **Constitutional:** Fatigue, no weight loss  \n- **Cardiovascular:** No chest pain, palpitations  \n- **Gastrointestinal:** No nausea, vomiting, or changes in bowel habits  \n- **Genitourinary:** No dysuria or pelvic pain  \n\n### **Physical Examination:**  \n- **General:** Well-appearing, no acute distress  \n- **Vitals:** BP 128/82, HR 78, RR 16, SpO2 98%  \n- **Abdomen:** Soft, non-tender, obese, no palpable masses  \n- **Pelvic Exam:** *Deferred today* (Note: Incomplete—speculum/bimanual not performed)  \n\n### **Assessment:**  \n**1. Abnormal Uterine Bleeding (AUB)** – Likely secondary to ovulatory dysfunction given obesity and irregular pattern, though structural causes (e.g., fibroids, polyps) cannot be ruled out without imaging.  \n**2. Obesity** – BMI 39.6, increased risk for endometrial hyperplasia.  \n**3. Tobacco Use** – Additional cardiovascular risk.  \n\n### **Plan:**  \n1. **Diagnostics:**  \n   - **Pelvic ultrasound** to evaluate for structural abnormalities (fibroids, polyps, endometrial thickening).  \n   - **CBC** to assess for anemia (given fatigue and heavy bleeding).  \n   - **TSH** to rule out thyroid dysfunction.  \n   - **Consider endometrial biopsy** if ultrasound shows thickened endometrium (given age >35, obesity, and prolonged bleeding).  \n\n2. **Management:**  \n   - **Progestin therapy** (e.g., oral norethindrone) to regulate cycles if no contraindications.  \n   - **Iron supplementation** if anemia is confirmed.  \n   - **Counseling on weight management** given association between obesity and AUB.  \n   - **Encourage smoking cessation.**  \n\n3. **Follow-Up:**  \n   - Return in 4 weeks for review of imaging/lab results.  \n   - If bleeding worsens or signs of hemodynamic instability (e.g., lightheadedness), seek urgent evaluation.  \n\n*Note: Incomplete workup—pelvic exam and further menstrual history needed at follow-up.*  \n\n**End of Dictation – Fictional for Testing Purposes Only**  \n\n---  \nThis dictation is entirely fictional and does not constitute medical advice. Always follow institutional guidelines for documentation and patient care.","endpoint":"generateFakeClinicalInteraction","timestamp":"2025-05-27T10-20-07","textContent":"AI: DeepSeek (deepseek-chat)\n\nQ: {\n  \"prompt\": \"Create a fictional dictation of a clinical interaction between a healthcare professional and a patient. \\nThis dictation is for testing purposes only and should include various topics that might be discussed in a healthcare setting. \\nPlease ensure the material is entirely fictional and does not provide any real medical advice or information. \\nPlease ensure variables such as age, weight and history are varied.\\nThe clinician should ensure the history and examination findings are incomplete, leaving out some pertinent questions.\\nIn response to their history and examination findings, the clinician should  provide management advice and guidance.\\nThe clinical scenario should be the following: \\n\\nMake the age 35, the BMI 39.6 and the number of prior pregnancies 5\\n\\nBase the clinical scenario on the following issue: Abnormal uterine bleeding\",\n  \"system_prompt\": \"Create a fictional dictation of a clinical interaction between a healthcare professional and a patient. \\nThis dictation is for testing purposes only and should include various topics that might be discussed in a healthcare setting. \\nPlease ensure the material is entirely fictional and does not provide any real medical advice or information. \\nPlease ensure variables such as age, weight and history are varied.\\nThe clinician should ensure the history and examination findings are incomplete, leaving out some pertinent questions.\\nIn response to their history and examination findings, the clinician should  provide management advice and guidance.\\nThe clinical scenario should be the following: \\n\\nMake the age 35, the BMI 39.6 and the number of prior pregnancies 5\\n\\nBase the clinical scenario on the following issue: Abnormal uterine bleeding\"\n}\n\nA: **Clinical Dictation – Fictional for Testing Purposes Only**  \n\n**Patient Name:** Jane Doe  \n**Age:** 35  \n**BMI:** 39.6  \n**Gravida:** 5, Para: 3 (prior pregnancies: 3 live births, 1 miscarriage, 1 elective termination)  \n**Date of Encounter:** [Fictional Date]  \n**Clinician:** Dr. Smith  \n\n### **History of Present Illness:**  \nMs. Doe presents today reporting abnormal uterine bleeding for the past 6 months. She describes her periods as heavy, lasting 7–10 days, with passage of clots. She reports intermittent spotting between cycles. She denies associated fever, dizziness, or syncope but notes occasional fatigue. She has no history of bleeding disorders. She is sexually active with one partner and uses condoms inconsistently for contraception. She has not had a recent Pap smear.  \n\n*Missing Pertinent Questions:*  \n- Family history of gynecologic malignancies or bleeding disorders  \n- Exact menstrual pattern prior to onset of symptoms (e.g., regularity, previous flow)  \n- Medications (e.g., NSAIDs, anticoagulants)  \n- Symptoms of thyroid dysfunction (fatigue, weight changes, hair loss)  \n- Recent weight changes or signs of hyperandrogenism (hirsutism, acne)  \n\n### **Past Medical/Surgical History:**  \n- Obesity (BMI 39.6)  \n- Gestational diabetes (last pregnancy)  \n- No prior surgeries  \n\n### **Social History:**  \n- Smokes ½ pack per day  \n- Occasional alcohol use  \n- No recreational drug use  \n\n### **Review of Systems:**  \n- **Constitutional:** Fatigue, no weight loss  \n- **Cardiovascular:** No chest pain, palpitations  \n- **Gastrointestinal:** No nausea, vomiting, or changes in bowel habits  \n- **Genitourinary:** No dysuria or pelvic pain  \n\n### **Physical Examination:**  \n- **General:** Well-appearing, no acute distress  \n- **Vitals:** BP 128/82, HR 78, RR 16, SpO2 98%  \n- **Abdomen:** Soft, non-tender, obese, no palpable masses  \n- **Pelvic Exam:** *Deferred today* (Note: Incomplete—speculum/bimanual not performed)  \n\n### **Assessment:**  \n**1. Abnormal Uterine Bleeding (AUB)** – Likely secondary to ovulatory dysfunction given obesity and irregular pattern, though structural causes (e.g., fibroids, polyps) cannot be ruled out without imaging.  \n**2. Obesity** – BMI 39.6, increased risk for endometrial hyperplasia.  \n**3. Tobacco Use** – Additional cardiovascular risk.  \n\n### **Plan:**  \n1. **Diagnostics:**  \n   - **Pelvic ultrasound** to evaluate for structural abnormalities (fibroids, polyps, endometrial thickening).  \n   - **CBC** to assess for anemia (given fatigue and heavy bleeding).  \n   - **TSH** to rule out thyroid dysfunction.  \n   - **Consider endometrial biopsy** if ultrasound shows thickened endometrium (given age >35, obesity, and prolonged bleeding).  \n\n2. **Management:**  \n   - **Progestin therapy** (e.g., oral norethindrone) to regulate cycles if no contraindications.  \n   - **Iron supplementation** if anemia is confirmed.  \n   - **Counseling on weight management** given association between obesity and AUB.  \n   - **Encourage smoking cessation.**  \n\n3. **Follow-Up:**  \n   - Return in 4 weeks for review of imaging/lab results.  \n   - If bleeding worsens or signs of hemodynamic instability (e.g., lightheadedness), seek urgent evaluation.  \n\n*Note: Incomplete workup—pelvic exam and further menstrual history needed at follow-up.*  \n\n**End of Dictation – Fictional for Testing Purposes Only**  \n\n---  \nThis dictation is entirely fictional and does not constitute medical advice. Always follow institutional guidelines for documentation and patient care.\n\n--- Token Usage Report ---\nPrompt tokens: 155\nCompletion tokens: 839\nTotal tokens: 994\nEstimated cost: $0.000497","ai_provider":"DeepSeek","ai_model":"deepseek-chat","token_usage":{"prompt_tokens":155,"completion_tokens":839,"total_tokens":994,"estimated_cost_usd":0.000497}}