{
  "prompt": {
    "prompt": "Create a fictional dictation of a clinical interaction between a healthcare professional and a patient. \nThis dictation is for testing purposes only and should include various topics that might be discussed in a healthcare setting. \nPlease ensure the material is entirely fictional and does not provide any real medical advice or information. \nPlease ensure variables such as age, weight and history are varied.\nThe clinician should ensure the history and examination findings are incomplete, leaving out some pertinent questions.\nIn response to their history and examination findings, the clinician should  provide management advice and guidance.\nThe clinical scenario should be the following:  \n      \nThe clinical scenario should focus on a patient with Abnormal uterine bleeding.",
    "system_prompt": "Create a fictional dictation of a clinical interaction between a healthcare professional and a patient. \nThis dictation is for testing purposes only and should include various topics that might be discussed in a healthcare setting. \nPlease ensure the material is entirely fictional and does not provide any real medical advice or information. \nPlease ensure variables such as age, weight and history are varied.\nThe clinician should ensure the history and examination findings are incomplete, leaving out some pertinent questions.\nIn response to their history and examination findings, the clinician should  provide management advice and guidance.\nThe clinical scenario should be the following:  \n      \nThe clinical scenario should focus on a patient with Abnormal uterine bleeding."
  },
  "response": "**Dictation: Clinical Interaction – Abnormal Uterine Bleeding**  \n*For testing purposes only. Fictional scenario. Not for clinical use.*  \n\n**Patient Details:**  \n- Name: Jane Doe (fictional)  \n- Age: 42  \n- Gender: Female  \n- Weight: 78 kg  \n- Occupation: Office administrator  \n- Referral: Self-referred for evaluation of abnormal uterine bleeding  \n\n**History of Presenting Complaint:**  \nMs. Doe reports a 4-month history of irregular, heavy menstrual bleeding. She describes episodes of bleeding lasting up to 10 days, with flooding requiring frequent pad changes (every 1–2 hours). She denies intermenstrual bleeding but reports occasional post-coital spotting. She has associated fatigue but denies dizziness, syncope, or significant pain. No history of clotting disorders or bleeding diatheses.  \n\n*Incomplete aspects:*  \n- No detailed menstrual history (e.g., age of menarche, prior regularity).  \n- Contraceptive history not explored (e.g., current or past hormonal use).  \n- Family history of gynecological conditions (e.g., fibroids, endometrial cancer) not elicited.  \n\n**Past Medical History:**  \n- Hypothyroidism (on levothyroxine 75 mcg daily).  \n- No known diabetes or hypertension.  \n- No prior surgeries.  \n\n**Medications:**  \n- Levothyroxine 75 mcg daily.  \n- Occasional ibuprofen for headaches.  \n\n**Examination Findings:**  \n- General: Pale conjunctiva (possible anemia), BMI 28.  \n- Abdominal: Soft, non-tender, no palpable masses.  \n- Pelvic: *Deferred at this visit due to patient preference.*  \n\n*Incomplete aspects:*  \n- No speculum or bimanual exam performed.  \n- Thyroid exam not documented despite history of hypothyroidism.  \n\n**Assessment:**  \n1. **Abnormal uterine bleeding (AUB)** – Likely secondary to ovulatory dysfunction (given age, weight, and thyroid history), though structural causes (e.g., fibroids, polyps) cannot be excluded.  \n2. **Possible iron-deficiency anemia** – Given fatigue and pallor.  \n\n**Management Plan:**  \n1. **Investigations:**  \n   - Full blood count (FBC), ferritin, TSH (given hypothyroidism).  \n   - Pelvic ultrasound to assess for structural pathology.  \n   - *Endometrial biopsy not yet arranged – to consider if ultrasound abnormal or if bleeding persists.*  \n2. **Symptomatic Management:**  \n   - Start tranexamic acid 1 g TDS during heavy bleeding days.  \n   - Consider trial of cyclical progestogens (e.g., norethisterone) if bleeding pattern suggests anovulation.  \n3. **Follow-up:**  \n   - Review in 4 weeks with investigation results.  \n   - Counsel about red flags (e.g., worsening anemia, persistent bleeding).  \n   - *Hormonal contraception options not discussed – to address at next visit.*  \n\n**Clinician’s Note:**  \nIncomplete history and examination limit full assessment. Urgent investigations prioritized. Patient advised to return sooner if symptoms worsen.  \n\n---  \n*End of dictation. This is a fictional example for testing purposes only. No real patient data or medical advice is implied.*",
  "endpoint": "generateFakeClinicalInteraction",
  "timestamp": "2025-05-26T15-39-34",
  "textContent": "AI: DeepSeek (deepseek-chat)\n\nQ: {\n  \"prompt\": \"Create a fictional dictation of a clinical interaction between a healthcare professional and a patient. \\nThis dictation is for testing purposes only and should include various topics that might be discussed in a healthcare setting. \\nPlease ensure the material is entirely fictional and does not provide any real medical advice or information. \\nPlease ensure variables such as age, weight and history are varied.\\nThe clinician should ensure the history and examination findings are incomplete, leaving out some pertinent questions.\\nIn response to their history and examination findings, the clinician should  provide management advice and guidance.\\nThe clinical scenario should be the following:  \\n      \\nThe clinical scenario should focus on a patient with Abnormal uterine bleeding.\",\n  \"system_prompt\": \"Create a fictional dictation of a clinical interaction between a healthcare professional and a patient. \\nThis dictation is for testing purposes only and should include various topics that might be discussed in a healthcare setting. \\nPlease ensure the material is entirely fictional and does not provide any real medical advice or information. \\nPlease ensure variables such as age, weight and history are varied.\\nThe clinician should ensure the history and examination findings are incomplete, leaving out some pertinent questions.\\nIn response to their history and examination findings, the clinician should  provide management advice and guidance.\\nThe clinical scenario should be the following:  \\n      \\nThe clinical scenario should focus on a patient with Abnormal uterine bleeding.\"\n}\n\nA: **Dictation: Clinical Interaction – Abnormal Uterine Bleeding**  \n*For testing purposes only. Fictional scenario. Not for clinical use.*  \n\n**Patient Details:**  \n- Name: Jane Doe (fictional)  \n- Age: 42  \n- Gender: Female  \n- Weight: 78 kg  \n- Occupation: Office administrator  \n- Referral: Self-referred for evaluation of abnormal uterine bleeding  \n\n**History of Presenting Complaint:**  \nMs. Doe reports a 4-month history of irregular, heavy menstrual bleeding. She describes episodes of bleeding lasting up to 10 days, with flooding requiring frequent pad changes (every 1–2 hours). She denies intermenstrual bleeding but reports occasional post-coital spotting. She has associated fatigue but denies dizziness, syncope, or significant pain. No history of clotting disorders or bleeding diatheses.  \n\n*Incomplete aspects:*  \n- No detailed menstrual history (e.g., age of menarche, prior regularity).  \n- Contraceptive history not explored (e.g., current or past hormonal use).  \n- Family history of gynecological conditions (e.g., fibroids, endometrial cancer) not elicited.  \n\n**Past Medical History:**  \n- Hypothyroidism (on levothyroxine 75 mcg daily).  \n- No known diabetes or hypertension.  \n- No prior surgeries.  \n\n**Medications:**  \n- Levothyroxine 75 mcg daily.  \n- Occasional ibuprofen for headaches.  \n\n**Examination Findings:**  \n- General: Pale conjunctiva (possible anemia), BMI 28.  \n- Abdominal: Soft, non-tender, no palpable masses.  \n- Pelvic: *Deferred at this visit due to patient preference.*  \n\n*Incomplete aspects:*  \n- No speculum or bimanual exam performed.  \n- Thyroid exam not documented despite history of hypothyroidism.  \n\n**Assessment:**  \n1. **Abnormal uterine bleeding (AUB)** – Likely secondary to ovulatory dysfunction (given age, weight, and thyroid history), though structural causes (e.g., fibroids, polyps) cannot be excluded.  \n2. **Possible iron-deficiency anemia** – Given fatigue and pallor.  \n\n**Management Plan:**  \n1. **Investigations:**  \n   - Full blood count (FBC), ferritin, TSH (given hypothyroidism).  \n   - Pelvic ultrasound to assess for structural pathology.  \n   - *Endometrial biopsy not yet arranged – to consider if ultrasound abnormal or if bleeding persists.*  \n2. **Symptomatic Management:**  \n   - Start tranexamic acid 1 g TDS during heavy bleeding days.  \n   - Consider trial of cyclical progestogens (e.g., norethisterone) if bleeding pattern suggests anovulation.  \n3. **Follow-up:**  \n   - Review in 4 weeks with investigation results.  \n   - Counsel about red flags (e.g., worsening anemia, persistent bleeding).  \n   - *Hormonal contraception options not discussed – to address at next visit.*  \n\n**Clinician’s Note:**  \nIncomplete history and examination limit full assessment. Urgent investigations prioritized. Patient advised to return sooner if symptoms worsen.  \n\n---  \n*End of dictation. This is a fictional example for testing purposes only. No real patient data or medical advice is implied.*\n\n--- Token Usage Report ---\nPrompt tokens: 136\nCompletion tokens: 683\nTotal tokens: 819\nEstimated cost: $0.000410",
  "ai_provider": "DeepSeek",
  "ai_model": "deepseek-chat",
  "token_usage": {
    "prompt_tokens": 136,
    "completion_tokens": 683,
    "total_tokens": 819,
    "estimated_cost_usd": 0.00040950000000000003
  }
}