{
  "prompt": {
    "prompt": "Please write a concise clinical note using medical terminology, based solely on the clinical transcript provided below. Do not invent or assume any details that are not explicitly mentioned in the transcript.\n\nThe output should be in 3 sectiions.\nThe first section should be a simple summary of the presentation in bullet points, each point on a new line, including age, presenting complaint(s), and if relevant things like previous pregnancies (or lack thereof) and BMI. \nThen there should be a newline, then the middle section should be describe each issue in detail with the appropriate context and the associated advice from the doctor.\nThen there should be a newline, then the plan: first write &#x27;Plan:&#x27; and then, from a new line, a numbered list of the management steps anticipated\n\nRules:\n- Use professional medical terminology.\n- Use one sentence per line.\n- Only include details that are directly mentioned in the transcript\n\nClinical transcript:\n**Dictation: Clinical Interaction – Abnormal Uterine Bleeding**  **Patient Details:**  \n- Name: [Fictional Name] Jane Doe  \n- Age: 36  \n- BMI: 18.9 (weight 52 kg, height 1.65 m)  \n- Gravida: 1, Para: 1 (prior full-term vaginal delivery)  \nLast Menstrual Period (LMP): 2 weeks ago (currently mid-cycle)  \n- Contraception: None currently  **History of Presenting Complaint:**  \nMs. Doe presents with a 4-month history of irregular menstrual bleeding. She reports episodes of heavy bleeding lasting 7–10 days, occurring every 2–3 weeks, with associated fatigue. She denies intermenstrual spotting but admits to occasional cramping. No history of post-coital bleeding. She has not been sexually active in the past year.  **Relevant Medical History:**  \nNo known bleeding disorders or thyroid dysfunction.  \nNo prior gynecological procedures (e.g., hysteroscopy, D&amp;C).  \nNo history of fibroids or endometriosis.  \nNo chronic medical conditions.  **Medications &amp; Allergies:**  \nOccasional ibuprofen for cramps (no regular medications).  \nNo known drug allergies.  **Social History:**  \nNon-smoker, occasional alcohol (1–2 units&#x2F;week).  \nWorks as a teacher; moderate stress levels reported.  **Examination Findings:**  \n- General appearance: Pale conjunctivae (possible anemia).  \n- Abdomen: Soft, non-tender, no palpable masses.  \n- Speculum exam: Cervix appears normal, no visible lesions.  \n- Bimanual exam: Uterus anteverted, normal size, no adnexal tenderness.  **Notable Omissions (for testing purposes):**  \nNo documented assessment of iron studies or hemoglobin.  \nNo inquiry about family history of gynecological malignancies.  \nNo discussion of prior Pap smear history or HPV vaccination status.  \nPelvic ultrasound not yet performed.  **Impression:**  \nAbnormal uterine bleeding (AUB) in a premenopausal patient—differential includes ovulatory dysfunction (e.g., PCOS, thyroid disorder), endometrial polyp, or early perimenopausal changes.  **Management Plan:**  \n1. **Investigations:**  \n   Full blood count (FBC) to assess for anemia.  \n   TSH and prolactin to evaluate endocrine causes.  \n   Pelvic ultrasound to rule out structural pathology.  \n   (No endometrial biopsy arranged at this stage.)  2. **Symptomatic Relief:**  \n   Trial of tranexamic acid during heavy bleeding.  \n   Consider combined oral contraceptive pill (COCP) for cycle regulation if no contraindications.  3. **Follow-Up:**  \n   Review in 6 weeks with investigation results.  \n   If bleeding worsens or anemia confirmed, escalate to gynecology referral.  **Counseling Provided:**  \nReassured that AUB is common but requires evaluation.  \nAdvised to monitor bleeding patterns and report syncope or severe fatigue.  **Dictated by:** Dr. [Fictional Name] Smith  \n**Date:** [Fictional Date]  --*Note: This is a fictional dictation for testing purposes only. No real patient data or medical advice is contained herein.*",
    "system_prompt": "Please write a concise clinical note using medical terminology, based solely on the clinical transcript provided below. Do not invent or assume any details that are not explicitly mentioned in the transcript.\n\nThe output should be in 3 sectiions.\nThe first section should be a simple summary of the presentation in bullet points, each point on a new line, including age, presenting complaint(s), and if relevant things like previous pregnancies (or lack thereof) and BMI. \nThen there should be a newline, then the middle section should be describe each issue in detail with the appropriate context and the associated advice from the doctor.\nThen there should be a newline, then the plan: first write &#x27;Plan:&#x27; and then, from a new line, a numbered list of the management steps anticipated\n\nRules:\n- Use professional medical terminology.\n- Use one sentence per line.\n- Only include details that are directly mentioned in the transcript\n\nClinical transcript:\n**Dictation: Clinical Interaction – Abnormal Uterine Bleeding**  **Patient Details:**  \n- Name: [Fictional Name] Jane Doe  \n- Age: 36  \n- BMI: 18.9 (weight 52 kg, height 1.65 m)  \n- Gravida: 1, Para: 1 (prior full-term vaginal delivery)  \nLast Menstrual Period (LMP): 2 weeks ago (currently mid-cycle)  \n- Contraception: None currently  **History of Presenting Complaint:**  \nMs. Doe presents with a 4-month history of irregular menstrual bleeding. She reports episodes of heavy bleeding lasting 7–10 days, occurring every 2–3 weeks, with associated fatigue. She denies intermenstrual spotting but admits to occasional cramping. No history of post-coital bleeding. She has not been sexually active in the past year.  **Relevant Medical History:**  \nNo known bleeding disorders or thyroid dysfunction.  \nNo prior gynecological procedures (e.g., hysteroscopy, D&amp;C).  \nNo history of fibroids or endometriosis.  \nNo chronic medical conditions.  **Medications &amp; Allergies:**  \nOccasional ibuprofen for cramps (no regular medications).  \nNo known drug allergies.  **Social History:**  \nNon-smoker, occasional alcohol (1–2 units&#x2F;week).  \nWorks as a teacher; moderate stress levels reported.  **Examination Findings:**  \n- General appearance: Pale conjunctivae (possible anemia).  \n- Abdomen: Soft, non-tender, no palpable masses.  \n- Speculum exam: Cervix appears normal, no visible lesions.  \n- Bimanual exam: Uterus anteverted, normal size, no adnexal tenderness.  **Notable Omissions (for testing purposes):**  \nNo documented assessment of iron studies or hemoglobin.  \nNo inquiry about family history of gynecological malignancies.  \nNo discussion of prior Pap smear history or HPV vaccination status.  \nPelvic ultrasound not yet performed.  **Impression:**  \nAbnormal uterine bleeding (AUB) in a premenopausal patient—differential includes ovulatory dysfunction (e.g., PCOS, thyroid disorder), endometrial polyp, or early perimenopausal changes.  **Management Plan:**  \n1. **Investigations:**  \n   Full blood count (FBC) to assess for anemia.  \n   TSH and prolactin to evaluate endocrine causes.  \n   Pelvic ultrasound to rule out structural pathology.  \n   (No endometrial biopsy arranged at this stage.)  2. **Symptomatic Relief:**  \n   Trial of tranexamic acid during heavy bleeding.  \n   Consider combined oral contraceptive pill (COCP) for cycle regulation if no contraindications.  3. **Follow-Up:**  \n   Review in 6 weeks with investigation results.  \n   If bleeding worsens or anemia confirmed, escalate to gynecology referral.  **Counseling Provided:**  \nReassured that AUB is common but requires evaluation.  \nAdvised to monitor bleeding patterns and report syncope or severe fatigue.  **Dictated by:** Dr. [Fictional Name] Smith  \n**Date:** [Fictional Date]  --*Note: This is a fictional dictation for testing purposes only. No real patient data or medical advice is contained herein.*"
  },
  "response": "**Summary:**  \n- 36-year-old female, BMI 18.9.  \n- G1P1, prior full-term vaginal delivery.  \n- Presents with 4-month history of irregular, heavy menstrual bleeding (7–10 days, every 2–3 weeks).  \n- Associated fatigue, occasional cramping, no intermenstrual or post-coital bleeding.  \n- Not sexually active in the past year.  \n- Pale conjunctivae on exam; otherwise unremarkable pelvic exam.  \n\n**Details:**  \n- Irregular bleeding suggests abnormal uterine bleeding (AUB), with differentials including ovulatory dysfunction (e.g., PCOS, thyroid disorder), endometrial polyp, or perimenopausal changes.  \n- Fatigue and pale conjunctivae raise concern for anemia, though iron studies or hemoglobin not yet assessed.  \n- No structural abnormalities on exam, but pelvic ultrasound needed to rule out pathology.  \n- Advised tranexamic acid for symptomatic relief and COCP for cycle regulation if no contraindications.  \n- Reassured patient about commonality of AUB but emphasized need for further evaluation.  \n\n**Plan:**  \n1. Investigations: FBC (anemia), TSH/prolactin (endocrine), pelvic ultrasound (structural).  \n2. Symptomatic relief: Tranexamic acid for heavy bleeding; consider COCP if appropriate.  \n3. Follow-up in 6 weeks with results; escalate to gynecology if worsening bleeding or anemia confirmed.  \n4. Advised monitoring for syncope/severe fatigue.",
  "endpoint": "generateFakeClinicalInteraction",
  "timestamp": "2025-05-29T10-47-08",
  "textContent": "AI: DeepSeek (deepseek-chat)\n\nQ: {\n  \"prompt\": \"Please write a concise clinical note using medical terminology, based solely on the clinical transcript provided below. Do not invent or assume any details that are not explicitly mentioned in the transcript.\\n\\nThe output should be in 3 sectiions.\\nThe first section should be a simple summary of the presentation in bullet points, each point on a new line, including age, presenting complaint(s), and if relevant things like previous pregnancies (or lack thereof) and BMI. \\nThen there should be a newline, then the middle section should be describe each issue in detail with the appropriate context and the associated advice from the doctor.\\nThen there should be a newline, then the plan: first write &#x27;Plan:&#x27; and then, from a new line, a numbered list of the management steps anticipated\\n\\nRules:\\n- Use professional medical terminology.\\n- Use one sentence per line.\\n- Only include details that are directly mentioned in the transcript\\n\\nClinical transcript:\\n**Dictation: Clinical Interaction – Abnormal Uterine Bleeding**  **Patient Details:**  \\n- Name: [Fictional Name] Jane Doe  \\n- Age: 36  \\n- BMI: 18.9 (weight 52 kg, height 1.65 m)  \\n- Gravida: 1, Para: 1 (prior full-term vaginal delivery)  \\nLast Menstrual Period (LMP): 2 weeks ago (currently mid-cycle)  \\n- Contraception: None currently  **History of Presenting Complaint:**  \\nMs. Doe presents with a 4-month history of irregular menstrual bleeding. She reports episodes of heavy bleeding lasting 7–10 days, occurring every 2–3 weeks, with associated fatigue. She denies intermenstrual spotting but admits to occasional cramping. No history of post-coital bleeding. She has not been sexually active in the past year.  **Relevant Medical History:**  \\nNo known bleeding disorders or thyroid dysfunction.  \\nNo prior gynecological procedures (e.g., hysteroscopy, D&amp;C).  \\nNo history of fibroids or endometriosis.  \\nNo chronic medical conditions.  **Medications &amp; Allergies:**  \\nOccasional ibuprofen for cramps (no regular medications).  \\nNo known drug allergies.  **Social History:**  \\nNon-smoker, occasional alcohol (1–2 units&#x2F;week).  \\nWorks as a teacher; moderate stress levels reported.  **Examination Findings:**  \\n- General appearance: Pale conjunctivae (possible anemia).  \\n- Abdomen: Soft, non-tender, no palpable masses.  \\n- Speculum exam: Cervix appears normal, no visible lesions.  \\n- Bimanual exam: Uterus anteverted, normal size, no adnexal tenderness.  **Notable Omissions (for testing purposes):**  \\nNo documented assessment of iron studies or hemoglobin.  \\nNo inquiry about family history of gynecological malignancies.  \\nNo discussion of prior Pap smear history or HPV vaccination status.  \\nPelvic ultrasound not yet performed.  **Impression:**  \\nAbnormal uterine bleeding (AUB) in a premenopausal patient—differential includes ovulatory dysfunction (e.g., PCOS, thyroid disorder), endometrial polyp, or early perimenopausal changes.  **Management Plan:**  \\n1. **Investigations:**  \\n   Full blood count (FBC) to assess for anemia.  \\n   TSH and prolactin to evaluate endocrine causes.  \\n   Pelvic ultrasound to rule out structural pathology.  \\n   (No endometrial biopsy arranged at this stage.)  2. **Symptomatic Relief:**  \\n   Trial of tranexamic acid during heavy bleeding.  \\n   Consider combined oral contraceptive pill (COCP) for cycle regulation if no contraindications.  3. **Follow-Up:**  \\n   Review in 6 weeks with investigation results.  \\n   If bleeding worsens or anemia confirmed, escalate to gynecology referral.  **Counseling Provided:**  \\nReassured that AUB is common but requires evaluation.  \\nAdvised to monitor bleeding patterns and report syncope or severe fatigue.  **Dictated by:** Dr. [Fictional Name] Smith  \\n**Date:** [Fictional Date]  --*Note: This is a fictional dictation for testing purposes only. No real patient data or medical advice is contained herein.*\",\n  \"system_prompt\": \"Please write a concise clinical note using medical terminology, based solely on the clinical transcript provided below. Do not invent or assume any details that are not explicitly mentioned in the transcript.\\n\\nThe output should be in 3 sectiions.\\nThe first section should be a simple summary of the presentation in bullet points, each point on a new line, including age, presenting complaint(s), and if relevant things like previous pregnancies (or lack thereof) and BMI. \\nThen there should be a newline, then the middle section should be describe each issue in detail with the appropriate context and the associated advice from the doctor.\\nThen there should be a newline, then the plan: first write &#x27;Plan:&#x27; and then, from a new line, a numbered list of the management steps anticipated\\n\\nRules:\\n- Use professional medical terminology.\\n- Use one sentence per line.\\n- Only include details that are directly mentioned in the transcript\\n\\nClinical transcript:\\n**Dictation: Clinical Interaction – Abnormal Uterine Bleeding**  **Patient Details:**  \\n- Name: [Fictional Name] Jane Doe  \\n- Age: 36  \\n- BMI: 18.9 (weight 52 kg, height 1.65 m)  \\n- Gravida: 1, Para: 1 (prior full-term vaginal delivery)  \\nLast Menstrual Period (LMP): 2 weeks ago (currently mid-cycle)  \\n- Contraception: None currently  **History of Presenting Complaint:**  \\nMs. Doe presents with a 4-month history of irregular menstrual bleeding. She reports episodes of heavy bleeding lasting 7–10 days, occurring every 2–3 weeks, with associated fatigue. She denies intermenstrual spotting but admits to occasional cramping. No history of post-coital bleeding. She has not been sexually active in the past year.  **Relevant Medical History:**  \\nNo known bleeding disorders or thyroid dysfunction.  \\nNo prior gynecological procedures (e.g., hysteroscopy, D&amp;C).  \\nNo history of fibroids or endometriosis.  \\nNo chronic medical conditions.  **Medications &amp; Allergies:**  \\nOccasional ibuprofen for cramps (no regular medications).  \\nNo known drug allergies.  **Social History:**  \\nNon-smoker, occasional alcohol (1–2 units&#x2F;week).  \\nWorks as a teacher; moderate stress levels reported.  **Examination Findings:**  \\n- General appearance: Pale conjunctivae (possible anemia).  \\n- Abdomen: Soft, non-tender, no palpable masses.  \\n- Speculum exam: Cervix appears normal, no visible lesions.  \\n- Bimanual exam: Uterus anteverted, normal size, no adnexal tenderness.  **Notable Omissions (for testing purposes):**  \\nNo documented assessment of iron studies or hemoglobin.  \\nNo inquiry about family history of gynecological malignancies.  \\nNo discussion of prior Pap smear history or HPV vaccination status.  \\nPelvic ultrasound not yet performed.  **Impression:**  \\nAbnormal uterine bleeding (AUB) in a premenopausal patient—differential includes ovulatory dysfunction (e.g., PCOS, thyroid disorder), endometrial polyp, or early perimenopausal changes.  **Management Plan:**  \\n1. **Investigations:**  \\n   Full blood count (FBC) to assess for anemia.  \\n   TSH and prolactin to evaluate endocrine causes.  \\n   Pelvic ultrasound to rule out structural pathology.  \\n   (No endometrial biopsy arranged at this stage.)  2. **Symptomatic Relief:**  \\n   Trial of tranexamic acid during heavy bleeding.  \\n   Consider combined oral contraceptive pill (COCP) for cycle regulation if no contraindications.  3. **Follow-Up:**  \\n   Review in 6 weeks with investigation results.  \\n   If bleeding worsens or anemia confirmed, escalate to gynecology referral.  **Counseling Provided:**  \\nReassured that AUB is common but requires evaluation.  \\nAdvised to monitor bleeding patterns and report syncope or severe fatigue.  **Dictated by:** Dr. [Fictional Name] Smith  \\n**Date:** [Fictional Date]  --*Note: This is a fictional dictation for testing purposes only. No real patient data or medical advice is contained herein.*\"\n}\n\nA: **Summary:**  \n- 36-year-old female, BMI 18.9.  \n- G1P1, prior full-term vaginal delivery.  \n- Presents with 4-month history of irregular, heavy menstrual bleeding (7–10 days, every 2–3 weeks).  \n- Associated fatigue, occasional cramping, no intermenstrual or post-coital bleeding.  \n- Not sexually active in the past year.  \n- Pale conjunctivae on exam; otherwise unremarkable pelvic exam.  \n\n**Details:**  \n- Irregular bleeding suggests abnormal uterine bleeding (AUB), with differentials including ovulatory dysfunction (e.g., PCOS, thyroid disorder), endometrial polyp, or perimenopausal changes.  \n- Fatigue and pale conjunctivae raise concern for anemia, though iron studies or hemoglobin not yet assessed.  \n- No structural abnormalities on exam, but pelvic ultrasound needed to rule out pathology.  \n- Advised tranexamic acid for symptomatic relief and COCP for cycle regulation if no contraindications.  \n- Reassured patient about commonality of AUB but emphasized need for further evaluation.  \n\n**Plan:**  \n1. Investigations: FBC (anemia), TSH/prolactin (endocrine), pelvic ultrasound (structural).  \n2. Symptomatic relief: Tranexamic acid for heavy bleeding; consider COCP if appropriate.  \n3. Follow-up in 6 weeks with results; escalate to gynecology if worsening bleeding or anemia confirmed.  \n4. Advised monitoring for syncope/severe fatigue.\n\n--- Token Usage Report ---\nPrompt tokens: 884\nCompletion tokens: 311\nTotal tokens: 1195\nEstimated cost: $0.000598",
  "ai_provider": "DeepSeek",
  "ai_model": "deepseek-chat",
  "token_usage": {
    "prompt_tokens": 884,
    "completion_tokens": 311,
    "total_tokens": 1195,
    "estimated_cost_usd": 0.0005975
  }
}