{
  "prompt": {
    "prompt": "Create a fictional dictation of a clinical interaction between a healthcare professional and a patient. \nThis dictation is for testing purposes only and should include various topics that might be discussed in a healthcare setting. \nPlease ensure the material is entirely fictional and does not provide any real medical advice or information. \nPlease ensure variables such as age, weight and history are varied.\nThe clinician should ensure the history and examination findings are incomplete, leaving out some pertinent questions.\nIn response to their history and examination findings, the clinician should  provide management advice and guidance.\nThe clinical scenario should be the following: \n\nMake the age 47, the BMI 22.4 and the number of prior pregnancies 1\n\nBase the clinical scenario on the following gynecology issue: Abnormal uterine bleeding",
    "system_prompt": "Create a fictional dictation of a clinical interaction between a healthcare professional and a patient. \nThis dictation is for testing purposes only and should include various topics that might be discussed in a healthcare setting. \nPlease ensure the material is entirely fictional and does not provide any real medical advice or information. \nPlease ensure variables such as age, weight and history are varied.\nThe clinician should ensure the history and examination findings are incomplete, leaving out some pertinent questions.\nIn response to their history and examination findings, the clinician should  provide management advice and guidance.\nThe clinical scenario should be the following: \n\nMake the age 47, the BMI 22.4 and the number of prior pregnancies 1\n\nBase the clinical scenario on the following gynecology issue: Abnormal uterine bleeding"
  },
  "response": "**Dictation: Clinical Interaction – Abnormal Uterine Bleeding**  \n**Date:** [Fictional Date]  \n**Clinician:** Dr. A. Smith  \n**Patient:** Ms. Jane Doe (Fictional Name)  \n**Age:** 47  \n**BMI:** 22.4  \n**Gravida:** 1, Para: 1  \n\n---\n\n**Subjective:**  \nMs. Doe presents today reporting a 4-month history of abnormal uterine bleeding. She describes episodes of heavy menstrual bleeding lasting 8–10 days, occurring every 2–3 weeks, with associated passage of small clots. She denies intermenstrual bleeding but reports occasional postcoital spotting. She has mild fatigue but no dizziness, syncope, or symptoms of anemia.  \n\nShe has no significant pelvic pain or dyspareunia. Her last Pap smear was 2 years ago (normal). She has no personal or family history of bleeding disorders or gynecologic malignancies. She is sexually active with one partner and uses condoms inconsistently for contraception. She has one prior full-term vaginal delivery without complications.  \n\n*Incomplete history:*  \n- No documentation of prior contraceptive use (e.g., hormonal methods).  \n- No inquiry about weight changes, hirsutism, or acne (to assess for PCOS).  \n- Thyroid symptoms (e.g., heat/cold intolerance, hair loss) not explored.  \n- Medications/supplements not reviewed (e.g., NSAIDs, anticoagulants).  \n\n**Objective:**  \n- Vitals: BP 118/76, HR 72, afebrile.  \n- BMI: 22.4 (normal range).  \n- Abdomen: Soft, non-tender, no masses.  \n- Pelvic exam: Cervix appears normal; no visible lesions. Uterus midline, normal size, no adnexal tenderness.  \n- *Incomplete exam:* No speculum exam performed today to evaluate for cervical polyps/lesions.  \n\n**Assessment:**  \n47-year-old woman with abnormal uterine bleeding (likely AUB-O given age and pattern, but structural causes like polyps or fibroids not excluded). Differential includes perimenopausal hormonal changes, endometrial hyperplasia, or thyroid dysfunction.  \n\n**Plan:**  \n1. **Diagnostics:**  \n   - Pelvic ultrasound to assess for fibroids/polyps/endometrial thickness.  \n   - CBC to evaluate for anemia (despite no overt symptoms).  \n   - TSH to rule out thyroid dysfunction.  \n   - *Missing:* Endometrial biopsy (highly recommended in age >45 with AUB).  \n\n2. **Management:**  \n   - Start empiric tranexamic acid for heavy bleeding (no contraindications per history).  \n   - Consider trial of low-dose combined oral contraceptive pill if no HTN/smoking (not yet discussed with patient).  \n   - Advise iron supplementation if CBC confirms anemia.  \n\n3. **Follow-up:**  \n   - Return in 4 weeks for results and reassessment.  \n   - Counsel on urgency if bleeding worsens (e.g., soaking pad hourly).  \n\n**Patient Instructions:**  \nMs. Doe verbalized understanding and will schedule ultrasound/labs. No questions at this time.  \n\n---  \n**Note:** This is a fictional dictation for testing purposes only. No real medical advice is implied. Pertinent gaps intentionally left for educational reflection.  \n\n---  \nWould you like any modifications to the scenario or additional omissions?",
  "endpoint": "newFunctionName",
  "timestamp": "2025-05-11T06-53-30",
  "textContent": "AI: DeepSeek (deepseek-chat)\n\nQ: {\n  \"prompt\": \"Create a fictional dictation of a clinical interaction between a healthcare professional and a patient. \\nThis dictation is for testing purposes only and should include various topics that might be discussed in a healthcare setting. \\nPlease ensure the material is entirely fictional and does not provide any real medical advice or information. \\nPlease ensure variables such as age, weight and history are varied.\\nThe clinician should ensure the history and examination findings are incomplete, leaving out some pertinent questions.\\nIn response to their history and examination findings, the clinician should  provide management advice and guidance.\\nThe clinical scenario should be the following: \\n\\nMake the age 47, the BMI 22.4 and the number of prior pregnancies 1\\n\\nBase the clinical scenario on the following gynecology issue: Abnormal uterine bleeding\",\n  \"system_prompt\": \"Create a fictional dictation of a clinical interaction between a healthcare professional and a patient. \\nThis dictation is for testing purposes only and should include various topics that might be discussed in a healthcare setting. \\nPlease ensure the material is entirely fictional and does not provide any real medical advice or information. \\nPlease ensure variables such as age, weight and history are varied.\\nThe clinician should ensure the history and examination findings are incomplete, leaving out some pertinent questions.\\nIn response to their history and examination findings, the clinician should  provide management advice and guidance.\\nThe clinical scenario should be the following: \\n\\nMake the age 47, the BMI 22.4 and the number of prior pregnancies 1\\n\\nBase the clinical scenario on the following gynecology issue: Abnormal uterine bleeding\"\n}\n\nA: **Dictation: Clinical Interaction – Abnormal Uterine Bleeding**  \n**Date:** [Fictional Date]  \n**Clinician:** Dr. A. Smith  \n**Patient:** Ms. Jane Doe (Fictional Name)  \n**Age:** 47  \n**BMI:** 22.4  \n**Gravida:** 1, Para: 1  \n\n---\n\n**Subjective:**  \nMs. Doe presents today reporting a 4-month history of abnormal uterine bleeding. She describes episodes of heavy menstrual bleeding lasting 8–10 days, occurring every 2–3 weeks, with associated passage of small clots. She denies intermenstrual bleeding but reports occasional postcoital spotting. She has mild fatigue but no dizziness, syncope, or symptoms of anemia.  \n\nShe has no significant pelvic pain or dyspareunia. Her last Pap smear was 2 years ago (normal). She has no personal or family history of bleeding disorders or gynecologic malignancies. She is sexually active with one partner and uses condoms inconsistently for contraception. She has one prior full-term vaginal delivery without complications.  \n\n*Incomplete history:*  \n- No documentation of prior contraceptive use (e.g., hormonal methods).  \n- No inquiry about weight changes, hirsutism, or acne (to assess for PCOS).  \n- Thyroid symptoms (e.g., heat/cold intolerance, hair loss) not explored.  \n- Medications/supplements not reviewed (e.g., NSAIDs, anticoagulants).  \n\n**Objective:**  \n- Vitals: BP 118/76, HR 72, afebrile.  \n- BMI: 22.4 (normal range).  \n- Abdomen: Soft, non-tender, no masses.  \n- Pelvic exam: Cervix appears normal; no visible lesions. Uterus midline, normal size, no adnexal tenderness.  \n- *Incomplete exam:* No speculum exam performed today to evaluate for cervical polyps/lesions.  \n\n**Assessment:**  \n47-year-old woman with abnormal uterine bleeding (likely AUB-O given age and pattern, but structural causes like polyps or fibroids not excluded). Differential includes perimenopausal hormonal changes, endometrial hyperplasia, or thyroid dysfunction.  \n\n**Plan:**  \n1. **Diagnostics:**  \n   - Pelvic ultrasound to assess for fibroids/polyps/endometrial thickness.  \n   - CBC to evaluate for anemia (despite no overt symptoms).  \n   - TSH to rule out thyroid dysfunction.  \n   - *Missing:* Endometrial biopsy (highly recommended in age >45 with AUB).  \n\n2. **Management:**  \n   - Start empiric tranexamic acid for heavy bleeding (no contraindications per history).  \n   - Consider trial of low-dose combined oral contraceptive pill if no HTN/smoking (not yet discussed with patient).  \n   - Advise iron supplementation if CBC confirms anemia.  \n\n3. **Follow-up:**  \n   - Return in 4 weeks for results and reassessment.  \n   - Counsel on urgency if bleeding worsens (e.g., soaking pad hourly).  \n\n**Patient Instructions:**  \nMs. Doe verbalized understanding and will schedule ultrasound/labs. No questions at this time.  \n\n---  \n**Note:** This is a fictional dictation for testing purposes only. No real medical advice is implied. Pertinent gaps intentionally left for educational reflection.  \n\n---  \nWould you like any modifications to the scenario or additional omissions?\n\n--- Token Usage Report ---\nPrompt tokens: 158\nCompletion tokens: 708\nTotal tokens: 866\nEstimated cost: $0.000433",
  "ai_provider": "DeepSeek",
  "ai_model": "deepseek-chat",
  "token_usage": {
    "prompt_tokens": 158,
    "completion_tokens": 708,
    "total_tokens": 866,
    "estimated_cost_usd": 0.000433
  }
}