{
  "prompt": {
    "prompt": "Please write a concise clinical note using medical terminology, based solely on the clinical transcript provided below. Do not invent or assume any details that are not explicitly mentioned in the transcript.\n\nThe output should be in 3 sectiions.\nThe first section should be a simple summary of the presentation in bullet points, each point on a new line, including age, presenting complaint(s), and if relevant things like previous pregnancies (or lack thereof) and BMI. \nThen there should be a newline, then the middle section should be describe each issue in detail with the appropriate context and the associated advice from the doctor.\nThen there should be a newline, then the plan: first write &#x27;Plan:&#x27; and then, from a new line, a numbered list of the management steps anticipated\n\nRules:\n- Use professional medical terminology.\n- Use one sentence per line.\n- Only include details that are directly mentioned in the transcript\n\nClinical transcript:\n&lt;textarea class=&quot;fallback-editor&quot; placeholder=&quot;Enter transcript here...&quot; style=&quot;width: 100%; height: 100%; min-height: 200px; box-sizing: border-box; padding: 10px; border: 1px solid rgb(204, 204, 204); border-radius: 4px; resize: vertical;&quot;&gt;&lt;&#x2F;textarea&gt;",
    "system_prompt": "Please write a concise clinical note using medical terminology, based solely on the clinical transcript provided below. Do not invent or assume any details that are not explicitly mentioned in the transcript.\n\nThe output should be in 3 sectiions.\nThe first section should be a simple summary of the presentation in bullet points, each point on a new line, including age, presenting complaint(s), and if relevant things like previous pregnancies (or lack thereof) and BMI. \nThen there should be a newline, then the middle section should be describe each issue in detail with the appropriate context and the associated advice from the doctor.\nThen there should be a newline, then the plan: first write &#x27;Plan:&#x27; and then, from a new line, a numbered list of the management steps anticipated\n\nRules:\n- Use professional medical terminology.\n- Use one sentence per line.\n- Only include details that are directly mentioned in the transcript\n\nClinical transcript:\n&lt;textarea class=&quot;fallback-editor&quot; placeholder=&quot;Enter transcript here...&quot; style=&quot;width: 100%; height: 100%; min-height: 200px; box-sizing: border-box; padding: 10px; border: 1px solid rgb(204, 204, 204); border-radius: 4px; resize: vertical;&quot;&gt;&lt;&#x2F;textarea&gt;"
  },
  "response": "Since the clinical transcript was not provided in your message, I cannot generate a clinical note. Please provide the transcript, and I will create a structured note following your requested format.  \n\nFor reference, here is the general structure I will follow once the transcript is provided:  \n\n---  \n**Summary:**  \n- Age: [if mentioned]  \n- Presenting complaint(s): [list]  \n- Gravida/Para: [if mentioned]  \n- BMI: [if mentioned]  \n\n**Details:**  \n[Detailed description of each issue and associated advice, strictly based on the transcript.]  \n\n**Plan:**  \n1. [First management step]  \n2. [Second management step]  \n...  \n\n---  \n\nPlease share the transcript, and I will generate the note accordingly.",
  "endpoint": "generateFakeClinicalInteraction",
  "timestamp": "2025-05-27T14-43-58",
  "textContent": "AI: DeepSeek (deepseek-chat)\n\nQ: {\n  \"prompt\": \"Please write a concise clinical note using medical terminology, based solely on the clinical transcript provided below. Do not invent or assume any details that are not explicitly mentioned in the transcript.\\n\\nThe output should be in 3 sectiions.\\nThe first section should be a simple summary of the presentation in bullet points, each point on a new line, including age, presenting complaint(s), and if relevant things like previous pregnancies (or lack thereof) and BMI. \\nThen there should be a newline, then the middle section should be describe each issue in detail with the appropriate context and the associated advice from the doctor.\\nThen there should be a newline, then the plan: first write &#x27;Plan:&#x27; and then, from a new line, a numbered list of the management steps anticipated\\n\\nRules:\\n- Use professional medical terminology.\\n- Use one sentence per line.\\n- Only include details that are directly mentioned in the transcript\\n\\nClinical transcript:\\n&lt;textarea class=&quot;fallback-editor&quot; placeholder=&quot;Enter transcript here...&quot; style=&quot;width: 100%; height: 100%; min-height: 200px; box-sizing: border-box; padding: 10px; border: 1px solid rgb(204, 204, 204); border-radius: 4px; resize: vertical;&quot;&gt;&lt;&#x2F;textarea&gt;\",\n  \"system_prompt\": \"Please write a concise clinical note using medical terminology, based solely on the clinical transcript provided below. Do not invent or assume any details that are not explicitly mentioned in the transcript.\\n\\nThe output should be in 3 sectiions.\\nThe first section should be a simple summary of the presentation in bullet points, each point on a new line, including age, presenting complaint(s), and if relevant things like previous pregnancies (or lack thereof) and BMI. \\nThen there should be a newline, then the middle section should be describe each issue in detail with the appropriate context and the associated advice from the doctor.\\nThen there should be a newline, then the plan: first write &#x27;Plan:&#x27; and then, from a new line, a numbered list of the management steps anticipated\\n\\nRules:\\n- Use professional medical terminology.\\n- Use one sentence per line.\\n- Only include details that are directly mentioned in the transcript\\n\\nClinical transcript:\\n&lt;textarea class=&quot;fallback-editor&quot; placeholder=&quot;Enter transcript here...&quot; style=&quot;width: 100%; height: 100%; min-height: 200px; box-sizing: border-box; padding: 10px; border: 1px solid rgb(204, 204, 204); border-radius: 4px; resize: vertical;&quot;&gt;&lt;&#x2F;textarea&gt;\"\n}\n\nA: Since the clinical transcript was not provided in your message, I cannot generate a clinical note. Please provide the transcript, and I will create a structured note following your requested format.  \n\nFor reference, here is the general structure I will follow once the transcript is provided:  \n\n---  \n**Summary:**  \n- Age: [if mentioned]  \n- Presenting complaint(s): [list]  \n- Gravida/Para: [if mentioned]  \n- BMI: [if mentioned]  \n\n**Details:**  \n[Detailed description of each issue and associated advice, strictly based on the transcript.]  \n\n**Plan:**  \n1. [First management step]  \n2. [Second management step]  \n...  \n\n---  \n\nPlease share the transcript, and I will generate the note accordingly.\n\n--- Token Usage Report ---\nPrompt tokens: 294\nCompletion tokens: 155\nTotal tokens: 449\nEstimated cost: $0.000224",
  "ai_provider": "DeepSeek",
  "ai_model": "deepseek-chat",
  "token_usage": {
    "prompt_tokens": 294,
    "completion_tokens": 155,
    "total_tokens": 449,
    "estimated_cost_usd": 0.00022449999999999998
  }
}