{
  "prompt": {
    "prompt": "Create a fictional dictation of a clinical interaction between a healthcare professional and a patient. \nThis dictation is for testing purposes only and should include various topics that might be discussed in a healthcare setting. \nPlease ensure the material is entirely fictional and does not provide any real medical advice or information. \nPlease ensure variables such as age, weight and history are varied.\nThe clinician should ensure the history and examination findings are incomplete, leaving out some pertinent questions.\nIn response to their history and examination findings, the clinician should  provide management advice and guidance.\nThe clinical scenario should be the following:  \n      \nThe clinical scenario should focus on a patient with Bacterial vaginosis.",
    "system_prompt": "Create a fictional dictation of a clinical interaction between a healthcare professional and a patient. \nThis dictation is for testing purposes only and should include various topics that might be discussed in a healthcare setting. \nPlease ensure the material is entirely fictional and does not provide any real medical advice or information. \nPlease ensure variables such as age, weight and history are varied.\nThe clinician should ensure the history and examination findings are incomplete, leaving out some pertinent questions.\nIn response to their history and examination findings, the clinician should  provide management advice and guidance.\nThe clinical scenario should be the following:  \n      \nThe clinical scenario should focus on a patient with Bacterial vaginosis."
  },
  "response": "**Fictional Clinical Dictation – Testing Purposes Only**  \n\n**Patient Name:** Jane Doe  \n**Age:** 32 years  \n**Sex:** Female  \n**Weight:** 68 kg  \n**Date of Visit:** October 10, 2023  \n**Clinician:** Dr. Smith  \n\n### **Subjective:**  \nMs. Doe presents today reporting a 2-week history of abnormal vaginal discharge. She describes the discharge as thin, grayish-white, and with a noticeable \"fishy\" odor, particularly after intercourse. She denies any associated itching, burning, or dysuria. She has had no recent fever, abdominal pain, or urinary symptoms.  \n\n**Sexual History:** Sexually active with one male partner in the last 6 months. Uses condoms inconsistently. No history of STIs. Last Pap smear was 2 years ago, reportedly normal.  \n\n**Past Medical History:** No significant medical conditions. No prior episodes of vaginitis.  \n\n**Medications:** Oral contraceptive pill (no recent changes). No recent antibiotic use.  \n\n**Allergies:** NKDA  \n\n**Social History:** Non-smoker, occasional alcohol. Works as a teacher.  \n\n*(Missing Pertinent Questions: No inquiry about recent douching, new soaps/body washes, or partner symptoms. No detailed menstrual history.)*  \n\n### **Objective:**  \n**Vital Signs:** BP 118/72, HR 72, Temp 36.8°C, RR 14.  \n\n**Genitourinary Exam:**  \n- External genitalia: No erythema, lesions, or swelling.  \n- Vaginal discharge: Thin, homogenous, grayish-white, adherent to vaginal walls. Mild \"fishy\" odor noted on speculum exam.  \n- Cervix: No erythema, no friability. No cervical motion tenderness on bimanual exam.  \n- No vulvar or vaginal erythema or excoriations.  \n\n*(Missing Pertinent Findings: No pH testing or whiff test performed. No microscopy or wet prep ordered.)*  \n\n### **Assessment:**  \n**Working Diagnosis:** Bacterial vaginosis (based on clinical presentation—Amsel criteria not fully assessed).  \n\n### **Plan:**  \n1. **Empiric Treatment:** Given the characteristic discharge and odor, will treat empirically for bacterial vaginosis.  \n   - **Metronidazole 500 mg PO BID x 7 days** (alternative: vaginal clindamycin cream if preferred).  \n2. **Counseling:**  \n   - Avoid douching and scented soaps.  \n   - Use condoms consistently to reduce risk of recurrence.  \n   - Return if symptoms persist or worsen.  \n3. **Follow-Up:** No routine follow-up needed if symptoms resolve. If recurrent BV (>3 episodes/year), consider further workup.  \n\n*(Missing Pertinent Guidance: No discussion of partner treatment, no recommendation for STI screening despite inconsistent condom use.)*  \n\n**Dictated by:** Dr. Smith  \n**Date:** October 10, 2023  \n\n---  \n**Note:** This is a fictional dictation for testing purposes only. No real medical advice is provided. Patient details are entirely fabricated.",
  "endpoint": "generateFakeClinicalInteraction",
  "timestamp": "2025-05-26T16-01-18",
  "textContent": "AI: DeepSeek (deepseek-chat)\n\nQ: {\n  \"prompt\": \"Create a fictional dictation of a clinical interaction between a healthcare professional and a patient. \\nThis dictation is for testing purposes only and should include various topics that might be discussed in a healthcare setting. \\nPlease ensure the material is entirely fictional and does not provide any real medical advice or information. \\nPlease ensure variables such as age, weight and history are varied.\\nThe clinician should ensure the history and examination findings are incomplete, leaving out some pertinent questions.\\nIn response to their history and examination findings, the clinician should  provide management advice and guidance.\\nThe clinical scenario should be the following:  \\n      \\nThe clinical scenario should focus on a patient with Bacterial vaginosis.\",\n  \"system_prompt\": \"Create a fictional dictation of a clinical interaction between a healthcare professional and a patient. \\nThis dictation is for testing purposes only and should include various topics that might be discussed in a healthcare setting. \\nPlease ensure the material is entirely fictional and does not provide any real medical advice or information. \\nPlease ensure variables such as age, weight and history are varied.\\nThe clinician should ensure the history and examination findings are incomplete, leaving out some pertinent questions.\\nIn response to their history and examination findings, the clinician should  provide management advice and guidance.\\nThe clinical scenario should be the following:  \\n      \\nThe clinical scenario should focus on a patient with Bacterial vaginosis.\"\n}\n\nA: **Fictional Clinical Dictation – Testing Purposes Only**  \n\n**Patient Name:** Jane Doe  \n**Age:** 32 years  \n**Sex:** Female  \n**Weight:** 68 kg  \n**Date of Visit:** October 10, 2023  \n**Clinician:** Dr. Smith  \n\n### **Subjective:**  \nMs. Doe presents today reporting a 2-week history of abnormal vaginal discharge. She describes the discharge as thin, grayish-white, and with a noticeable \"fishy\" odor, particularly after intercourse. She denies any associated itching, burning, or dysuria. She has had no recent fever, abdominal pain, or urinary symptoms.  \n\n**Sexual History:** Sexually active with one male partner in the last 6 months. Uses condoms inconsistently. No history of STIs. Last Pap smear was 2 years ago, reportedly normal.  \n\n**Past Medical History:** No significant medical conditions. No prior episodes of vaginitis.  \n\n**Medications:** Oral contraceptive pill (no recent changes). No recent antibiotic use.  \n\n**Allergies:** NKDA  \n\n**Social History:** Non-smoker, occasional alcohol. Works as a teacher.  \n\n*(Missing Pertinent Questions: No inquiry about recent douching, new soaps/body washes, or partner symptoms. No detailed menstrual history.)*  \n\n### **Objective:**  \n**Vital Signs:** BP 118/72, HR 72, Temp 36.8°C, RR 14.  \n\n**Genitourinary Exam:**  \n- External genitalia: No erythema, lesions, or swelling.  \n- Vaginal discharge: Thin, homogenous, grayish-white, adherent to vaginal walls. Mild \"fishy\" odor noted on speculum exam.  \n- Cervix: No erythema, no friability. No cervical motion tenderness on bimanual exam.  \n- No vulvar or vaginal erythema or excoriations.  \n\n*(Missing Pertinent Findings: No pH testing or whiff test performed. No microscopy or wet prep ordered.)*  \n\n### **Assessment:**  \n**Working Diagnosis:** Bacterial vaginosis (based on clinical presentation—Amsel criteria not fully assessed).  \n\n### **Plan:**  \n1. **Empiric Treatment:** Given the characteristic discharge and odor, will treat empirically for bacterial vaginosis.  \n   - **Metronidazole 500 mg PO BID x 7 days** (alternative: vaginal clindamycin cream if preferred).  \n2. **Counseling:**  \n   - Avoid douching and scented soaps.  \n   - Use condoms consistently to reduce risk of recurrence.  \n   - Return if symptoms persist or worsen.  \n3. **Follow-Up:** No routine follow-up needed if symptoms resolve. If recurrent BV (>3 episodes/year), consider further workup.  \n\n*(Missing Pertinent Guidance: No discussion of partner treatment, no recommendation for STI screening despite inconsistent condom use.)*  \n\n**Dictated by:** Dr. Smith  \n**Date:** October 10, 2023  \n\n---  \n**Note:** This is a fictional dictation for testing purposes only. No real medical advice is provided. Patient details are entirely fabricated.\n\n--- Token Usage Report ---\nPrompt tokens: 137\nCompletion tokens: 653\nTotal tokens: 790\nEstimated cost: $0.000395",
  "ai_provider": "DeepSeek",
  "ai_model": "deepseek-chat",
  "token_usage": {
    "prompt_tokens": 137,
    "completion_tokens": 653,
    "total_tokens": 790,
    "estimated_cost_usd": 0.00039500000000000006
  }
}