{
  "prompt": {
    "prompt": "Please write a concise clinical note using medical terminology, based solely on the clinical transcript provided below. Do not invent or assume any details that are not explicitly mentioned in the transcript.\n\nThe output should be in 3 sectiions.\nThe first section should be a simple summary of the presentation in bullet points, each point on a new line, including age, presenting complaint(s), and if relevant things like previous pregnancies (or lack thereof) and BMI. \nThen there should be a newline, then the middle section should be describe each issue in detail with the appropriate context and the associated advice from the doctor.\nThen there should be a newline, then the plan: first write &#x27;Plan:&#x27; and then, from a new line, a numbered list of the management steps anticipated\n\nRules:\n- Use professional medical terminology.\n- Use one sentence per line.\n- Only include details that are directly mentioned in the transcript\n\nClinical transcript:\nSummary:\n\n36-year-old female, BMI 18.9.\nG1P1, prior full-term vaginal delivery.\nPresents with 4-month history of irregular, heavy menstrual bleeding (7–10 days, every 2–3 weeks).\nAssociated fatigue, occasional cramping, no intermenstrual or post-coital bleeding.\nNot sexually active in the past year.\nPale conjunctivae on exam; otherwise unremarkable pelvic exam.\nDetails:\n\nIrregular bleeding suggests abnormal uterine bleeding (AUB), with differentials including ovulatory dysfunction (e.g., PCOS, thyroid disorder), endometrial polyp, or perimenopausal changes.\nFatigue and pale conjunctivae raise concern for anemia, though iron studies or hemoglobin not yet assessed.\nNo structural abnormalities on exam, but pelvic ultrasound needed to rule out pathology.\nAdvised tranexamic acid for symptomatic relief and COCP for cycle regulation if no contraindications.\nReassured patient about commonality of AUB but emphasized need for further evaluation.\nPlan:\n\nInvestigations: FBC (anemia), TSH&#x2F;prolactin (endocrine), pelvic ultrasound (structural).\nSymptomatic relief: Tranexamic acid for heavy bleeding; consider COCP if appropriate.\nFollow-up in 6 weeks with results; escalate to gynecology if worsening bleeding or anemia confirmed.\nAdvised monitoring for syncope&#x2F;severe fatigue.",
    "system_prompt": "Please write a concise clinical note using medical terminology, based solely on the clinical transcript provided below. Do not invent or assume any details that are not explicitly mentioned in the transcript.\n\nThe output should be in 3 sectiions.\nThe first section should be a simple summary of the presentation in bullet points, each point on a new line, including age, presenting complaint(s), and if relevant things like previous pregnancies (or lack thereof) and BMI. \nThen there should be a newline, then the middle section should be describe each issue in detail with the appropriate context and the associated advice from the doctor.\nThen there should be a newline, then the plan: first write &#x27;Plan:&#x27; and then, from a new line, a numbered list of the management steps anticipated\n\nRules:\n- Use professional medical terminology.\n- Use one sentence per line.\n- Only include details that are directly mentioned in the transcript\n\nClinical transcript:\nSummary:\n\n36-year-old female, BMI 18.9.\nG1P1, prior full-term vaginal delivery.\nPresents with 4-month history of irregular, heavy menstrual bleeding (7–10 days, every 2–3 weeks).\nAssociated fatigue, occasional cramping, no intermenstrual or post-coital bleeding.\nNot sexually active in the past year.\nPale conjunctivae on exam; otherwise unremarkable pelvic exam.\nDetails:\n\nIrregular bleeding suggests abnormal uterine bleeding (AUB), with differentials including ovulatory dysfunction (e.g., PCOS, thyroid disorder), endometrial polyp, or perimenopausal changes.\nFatigue and pale conjunctivae raise concern for anemia, though iron studies or hemoglobin not yet assessed.\nNo structural abnormalities on exam, but pelvic ultrasound needed to rule out pathology.\nAdvised tranexamic acid for symptomatic relief and COCP for cycle regulation if no contraindications.\nReassured patient about commonality of AUB but emphasized need for further evaluation.\nPlan:\n\nInvestigations: FBC (anemia), TSH&#x2F;prolactin (endocrine), pelvic ultrasound (structural).\nSymptomatic relief: Tranexamic acid for heavy bleeding; consider COCP if appropriate.\nFollow-up in 6 weeks with results; escalate to gynecology if worsening bleeding or anemia confirmed.\nAdvised monitoring for syncope&#x2F;severe fatigue."
  },
  "response": "### Summary:  \n- 36-year-old female, BMI 18.9.  \n- G1P1, prior full-term vaginal delivery.  \n- Presents with 4-month history of irregular, heavy menstrual bleeding (7–10 days, every 2–3 weeks).  \n- Associated fatigue, occasional cramping.  \n- No intermenstrual or post-coital bleeding.  \n- Not sexually active in the past year.  \n- Pale conjunctivae on exam; otherwise unremarkable pelvic exam.  \n\n### Details:  \n- Irregular bleeding pattern consistent with abnormal uterine bleeding (AUB), with differentials including ovulatory dysfunction (e.g., PCOS, thyroid disorder), endometrial polyp, or perimenopausal changes.  \n- Fatigue and pale conjunctivae suggest possible anemia, though iron studies or hemoglobin levels were not assessed.  \n- No structural abnormalities noted on pelvic exam, but pelvic ultrasound is required to exclude underlying pathology.  \n- Tranexamic acid was advised for symptomatic relief of heavy bleeding.  \n- Combined oral contraceptive pill (COCP) was suggested for cycle regulation if no contraindications exist.  \n- Patient reassured about the commonality of AUB but advised on the necessity of further evaluation.  \n\n### Plan:  \nPlan:  \n1. Investigations:  \n   - Full blood count (FBC) to assess for anemia.  \n   - TSH and prolactin levels to evaluate endocrine causes.  \n   - Pelvic ultrasound to rule out structural abnormalities.  \n2. Symptomatic relief:  \n   - Tranexamic acid for heavy menstrual bleeding.  \n   - Consider COCP for cycle regulation if appropriate.  \n3. Follow-up in 6 weeks with results; escalate to gynecology if bleeding worsens or anemia is confirmed.  \n4. Advised to monitor for syncope or severe fatigue.",
  "endpoint": "generateFakeClinicalInteraction",
  "timestamp": "2025-05-29T10-56-03",
  "textContent": "AI: DeepSeek (deepseek-chat)\n\nQ: {\n  \"prompt\": \"Please write a concise clinical note using medical terminology, based solely on the clinical transcript provided below. Do not invent or assume any details that are not explicitly mentioned in the transcript.\\n\\nThe output should be in 3 sectiions.\\nThe first section should be a simple summary of the presentation in bullet points, each point on a new line, including age, presenting complaint(s), and if relevant things like previous pregnancies (or lack thereof) and BMI. \\nThen there should be a newline, then the middle section should be describe each issue in detail with the appropriate context and the associated advice from the doctor.\\nThen there should be a newline, then the plan: first write &#x27;Plan:&#x27; and then, from a new line, a numbered list of the management steps anticipated\\n\\nRules:\\n- Use professional medical terminology.\\n- Use one sentence per line.\\n- Only include details that are directly mentioned in the transcript\\n\\nClinical transcript:\\nSummary:\\n\\n36-year-old female, BMI 18.9.\\nG1P1, prior full-term vaginal delivery.\\nPresents with 4-month history of irregular, heavy menstrual bleeding (7–10 days, every 2–3 weeks).\\nAssociated fatigue, occasional cramping, no intermenstrual or post-coital bleeding.\\nNot sexually active in the past year.\\nPale conjunctivae on exam; otherwise unremarkable pelvic exam.\\nDetails:\\n\\nIrregular bleeding suggests abnormal uterine bleeding (AUB), with differentials including ovulatory dysfunction (e.g., PCOS, thyroid disorder), endometrial polyp, or perimenopausal changes.\\nFatigue and pale conjunctivae raise concern for anemia, though iron studies or hemoglobin not yet assessed.\\nNo structural abnormalities on exam, but pelvic ultrasound needed to rule out pathology.\\nAdvised tranexamic acid for symptomatic relief and COCP for cycle regulation if no contraindications.\\nReassured patient about commonality of AUB but emphasized need for further evaluation.\\nPlan:\\n\\nInvestigations: FBC (anemia), TSH&#x2F;prolactin (endocrine), pelvic ultrasound (structural).\\nSymptomatic relief: Tranexamic acid for heavy bleeding; consider COCP if appropriate.\\nFollow-up in 6 weeks with results; escalate to gynecology if worsening bleeding or anemia confirmed.\\nAdvised monitoring for syncope&#x2F;severe fatigue.\",\n  \"system_prompt\": \"Please write a concise clinical note using medical terminology, based solely on the clinical transcript provided below. Do not invent or assume any details that are not explicitly mentioned in the transcript.\\n\\nThe output should be in 3 sectiions.\\nThe first section should be a simple summary of the presentation in bullet points, each point on a new line, including age, presenting complaint(s), and if relevant things like previous pregnancies (or lack thereof) and BMI. \\nThen there should be a newline, then the middle section should be describe each issue in detail with the appropriate context and the associated advice from the doctor.\\nThen there should be a newline, then the plan: first write &#x27;Plan:&#x27; and then, from a new line, a numbered list of the management steps anticipated\\n\\nRules:\\n- Use professional medical terminology.\\n- Use one sentence per line.\\n- Only include details that are directly mentioned in the transcript\\n\\nClinical transcript:\\nSummary:\\n\\n36-year-old female, BMI 18.9.\\nG1P1, prior full-term vaginal delivery.\\nPresents with 4-month history of irregular, heavy menstrual bleeding (7–10 days, every 2–3 weeks).\\nAssociated fatigue, occasional cramping, no intermenstrual or post-coital bleeding.\\nNot sexually active in the past year.\\nPale conjunctivae on exam; otherwise unremarkable pelvic exam.\\nDetails:\\n\\nIrregular bleeding suggests abnormal uterine bleeding (AUB), with differentials including ovulatory dysfunction (e.g., PCOS, thyroid disorder), endometrial polyp, or perimenopausal changes.\\nFatigue and pale conjunctivae raise concern for anemia, though iron studies or hemoglobin not yet assessed.\\nNo structural abnormalities on exam, but pelvic ultrasound needed to rule out pathology.\\nAdvised tranexamic acid for symptomatic relief and COCP for cycle regulation if no contraindications.\\nReassured patient about commonality of AUB but emphasized need for further evaluation.\\nPlan:\\n\\nInvestigations: FBC (anemia), TSH&#x2F;prolactin (endocrine), pelvic ultrasound (structural).\\nSymptomatic relief: Tranexamic acid for heavy bleeding; consider COCP if appropriate.\\nFollow-up in 6 weeks with results; escalate to gynecology if worsening bleeding or anemia confirmed.\\nAdvised monitoring for syncope&#x2F;severe fatigue.\"\n}\n\nA: ### Summary:  \n- 36-year-old female, BMI 18.9.  \n- G1P1, prior full-term vaginal delivery.  \n- Presents with 4-month history of irregular, heavy menstrual bleeding (7–10 days, every 2–3 weeks).  \n- Associated fatigue, occasional cramping.  \n- No intermenstrual or post-coital bleeding.  \n- Not sexually active in the past year.  \n- Pale conjunctivae on exam; otherwise unremarkable pelvic exam.  \n\n### Details:  \n- Irregular bleeding pattern consistent with abnormal uterine bleeding (AUB), with differentials including ovulatory dysfunction (e.g., PCOS, thyroid disorder), endometrial polyp, or perimenopausal changes.  \n- Fatigue and pale conjunctivae suggest possible anemia, though iron studies or hemoglobin levels were not assessed.  \n- No structural abnormalities noted on pelvic exam, but pelvic ultrasound is required to exclude underlying pathology.  \n- Tranexamic acid was advised for symptomatic relief of heavy bleeding.  \n- Combined oral contraceptive pill (COCP) was suggested for cycle regulation if no contraindications exist.  \n- Patient reassured about the commonality of AUB but advised on the necessity of further evaluation.  \n\n### Plan:  \nPlan:  \n1. Investigations:  \n   - Full blood count (FBC) to assess for anemia.  \n   - TSH and prolactin levels to evaluate endocrine causes.  \n   - Pelvic ultrasound to rule out structural abnormalities.  \n2. Symptomatic relief:  \n   - Tranexamic acid for heavy menstrual bleeding.  \n   - Consider COCP for cycle regulation if appropriate.  \n3. Follow-up in 6 weeks with results; escalate to gynecology if bleeding worsens or anemia is confirmed.  \n4. Advised to monitor for syncope or severe fatigue.\n\n--- Token Usage Report ---\nPrompt tokens: 482\nCompletion tokens: 371\nTotal tokens: 853\nEstimated cost: $0.000427",
  "ai_provider": "DeepSeek",
  "ai_model": "deepseek-chat",
  "token_usage": {
    "prompt_tokens": 482,
    "completion_tokens": 371,
    "total_tokens": 853,
    "estimated_cost_usd": 0.0004265
  }
}