{
  "prompt": {
    "prompt": "Create a fictional dictation of a clinical interaction between a healthcare professional and a patient. \nThis dictation is for testing purposes only and should include various topics that might be discussed in a healthcare setting. \nPlease ensure the material is entirely fictional and does not provide any real medical advice or information. \nPlease ensure variables such as age, weight and history are varied.\nThe clinician should ensure the history and examination findings are incomplete, leaving out some pertinent questions.\nIn response to their history and examination findings, the clinician should  provide management advice and guidance.\nThe clinical scenario should be the following:  \n      \nThe clinical scenario should focus on a patient with Abnormal uterine bleeding.",
    "system_prompt": "Create a fictional dictation of a clinical interaction between a healthcare professional and a patient. \nThis dictation is for testing purposes only and should include various topics that might be discussed in a healthcare setting. \nPlease ensure the material is entirely fictional and does not provide any real medical advice or information. \nPlease ensure variables such as age, weight and history are varied.\nThe clinician should ensure the history and examination findings are incomplete, leaving out some pertinent questions.\nIn response to their history and examination findings, the clinician should  provide management advice and guidance.\nThe clinical scenario should be the following:  \n      \nThe clinical scenario should focus on a patient with Abnormal uterine bleeding."
  },
  "response": "**Fictional Clinical Dictation: Abnormal Uterine Bleeding**  \n\n**Patient Name:** Jane Doe (Fictional)  \n**Age:** 42 years  \n**Date of Visit:** October 10, 2023  \n**Clinician:** Dr. Smith (Fictional)  \n\n---  \n\n### **Subjective:**  \nMs. Doe presents today reporting a 4-month history of abnormal uterine bleeding. She describes her periods as \"heavier and longer\" than usual, lasting 10–14 days with flooding and clots. She denies intermenstrual bleeding but reports occasional spotting. She has no associated pelvic pain or dyspareunia.  \n\nShe has no significant past medical history, though she admits to a family history of \"thyroid problems\" (unspecified). She takes no medications, including hormonal contraception, and has no known drug allergies. She is a non-smoker and drinks alcohol socially.  \n\n*[Missing Pertinent Questions: Last Pap smear, sexual activity history, weight changes, symptoms of anemia (fatigue, dizziness), or thyroid dysfunction.]*  \n\n### **Objective:**  \n**Vitals:** BP 118/76, HR 78, BMI 28 (weight 75 kg).  \n**General:** Well-appearing, no pallor.  \n**Abdominal Exam:** Soft, non-tender, no masses.  \n**Pelvic Exam (limited):** External genitalia normal. No active bleeding at time of exam. Cervix appears normal; no visible lesions. Uterus is anteverted, non-tender, normal size. Adnexa non-tender.  \n\n*[Missing Pertinent Findings: No speculum exam documented, no cervical motion tenderness, no assessment for uterine enlargement/fibroids, no thyroid exam.]*  \n\n### **Assessment:**  \n42-year-old female with abnormal uterine bleeding (AUB), likely secondary to perimenopausal hormonal changes or structural causes (e.g., fibroids, polyps). Other possibilities include thyroid dysfunction or coagulopathy, though not yet assessed.  \n\n### **Plan:**  \n1. **Initial Workup:**  \n   - CBC (to assess for anemia).  \n   - TSH (given family history of thyroid issues).  \n   - Pelvic ultrasound (to evaluate for fibroids/polyps).  \n   - *[Missing: No coagulation studies, no endometrial biopsy despite age >40, no discussion of Pap smear if overdue.]*  \n\n2. **Symptomatic Management:**  \n   - Start tranexamic acid 1g TID during heavy bleeding days.  \n   - Consider trial of NSAIDs (e.g., ibuprofen) for pain/bleeding reduction.  \n   - *[Missing: No discussion of hormonal options (e.g., OCPs, progesterone) or iron supplementation if anemic.]*  \n\n3. **Follow-Up:**  \n   - Return in 4 weeks to review results and adjust plan.  \n   - Emergency referral if hemodynamically unstable bleeding.  \n\n**Counseling:**  \nDiscussed that bleeding could be due to perimenopause but requires further evaluation to rule out other causes. Advised to track bleeding patterns and symptoms.  \n\n---  \n**Note:** This is a fictional dictation for testing purposes only. No real medical advice is given. Key history and exam elements are intentionally omitted to simulate an incomplete assessment.  \n\n---  \nWould you like any modifications (e.g., more omissions, different management approaches)?",
  "endpoint": "generateFakeClinicalInteraction",
  "timestamp": "2025-05-26T15-54-06",
  "textContent": "AI: DeepSeek (deepseek-chat)\n\nQ: {\n  \"prompt\": \"Create a fictional dictation of a clinical interaction between a healthcare professional and a patient. \\nThis dictation is for testing purposes only and should include various topics that might be discussed in a healthcare setting. \\nPlease ensure the material is entirely fictional and does not provide any real medical advice or information. \\nPlease ensure variables such as age, weight and history are varied.\\nThe clinician should ensure the history and examination findings are incomplete, leaving out some pertinent questions.\\nIn response to their history and examination findings, the clinician should  provide management advice and guidance.\\nThe clinical scenario should be the following:  \\n      \\nThe clinical scenario should focus on a patient with Abnormal uterine bleeding.\",\n  \"system_prompt\": \"Create a fictional dictation of a clinical interaction between a healthcare professional and a patient. \\nThis dictation is for testing purposes only and should include various topics that might be discussed in a healthcare setting. \\nPlease ensure the material is entirely fictional and does not provide any real medical advice or information. \\nPlease ensure variables such as age, weight and history are varied.\\nThe clinician should ensure the history and examination findings are incomplete, leaving out some pertinent questions.\\nIn response to their history and examination findings, the clinician should  provide management advice and guidance.\\nThe clinical scenario should be the following:  \\n      \\nThe clinical scenario should focus on a patient with Abnormal uterine bleeding.\"\n}\n\nA: **Fictional Clinical Dictation: Abnormal Uterine Bleeding**  \n\n**Patient Name:** Jane Doe (Fictional)  \n**Age:** 42 years  \n**Date of Visit:** October 10, 2023  \n**Clinician:** Dr. Smith (Fictional)  \n\n---  \n\n### **Subjective:**  \nMs. Doe presents today reporting a 4-month history of abnormal uterine bleeding. She describes her periods as \"heavier and longer\" than usual, lasting 10–14 days with flooding and clots. She denies intermenstrual bleeding but reports occasional spotting. She has no associated pelvic pain or dyspareunia.  \n\nShe has no significant past medical history, though she admits to a family history of \"thyroid problems\" (unspecified). She takes no medications, including hormonal contraception, and has no known drug allergies. She is a non-smoker and drinks alcohol socially.  \n\n*[Missing Pertinent Questions: Last Pap smear, sexual activity history, weight changes, symptoms of anemia (fatigue, dizziness), or thyroid dysfunction.]*  \n\n### **Objective:**  \n**Vitals:** BP 118/76, HR 78, BMI 28 (weight 75 kg).  \n**General:** Well-appearing, no pallor.  \n**Abdominal Exam:** Soft, non-tender, no masses.  \n**Pelvic Exam (limited):** External genitalia normal. No active bleeding at time of exam. Cervix appears normal; no visible lesions. Uterus is anteverted, non-tender, normal size. Adnexa non-tender.  \n\n*[Missing Pertinent Findings: No speculum exam documented, no cervical motion tenderness, no assessment for uterine enlargement/fibroids, no thyroid exam.]*  \n\n### **Assessment:**  \n42-year-old female with abnormal uterine bleeding (AUB), likely secondary to perimenopausal hormonal changes or structural causes (e.g., fibroids, polyps). Other possibilities include thyroid dysfunction or coagulopathy, though not yet assessed.  \n\n### **Plan:**  \n1. **Initial Workup:**  \n   - CBC (to assess for anemia).  \n   - TSH (given family history of thyroid issues).  \n   - Pelvic ultrasound (to evaluate for fibroids/polyps).  \n   - *[Missing: No coagulation studies, no endometrial biopsy despite age >40, no discussion of Pap smear if overdue.]*  \n\n2. **Symptomatic Management:**  \n   - Start tranexamic acid 1g TID during heavy bleeding days.  \n   - Consider trial of NSAIDs (e.g., ibuprofen) for pain/bleeding reduction.  \n   - *[Missing: No discussion of hormonal options (e.g., OCPs, progesterone) or iron supplementation if anemic.]*  \n\n3. **Follow-Up:**  \n   - Return in 4 weeks to review results and adjust plan.  \n   - Emergency referral if hemodynamically unstable bleeding.  \n\n**Counseling:**  \nDiscussed that bleeding could be due to perimenopause but requires further evaluation to rule out other causes. Advised to track bleeding patterns and symptoms.  \n\n---  \n**Note:** This is a fictional dictation for testing purposes only. No real medical advice is given. Key history and exam elements are intentionally omitted to simulate an incomplete assessment.  \n\n---  \nWould you like any modifications (e.g., more omissions, different management approaches)?\n\n--- Token Usage Report ---\nPrompt tokens: 136\nCompletion tokens: 697\nTotal tokens: 833\nEstimated cost: $0.000416",
  "ai_provider": "DeepSeek",
  "ai_model": "deepseek-chat",
  "token_usage": {
    "prompt_tokens": 136,
    "completion_tokens": 697,
    "total_tokens": 833,
    "estimated_cost_usd": 0.0004165
  }
}