{
  "prompt": {
    "prompt": "Create a fictional dictation of a clinical interaction between a healthcare professional and a patient. \nThis dictation is for testing purposes only and should include various topics that might be discussed in a healthcare setting. \nPlease ensure the material is entirely fictional and does not provide any real medical advice or information. \nPlease ensure variables such as age, weight and history are varied.\nThe clinician should ensure the history and examination findings are incomplete, leaving out some pertinent questions.\nIn response to their history and examination findings, the clinician should  provide management advice and guidance.\nThe clinical scenario should be the following: \n\nMake the age 58, the BMI 32.9 and the number of prior pregnancies 4\n\nBase the clinical scenario on the following gynecology issue: Cervical cancer",
    "system_prompt": "Create a fictional dictation of a clinical interaction between a healthcare professional and a patient. \nThis dictation is for testing purposes only and should include various topics that might be discussed in a healthcare setting. \nPlease ensure the material is entirely fictional and does not provide any real medical advice or information. \nPlease ensure variables such as age, weight and history are varied.\nThe clinician should ensure the history and examination findings are incomplete, leaving out some pertinent questions.\nIn response to their history and examination findings, the clinician should  provide management advice and guidance.\nThe clinical scenario should be the following: \n\nMake the age 58, the BMI 32.9 and the number of prior pregnancies 4\n\nBase the clinical scenario on the following gynecology issue: Cervical cancer"
  },
  "response": "**Dictation: Clinical Interaction – Fictional Example for Testing Purposes**  \n\n**Patient Details:**  \n- Name: Jane Doe (fictional)  \n- Age: 58  \n- BMI: 32.9  \n- Gravida: 4, Para: 4  \n- Last Menstrual Period: 12 years ago (postmenopausal)  \n- Occupation: Retired teacher  \n\n**Chief Complaint:**  \nThe patient presents with a 3-month history of intermittent postmenopausal bleeding and pelvic discomfort.  \n\n**History of Present Illness:**  \nMs. Doe reports light vaginal bleeding over the past three months, occurring approximately once every two weeks. She describes the bleeding as scant but persistent, requiring panty liners. She denies any associated pain at the time of bleeding but notes mild, intermittent pelvic pressure. She has no history of trauma or recent sexual activity. She has not noticed any weight loss, fever, or changes in bowel/bladder habits.  \n\n**Past Medical History:**  \n- Hypertension (on lisinopril)  \n- Type 2 diabetes (on metformin)  \n- Osteoarthritis  \n\n**Past Surgical History:**  \n- Cholecystectomy (age 45)  \n- No prior gynecologic surgeries  \n\n**Family History:**  \n- Mother had breast cancer (diagnosed at 65)  \n- No known family history of cervical or ovarian cancer  \n\n**Social History:**  \n- Former smoker (quit 10 years ago, 15 pack-year history)  \n- Occasional alcohol (1-2 glasses of wine per week)  \n- No recreational drug use  \n\n**Review of Systems (Incomplete – Pertinent Omissions Noted):**  \n- **General:** No fever, chills, or fatigue reported.  \n- **Cardiovascular:** No chest pain or palpitations.  \n- **Respiratory:** No shortness of breath or cough.  \n- **Gastrointestinal:** No nausea, vomiting, or changes in bowel habits. *(Omitted: Any recent constipation or bloating?)*  \n- **Genitourinary:** Postmenopausal bleeding as above. No dysuria or hematuria. *(Omitted: Any urinary incontinence or urgency?)*  \n- **Neurological:** No headaches or dizziness.  \n\n**Examination Findings (Incomplete – Pertinent Omissions Noted):**  \n- **Vital Signs:** BP 138/82, HR 78, Temp 98.4°F, SpO2 98% RA  \n- **General:** Well-appearing, no acute distress  \n- **Abdomen:** Soft, mildly tender in lower quadrants, no palpable masses *(Omitted: Any organomegaly noted?)*  \n- **Pelvic Exam:**  \n  - External genitalia: Normal appearance  \n  - Speculum: Small amount of dark blood in vaginal vault, cervix appears irregular with slight friability *(Omitted: Any visible lesions?)*  \n  - Bimanual: Uterus slightly enlarged, no adnexal masses palpated *(Omitted: Any cervical motion tenderness?)*  \n\n**Assessment:**  \n- Postmenopausal bleeding – concerning for possible cervical malignancy  \n- Additional differentials: endometrial hyperplasia, atrophic vaginitis, cervical polyp  \n\n**Plan:**  \n1. **Diagnostics:**  \n   - Pelvic ultrasound to assess endometrial thickness  \n   - Pap smear and HPV testing *(Omitted: Should colposcopy be considered upfront given irregular cervix?)*  \n   - CBC to evaluate for anemia  \n   - Consider endometrial biopsy if imaging is inconclusive  \n\n2. **Referrals:**  \n   - Gynecology oncology consult given high suspicion for cervical pathology  \n   - Diabetes and hypertension management to be continued with PCP  \n\n3. **Patient Counseling:**  \n   - Advised patient to monitor for heavy bleeding, severe pain, or fever  \n   - Encouraged smoking cessation reinforcement despite prior quit  \n   - Discussed importance of follow-up for biopsy results  \n\n4. **Follow-Up:**  \n   - Return in 1 week for test results  \n   - Earlier if symptoms worsen  \n\n**Clinician Signature:**  \nDr. Smith (fictional)  \n*Date: XX/XX/XXXX*  \n\n---  \n**Note:** This dictation is entirely fictional and for testing purposes only. No real medical advice is provided. Pertinent history and exam elements were intentionally omitted to simulate incomplete documentation. Management suggestions are not clinically validated.",
  "endpoint": "newFunctionName",
  "timestamp": "2025-05-11T06-14-19",
  "textContent": "AI: DeepSeek (deepseek-chat)\n\nQ: {\n  \"prompt\": \"Create a fictional dictation of a clinical interaction between a healthcare professional and a patient. \\nThis dictation is for testing purposes only and should include various topics that might be discussed in a healthcare setting. \\nPlease ensure the material is entirely fictional and does not provide any real medical advice or information. \\nPlease ensure variables such as age, weight and history are varied.\\nThe clinician should ensure the history and examination findings are incomplete, leaving out some pertinent questions.\\nIn response to their history and examination findings, the clinician should  provide management advice and guidance.\\nThe clinical scenario should be the following: \\n\\nMake the age 58, the BMI 32.9 and the number of prior pregnancies 4\\n\\nBase the clinical scenario on the following gynecology issue: Cervical cancer\",\n  \"system_prompt\": \"Create a fictional dictation of a clinical interaction between a healthcare professional and a patient. \\nThis dictation is for testing purposes only and should include various topics that might be discussed in a healthcare setting. \\nPlease ensure the material is entirely fictional and does not provide any real medical advice or information. \\nPlease ensure variables such as age, weight and history are varied.\\nThe clinician should ensure the history and examination findings are incomplete, leaving out some pertinent questions.\\nIn response to their history and examination findings, the clinician should  provide management advice and guidance.\\nThe clinical scenario should be the following: \\n\\nMake the age 58, the BMI 32.9 and the number of prior pregnancies 4\\n\\nBase the clinical scenario on the following gynecology issue: Cervical cancer\"\n}\n\nA: **Dictation: Clinical Interaction – Fictional Example for Testing Purposes**  \n\n**Patient Details:**  \n- Name: Jane Doe (fictional)  \n- Age: 58  \n- BMI: 32.9  \n- Gravida: 4, Para: 4  \n- Last Menstrual Period: 12 years ago (postmenopausal)  \n- Occupation: Retired teacher  \n\n**Chief Complaint:**  \nThe patient presents with a 3-month history of intermittent postmenopausal bleeding and pelvic discomfort.  \n\n**History of Present Illness:**  \nMs. Doe reports light vaginal bleeding over the past three months, occurring approximately once every two weeks. She describes the bleeding as scant but persistent, requiring panty liners. She denies any associated pain at the time of bleeding but notes mild, intermittent pelvic pressure. She has no history of trauma or recent sexual activity. She has not noticed any weight loss, fever, or changes in bowel/bladder habits.  \n\n**Past Medical History:**  \n- Hypertension (on lisinopril)  \n- Type 2 diabetes (on metformin)  \n- Osteoarthritis  \n\n**Past Surgical History:**  \n- Cholecystectomy (age 45)  \n- No prior gynecologic surgeries  \n\n**Family History:**  \n- Mother had breast cancer (diagnosed at 65)  \n- No known family history of cervical or ovarian cancer  \n\n**Social History:**  \n- Former smoker (quit 10 years ago, 15 pack-year history)  \n- Occasional alcohol (1-2 glasses of wine per week)  \n- No recreational drug use  \n\n**Review of Systems (Incomplete – Pertinent Omissions Noted):**  \n- **General:** No fever, chills, or fatigue reported.  \n- **Cardiovascular:** No chest pain or palpitations.  \n- **Respiratory:** No shortness of breath or cough.  \n- **Gastrointestinal:** No nausea, vomiting, or changes in bowel habits. *(Omitted: Any recent constipation or bloating?)*  \n- **Genitourinary:** Postmenopausal bleeding as above. No dysuria or hematuria. *(Omitted: Any urinary incontinence or urgency?)*  \n- **Neurological:** No headaches or dizziness.  \n\n**Examination Findings (Incomplete – Pertinent Omissions Noted):**  \n- **Vital Signs:** BP 138/82, HR 78, Temp 98.4°F, SpO2 98% RA  \n- **General:** Well-appearing, no acute distress  \n- **Abdomen:** Soft, mildly tender in lower quadrants, no palpable masses *(Omitted: Any organomegaly noted?)*  \n- **Pelvic Exam:**  \n  - External genitalia: Normal appearance  \n  - Speculum: Small amount of dark blood in vaginal vault, cervix appears irregular with slight friability *(Omitted: Any visible lesions?)*  \n  - Bimanual: Uterus slightly enlarged, no adnexal masses palpated *(Omitted: Any cervical motion tenderness?)*  \n\n**Assessment:**  \n- Postmenopausal bleeding – concerning for possible cervical malignancy  \n- Additional differentials: endometrial hyperplasia, atrophic vaginitis, cervical polyp  \n\n**Plan:**  \n1. **Diagnostics:**  \n   - Pelvic ultrasound to assess endometrial thickness  \n   - Pap smear and HPV testing *(Omitted: Should colposcopy be considered upfront given irregular cervix?)*  \n   - CBC to evaluate for anemia  \n   - Consider endometrial biopsy if imaging is inconclusive  \n\n2. **Referrals:**  \n   - Gynecology oncology consult given high suspicion for cervical pathology  \n   - Diabetes and hypertension management to be continued with PCP  \n\n3. **Patient Counseling:**  \n   - Advised patient to monitor for heavy bleeding, severe pain, or fever  \n   - Encouraged smoking cessation reinforcement despite prior quit  \n   - Discussed importance of follow-up for biopsy results  \n\n4. **Follow-Up:**  \n   - Return in 1 week for test results  \n   - Earlier if symptoms worsen  \n\n**Clinician Signature:**  \nDr. Smith (fictional)  \n*Date: XX/XX/XXXX*  \n\n---  \n**Note:** This dictation is entirely fictional and for testing purposes only. No real medical advice is provided. Pertinent history and exam elements were intentionally omitted to simulate incomplete documentation. Management suggestions are not clinically validated.\n\n--- Token Usage Report ---\nPrompt tokens: 158\nCompletion tokens: 892\nTotal tokens: 1050\nEstimated cost: $0.000525",
  "ai_provider": "DeepSeek",
  "ai_model": "deepseek-chat",
  "token_usage": {
    "prompt_tokens": 158,
    "completion_tokens": 892,
    "total_tokens": 1050,
    "estimated_cost_usd": 0.000525
  }
}