{
  "prompt": {
    "prompt": "Create a fictional dictation of a clinical interaction between a healthcare professional and a patient. \nThis dictation is for testing purposes only and should include various topics that might be discussed in a healthcare setting. \nPlease ensure the material is entirely fictional and does not provide any real medical advice or information. \nPlease ensure variables such as age, weight and history are varied.\nThe clinician should ensure the history and examination findings are incomplete, leaving out some pertinent questions.\nIn response to their history and examination findings, the clinician should  provide management advice and guidance.\nThe clinical scenario should be the following: Multiple gestation",
    "system_prompt": "Create a fictional dictation of a clinical interaction between a healthcare professional and a patient. \nThis dictation is for testing purposes only and should include various topics that might be discussed in a healthcare setting. \nPlease ensure the material is entirely fictional and does not provide any real medical advice or information. \nPlease ensure variables such as age, weight and history are varied.\nThe clinician should ensure the history and examination findings are incomplete, leaving out some pertinent questions.\nIn response to their history and examination findings, the clinician should  provide management advice and guidance.\nThe clinical scenario should be the following: Multiple gestation"
  },
  "response": "**Dictation: Clinical Interaction – Multiple Gestation (Fictional for Testing Purposes Only)**  \n\n**Patient Name:** Sarah Thompson  \n**Age:** 32  \n**Gestational Age:** 24 weeks  \n**Gravidity/Parity:** G3 P1 (previous vaginal delivery at term)  \n**Weight:** 68 kg  \n**Last Menstrual Period:** Estimated based on early ultrasound  \n**Chief Complaint:** \"I’ve been having more frequent Braxton Hicks contractions and some lower back pain.\"  \n\n### **History of Present Illness:**  \nMs. Thompson is a 32-year-old woman with a dichorionic diamniotic twin pregnancy, confirmed by first-trimester ultrasound. She reports increased frequency of Braxton Hicks contractions over the past week, occurring 3–4 times per hour, non-painful but noticeable. She denies vaginal bleeding, fluid leakage, or decreased fetal movement. She notes intermittent lower back pain, which she attributes to prolonged standing at work. No recent travel or illness.  \n\n*Missing Pertinent Questions:*  \n- No documented inquiry about urinary symptoms (possible UTI contributing to contractions).  \n- No detailed dietary history (potential nutritional deficiencies in twin gestation).  \n- No assessment of recent stressors or sleep disturbances.  \n\n### **Past Medical/Surgical History:**  \n- Hypothyroidism (on levothyroxine, last TSH within normal range).  \n- No prior gestational diabetes or hypertension.  \n- No surgeries.  \n\n### **Medications:**  \n- Prenatal vitamins  \n- Levothyroxine 50 mcg daily  \n\n### **Family History:**  \n- Mother with type 2 diabetes.  \n- No known twin pregnancies in family.  \n\n### **Social History:**  \n- Works full-time as a teacher.  \n- No tobacco, alcohol, or recreational drug use.  \n- Married, supportive partner.  \n\n### **Review of Systems:**  \n- **Constitutional:** No fever, fatigue reported.  \n- **Cardiovascular:** No palpitations or edema.  \n- **Respiratory:** No shortness of breath.  \n- **Gastrointestinal:** Occasional heartburn, no nausea/vomiting.  \n- **Neurological:** No headaches or visual changes.  \n\n*Missing Pertinent Exam Findings:*  \n- No fundal height measurement documented.  \n- No cervical exam performed (to assess for shortening/dilation).  \n- No documentation of fetal heart tones for both twins.  \n\n### **Assessment:**  \n- **Multiple gestation (DCDA twins)** at 24 weeks with increased Braxton Hicks contractions.  \n- Differential includes normal uterine irritability vs. preterm labor risk.  \n- Back pain may be musculoskeletal but requires monitoring.  \n\n### **Plan:**  \n1. **Activity Modification:** Advised reduced standing, pelvic rest, and hydration.  \n2. **Contraction Monitoring:** Instructed to time contractions—if ≥6/hour or painful, present to labor and delivery.  \n3. **Nutrition:** Emphasized increased protein/caloric intake (not quantified).  \n4. **Follow-Up:** Scheduled for growth ultrasound in 2 weeks; no additional cervical length screening ordered.  \n5. **Patient Counseling:** Discussed signs of preterm labor but did not provide written materials.  \n\n*Gaps in Management:*  \n- No referral to maternal-fetal medicine despite twin gestation.  \n- No discussion of antenatal corticosteroids for fetal lung maturity in case of preterm delivery.  \n- No contingency plan if symptoms worsen before next visit.  \n\n**Dictated by:** Dr. A. Smith, OB/GYN  \n**Date:** [Fictional]  \n*For testing purposes only—not real medical advice.*  \n\n---  \nThis fictional dictation includes intentional omissions and management gaps for testing/educational review. Always verify clinical details in real practice.",
  "endpoint": "generateFakeClinicalInteraction",
  "timestamp": "2025-06-10T19-29-53",
  "textContent": "AI: DeepSeek (deepseek-chat)\n\nQ: {\n  \"prompt\": \"Create a fictional dictation of a clinical interaction between a healthcare professional and a patient. \\nThis dictation is for testing purposes only and should include various topics that might be discussed in a healthcare setting. \\nPlease ensure the material is entirely fictional and does not provide any real medical advice or information. \\nPlease ensure variables such as age, weight and history are varied.\\nThe clinician should ensure the history and examination findings are incomplete, leaving out some pertinent questions.\\nIn response to their history and examination findings, the clinician should  provide management advice and guidance.\\nThe clinical scenario should be the following: Multiple gestation\",\n  \"system_prompt\": \"Create a fictional dictation of a clinical interaction between a healthcare professional and a patient. \\nThis dictation is for testing purposes only and should include various topics that might be discussed in a healthcare setting. \\nPlease ensure the material is entirely fictional and does not provide any real medical advice or information. \\nPlease ensure variables such as age, weight and history are varied.\\nThe clinician should ensure the history and examination findings are incomplete, leaving out some pertinent questions.\\nIn response to their history and examination findings, the clinician should  provide management advice and guidance.\\nThe clinical scenario should be the following: Multiple gestation\"\n}\n\nA: **Dictation: Clinical Interaction – Multiple Gestation (Fictional for Testing Purposes Only)**  \n\n**Patient Name:** Sarah Thompson  \n**Age:** 32  \n**Gestational Age:** 24 weeks  \n**Gravidity/Parity:** G3 P1 (previous vaginal delivery at term)  \n**Weight:** 68 kg  \n**Last Menstrual Period:** Estimated based on early ultrasound  \n**Chief Complaint:** \"I’ve been having more frequent Braxton Hicks contractions and some lower back pain.\"  \n\n### **History of Present Illness:**  \nMs. Thompson is a 32-year-old woman with a dichorionic diamniotic twin pregnancy, confirmed by first-trimester ultrasound. She reports increased frequency of Braxton Hicks contractions over the past week, occurring 3–4 times per hour, non-painful but noticeable. She denies vaginal bleeding, fluid leakage, or decreased fetal movement. She notes intermittent lower back pain, which she attributes to prolonged standing at work. No recent travel or illness.  \n\n*Missing Pertinent Questions:*  \n- No documented inquiry about urinary symptoms (possible UTI contributing to contractions).  \n- No detailed dietary history (potential nutritional deficiencies in twin gestation).  \n- No assessment of recent stressors or sleep disturbances.  \n\n### **Past Medical/Surgical History:**  \n- Hypothyroidism (on levothyroxine, last TSH within normal range).  \n- No prior gestational diabetes or hypertension.  \n- No surgeries.  \n\n### **Medications:**  \n- Prenatal vitamins  \n- Levothyroxine 50 mcg daily  \n\n### **Family History:**  \n- Mother with type 2 diabetes.  \n- No known twin pregnancies in family.  \n\n### **Social History:**  \n- Works full-time as a teacher.  \n- No tobacco, alcohol, or recreational drug use.  \n- Married, supportive partner.  \n\n### **Review of Systems:**  \n- **Constitutional:** No fever, fatigue reported.  \n- **Cardiovascular:** No palpitations or edema.  \n- **Respiratory:** No shortness of breath.  \n- **Gastrointestinal:** Occasional heartburn, no nausea/vomiting.  \n- **Neurological:** No headaches or visual changes.  \n\n*Missing Pertinent Exam Findings:*  \n- No fundal height measurement documented.  \n- No cervical exam performed (to assess for shortening/dilation).  \n- No documentation of fetal heart tones for both twins.  \n\n### **Assessment:**  \n- **Multiple gestation (DCDA twins)** at 24 weeks with increased Braxton Hicks contractions.  \n- Differential includes normal uterine irritability vs. preterm labor risk.  \n- Back pain may be musculoskeletal but requires monitoring.  \n\n### **Plan:**  \n1. **Activity Modification:** Advised reduced standing, pelvic rest, and hydration.  \n2. **Contraction Monitoring:** Instructed to time contractions—if ≥6/hour or painful, present to labor and delivery.  \n3. **Nutrition:** Emphasized increased protein/caloric intake (not quantified).  \n4. **Follow-Up:** Scheduled for growth ultrasound in 2 weeks; no additional cervical length screening ordered.  \n5. **Patient Counseling:** Discussed signs of preterm labor but did not provide written materials.  \n\n*Gaps in Management:*  \n- No referral to maternal-fetal medicine despite twin gestation.  \n- No discussion of antenatal corticosteroids for fetal lung maturity in case of preterm delivery.  \n- No contingency plan if symptoms worsen before next visit.  \n\n**Dictated by:** Dr. A. Smith, OB/GYN  \n**Date:** [Fictional]  \n*For testing purposes only—not real medical advice.*  \n\n---  \nThis fictional dictation includes intentional omissions and management gaps for testing/educational review. Always verify clinical details in real practice.\n\n--- Token Usage Report ---\nPrompt tokens: 123\nCompletion tokens: 765\nTotal tokens: 888\nEstimated cost: $0.000444",
  "ai_provider": "DeepSeek",
  "ai_model": "deepseek-chat",
  "token_usage": {
    "prompt_tokens": 123,
    "completion_tokens": 765,
    "total_tokens": 888,
    "estimated_cost_usd": 0.00044400000000000006
  }
}