{
  "prompt": {
    "prompt": "Original Transcript:\n25yo, P0, 34+5, BMI 30\n\nSituation: PPROM @ 0400\nHealthy pregnancy so far\nFirst MAU admission\nAttending triage ?SROM\nNo PVB/not contracting\n\nMed hx:\nNKDA\nO+\n\nBloods yesterday\nCRP 6\nHb 110\nPLT 255\nWBC 10.3\n\nFND seizure 2x week, sees neurologist every three months, on CBT therapy\nWrist surgery\n\nSocial and PNMH:\nAnxiety\nDepression\nPTSD\nPsychosis\nOutpatient Psychiatric unit\n- on VENLAFLAXINE 150mg OD and PROPRANOLOL 10mg prn\n- Declined PNMH referral\nStopped smoking cannabis, tobacco and vaping more than 6 wks ago\n\nObstetric hx:\nNil to note\n\nThis pregnancy:\nBooked ELCS for maternal request due to PTSD and NFT seizures 01/08/2025\nSerology - NAD\nLatest USS (26/6) - normal growth\nSBL pathway\n\nCurrently:\nClinically well\nNo symptoms of infection\nMEOWS 0\nFM N\nCTG N\nNo tightenings/contractions\n\nAdvice:\nContinue pregnancy until 37/40 - then deliver for PPROM\nAs wishing for ELCS - book for then\nAs had steroids on this admission, no further steroids required\nOn erythomycin - to continue for 10 days\nWeekly DAU follow-up (obs / CTG +/- bloods as required)\nLow threshold to call/come in for any clinical concerns (pain/bleeding/abn dx/change in FM/unwell)\nMonitor for temp at home, if raised (>37.5) call us\nHome later today\n\nApply these changes:\nACCEPT: Replace \"No documentation of emotional support offered\" with \"Document offering emotional support given PPROM diagnosis and patient's complex mental health history\" (Reason: The guideline recommends: 'Emotional support should be offered to women with PPROM and their partners'. This is particularly important for this patient with PTSD, anxiety, depression and psychosis. The stress of PPROM could exacerbate these conditions.)\n\nReturn the updated transcript with these changes applied.",
    "system_prompt": "You are a medical AI assistant that applies user decisions to clinical transcripts based on guideline suggestions.\n\nYou will receive:\n1. An original transcript\n2. A list of suggestions with user decisions (accept, reject, or modify)\n3. For modifications, the user's custom text\n\nYour task is to apply only the ACCEPTED and MODIFIED suggestions to create an updated transcript. For each change:\n- ACCEPTED suggestions: Apply the suggested text exactly as provided\n- MODIFIED suggestions: Apply the user's modified text instead of the original suggestion\n- REJECTED suggestions: Leave the original text unchanged\n\nReturn the updated transcript as clean, properly formatted medical text. Maintain the original structure and formatting as much as possible while incorporating the accepted changes.\n\nImportant guidelines:\n- Only apply changes that the user has accepted or modified\n- Preserve the medical accuracy and professional tone\n- Maintain logical flow and readability\n- Do not add any explanatory text or comments\n- Return only the updated transcript",
    "session_id": "advice_1751456492361_r322qbuxu",
    "original_transcript_length": 1221,
    "changes_applied": 1,
    "decisions_summary": {
      "accepted": 1,
      "modified": 0,
      "rejected": 4
    }
  },
  "response": "25yo, P0, 34+5, BMI 30\n\nSituation: PPROM @ 0400\nHealthy pregnancy so far\nFirst MAU admission\nAttending triage ?SROM\nNo PVB/not contracting\n\nMed hx:\nNKDA\nO+\n\nBloods yesterday\nCRP 6\nHb 110\nPLT 255\nWBC 10.3\n\nFND seizure 2x week, sees neurologist every three months, on CBT therapy\nWrist surgery\n\nSocial and PNMH:\nAnxiety\nDepression\nPTSD\nPsychosis\nOutpatient Psychiatric unit\n- on VENLAFLAXINE 150mg OD and PROPRANOLOL 10mg prn\n- Declined PNMH referral\nStopped smoking cannabis, tobacco and vaping more than 6 wks ago\nDocument offering emotional support given PPROM diagnosis and patient's complex mental health history\n\nObstetric hx:\nNil to note\n\nThis pregnancy:\nBooked ELCS for maternal request due to PTSD and NFT seizures 01/08/2025\nSerology - NAD\nLatest USS (26/6) - normal growth\nSBL pathway\n\nCurrently:\nClinically well\nNo symptoms of infection\nMEOWS 0\nFM N\nCTG N\nNo tightenings/contractions\n\nAdvice:\nContinue pregnancy until 37/40 - then deliver for PPROM\nAs wishing for ELCS - book for then\nAs had steroids on this admission, no further steroids required\nOn erythomycin - to continue for 10 days\nWeekly DAU follow-up (obs / CTG +/- bloods as required)\nLow threshold to call/come in for any clinical concerns (pain/bleeding/abn dx/change in FM/unwell)\nMonitor for temp at home, if raised (>37.5) call us\nHome later today",
  "endpoint": "applyDynamicAdvice",
  "timestamp": "2025-07-02T11-47-51",
  "textContent": "AI: DeepSeek (deepseek-chat)\n\nQ: {\n  \"prompt\": \"Original Transcript:\\n25yo, P0, 34+5, BMI 30\\n\\nSituation: PPROM @ 0400\\nHealthy pregnancy so far\\nFirst MAU admission\\nAttending triage ?SROM\\nNo PVB/not contracting\\n\\nMed hx:\\nNKDA\\nO+\\n\\nBloods yesterday\\nCRP 6\\nHb 110\\nPLT 255\\nWBC 10.3\\n\\nFND seizure 2x week, sees neurologist every three months, on CBT therapy\\nWrist surgery\\n\\nSocial and PNMH:\\nAnxiety\\nDepression\\nPTSD\\nPsychosis\\nOutpatient Psychiatric unit\\n- on VENLAFLAXINE 150mg OD and PROPRANOLOL 10mg prn\\n- Declined PNMH referral\\nStopped smoking cannabis, tobacco and vaping more than 6 wks ago\\n\\nObstetric hx:\\nNil to note\\n\\nThis pregnancy:\\nBooked ELCS for maternal request due to PTSD and NFT seizures 01/08/2025\\nSerology - NAD\\nLatest USS (26/6) - normal growth\\nSBL pathway\\n\\nCurrently:\\nClinically well\\nNo symptoms of infection\\nMEOWS 0\\nFM N\\nCTG N\\nNo tightenings/contractions\\n\\nAdvice:\\nContinue pregnancy until 37/40 - then deliver for PPROM\\nAs wishing for ELCS - book for then\\nAs had steroids on this admission, no further steroids required\\nOn erythomycin - to continue for 10 days\\nWeekly DAU follow-up (obs / CTG +/- bloods as required)\\nLow threshold to call/come in for any clinical concerns (pain/bleeding/abn dx/change in FM/unwell)\\nMonitor for temp at home, if raised (>37.5) call us\\nHome later today\\n\\nApply these changes:\\nACCEPT: Replace \\\"No documentation of emotional support offered\\\" with \\\"Document offering emotional support given PPROM diagnosis and patient's complex mental health history\\\" (Reason: The guideline recommends: 'Emotional support should be offered to women with PPROM and their partners'. This is particularly important for this patient with PTSD, anxiety, depression and psychosis. The stress of PPROM could exacerbate these conditions.)\\n\\nReturn the updated transcript with these changes applied.\",\n  \"system_prompt\": \"You are a medical AI assistant that applies user decisions to clinical transcripts based on guideline suggestions.\\n\\nYou will receive:\\n1. An original transcript\\n2. A list of suggestions with user decisions (accept, reject, or modify)\\n3. For modifications, the user's custom text\\n\\nYour task is to apply only the ACCEPTED and MODIFIED suggestions to create an updated transcript. For each change:\\n- ACCEPTED suggestions: Apply the suggested text exactly as provided\\n- MODIFIED suggestions: Apply the user's modified text instead of the original suggestion\\n- REJECTED suggestions: Leave the original text unchanged\\n\\nReturn the updated transcript as clean, properly formatted medical text. Maintain the original structure and formatting as much as possible while incorporating the accepted changes.\\n\\nImportant guidelines:\\n- Only apply changes that the user has accepted or modified\\n- Preserve the medical accuracy and professional tone\\n- Maintain logical flow and readability\\n- Do not add any explanatory text or comments\\n- Return only the updated transcript\",\n  \"session_id\": \"advice_1751456492361_r322qbuxu\",\n  \"original_transcript_length\": 1221,\n  \"changes_applied\": 1,\n  \"decisions_summary\": {\n    \"accepted\": 1,\n    \"modified\": 0,\n    \"rejected\": 4\n  }\n}\n\nA: 25yo, P0, 34+5, BMI 30\n\nSituation: PPROM @ 0400\nHealthy pregnancy so far\nFirst MAU admission\nAttending triage ?SROM\nNo PVB/not contracting\n\nMed hx:\nNKDA\nO+\n\nBloods yesterday\nCRP 6\nHb 110\nPLT 255\nWBC 10.3\n\nFND seizure 2x week, sees neurologist every three months, on CBT therapy\nWrist surgery\n\nSocial and PNMH:\nAnxiety\nDepression\nPTSD\nPsychosis\nOutpatient Psychiatric unit\n- on VENLAFLAXINE 150mg OD and PROPRANOLOL 10mg prn\n- Declined PNMH referral\nStopped smoking cannabis, tobacco and vaping more than 6 wks ago\nDocument offering emotional support given PPROM diagnosis and patient's complex mental health history\n\nObstetric hx:\nNil to note\n\nThis pregnancy:\nBooked ELCS for maternal request due to PTSD and NFT seizures 01/08/2025\nSerology - NAD\nLatest USS (26/6) - normal growth\nSBL pathway\n\nCurrently:\nClinically well\nNo symptoms of infection\nMEOWS 0\nFM N\nCTG N\nNo tightenings/contractions\n\nAdvice:\nContinue pregnancy until 37/40 - then deliver for PPROM\nAs wishing for ELCS - book for then\nAs had steroids on this admission, no further steroids required\nOn erythomycin - to continue for 10 days\nWeekly DAU follow-up (obs / CTG +/- bloods as required)\nLow threshold to call/come in for any clinical concerns (pain/bleeding/abn dx/change in FM/unwell)\nMonitor for temp at home, if raised (>37.5) call us\nHome later today\n\n--- Token Usage Report ---\nPrompt tokens: 671\nCompletion tokens: 389\nTotal tokens: 1060\nEstimated cost: $0.000530",
  "ai_provider": "DeepSeek",
  "ai_model": "deepseek-chat",
  "token_usage": {
    "prompt_tokens": 671,
    "completion_tokens": 389,
    "total_tokens": 1060,
    "estimated_cost_usd": 0.0005300000000000001
  }
}