{
  "prompt": {
    "prompt": "Create a fictional dictation of a clinical interaction between a healthcare professional and a patient. \nThis dictation is for testing purposes only and should include various topics that might be discussed in a healthcare setting. \nPlease ensure the material is entirely fictional and does not provide any real medical advice or information. \nPlease ensure variables such as age, weight and history are varied.\nThe clinician should ensure the history and examination findings are incomplete, leaving out some pertinent questions.\nIn response to their history and examination findings, the clinician should  provide management advice and guidance.\nThe clinical scenario should be the following: \n\nMake the age 64, the BMI 21.8 and the number of prior pregnancies 4\n\nBase the clinical scenario on the following gynecology issue: Abnormal uterine bleeding",
    "system_prompt": "Create a fictional dictation of a clinical interaction between a healthcare professional and a patient. \nThis dictation is for testing purposes only and should include various topics that might be discussed in a healthcare setting. \nPlease ensure the material is entirely fictional and does not provide any real medical advice or information. \nPlease ensure variables such as age, weight and history are varied.\nThe clinician should ensure the history and examination findings are incomplete, leaving out some pertinent questions.\nIn response to their history and examination findings, the clinician should  provide management advice and guidance.\nThe clinical scenario should be the following: \n\nMake the age 64, the BMI 21.8 and the number of prior pregnancies 4\n\nBase the clinical scenario on the following gynecology issue: Abnormal uterine bleeding"
  },
  "response": "**Dictation: Clinical Interaction – Abnormal Uterine Bleeding**  \n\n**Patient Details:**  \n- Name: [Fictional Name] Jane Doe  \n- Age: 64  \n- BMI: 21.8  \n- Gravida: 4, Para: 4  \n- Last Menstrual Period: Approximately 12 months ago (patient reports prior cessation of menses)  \n- Chief Complaint: Recurrent vaginal bleeding over the past 3 months  \n\n**History of Presenting Complaint:**  \nMs. Doe reports intermittent vaginal bleeding for the past three months, occurring approximately every two weeks and lasting 2–3 days. She describes the bleeding as light to moderate, requiring panty liners but no heavy clots. She denies associated pain, dyspareunia, or post-coital bleeding. She has no history of abnormal Pap smears or prior gynecologic procedures.  \n\n*[Missing Pertinent Questions: No inquiry about hormone replacement therapy, family history of gynecologic cancers, or anticoagulant use.]*  \n\n**Past Medical History:**  \n- Hypertension (well-controlled on lisinopril)  \n- Osteoporosis (on calcium and vitamin D supplementation)  \n- No history of diabetes or thyroid disorders  \n\n**Past Surgical History:**  \n- Tubal ligation (age 35)  \n- No prior hysteroscopy or endometrial sampling  \n\n**Medications:**  \n- Lisinopril 10 mg daily  \n- Calcium 600 mg + Vitamin D 800 IU daily  \n\n**Allergies:**  \n- NKDA  \n\n**Social History:**  \n- Non-smoker, occasional alcohol (1–2 glasses of wine per week)  \n- Retired teacher, lives with spouse  \n\n**Family History:**  \n- Mother with breast cancer (diagnosed age 70)  \n- No known endometrial or ovarian cancer in family  \n\n*[Missing Pertinent Questions: No detailed menstrual history prior to menopause, no assessment of weight changes or constitutional symptoms.]*  \n\n**Examination Findings:**  \n- General: Well-appearing, no pallor or signs of acute distress  \n- Abdomen: Soft, non-tender, no palpable masses  \n- Pelvic Exam:  \n  - External genitalia: Normal  \n  - Speculum: Small amount of old blood in vault, no visible cervical lesions  \n  - Bimanual: Uterus normal size, no adnexal tenderness or masses  \n\n*[Missing Pertinent Findings: No transvaginal ultrasound or endometrial biopsy performed at this visit.]*  \n\n**Assessment:**  \n- Postmenopausal bleeding (abnormal uterine bleeding) in a 64-year-old woman  \n- Differential includes endometrial atrophy, endometrial polyp, or endometrial hyperplasia/carcinoma (given age, requires exclusion)  \n\n**Plan:**  \n1. **Diagnostic Workup:**  \n   - Transvaginal ultrasound to assess endometrial thickness  \n   - Endometrial biopsy (office-based or referral for hysteroscopy if needed)  \n   - Consider CBC to evaluate for anemia  \n\n2. **Patient Counseling:**  \n   - Advised that postmenopausal bleeding is never normal and requires further evaluation.  \n   - Reassurance that most causes are benign but malignancy must be ruled out.  \n\n3. **Follow-Up:**  \n   - Return in 2 weeks for biopsy results and further management.  \n   - If bleeding becomes heavy or associated with dizziness/weakness, seek urgent care.  \n\n*[Missing Management Considerations: No discussion of hormone replacement therapy risks/benefits, no referral to gynecologic oncology if high suspicion of malignancy.]*  \n\n**Dictated by:** Dr. [Fictional Name] Smith, MD  \n**Date:** [Fictional Date]  \n\n*Note: This dictation is for testing purposes only and does not constitute real medical advice. All patient details are fictional.*",
  "endpoint": "newFunctionName",
  "timestamp": "2025-05-11T06-20-49",
  "textContent": "AI: DeepSeek (deepseek-chat)\n\nQ: {\n  \"prompt\": \"Create a fictional dictation of a clinical interaction between a healthcare professional and a patient. \\nThis dictation is for testing purposes only and should include various topics that might be discussed in a healthcare setting. \\nPlease ensure the material is entirely fictional and does not provide any real medical advice or information. \\nPlease ensure variables such as age, weight and history are varied.\\nThe clinician should ensure the history and examination findings are incomplete, leaving out some pertinent questions.\\nIn response to their history and examination findings, the clinician should  provide management advice and guidance.\\nThe clinical scenario should be the following: \\n\\nMake the age 64, the BMI 21.8 and the number of prior pregnancies 4\\n\\nBase the clinical scenario on the following gynecology issue: Abnormal uterine bleeding\",\n  \"system_prompt\": \"Create a fictional dictation of a clinical interaction between a healthcare professional and a patient. \\nThis dictation is for testing purposes only and should include various topics that might be discussed in a healthcare setting. \\nPlease ensure the material is entirely fictional and does not provide any real medical advice or information. \\nPlease ensure variables such as age, weight and history are varied.\\nThe clinician should ensure the history and examination findings are incomplete, leaving out some pertinent questions.\\nIn response to their history and examination findings, the clinician should  provide management advice and guidance.\\nThe clinical scenario should be the following: \\n\\nMake the age 64, the BMI 21.8 and the number of prior pregnancies 4\\n\\nBase the clinical scenario on the following gynecology issue: Abnormal uterine bleeding\"\n}\n\nA: **Dictation: Clinical Interaction – Abnormal Uterine Bleeding**  \n\n**Patient Details:**  \n- Name: [Fictional Name] Jane Doe  \n- Age: 64  \n- BMI: 21.8  \n- Gravida: 4, Para: 4  \n- Last Menstrual Period: Approximately 12 months ago (patient reports prior cessation of menses)  \n- Chief Complaint: Recurrent vaginal bleeding over the past 3 months  \n\n**History of Presenting Complaint:**  \nMs. Doe reports intermittent vaginal bleeding for the past three months, occurring approximately every two weeks and lasting 2–3 days. She describes the bleeding as light to moderate, requiring panty liners but no heavy clots. She denies associated pain, dyspareunia, or post-coital bleeding. She has no history of abnormal Pap smears or prior gynecologic procedures.  \n\n*[Missing Pertinent Questions: No inquiry about hormone replacement therapy, family history of gynecologic cancers, or anticoagulant use.]*  \n\n**Past Medical History:**  \n- Hypertension (well-controlled on lisinopril)  \n- Osteoporosis (on calcium and vitamin D supplementation)  \n- No history of diabetes or thyroid disorders  \n\n**Past Surgical History:**  \n- Tubal ligation (age 35)  \n- No prior hysteroscopy or endometrial sampling  \n\n**Medications:**  \n- Lisinopril 10 mg daily  \n- Calcium 600 mg + Vitamin D 800 IU daily  \n\n**Allergies:**  \n- NKDA  \n\n**Social History:**  \n- Non-smoker, occasional alcohol (1–2 glasses of wine per week)  \n- Retired teacher, lives with spouse  \n\n**Family History:**  \n- Mother with breast cancer (diagnosed age 70)  \n- No known endometrial or ovarian cancer in family  \n\n*[Missing Pertinent Questions: No detailed menstrual history prior to menopause, no assessment of weight changes or constitutional symptoms.]*  \n\n**Examination Findings:**  \n- General: Well-appearing, no pallor or signs of acute distress  \n- Abdomen: Soft, non-tender, no palpable masses  \n- Pelvic Exam:  \n  - External genitalia: Normal  \n  - Speculum: Small amount of old blood in vault, no visible cervical lesions  \n  - Bimanual: Uterus normal size, no adnexal tenderness or masses  \n\n*[Missing Pertinent Findings: No transvaginal ultrasound or endometrial biopsy performed at this visit.]*  \n\n**Assessment:**  \n- Postmenopausal bleeding (abnormal uterine bleeding) in a 64-year-old woman  \n- Differential includes endometrial atrophy, endometrial polyp, or endometrial hyperplasia/carcinoma (given age, requires exclusion)  \n\n**Plan:**  \n1. **Diagnostic Workup:**  \n   - Transvaginal ultrasound to assess endometrial thickness  \n   - Endometrial biopsy (office-based or referral for hysteroscopy if needed)  \n   - Consider CBC to evaluate for anemia  \n\n2. **Patient Counseling:**  \n   - Advised that postmenopausal bleeding is never normal and requires further evaluation.  \n   - Reassurance that most causes are benign but malignancy must be ruled out.  \n\n3. **Follow-Up:**  \n   - Return in 2 weeks for biopsy results and further management.  \n   - If bleeding becomes heavy or associated with dizziness/weakness, seek urgent care.  \n\n*[Missing Management Considerations: No discussion of hormone replacement therapy risks/benefits, no referral to gynecologic oncology if high suspicion of malignancy.]*  \n\n**Dictated by:** Dr. [Fictional Name] Smith, MD  \n**Date:** [Fictional Date]  \n\n*Note: This dictation is for testing purposes only and does not constitute real medical advice. All patient details are fictional.*\n\n--- Token Usage Report ---\nPrompt tokens: 158\nCompletion tokens: 766\nTotal tokens: 924\nEstimated cost: $0.000462",
  "ai_provider": "DeepSeek",
  "ai_model": "deepseek-chat",
  "token_usage": {
    "prompt_tokens": 158,
    "completion_tokens": 766,
    "total_tokens": 924,
    "estimated_cost_usd": 0.00046200000000000006
  }
}