{
  "prompt": {
    "prompt": "Create a fictional dictation of a clinical interaction between a healthcare professional and a patient. \nThis dictation is for testing purposes only and should include various topics that might be discussed in a healthcare setting. \nPlease ensure the material is entirely fictional and does not provide any real medical advice or information. \nPlease ensure variables such as age, weight and history are varied.\nThe clinician should ensure the history and examination findings are incomplete, leaving out some pertinent questions.\nIn response to their history and examination findings, the clinician should  provide management advice and guidance.\nThe clinical scenario should be the following: Gestational hypertension",
    "system_prompt": "Create a fictional dictation of a clinical interaction between a healthcare professional and a patient. \nThis dictation is for testing purposes only and should include various topics that might be discussed in a healthcare setting. \nPlease ensure the material is entirely fictional and does not provide any real medical advice or information. \nPlease ensure variables such as age, weight and history are varied.\nThe clinician should ensure the history and examination findings are incomplete, leaving out some pertinent questions.\nIn response to their history and examination findings, the clinician should  provide management advice and guidance.\nThe clinical scenario should be the following: Gestational hypertension"
  },
  "response": "**Dictation: Clinical Interaction – Gestational Hypertension**  \n\n**Date:** [Fictional Date]  \n**Clinician:** Dr. A. Smith  \n**Patient:** Ms. J. Doe  \n**Age:** 32 years  \n**Gestational Age:** 28 weeks  \n**Weight:** 185 lbs (pre-pregnancy weight: 160 lbs)  \n\n### **History of Present Illness:**  \nMs. Doe presents today for a routine prenatal visit. She reports a recent diagnosis of gestational hypertension, noted at her last appointment two weeks ago. She denies headaches, visual disturbances, or right upper quadrant pain. She reports occasional mild swelling in her feet but no significant shortness of breath or chest pain. She has been monitoring her blood pressure at home with readings ranging from 140-150/90-95 mmHg. No prior history of chronic hypertension or renal disease.  \n\n*[Missing Pertinent Information: No documented inquiry about proteinuria, family history of preeclampsia, or medication adherence if previously prescribed.]*  \n\n### **Past Medical History:**  \n- G2P1 (previous uncomplicated vaginal delivery)  \n- No known diabetes, thyroid disease, or autoimmune conditions  \n- No prior history of preeclampsia  \n\n### **Medications:**  \n- Prenatal vitamins  \n- No current antihypertensive medications  \n\n### **Allergies:**  \n- NKDA  \n\n### **Social History:**  \n- Works as a teacher, denies tobacco or illicit drug use  \n- Occasional alcohol prior to pregnancy (none since conception)  \n\n### **Examination Findings:**  \n- **Vitals:** BP 148/92 mmHg (seated, left arm), HR 82 bpm, afebrile  \n- **General:** No acute distress  \n- **Cardiovascular:** Regular rate and rhythm, no murmurs  \n- **Respiratory:** Clear to auscultation bilaterally  \n- **Abdomen:** Soft, non-tender, fundal height appropriate for gestational age  \n- **Extremities:** Mild pitting edema bilaterally to ankles  \n\n*[Missing Pertinent Information: No fundoscopic exam documented, no assessment for hyperreflexia, no urinalysis results available in this dictation.]*  \n\n### **Assessment:**  \nGestational hypertension (without severe features at this time).  \n\n### **Plan:**  \n1. **Monitoring:**  \n   - Continue home BP monitoring twice daily, keeping a log.  \n   - Return for follow-up in **1 week** for repeat BP check and assessment of symptoms.  \n2. **Lifestyle:**  \n   - Reduce sodium intake, increase rest periods with legs elevated.  \n   - Report any severe headache, visual changes, or epigastric pain immediately.  \n3. **Investigations:**  \n   - *[Missing: No lab work ordered in this dictation (e.g., CBC, liver enzymes, creatinine, uric acid, or 24-hour urine protein).]*  \n4. **Medications:**  \n   - No antihypertensive initiated today, but will reconsider if BP trends upward.  \n5. **Fetal Surveillance:**  \n   - Schedule growth ultrasound in 2 weeks to assess fetal well-being.  \n   - No formal NST ordered at this visit.  \n\n*[Note: This dictation is incomplete for testing purposes—key elements such as full lab workup, detailed preeclampsia screening, and contingency planning for worsening hypertension are omitted.]*  \n\n**Next Steps:**  \n- Patient instructed to call with any concerning symptoms.  \n- Will reassess at next visit.  \n\n**End of Dictation.**  \n\n*Disclaimer: This is a fictional clinical scenario for testing purposes only. No real medical advice is implied or provided.*",
  "endpoint": "generateFakeClinicalInteraction",
  "timestamp": "2025-06-10T19-11-23",
  "textContent": "AI: DeepSeek (deepseek-chat)\n\nQ: {\n  \"prompt\": \"Create a fictional dictation of a clinical interaction between a healthcare professional and a patient. \\nThis dictation is for testing purposes only and should include various topics that might be discussed in a healthcare setting. \\nPlease ensure the material is entirely fictional and does not provide any real medical advice or information. \\nPlease ensure variables such as age, weight and history are varied.\\nThe clinician should ensure the history and examination findings are incomplete, leaving out some pertinent questions.\\nIn response to their history and examination findings, the clinician should  provide management advice and guidance.\\nThe clinical scenario should be the following: Gestational hypertension\",\n  \"system_prompt\": \"Create a fictional dictation of a clinical interaction between a healthcare professional and a patient. \\nThis dictation is for testing purposes only and should include various topics that might be discussed in a healthcare setting. \\nPlease ensure the material is entirely fictional and does not provide any real medical advice or information. \\nPlease ensure variables such as age, weight and history are varied.\\nThe clinician should ensure the history and examination findings are incomplete, leaving out some pertinent questions.\\nIn response to their history and examination findings, the clinician should  provide management advice and guidance.\\nThe clinical scenario should be the following: Gestational hypertension\"\n}\n\nA: **Dictation: Clinical Interaction – Gestational Hypertension**  \n\n**Date:** [Fictional Date]  \n**Clinician:** Dr. A. Smith  \n**Patient:** Ms. J. Doe  \n**Age:** 32 years  \n**Gestational Age:** 28 weeks  \n**Weight:** 185 lbs (pre-pregnancy weight: 160 lbs)  \n\n### **History of Present Illness:**  \nMs. Doe presents today for a routine prenatal visit. She reports a recent diagnosis of gestational hypertension, noted at her last appointment two weeks ago. She denies headaches, visual disturbances, or right upper quadrant pain. She reports occasional mild swelling in her feet but no significant shortness of breath or chest pain. She has been monitoring her blood pressure at home with readings ranging from 140-150/90-95 mmHg. No prior history of chronic hypertension or renal disease.  \n\n*[Missing Pertinent Information: No documented inquiry about proteinuria, family history of preeclampsia, or medication adherence if previously prescribed.]*  \n\n### **Past Medical History:**  \n- G2P1 (previous uncomplicated vaginal delivery)  \n- No known diabetes, thyroid disease, or autoimmune conditions  \n- No prior history of preeclampsia  \n\n### **Medications:**  \n- Prenatal vitamins  \n- No current antihypertensive medications  \n\n### **Allergies:**  \n- NKDA  \n\n### **Social History:**  \n- Works as a teacher, denies tobacco or illicit drug use  \n- Occasional alcohol prior to pregnancy (none since conception)  \n\n### **Examination Findings:**  \n- **Vitals:** BP 148/92 mmHg (seated, left arm), HR 82 bpm, afebrile  \n- **General:** No acute distress  \n- **Cardiovascular:** Regular rate and rhythm, no murmurs  \n- **Respiratory:** Clear to auscultation bilaterally  \n- **Abdomen:** Soft, non-tender, fundal height appropriate for gestational age  \n- **Extremities:** Mild pitting edema bilaterally to ankles  \n\n*[Missing Pertinent Information: No fundoscopic exam documented, no assessment for hyperreflexia, no urinalysis results available in this dictation.]*  \n\n### **Assessment:**  \nGestational hypertension (without severe features at this time).  \n\n### **Plan:**  \n1. **Monitoring:**  \n   - Continue home BP monitoring twice daily, keeping a log.  \n   - Return for follow-up in **1 week** for repeat BP check and assessment of symptoms.  \n2. **Lifestyle:**  \n   - Reduce sodium intake, increase rest periods with legs elevated.  \n   - Report any severe headache, visual changes, or epigastric pain immediately.  \n3. **Investigations:**  \n   - *[Missing: No lab work ordered in this dictation (e.g., CBC, liver enzymes, creatinine, uric acid, or 24-hour urine protein).]*  \n4. **Medications:**  \n   - No antihypertensive initiated today, but will reconsider if BP trends upward.  \n5. **Fetal Surveillance:**  \n   - Schedule growth ultrasound in 2 weeks to assess fetal well-being.  \n   - No formal NST ordered at this visit.  \n\n*[Note: This dictation is incomplete for testing purposes—key elements such as full lab workup, detailed preeclampsia screening, and contingency planning for worsening hypertension are omitted.]*  \n\n**Next Steps:**  \n- Patient instructed to call with any concerning symptoms.  \n- Will reassess at next visit.  \n\n**End of Dictation.**  \n\n*Disclaimer: This is a fictional clinical scenario for testing purposes only. No real medical advice is implied or provided.*\n\n--- Token Usage Report ---\nPrompt tokens: 124\nCompletion tokens: 747\nTotal tokens: 871\nEstimated cost: $0.000436",
  "ai_provider": "DeepSeek",
  "ai_model": "deepseek-chat",
  "token_usage": {
    "prompt_tokens": 124,
    "completion_tokens": 747,
    "total_tokens": 871,
    "estimated_cost_usd": 0.0004355
  }
}