{
  "prompt": {
    "prompt": "Create a fictional dictation of a clinical interaction between a healthcare professional and a patient. \nThis dictation is for testing purposes only and should include various topics that might be discussed in a healthcare setting. \nPlease ensure the material is entirely fictional and does not provide any real medical advice or information. \nPlease ensure variables such as age, weight and history are varied.\nThe clinician should ensure the history and examination findings are incomplete, leaving out some pertinent questions.\nIn response to their history and examination findings, the clinician should  provide management advice and guidance.\nThe clinical scenario should be the following: \n\nMake the age 32, the BMI 35.0 and the number of prior pregnancies 4\n\nBase the clinical scenario on the following obstetrics issue: Hyperemesis gravidarum",
    "system_prompt": "Create a fictional dictation of a clinical interaction between a healthcare professional and a patient. \nThis dictation is for testing purposes only and should include various topics that might be discussed in a healthcare setting. \nPlease ensure the material is entirely fictional and does not provide any real medical advice or information. \nPlease ensure variables such as age, weight and history are varied.\nThe clinician should ensure the history and examination findings are incomplete, leaving out some pertinent questions.\nIn response to their history and examination findings, the clinician should  provide management advice and guidance.\nThe clinical scenario should be the following: \n\nMake the age 32, the BMI 35.0 and the number of prior pregnancies 4\n\nBase the clinical scenario on the following obstetrics issue: Hyperemesis gravidarum"
  },
  "response": "**Fictional Clinical Dictation – Hyperemesis Gravidarum**  \n\n**Patient Name:** Jane Doe  \n**Age:** 32  \n**BMI:** 35.0  \n**Gravidity:** 4 (Prior pregnancies: 3 live births, 1 miscarriage at 8 weeks)  \n**Last Menstrual Period (LMP):** 10 weeks ago  \n**Chief Complaint:** Severe nausea and vomiting, inability to tolerate food or fluids for the past 2 weeks  \n\n### **History of Present Illness:**  \nMs. Doe is a 32-year-old female at approximately 10 weeks gestation with a history of obesity (BMI 35.0) presenting with persistent nausea and vomiting for the past 2 weeks. She reports vomiting 8–10 times per day, with episodes occurring both during the day and night. She has been unable to keep down solid foods and has had minimal oral fluid intake. She denies hematemesis but notes occasional dry heaving. She reports a 5-pound weight loss over the past week.  \n\nShe has tried ginger tea and over-the-counter antacids without relief. No prior history of hyperemesis in previous pregnancies, though she had mild nausea in the first trimester with her last pregnancy.  \n\n### **Past Medical History:**  \n- Obesity (BMI 35.0)  \n- Gestational diabetes (prior pregnancy, diet-controlled)  \n- Anxiety (not currently medicated)  \n\n### **Past Surgical History:**  \n- Cesarean section x 2  \n\n### **Medications:**  \n- Prenatal vitamins (unable to tolerate recently)  \n- No current antiemetics  \n\n### **Allergies:**  \n- NKDA  \n\n### **Social History:**  \n- No smoking, occasional alcohol prior to pregnancy  \n- Works as a teacher, currently on sick leave due to symptoms  \n\n### **Review of Systems (Incomplete – Pertinent Negatives/Omissions):**  \n- **General:** Fatigue, weight loss  \n- **GI:** Nausea, vomiting, no diarrhea, no abdominal pain *(omitted: presence of ketonuria, signs of dehydration such as dry mucous membranes, dizziness, or oliguria)*  \n- **Neuro:** No headaches, no visual changes *(omitted: assessment for confusion or altered mental status)*  \n- **Psych:** Reports increased stress due to symptoms *(omitted: screening for depression or suicidal ideation)*  \n\n### **Physical Examination (Incomplete – Pertinent Findings/Omissions):**  \n- **Vitals:** BP 110/70, HR 98, RR 16, Temp 37.0°C *(omitted: orthostatic vitals, weight trend)*  \n- **General:** Appears fatigued, no acute distress  \n- **Cardiovascular:** Tachycardic, regular rhythm, no murmurs  \n- **Respiratory:** Clear to auscultation bilaterally  \n- **Abdomen:** Soft, non-tender, no palpable masses *(omitted: assessment for hepatomegaly or epigastric tenderness)*  \n- **Extremities:** No edema  \n\n### **Assessment:**  \n32-year-old female, G4P3, at 10 weeks gestation with **hyperemesis gravidarum**, likely exacerbated by obesity and prior gestational diabetes. High risk for dehydration and nutritional deficiencies.  \n\n### **Plan:**  \n1. **Labs & Diagnostics:**  \n   - CBC, CMP, TSH, urine ketones, urine hCG (quantitative if needed) *(omitted: consideration of additional tests such as liver function tests or lipase if symptoms persist)*  \n2. **Management:**  \n   - **IV Hydration:** Admit for IV fluids (normal saline with dextrose and multivitamins)  \n   - **Antiemetics:** Start ondansetron 4mg IV/PO q8h PRN nausea, consider adding pyridoxine-doxylamine if symptoms persist  \n   - **Nutritional Support:** Thiamine supplementation due to prolonged vomiting, consider dietitian consult  \n3. **Follow-Up:**  \n   - Reassess in 24–48 hours for response to therapy  \n   - Consider outpatient follow-up with OB if symptoms improve  \n   - If no improvement, may require further workup for alternative causes (e.g., thyroid dysfunction, molar pregnancy)  \n\n### **Counseling:**  \n- Advised patient to seek emergency care if unable to tolerate any fluids, if dizziness worsens, or if she develops severe abdominal pain.  \n- Discussed risks of prolonged vomiting (e.g., electrolyte imbalances, weight loss).  \n- Encouraged small, frequent meals if able to tolerate.  \n\n**Dictated by:** Dr. Smith  \n**Date:** [Fictional Date]  \n\n---  \n*Note: This is a fictional dictation for testing purposes only. No real medical advice is provided.*",
  "endpoint": "newFunctionName",
  "timestamp": "2025-04-30T17-39-31",
  "textContent": "AI: DeepSeek (deepseek-chat)\n\nQ: {\n  \"prompt\": \"Create a fictional dictation of a clinical interaction between a healthcare professional and a patient. \\nThis dictation is for testing purposes only and should include various topics that might be discussed in a healthcare setting. \\nPlease ensure the material is entirely fictional and does not provide any real medical advice or information. \\nPlease ensure variables such as age, weight and history are varied.\\nThe clinician should ensure the history and examination findings are incomplete, leaving out some pertinent questions.\\nIn response to their history and examination findings, the clinician should  provide management advice and guidance.\\nThe clinical scenario should be the following: \\n\\nMake the age 32, the BMI 35.0 and the number of prior pregnancies 4\\n\\nBase the clinical scenario on the following obstetrics issue: Hyperemesis gravidarum\",\n  \"system_prompt\": \"Create a fictional dictation of a clinical interaction between a healthcare professional and a patient. \\nThis dictation is for testing purposes only and should include various topics that might be discussed in a healthcare setting. \\nPlease ensure the material is entirely fictional and does not provide any real medical advice or information. \\nPlease ensure variables such as age, weight and history are varied.\\nThe clinician should ensure the history and examination findings are incomplete, leaving out some pertinent questions.\\nIn response to their history and examination findings, the clinician should  provide management advice and guidance.\\nThe clinical scenario should be the following: \\n\\nMake the age 32, the BMI 35.0 and the number of prior pregnancies 4\\n\\nBase the clinical scenario on the following obstetrics issue: Hyperemesis gravidarum\"\n}\n\nA: **Fictional Clinical Dictation – Hyperemesis Gravidarum**  \n\n**Patient Name:** Jane Doe  \n**Age:** 32  \n**BMI:** 35.0  \n**Gravidity:** 4 (Prior pregnancies: 3 live births, 1 miscarriage at 8 weeks)  \n**Last Menstrual Period (LMP):** 10 weeks ago  \n**Chief Complaint:** Severe nausea and vomiting, inability to tolerate food or fluids for the past 2 weeks  \n\n### **History of Present Illness:**  \nMs. Doe is a 32-year-old female at approximately 10 weeks gestation with a history of obesity (BMI 35.0) presenting with persistent nausea and vomiting for the past 2 weeks. She reports vomiting 8–10 times per day, with episodes occurring both during the day and night. She has been unable to keep down solid foods and has had minimal oral fluid intake. She denies hematemesis but notes occasional dry heaving. She reports a 5-pound weight loss over the past week.  \n\nShe has tried ginger tea and over-the-counter antacids without relief. No prior history of hyperemesis in previous pregnancies, though she had mild nausea in the first trimester with her last pregnancy.  \n\n### **Past Medical History:**  \n- Obesity (BMI 35.0)  \n- Gestational diabetes (prior pregnancy, diet-controlled)  \n- Anxiety (not currently medicated)  \n\n### **Past Surgical History:**  \n- Cesarean section x 2  \n\n### **Medications:**  \n- Prenatal vitamins (unable to tolerate recently)  \n- No current antiemetics  \n\n### **Allergies:**  \n- NKDA  \n\n### **Social History:**  \n- No smoking, occasional alcohol prior to pregnancy  \n- Works as a teacher, currently on sick leave due to symptoms  \n\n### **Review of Systems (Incomplete – Pertinent Negatives/Omissions):**  \n- **General:** Fatigue, weight loss  \n- **GI:** Nausea, vomiting, no diarrhea, no abdominal pain *(omitted: presence of ketonuria, signs of dehydration such as dry mucous membranes, dizziness, or oliguria)*  \n- **Neuro:** No headaches, no visual changes *(omitted: assessment for confusion or altered mental status)*  \n- **Psych:** Reports increased stress due to symptoms *(omitted: screening for depression or suicidal ideation)*  \n\n### **Physical Examination (Incomplete – Pertinent Findings/Omissions):**  \n- **Vitals:** BP 110/70, HR 98, RR 16, Temp 37.0°C *(omitted: orthostatic vitals, weight trend)*  \n- **General:** Appears fatigued, no acute distress  \n- **Cardiovascular:** Tachycardic, regular rhythm, no murmurs  \n- **Respiratory:** Clear to auscultation bilaterally  \n- **Abdomen:** Soft, non-tender, no palpable masses *(omitted: assessment for hepatomegaly or epigastric tenderness)*  \n- **Extremities:** No edema  \n\n### **Assessment:**  \n32-year-old female, G4P3, at 10 weeks gestation with **hyperemesis gravidarum**, likely exacerbated by obesity and prior gestational diabetes. High risk for dehydration and nutritional deficiencies.  \n\n### **Plan:**  \n1. **Labs & Diagnostics:**  \n   - CBC, CMP, TSH, urine ketones, urine hCG (quantitative if needed) *(omitted: consideration of additional tests such as liver function tests or lipase if symptoms persist)*  \n2. **Management:**  \n   - **IV Hydration:** Admit for IV fluids (normal saline with dextrose and multivitamins)  \n   - **Antiemetics:** Start ondansetron 4mg IV/PO q8h PRN nausea, consider adding pyridoxine-doxylamine if symptoms persist  \n   - **Nutritional Support:** Thiamine supplementation due to prolonged vomiting, consider dietitian consult  \n3. **Follow-Up:**  \n   - Reassess in 24–48 hours for response to therapy  \n   - Consider outpatient follow-up with OB if symptoms improve  \n   - If no improvement, may require further workup for alternative causes (e.g., thyroid dysfunction, molar pregnancy)  \n\n### **Counseling:**  \n- Advised patient to seek emergency care if unable to tolerate any fluids, if dizziness worsens, or if she develops severe abdominal pain.  \n- Discussed risks of prolonged vomiting (e.g., electrolyte imbalances, weight loss).  \n- Encouraged small, frequent meals if able to tolerate.  \n\n**Dictated by:** Dr. Smith  \n**Date:** [Fictional Date]  \n\n---  \n*Note: This is a fictional dictation for testing purposes only. No real medical advice is provided.*\n\n--- Token Usage Report ---\nPrompt tokens: 160\nCompletion tokens: 983\nTotal tokens: 1143\nEstimated cost: $0.000571",
  "ai_provider": "DeepSeek",
  "ai_model": "deepseek-chat",
  "token_usage": {
    "prompt_tokens": 160,
    "completion_tokens": 983,
    "total_tokens": 1143,
    "estimated_cost_usd": 0.0005715
  }
}