{
  "prompt": {
    "prompt": "Please write a concise clinical note using medical terminology, based solely on the clinical transcript provided below. Do not invent or assume any details that are not explicitly mentioned in the transcript.\n\nThe output should be in 3 sectiions.\nThe first section should be a simple summary of the presentation in bullet points, each point on a new line, including age, presenting complaint(s), and if relevant things like previous pregnancies (or lack thereof) and BMI. \nThen there should be a newline, then the middle section should be describe each issue in detail with the appropriate context and the associated advice from the doctor.\nThen there should be a newline, then the plan: first write &#x27;Plan:&#x27; and then, from a new line, a numbered list of the management steps anticipated\n\nRules:\n- Use professional medical terminology.\n- Use one sentence per line.\n- Only include details that are directly mentioned in the transcript\n\nClinical transcript:\n**Fictional Clinical Dictation: Abnormal Uterine Bleeding**  \n\n**Patient Name:** Jane Doe (Fictional)  \n**Age:** 42 years  \n**Date of Visit:** October 10, 2023  \n**Clinician:** Dr. Smith (Fictional)  \n\n---  \n\n### **Subjective:**  \nMs. Doe presents today reporting a 4-month history of abnormal uterine bleeding. She describes her periods as &quot;heavier and longer&quot; than usual, lasting 10–14 days with flooding and clots. She denies intermenstrual bleeding but reports occasional spotting. She has no associated pelvic pain or dyspareunia.  \n\nShe has no significant past medical history, though she admits to a family history of &quot;thyroid problems&quot; (unspecified). She takes no medications, including hormonal contraception, and has no known drug allergies. She is a non-smoker and drinks alcohol socially.  \n\n*[Missing Pertinent Questions: Last Pap smear, sexual activity history, weight changes, symptoms of anemia (fatigue, dizziness), or thyroid dysfunction.]*  \n\n### **Objective:**  \n**Vitals:** BP 118&#x2F;76, HR 78, BMI 28 (weight 75 kg).  \n**General:** Well-appearing, no pallor.  \n**Abdominal Exam:** Soft, non-tender, no masses.  \n**Pelvic Exam (limited):** External genitalia normal. No active bleeding at time of exam. Cervix appears normal; no visible lesions. Uterus is anteverted, non-tender, normal size. Adnexa non-tender.  \n\n*[Missing Pertinent Findings: No speculum exam documented, no cervical motion tenderness, no assessment for uterine enlargement&#x2F;fibroids, no thyroid exam.]*  \n\n### **Assessment:**  \n42-year-old female with abnormal uterine bleeding (AUB), likely secondary to perimenopausal hormonal changes or structural causes (e.g., fibroids, polyps). Other possibilities include thyroid dysfunction or coagulopathy, though not yet assessed.  \n\n### **Plan:**  \n1. **Initial Workup:**  \n   - CBC (to assess for anemia).  \n   - TSH (given family history of thyroid issues).  \n   - Pelvic ultrasound (to evaluate for fibroids&#x2F;polyps).  \n   - *[Missing: No coagulation studies, no endometrial biopsy despite age &gt;40, no discussion of Pap smear if overdue.]*  \n\n2. **Symptomatic Management:**  \n   - Start tranexamic acid 1g TID during heavy bleeding days.  \n   - Consider trial of NSAIDs (e.g., ibuprofen) for pain&#x2F;bleeding reduction.  \n   - *[Missing: No discussion of hormonal options (e.g., OCPs, progesterone) or iron supplementation if anemic.]*  \n\n3. **Follow-Up:**  \n   - Return in 4 weeks to review results and adjust plan.  \n   - Emergency referral if hemodynamically unstable bleeding.  \n\n**Counseling:**  \nDiscussed that bleeding could be due to perimenopause but requires further evaluation to rule out other causes. Advised to track bleeding patterns and symptoms.  \n\n---  \n**Note:** This is a fictional dictation for testing purposes only. No real medical advice is given. Key history and exam elements are intentionally omitted to simulate an incomplete assessment.  \n\n---  \nWould you like any modifications (e.g., more omissions, different management approaches)?",
    "system_prompt": "Please write a concise clinical note using medical terminology, based solely on the clinical transcript provided below. Do not invent or assume any details that are not explicitly mentioned in the transcript.\n\nThe output should be in 3 sectiions.\nThe first section should be a simple summary of the presentation in bullet points, each point on a new line, including age, presenting complaint(s), and if relevant things like previous pregnancies (or lack thereof) and BMI. \nThen there should be a newline, then the middle section should be describe each issue in detail with the appropriate context and the associated advice from the doctor.\nThen there should be a newline, then the plan: first write &#x27;Plan:&#x27; and then, from a new line, a numbered list of the management steps anticipated\n\nRules:\n- Use professional medical terminology.\n- Use one sentence per line.\n- Only include details that are directly mentioned in the transcript\n\nClinical transcript:\n**Fictional Clinical Dictation: Abnormal Uterine Bleeding**  \n\n**Patient Name:** Jane Doe (Fictional)  \n**Age:** 42 years  \n**Date of Visit:** October 10, 2023  \n**Clinician:** Dr. Smith (Fictional)  \n\n---  \n\n### **Subjective:**  \nMs. Doe presents today reporting a 4-month history of abnormal uterine bleeding. She describes her periods as &quot;heavier and longer&quot; than usual, lasting 10–14 days with flooding and clots. She denies intermenstrual bleeding but reports occasional spotting. She has no associated pelvic pain or dyspareunia.  \n\nShe has no significant past medical history, though she admits to a family history of &quot;thyroid problems&quot; (unspecified). She takes no medications, including hormonal contraception, and has no known drug allergies. She is a non-smoker and drinks alcohol socially.  \n\n*[Missing Pertinent Questions: Last Pap smear, sexual activity history, weight changes, symptoms of anemia (fatigue, dizziness), or thyroid dysfunction.]*  \n\n### **Objective:**  \n**Vitals:** BP 118&#x2F;76, HR 78, BMI 28 (weight 75 kg).  \n**General:** Well-appearing, no pallor.  \n**Abdominal Exam:** Soft, non-tender, no masses.  \n**Pelvic Exam (limited):** External genitalia normal. No active bleeding at time of exam. Cervix appears normal; no visible lesions. Uterus is anteverted, non-tender, normal size. Adnexa non-tender.  \n\n*[Missing Pertinent Findings: No speculum exam documented, no cervical motion tenderness, no assessment for uterine enlargement&#x2F;fibroids, no thyroid exam.]*  \n\n### **Assessment:**  \n42-year-old female with abnormal uterine bleeding (AUB), likely secondary to perimenopausal hormonal changes or structural causes (e.g., fibroids, polyps). Other possibilities include thyroid dysfunction or coagulopathy, though not yet assessed.  \n\n### **Plan:**  \n1. **Initial Workup:**  \n   - CBC (to assess for anemia).  \n   - TSH (given family history of thyroid issues).  \n   - Pelvic ultrasound (to evaluate for fibroids&#x2F;polyps).  \n   - *[Missing: No coagulation studies, no endometrial biopsy despite age &gt;40, no discussion of Pap smear if overdue.]*  \n\n2. **Symptomatic Management:**  \n   - Start tranexamic acid 1g TID during heavy bleeding days.  \n   - Consider trial of NSAIDs (e.g., ibuprofen) for pain&#x2F;bleeding reduction.  \n   - *[Missing: No discussion of hormonal options (e.g., OCPs, progesterone) or iron supplementation if anemic.]*  \n\n3. **Follow-Up:**  \n   - Return in 4 weeks to review results and adjust plan.  \n   - Emergency referral if hemodynamically unstable bleeding.  \n\n**Counseling:**  \nDiscussed that bleeding could be due to perimenopause but requires further evaluation to rule out other causes. Advised to track bleeding patterns and symptoms.  \n\n---  \n**Note:** This is a fictional dictation for testing purposes only. No real medical advice is given. Key history and exam elements are intentionally omitted to simulate an incomplete assessment.  \n\n---  \nWould you like any modifications (e.g., more omissions, different management approaches)?"
  },
  "response": "### Summary:  \n- 42-year-old female.  \n- Presenting with 4-month history of abnormal uterine bleeding (heavier, prolonged menses lasting 10–14 days, flooding, clots, occasional spotting).  \n- No intermenstrual bleeding, pelvic pain, or dyspareunia.  \n- No significant PMH; family history of unspecified thyroid problems.  \n- No medications, no hormonal contraception, no drug allergies.  \n- Non-smoker, social alcohol use.  \n- BMI 28 (weight 75 kg).  \n\n### Details:  \n- Patient reports menorrhagia with prolonged duration (10–14 days), flooding, and clots, but no intermenstrual bleeding or pain.  \n- No signs of anemia (well-appearing, no pallor) or pelvic pathology on limited exam (normal cervix, uterus anteverted, non-tender, normal size).  \n- Differential includes perimenopausal hormonal changes, structural causes (e.g., fibroids/polyps), or thyroid dysfunction (given family history).  \n- Advised symptomatic management with tranexamic acid (1g TID during heavy bleeding) and NSAIDs (e.g., ibuprofen) for pain/bleeding reduction.  \n- Counseled on tracking bleeding patterns and potential perimenopausal etiology pending further workup.  \n\n### Plan:  \n1. Initial workup:  \n   - CBC to assess for anemia.  \n   - TSH to evaluate thyroid function.  \n   - Pelvic ultrasound to rule out structural causes (fibroids/polyps).  \n2. Symptomatic management:  \n   - Tranexamic acid 1g TID during heavy bleeding.  \n   - Trial of NSAIDs (e.g., ibuprofen) as needed.  \n3. Follow-up in 4 weeks to review results and adjust management.  \n4. Emergency referral if hemodynamically unstable bleeding occurs.",
  "endpoint": "generateFakeClinicalInteraction",
  "timestamp": "2025-05-26T15-54-47",
  "textContent": "AI: DeepSeek (deepseek-chat)\n\nQ: {\n  \"prompt\": \"Please write a concise clinical note using medical terminology, based solely on the clinical transcript provided below. Do not invent or assume any details that are not explicitly mentioned in the transcript.\\n\\nThe output should be in 3 sectiions.\\nThe first section should be a simple summary of the presentation in bullet points, each point on a new line, including age, presenting complaint(s), and if relevant things like previous pregnancies (or lack thereof) and BMI. \\nThen there should be a newline, then the middle section should be describe each issue in detail with the appropriate context and the associated advice from the doctor.\\nThen there should be a newline, then the plan: first write &#x27;Plan:&#x27; and then, from a new line, a numbered list of the management steps anticipated\\n\\nRules:\\n- Use professional medical terminology.\\n- Use one sentence per line.\\n- Only include details that are directly mentioned in the transcript\\n\\nClinical transcript:\\n**Fictional Clinical Dictation: Abnormal Uterine Bleeding**  \\n\\n**Patient Name:** Jane Doe (Fictional)  \\n**Age:** 42 years  \\n**Date of Visit:** October 10, 2023  \\n**Clinician:** Dr. Smith (Fictional)  \\n\\n---  \\n\\n### **Subjective:**  \\nMs. Doe presents today reporting a 4-month history of abnormal uterine bleeding. She describes her periods as &quot;heavier and longer&quot; than usual, lasting 10–14 days with flooding and clots. She denies intermenstrual bleeding but reports occasional spotting. She has no associated pelvic pain or dyspareunia.  \\n\\nShe has no significant past medical history, though she admits to a family history of &quot;thyroid problems&quot; (unspecified). She takes no medications, including hormonal contraception, and has no known drug allergies. She is a non-smoker and drinks alcohol socially.  \\n\\n*[Missing Pertinent Questions: Last Pap smear, sexual activity history, weight changes, symptoms of anemia (fatigue, dizziness), or thyroid dysfunction.]*  \\n\\n### **Objective:**  \\n**Vitals:** BP 118&#x2F;76, HR 78, BMI 28 (weight 75 kg).  \\n**General:** Well-appearing, no pallor.  \\n**Abdominal Exam:** Soft, non-tender, no masses.  \\n**Pelvic Exam (limited):** External genitalia normal. No active bleeding at time of exam. Cervix appears normal; no visible lesions. Uterus is anteverted, non-tender, normal size. Adnexa non-tender.  \\n\\n*[Missing Pertinent Findings: No speculum exam documented, no cervical motion tenderness, no assessment for uterine enlargement&#x2F;fibroids, no thyroid exam.]*  \\n\\n### **Assessment:**  \\n42-year-old female with abnormal uterine bleeding (AUB), likely secondary to perimenopausal hormonal changes or structural causes (e.g., fibroids, polyps). Other possibilities include thyroid dysfunction or coagulopathy, though not yet assessed.  \\n\\n### **Plan:**  \\n1. **Initial Workup:**  \\n   - CBC (to assess for anemia).  \\n   - TSH (given family history of thyroid issues).  \\n   - Pelvic ultrasound (to evaluate for fibroids&#x2F;polyps).  \\n   - *[Missing: No coagulation studies, no endometrial biopsy despite age &gt;40, no discussion of Pap smear if overdue.]*  \\n\\n2. **Symptomatic Management:**  \\n   - Start tranexamic acid 1g TID during heavy bleeding days.  \\n   - Consider trial of NSAIDs (e.g., ibuprofen) for pain&#x2F;bleeding reduction.  \\n   - *[Missing: No discussion of hormonal options (e.g., OCPs, progesterone) or iron supplementation if anemic.]*  \\n\\n3. **Follow-Up:**  \\n   - Return in 4 weeks to review results and adjust plan.  \\n   - Emergency referral if hemodynamically unstable bleeding.  \\n\\n**Counseling:**  \\nDiscussed that bleeding could be due to perimenopause but requires further evaluation to rule out other causes. Advised to track bleeding patterns and symptoms.  \\n\\n---  \\n**Note:** This is a fictional dictation for testing purposes only. No real medical advice is given. Key history and exam elements are intentionally omitted to simulate an incomplete assessment.  \\n\\n---  \\nWould you like any modifications (e.g., more omissions, different management approaches)?\",\n  \"system_prompt\": \"Please write a concise clinical note using medical terminology, based solely on the clinical transcript provided below. Do not invent or assume any details that are not explicitly mentioned in the transcript.\\n\\nThe output should be in 3 sectiions.\\nThe first section should be a simple summary of the presentation in bullet points, each point on a new line, including age, presenting complaint(s), and if relevant things like previous pregnancies (or lack thereof) and BMI. \\nThen there should be a newline, then the middle section should be describe each issue in detail with the appropriate context and the associated advice from the doctor.\\nThen there should be a newline, then the plan: first write &#x27;Plan:&#x27; and then, from a new line, a numbered list of the management steps anticipated\\n\\nRules:\\n- Use professional medical terminology.\\n- Use one sentence per line.\\n- Only include details that are directly mentioned in the transcript\\n\\nClinical transcript:\\n**Fictional Clinical Dictation: Abnormal Uterine Bleeding**  \\n\\n**Patient Name:** Jane Doe (Fictional)  \\n**Age:** 42 years  \\n**Date of Visit:** October 10, 2023  \\n**Clinician:** Dr. Smith (Fictional)  \\n\\n---  \\n\\n### **Subjective:**  \\nMs. Doe presents today reporting a 4-month history of abnormal uterine bleeding. She describes her periods as &quot;heavier and longer&quot; than usual, lasting 10–14 days with flooding and clots. She denies intermenstrual bleeding but reports occasional spotting. She has no associated pelvic pain or dyspareunia.  \\n\\nShe has no significant past medical history, though she admits to a family history of &quot;thyroid problems&quot; (unspecified). She takes no medications, including hormonal contraception, and has no known drug allergies. She is a non-smoker and drinks alcohol socially.  \\n\\n*[Missing Pertinent Questions: Last Pap smear, sexual activity history, weight changes, symptoms of anemia (fatigue, dizziness), or thyroid dysfunction.]*  \\n\\n### **Objective:**  \\n**Vitals:** BP 118&#x2F;76, HR 78, BMI 28 (weight 75 kg).  \\n**General:** Well-appearing, no pallor.  \\n**Abdominal Exam:** Soft, non-tender, no masses.  \\n**Pelvic Exam (limited):** External genitalia normal. No active bleeding at time of exam. Cervix appears normal; no visible lesions. Uterus is anteverted, non-tender, normal size. Adnexa non-tender.  \\n\\n*[Missing Pertinent Findings: No speculum exam documented, no cervical motion tenderness, no assessment for uterine enlargement&#x2F;fibroids, no thyroid exam.]*  \\n\\n### **Assessment:**  \\n42-year-old female with abnormal uterine bleeding (AUB), likely secondary to perimenopausal hormonal changes or structural causes (e.g., fibroids, polyps). Other possibilities include thyroid dysfunction or coagulopathy, though not yet assessed.  \\n\\n### **Plan:**  \\n1. **Initial Workup:**  \\n   - CBC (to assess for anemia).  \\n   - TSH (given family history of thyroid issues).  \\n   - Pelvic ultrasound (to evaluate for fibroids&#x2F;polyps).  \\n   - *[Missing: No coagulation studies, no endometrial biopsy despite age &gt;40, no discussion of Pap smear if overdue.]*  \\n\\n2. **Symptomatic Management:**  \\n   - Start tranexamic acid 1g TID during heavy bleeding days.  \\n   - Consider trial of NSAIDs (e.g., ibuprofen) for pain&#x2F;bleeding reduction.  \\n   - *[Missing: No discussion of hormonal options (e.g., OCPs, progesterone) or iron supplementation if anemic.]*  \\n\\n3. **Follow-Up:**  \\n   - Return in 4 weeks to review results and adjust plan.  \\n   - Emergency referral if hemodynamically unstable bleeding.  \\n\\n**Counseling:**  \\nDiscussed that bleeding could be due to perimenopause but requires further evaluation to rule out other causes. Advised to track bleeding patterns and symptoms.  \\n\\n---  \\n**Note:** This is a fictional dictation for testing purposes only. No real medical advice is given. Key history and exam elements are intentionally omitted to simulate an incomplete assessment.  \\n\\n---  \\nWould you like any modifications (e.g., more omissions, different management approaches)?\"\n}\n\nA: ### Summary:  \n- 42-year-old female.  \n- Presenting with 4-month history of abnormal uterine bleeding (heavier, prolonged menses lasting 10–14 days, flooding, clots, occasional spotting).  \n- No intermenstrual bleeding, pelvic pain, or dyspareunia.  \n- No significant PMH; family history of unspecified thyroid problems.  \n- No medications, no hormonal contraception, no drug allergies.  \n- Non-smoker, social alcohol use.  \n- BMI 28 (weight 75 kg).  \n\n### Details:  \n- Patient reports menorrhagia with prolonged duration (10–14 days), flooding, and clots, but no intermenstrual bleeding or pain.  \n- No signs of anemia (well-appearing, no pallor) or pelvic pathology on limited exam (normal cervix, uterus anteverted, non-tender, normal size).  \n- Differential includes perimenopausal hormonal changes, structural causes (e.g., fibroids/polyps), or thyroid dysfunction (given family history).  \n- Advised symptomatic management with tranexamic acid (1g TID during heavy bleeding) and NSAIDs (e.g., ibuprofen) for pain/bleeding reduction.  \n- Counseled on tracking bleeding patterns and potential perimenopausal etiology pending further workup.  \n\n### Plan:  \n1. Initial workup:  \n   - CBC to assess for anemia.  \n   - TSH to evaluate thyroid function.  \n   - Pelvic ultrasound to rule out structural causes (fibroids/polyps).  \n2. Symptomatic management:  \n   - Tranexamic acid 1g TID during heavy bleeding.  \n   - Trial of NSAIDs (e.g., ibuprofen) as needed.  \n3. Follow-up in 4 weeks to review results and adjust management.  \n4. Emergency referral if hemodynamically unstable bleeding occurs.\n\n--- Token Usage Report ---\nPrompt tokens: 917\nCompletion tokens: 383\nTotal tokens: 1300\nEstimated cost: $0.000650",
  "ai_provider": "DeepSeek",
  "ai_model": "deepseek-chat",
  "token_usage": {
    "prompt_tokens": 917,
    "completion_tokens": 383,
    "total_tokens": 1300,
    "estimated_cost_usd": 0.0006500000000000001
  }
}