{
  "prompt": {
    "prompt": "Create a fictional dictation of a clinical interaction between a healthcare professional and a patient. \nThis dictation is for testing purposes only and should include various topics that might be discussed in a healthcare setting. \nPlease ensure the material is entirely fictional and does not provide any real medical advice or information. \nPlease ensure variables such as age, weight and history are varied.\nThe clinician should ensure the history and examination findings are incomplete, leaving out some pertinent questions.\nIn response to their history and examination findings, the clinician should  provide management advice and guidance.\nThe clinical scenario should be the following: \n\nMake the age 51, the BMI 19.8 and the number of prior pregnancies 0\n\nBase the clinical scenario on the following gynecology issue: Abnormal uterine bleeding",
    "system_prompt": "Create a fictional dictation of a clinical interaction between a healthcare professional and a patient. \nThis dictation is for testing purposes only and should include various topics that might be discussed in a healthcare setting. \nPlease ensure the material is entirely fictional and does not provide any real medical advice or information. \nPlease ensure variables such as age, weight and history are varied.\nThe clinician should ensure the history and examination findings are incomplete, leaving out some pertinent questions.\nIn response to their history and examination findings, the clinician should  provide management advice and guidance.\nThe clinical scenario should be the following: \n\nMake the age 51, the BMI 19.8 and the number of prior pregnancies 0\n\nBase the clinical scenario on the following gynecology issue: Abnormal uterine bleeding"
  },
  "response": "**Dictation: Clinical Interaction – Abnormal Uterine Bleeding**  \n\n**Patient Details:**  \n- Name: Jane Doe (fictional)  \n- Age: 51  \n- BMI: 19.8 (weight: 58 kg, height: 1.71 m)  \n- Gravida: 0, Para: 0  \n- Last Menstrual Period (LMP): Ongoing, irregular for 6 months  \n- Contraception: None  \n\n**History of Presenting Complaint:**  \nMs. Doe reports a 6-month history of irregular uterine bleeding, characterized by prolonged and heavy episodes lasting 10–14 days, followed by unpredictable light spotting. She denies intermenstrual bleeding but reports occasional clots. She has no dysmenorrhea or postcoital bleeding. She has not tracked her cycles but estimates they occur every 3–6 weeks.  \n\n**Relevant Medical History:**  \n- No prior gynecological procedures (e.g., hysteroscopy, D&C).  \n- No history of PCOS or endometriosis.  \n- No known bleeding disorders.  \n- No chronic medical conditions (e.g., diabetes, hypertension).  \n- Medications: Occasional ibuprofen for headaches.  \n- Allergies: None.  \n\n**Social History:**  \n- Non-smoker, occasional alcohol (1–2 units/week).  \n- Works as an office administrator; moderate stress levels.  \n- No recent weight changes or excessive exercise.  \n\n**Family History:**  \n- Mother had breast cancer at age 65.  \n- No known family history of gynecologic malignancies or bleeding disorders.  \n\n**Examination Findings (Incomplete):**  \n- General: Appears well, no pallor.  \n- Abdomen: Soft, non-tender, no masses.  \n- Speculum exam: Cervix appears normal; no visible lesions.  \n- Bimanual exam: Uterus anteverted, normal size; no adnexal tenderness.  \n*(Missing: Pelvic ultrasound results, thyroid function assessment, coagulation screen, endometrial biopsy.)*  \n\n**Assessment:**  \nGiven Ms. Doe’s age (perimenopausal), nulliparity, and abnormal bleeding pattern, the differential includes:  \n1. **Anovulatory bleeding** (most likely, due to perimenopause).  \n2. **Endometrial hyperplasia/polyp** (needs exclusion).  \n3. **Less likely:** Coagulopathy, thyroid dysfunction, or malignancy.  \n\n**Management Plan (Incomplete Guidance):**  \n1. **Initial workup:**  \n   - Pelvic ultrasound (transvaginal preferred) to assess endometrial thickness.  \n   - CBC to rule out anemia.  \n   *(Missing: TSH, coagulation studies, endometrial biopsy if indicated.)*  \n2. **Empirical treatment:**  \n   - Start oral progestin (e.g., medroxyprogesterone 10 mg daily for 10 days) to regulate bleeding.  \n   - Consider tranexamic acid if heavy bleeding persists.  \n3. **Follow-up:**  \n   - Review ultrasound and lab results in 2 weeks.  \n   - If bleeding persists or endometrial thickness >4 mm, recommend hysteroscopy ± biopsy.  \n   *(Missing: Discussion of hormonal therapy risks/benefits, screening for malignancy.)*  \n\n**Patient Counseling:**  \n- Reassured that this is likely perimenopausal but requires further evaluation.  \n- Advised to track bleeding patterns and report worsening symptoms.  \n- No advice given on bone health or cardiovascular risks related to hypoestrogenemia.  \n\n**Impression:**  \nProbable perimenopausal anovulatory bleeding, but endometrial pathology must be excluded.  \n\n**Dictated by:** Dr. Smith (fictional)  \n**Date:** [Today’s date]  \n\n**Note for Testing:** This is a fictional dictation for educational purposes only. No real patient data or medical advice is provided. Incomplete elements are intentional for training scenarios.",
  "endpoint": "newFunctionName",
  "timestamp": "2025-04-22T05-15-57",
  "textContent": "AI: DeepSeek (deepseek-chat)\n\nQ: {\n  \"prompt\": \"Create a fictional dictation of a clinical interaction between a healthcare professional and a patient. \\nThis dictation is for testing purposes only and should include various topics that might be discussed in a healthcare setting. \\nPlease ensure the material is entirely fictional and does not provide any real medical advice or information. \\nPlease ensure variables such as age, weight and history are varied.\\nThe clinician should ensure the history and examination findings are incomplete, leaving out some pertinent questions.\\nIn response to their history and examination findings, the clinician should  provide management advice and guidance.\\nThe clinical scenario should be the following: \\n\\nMake the age 51, the BMI 19.8 and the number of prior pregnancies 0\\n\\nBase the clinical scenario on the following gynecology issue: Abnormal uterine bleeding\",\n  \"system_prompt\": \"Create a fictional dictation of a clinical interaction between a healthcare professional and a patient. \\nThis dictation is for testing purposes only and should include various topics that might be discussed in a healthcare setting. \\nPlease ensure the material is entirely fictional and does not provide any real medical advice or information. \\nPlease ensure variables such as age, weight and history are varied.\\nThe clinician should ensure the history and examination findings are incomplete, leaving out some pertinent questions.\\nIn response to their history and examination findings, the clinician should  provide management advice and guidance.\\nThe clinical scenario should be the following: \\n\\nMake the age 51, the BMI 19.8 and the number of prior pregnancies 0\\n\\nBase the clinical scenario on the following gynecology issue: Abnormal uterine bleeding\"\n}\n\nA: **Dictation: Clinical Interaction – Abnormal Uterine Bleeding**  \n\n**Patient Details:**  \n- Name: Jane Doe (fictional)  \n- Age: 51  \n- BMI: 19.8 (weight: 58 kg, height: 1.71 m)  \n- Gravida: 0, Para: 0  \n- Last Menstrual Period (LMP): Ongoing, irregular for 6 months  \n- Contraception: None  \n\n**History of Presenting Complaint:**  \nMs. Doe reports a 6-month history of irregular uterine bleeding, characterized by prolonged and heavy episodes lasting 10–14 days, followed by unpredictable light spotting. She denies intermenstrual bleeding but reports occasional clots. She has no dysmenorrhea or postcoital bleeding. She has not tracked her cycles but estimates they occur every 3–6 weeks.  \n\n**Relevant Medical History:**  \n- No prior gynecological procedures (e.g., hysteroscopy, D&C).  \n- No history of PCOS or endometriosis.  \n- No known bleeding disorders.  \n- No chronic medical conditions (e.g., diabetes, hypertension).  \n- Medications: Occasional ibuprofen for headaches.  \n- Allergies: None.  \n\n**Social History:**  \n- Non-smoker, occasional alcohol (1–2 units/week).  \n- Works as an office administrator; moderate stress levels.  \n- No recent weight changes or excessive exercise.  \n\n**Family History:**  \n- Mother had breast cancer at age 65.  \n- No known family history of gynecologic malignancies or bleeding disorders.  \n\n**Examination Findings (Incomplete):**  \n- General: Appears well, no pallor.  \n- Abdomen: Soft, non-tender, no masses.  \n- Speculum exam: Cervix appears normal; no visible lesions.  \n- Bimanual exam: Uterus anteverted, normal size; no adnexal tenderness.  \n*(Missing: Pelvic ultrasound results, thyroid function assessment, coagulation screen, endometrial biopsy.)*  \n\n**Assessment:**  \nGiven Ms. Doe’s age (perimenopausal), nulliparity, and abnormal bleeding pattern, the differential includes:  \n1. **Anovulatory bleeding** (most likely, due to perimenopause).  \n2. **Endometrial hyperplasia/polyp** (needs exclusion).  \n3. **Less likely:** Coagulopathy, thyroid dysfunction, or malignancy.  \n\n**Management Plan (Incomplete Guidance):**  \n1. **Initial workup:**  \n   - Pelvic ultrasound (transvaginal preferred) to assess endometrial thickness.  \n   - CBC to rule out anemia.  \n   *(Missing: TSH, coagulation studies, endometrial biopsy if indicated.)*  \n2. **Empirical treatment:**  \n   - Start oral progestin (e.g., medroxyprogesterone 10 mg daily for 10 days) to regulate bleeding.  \n   - Consider tranexamic acid if heavy bleeding persists.  \n3. **Follow-up:**  \n   - Review ultrasound and lab results in 2 weeks.  \n   - If bleeding persists or endometrial thickness >4 mm, recommend hysteroscopy ± biopsy.  \n   *(Missing: Discussion of hormonal therapy risks/benefits, screening for malignancy.)*  \n\n**Patient Counseling:**  \n- Reassured that this is likely perimenopausal but requires further evaluation.  \n- Advised to track bleeding patterns and report worsening symptoms.  \n- No advice given on bone health or cardiovascular risks related to hypoestrogenemia.  \n\n**Impression:**  \nProbable perimenopausal anovulatory bleeding, but endometrial pathology must be excluded.  \n\n**Dictated by:** Dr. Smith (fictional)  \n**Date:** [Today’s date]  \n\n**Note for Testing:** This is a fictional dictation for educational purposes only. No real patient data or medical advice is provided. Incomplete elements are intentional for training scenarios.\n\n--- Token Usage Report ---\nPrompt tokens: 158\nCompletion tokens: 806\nTotal tokens: 964\nEstimated cost: $0.000482",
  "ai_provider": "DeepSeek",
  "ai_model": "deepseek-chat",
  "token_usage": {
    "prompt_tokens": 158,
    "completion_tokens": 806,
    "total_tokens": 964,
    "estimated_cost_usd": 0.000482
  }
}