{
  "prompt": {
    "prompt": "Create a fictional dictation of a clinical interaction between a healthcare professional and a patient. \nThis dictation is for testing purposes only and should include various topics that might be discussed in a healthcare setting. \nPlease ensure the material is entirely fictional and does not provide any real medical advice or information. \nPlease ensure variables such as age, weight and history are varied.\nThe clinician should ensure the history and examination findings are incomplete, leaving out some pertinent questions.\nIn response to their history and examination findings, the clinician should  provide management advice and guidance.\nThe clinical scenario should be the following:  \n            \nThe clinical scenario should focus on a patient with Bartholin&#x27;s cyst&#x2F;abscess.",
    "system_prompt": "Create a fictional dictation of a clinical interaction between a healthcare professional and a patient. \nThis dictation is for testing purposes only and should include various topics that might be discussed in a healthcare setting. \nPlease ensure the material is entirely fictional and does not provide any real medical advice or information. \nPlease ensure variables such as age, weight and history are varied.\nThe clinician should ensure the history and examination findings are incomplete, leaving out some pertinent questions.\nIn response to their history and examination findings, the clinician should  provide management advice and guidance.\nThe clinical scenario should be the following:  \n            \nThe clinical scenario should focus on a patient with Bartholin&#x27;s cyst&#x2F;abscess."
  },
  "response": "**Clinical Dictation: Fictional Patient Encounter – Bartholin’s Cyst/Abscess**  \n\n**Patient Details:**  \n- Name: Ms. Jane Doe (fictional)  \n- Age: 32 years  \n- Gender: Female  \n- Weight: 68 kg  \n- Occupation: Office administrator  \n- Marital Status: Single  \n- Allergies: NKDA  \n\n**History of Presenting Complaint:**  \nMs. Doe presents to the clinic with a 4-day history of increasing pain and swelling in the left vulvar region. She describes the pain as throbbing and worse with walking or sitting. She denies any recent trauma or sexual activity but reports mild dysuria. No fever or systemic symptoms reported. She has never had similar symptoms before.  \n\n**Past Medical History:**  \n- No significant medical history.  \n- No prior surgeries.  \n- No known chronic illnesses.  \n\n**Medications:**  \n- Occasional ibuprofen for headaches (last taken 2 days ago).  \n\n**Social History:**  \n- Non-smoker.  \n- Alcohol: Occasional social drinking.  \n- Denies recreational drug use.  \n\n**Examination Findings:**  \n- General: Well-appearing, afebrile, no signs of systemic illness.  \n- Local Exam: Left labia majora swollen with a tender, fluctuant 3 cm mass noted at the Bartholin’s gland location. Overlying skin erythematous but intact. No active discharge or visible pus. Right gland appears normal.  \n\n**Assessment:**  \nLikely left Bartholin’s abscess given acute onset, localized tenderness, and fluctuance. No signs of systemic infection.  \n\n**Plan:**  \n1. **Incision & Drainage (I&D):** Recommend bedside I&D under local anesthesia given symptomatic abscess. Risks/benefits discussed (pain, bleeding, recurrence).  \n2. **Pain Management:** Prescribe oral paracetamol 1g QID PRN and ibuprofen 400mg TID PRN.  \n3. **Antibiotics:** Not routinely indicated unless systemic signs of infection develop (none currently).  \n4. **Follow-Up:** Advised to return if worsening pain, fever, or recurrence. No routine follow-up scheduled.  \n\n**Missed Pertinent Questions:**  \n- Sexual history (e.g., new partners, STI risk).  \n- Contraceptive use (hormonal influences).  \n- Previous STI testing/treatment.  \n- Detailed menstrual history (timing related to symptoms).  \n\n**Counseling:**  \n- Educated on warm sitz baths for comfort.  \n- Advised to avoid tight clothing.  \n- No restrictions on sexual activity, but advised to return if symptoms worsen post-intercourse.  \n\n**Dictated by:** Dr. Smith (fictional)  \n**Date:** [Fictional date]  \n\n**Disclaimer:** This is a fictional dictation for testing purposes only. No real patient data or medical advice is provided.",
  "endpoint": "generateFakeClinicalInteraction",
  "timestamp": "2025-05-26T16-05-24",
  "textContent": "AI: DeepSeek (deepseek-chat)\n\nQ: {\n  \"prompt\": \"Create a fictional dictation of a clinical interaction between a healthcare professional and a patient. \\nThis dictation is for testing purposes only and should include various topics that might be discussed in a healthcare setting. \\nPlease ensure the material is entirely fictional and does not provide any real medical advice or information. \\nPlease ensure variables such as age, weight and history are varied.\\nThe clinician should ensure the history and examination findings are incomplete, leaving out some pertinent questions.\\nIn response to their history and examination findings, the clinician should  provide management advice and guidance.\\nThe clinical scenario should be the following:  \\n            \\nThe clinical scenario should focus on a patient with Bartholin&#x27;s cyst&#x2F;abscess.\",\n  \"system_prompt\": \"Create a fictional dictation of a clinical interaction between a healthcare professional and a patient. \\nThis dictation is for testing purposes only and should include various topics that might be discussed in a healthcare setting. \\nPlease ensure the material is entirely fictional and does not provide any real medical advice or information. \\nPlease ensure variables such as age, weight and history are varied.\\nThe clinician should ensure the history and examination findings are incomplete, leaving out some pertinent questions.\\nIn response to their history and examination findings, the clinician should  provide management advice and guidance.\\nThe clinical scenario should be the following:  \\n            \\nThe clinical scenario should focus on a patient with Bartholin&#x27;s cyst&#x2F;abscess.\"\n}\n\nA: **Clinical Dictation: Fictional Patient Encounter – Bartholin’s Cyst/Abscess**  \n\n**Patient Details:**  \n- Name: Ms. Jane Doe (fictional)  \n- Age: 32 years  \n- Gender: Female  \n- Weight: 68 kg  \n- Occupation: Office administrator  \n- Marital Status: Single  \n- Allergies: NKDA  \n\n**History of Presenting Complaint:**  \nMs. Doe presents to the clinic with a 4-day history of increasing pain and swelling in the left vulvar region. She describes the pain as throbbing and worse with walking or sitting. She denies any recent trauma or sexual activity but reports mild dysuria. No fever or systemic symptoms reported. She has never had similar symptoms before.  \n\n**Past Medical History:**  \n- No significant medical history.  \n- No prior surgeries.  \n- No known chronic illnesses.  \n\n**Medications:**  \n- Occasional ibuprofen for headaches (last taken 2 days ago).  \n\n**Social History:**  \n- Non-smoker.  \n- Alcohol: Occasional social drinking.  \n- Denies recreational drug use.  \n\n**Examination Findings:**  \n- General: Well-appearing, afebrile, no signs of systemic illness.  \n- Local Exam: Left labia majora swollen with a tender, fluctuant 3 cm mass noted at the Bartholin’s gland location. Overlying skin erythematous but intact. No active discharge or visible pus. Right gland appears normal.  \n\n**Assessment:**  \nLikely left Bartholin’s abscess given acute onset, localized tenderness, and fluctuance. No signs of systemic infection.  \n\n**Plan:**  \n1. **Incision & Drainage (I&D):** Recommend bedside I&D under local anesthesia given symptomatic abscess. Risks/benefits discussed (pain, bleeding, recurrence).  \n2. **Pain Management:** Prescribe oral paracetamol 1g QID PRN and ibuprofen 400mg TID PRN.  \n3. **Antibiotics:** Not routinely indicated unless systemic signs of infection develop (none currently).  \n4. **Follow-Up:** Advised to return if worsening pain, fever, or recurrence. No routine follow-up scheduled.  \n\n**Missed Pertinent Questions:**  \n- Sexual history (e.g., new partners, STI risk).  \n- Contraceptive use (hormonal influences).  \n- Previous STI testing/treatment.  \n- Detailed menstrual history (timing related to symptoms).  \n\n**Counseling:**  \n- Educated on warm sitz baths for comfort.  \n- Advised to avoid tight clothing.  \n- No restrictions on sexual activity, but advised to return if symptoms worsen post-intercourse.  \n\n**Dictated by:** Dr. Smith (fictional)  \n**Date:** [Fictional date]  \n\n**Disclaimer:** This is a fictional dictation for testing purposes only. No real patient data or medical advice is provided.\n\n--- Token Usage Report ---\nPrompt tokens: 147\nCompletion tokens: 601\nTotal tokens: 748\nEstimated cost: $0.000374",
  "ai_provider": "DeepSeek",
  "ai_model": "deepseek-chat",
  "token_usage": {
    "prompt_tokens": 147,
    "completion_tokens": 601,
    "total_tokens": 748,
    "estimated_cost_usd": 0.000374
  }
}