{
  "prompt": {
    "prompt": "Please analyze the clinical note against the provided guideline and suggest improvements to better align with the guideline recommendations.\n\nFor each recommendation, specify:\n1. The type of recommendation:\n   - Additional information needed (history/examination/investigations)\n   - Improved patient advice (options/statistics/patient information)\n   - Different management plan\n2. The specific recommendation\n3. The reason for the recommendation (referencing the guideline)\n\nCategorize each recommendation by importance:\n- Very Important: Critical for patient safety or guideline compliance\n- Somewhat Important: Significant for optimal care but not critical\n- Less Important: Would improve care but not essential\n- Unimportant: Minor suggestions that could be considered\n\nFormat the response as follows:\n\n### Very Important Recommendations\n[Type] - [Specific recommendation]\nReason: [Reference to guideline ID and relevant section]\n\n### Somewhat Important Recommendations\n[Type] - [Specific recommendation]\nReason: [Reference to guideline ID and relevant section]\n\n### Less Important Recommendations\n[Type] - [Specific recommendation]\nReason: [Reference to guideline ID and relevant section]\n\n### Unimportant Recommendations\n[Type] - [Specific recommendation]\nReason: [Reference to guideline ID and relevant section]\n\nClinical Note:\n29 years old tarot one nurses their inspection for sepsis and labor and 2023  current gestation 30 weeks and three days body mass index of 24 but group a positive VVC Council by Mr amtoo and  15 weeks regarding  associated risks of low pregnancies associated plasma protein a  it was impression's clinic with Harley Robertson at 23 weeks and one day and decided regarding motor delivery  routine discussed  20  four weeks with  no decisions delivery  phone engine may see  reviewed a 31 weeks leaning towards Jennifer in section and decided is the weather would accept induction of labor  worked for birth options kind of get 39 weeks with membrane suite and/or induction major by artificial membrane  growth that is appropriate for the gestational age with normal growth philosophy\n\nGuideline:\n[ID] cg20013-preterm-birth-risk-pathway-pdf\nTitle: CG20013 Preterm birth risk pathway\nContent: No content available",
    "system_prompt": "You are a medical guidelines compliance checker. Your task is to analyze if the given clinical note follows the specified guideline and suggest improvements.",
    "guideline_id": "cg20013-preterm-birth-risk-pathway-pdf",
    "guideline_title": "CG20013 Preterm birth risk pathway"
  },
  "response": "Given the lack of available guideline content (CG20013 Preterm birth risk pathway), it is impossible to perform a meaningful analysis or provide specific recommendations for improving the clinical note's alignment with the guideline. The clinical note itself is also highly fragmented and difficult to interpret, which further complicates the analysis.  \n\nTo proceed, the following would be required:  \n1. **Complete guideline content** (CG20013) to reference specific recommendations.  \n2. **A clearer, structured clinical note** to assess adherence to the guideline.  \n\n### Very Important Recommendations  \n**Additional information needed** - Obtain and review the full CG20013 guideline to assess compliance.  \nReason: Without the guideline content, no meaningful analysis can be performed.  \n\n**Different management plan** - Clarify and structure the clinical note to ensure accurate interpretation.  \nReason: The current note is disjointed and contains unclear phrasing, making it difficult to assess adherence to any guideline.  \n\nWould you be able to provide the full guideline text or a more structured clinical note for proper analysis?",
  "endpoint": "analyzeNoteAgainstGuideline",
  "timestamp": "2025-06-22T15-47-01",
  "textContent": "AI: DeepSeek (deepseek-chat)\n\nQ: {\n  \"prompt\": \"Please analyze the clinical note against the provided guideline and suggest improvements to better align with the guideline recommendations.\\n\\nFor each recommendation, specify:\\n1. The type of recommendation:\\n   - Additional information needed (history/examination/investigations)\\n   - Improved patient advice (options/statistics/patient information)\\n   - Different management plan\\n2. The specific recommendation\\n3. The reason for the recommendation (referencing the guideline)\\n\\nCategorize each recommendation by importance:\\n- Very Important: Critical for patient safety or guideline compliance\\n- Somewhat Important: Significant for optimal care but not critical\\n- Less Important: Would improve care but not essential\\n- Unimportant: Minor suggestions that could be considered\\n\\nFormat the response as follows:\\n\\n### Very Important Recommendations\\n[Type] - [Specific recommendation]\\nReason: [Reference to guideline ID and relevant section]\\n\\n### Somewhat Important Recommendations\\n[Type] - [Specific recommendation]\\nReason: [Reference to guideline ID and relevant section]\\n\\n### Less Important Recommendations\\n[Type] - [Specific recommendation]\\nReason: [Reference to guideline ID and relevant section]\\n\\n### Unimportant Recommendations\\n[Type] - [Specific recommendation]\\nReason: [Reference to guideline ID and relevant section]\\n\\nClinical Note:\\n29 years old tarot one nurses their inspection for sepsis and labor and 2023  current gestation 30 weeks and three days body mass index of 24 but group a positive VVC Council by Mr amtoo and  15 weeks regarding  associated risks of low pregnancies associated plasma protein a  it was impression's clinic with Harley Robertson at 23 weeks and one day and decided regarding motor delivery  routine discussed  20  four weeks with  no decisions delivery  phone engine may see  reviewed a 31 weeks leaning towards Jennifer in section and decided is the weather would accept induction of labor  worked for birth options kind of get 39 weeks with membrane suite and/or induction major by artificial membrane  growth that is appropriate for the gestational age with normal growth philosophy\\n\\nGuideline:\\n[ID] cg20013-preterm-birth-risk-pathway-pdf\\nTitle: CG20013 Preterm birth risk pathway\\nContent: No content available\",\n  \"system_prompt\": \"You are a medical guidelines compliance checker. Your task is to analyze if the given clinical note follows the specified guideline and suggest improvements.\",\n  \"guideline_id\": \"cg20013-preterm-birth-risk-pathway-pdf\",\n  \"guideline_title\": \"CG20013 Preterm birth risk pathway\"\n}\n\nA: Given the lack of available guideline content (CG20013 Preterm birth risk pathway), it is impossible to perform a meaningful analysis or provide specific recommendations for improving the clinical note's alignment with the guideline. The clinical note itself is also highly fragmented and difficult to interpret, which further complicates the analysis.  \n\nTo proceed, the following would be required:  \n1. **Complete guideline content** (CG20013) to reference specific recommendations.  \n2. **A clearer, structured clinical note** to assess adherence to the guideline.  \n\n### Very Important Recommendations  \n**Additional information needed** - Obtain and review the full CG20013 guideline to assess compliance.  \nReason: Without the guideline content, no meaningful analysis can be performed.  \n\n**Different management plan** - Clarify and structure the clinical note to ensure accurate interpretation.  \nReason: The current note is disjointed and contains unclear phrasing, making it difficult to assess adherence to any guideline.  \n\nWould you be able to provide the full guideline text or a more structured clinical note for proper analysis?\n\n--- Token Usage Report ---\nPrompt tokens: 464\nCompletion tokens: 210\nTotal tokens: 674\nEstimated cost: $0.000337",
  "ai_provider": "DeepSeek",
  "ai_model": "deepseek-chat",
  "token_usage": {
    "prompt_tokens": 464,
    "completion_tokens": 210,
    "total_tokens": 674,
    "estimated_cost_usd": 0.00033700000000000006
  }
}