{
  "prompt": {
    "prompt": "Create a fictional dictation of a clinical interaction between a healthcare professional and a patient. \nThis dictation is for testing purposes only and should include various topics that might be discussed in a healthcare setting. \nPlease ensure the material is entirely fictional and does not provide any real medical advice or information. \nPlease ensure variables such as age, weight and history are varied.\nThe clinician should ensure the history and examination findings are incomplete, leaving out some pertinent questions.\nIn response to their history and examination findings, the clinician should  provide management advice and guidance.\nThe clinical scenario should be the following: \n\nMake the age 37, the BMI 20.9 and the number of prior pregnancies 3\n\nBase the clinical scenario on the following gynecology issue: Abnormal uterine bleeding",
    "system_prompt": "Create a fictional dictation of a clinical interaction between a healthcare professional and a patient. \nThis dictation is for testing purposes only and should include various topics that might be discussed in a healthcare setting. \nPlease ensure the material is entirely fictional and does not provide any real medical advice or information. \nPlease ensure variables such as age, weight and history are varied.\nThe clinician should ensure the history and examination findings are incomplete, leaving out some pertinent questions.\nIn response to their history and examination findings, the clinician should  provide management advice and guidance.\nThe clinical scenario should be the following: \n\nMake the age 37, the BMI 20.9 and the number of prior pregnancies 3\n\nBase the clinical scenario on the following gynecology issue: Abnormal uterine bleeding"
  },
  "response": "**Dictation: Clinical Interaction – Abnormal Uterine Bleeding**  \n*Date: [Fictional Date] | Clinician: Dr. [Fictional Name] | Patient: [Fictional Name], Age 37*  \n\n**Subjective:**  \nThe patient is a 37-year-old female (BMI 20.9, G3P3) presenting with a 4-month history of abnormal uterine bleeding. She reports irregular cycles with episodes of heavy bleeding lasting 7–10 days, accompanied by clots. She denies intermenstrual bleeding but admits to occasional pelvic discomfort. She has no history of dyspareunia or postcoital bleeding. Her last Pap smear was 2 years ago (reported as normal). She uses condoms for contraception and has no known medical conditions. She takes no regular medications and has no allergies. Family history is notable for a mother with hypothyroidism.  \n\n*Incomplete history:*  \n- No documented menstrual cycle frequency prior to symptoms.  \n- No inquiry about symptoms of anemia (e.g., fatigue, dizziness).  \n- Sexual activity frequency and impact on bleeding not explored.  \n- Diet/exercise habits and recent weight changes not assessed.  \n\n**Objective:**  \n- Vital signs: BP 118/76, HR 72, afebrile.  \n- General appearance: No pallor or distress.  \n- Abdominal exam: Soft, non-tender, no masses.  \n- Pelvic exam deferred today due to patient discomfort.  \n- No speculum or bimanual exam performed.  \n\n*Incomplete examination:*  \n- No documentation of uterine size or adnexal tenderness.  \n- No assessment for signs of hirsutism/acne (possible PCOS).  \n\n**Assessment:**  \nAbnormal uterine bleeding (AUB) in a premenopausal patient. Differential includes:  \n1. Hormonal imbalance (e.g., anovulatory cycles).  \n2. Structural causes (e.g., fibroids, polyps—though not confirmed without imaging).  \n3. Less likely: Coagulopathy or thyroid dysfunction (no testing yet).  \n\n**Plan:**  \n1. **Investigations:**  \n   - CBC to assess for anemia.  \n   - TSH to rule out thyroid dysfunction.  \n   - Pelvic ultrasound to evaluate for structural abnormalities.  \n   - *Omitted:* Coagulation studies (despite heavy bleeding), endometrial biopsy (given age >35 and prolonged symptoms).  \n\n2. **Management:**  \n   - Start tranexamic acid 1g TID during heavy bleeding days.  \n   - Consider trial of combined oral contraceptive pill for cycle regulation if no contraindications found.  \n   - *Omitted:* Discussion of progesterone-only options or referral to gynecology if symptoms persist.  \n\n3. **Follow-up:**  \n   - Return in 4 weeks to review lab/imaging results and symptom progression.  \n   - *Omitted:* Clear instructions for urgent review if worsening anemia or severe pain.  \n\n**Patient Counseling:**  \nDiscussed likely benign causes but emphasized need for further evaluation. Advised to track bleeding patterns using a diary. No questions asked about patient’s reproductive goals or desire for future contraception.  \n\n*Note: This dictation is fictional for testing purposes only. No real medical advice is implied.*  \n\n---  \n**Testing Notes:**  \n- Intentional gaps include incomplete menstrual history, lack of pelvic exam details, and omitted differentials (e.g., endometrial hyperplasia).  \n- Management includes initial steps but lacks contingency planning for abnormal results.  \n- Patient counseling is minimal to simulate a time-constrained encounter.",
  "endpoint": "generateFakeClinicalInteraction",
  "timestamp": "2025-05-27T14-09-37",
  "textContent": "AI: DeepSeek (deepseek-chat)\n\nQ: {\n  \"prompt\": \"Create a fictional dictation of a clinical interaction between a healthcare professional and a patient. \\nThis dictation is for testing purposes only and should include various topics that might be discussed in a healthcare setting. \\nPlease ensure the material is entirely fictional and does not provide any real medical advice or information. \\nPlease ensure variables such as age, weight and history are varied.\\nThe clinician should ensure the history and examination findings are incomplete, leaving out some pertinent questions.\\nIn response to their history and examination findings, the clinician should  provide management advice and guidance.\\nThe clinical scenario should be the following: \\n\\nMake the age 37, the BMI 20.9 and the number of prior pregnancies 3\\n\\nBase the clinical scenario on the following gynecology issue: Abnormal uterine bleeding\",\n  \"system_prompt\": \"Create a fictional dictation of a clinical interaction between a healthcare professional and a patient. \\nThis dictation is for testing purposes only and should include various topics that might be discussed in a healthcare setting. \\nPlease ensure the material is entirely fictional and does not provide any real medical advice or information. \\nPlease ensure variables such as age, weight and history are varied.\\nThe clinician should ensure the history and examination findings are incomplete, leaving out some pertinent questions.\\nIn response to their history and examination findings, the clinician should  provide management advice and guidance.\\nThe clinical scenario should be the following: \\n\\nMake the age 37, the BMI 20.9 and the number of prior pregnancies 3\\n\\nBase the clinical scenario on the following gynecology issue: Abnormal uterine bleeding\"\n}\n\nA: **Dictation: Clinical Interaction – Abnormal Uterine Bleeding**  \n*Date: [Fictional Date] | Clinician: Dr. [Fictional Name] | Patient: [Fictional Name], Age 37*  \n\n**Subjective:**  \nThe patient is a 37-year-old female (BMI 20.9, G3P3) presenting with a 4-month history of abnormal uterine bleeding. She reports irregular cycles with episodes of heavy bleeding lasting 7–10 days, accompanied by clots. She denies intermenstrual bleeding but admits to occasional pelvic discomfort. She has no history of dyspareunia or postcoital bleeding. Her last Pap smear was 2 years ago (reported as normal). She uses condoms for contraception and has no known medical conditions. She takes no regular medications and has no allergies. Family history is notable for a mother with hypothyroidism.  \n\n*Incomplete history:*  \n- No documented menstrual cycle frequency prior to symptoms.  \n- No inquiry about symptoms of anemia (e.g., fatigue, dizziness).  \n- Sexual activity frequency and impact on bleeding not explored.  \n- Diet/exercise habits and recent weight changes not assessed.  \n\n**Objective:**  \n- Vital signs: BP 118/76, HR 72, afebrile.  \n- General appearance: No pallor or distress.  \n- Abdominal exam: Soft, non-tender, no masses.  \n- Pelvic exam deferred today due to patient discomfort.  \n- No speculum or bimanual exam performed.  \n\n*Incomplete examination:*  \n- No documentation of uterine size or adnexal tenderness.  \n- No assessment for signs of hirsutism/acne (possible PCOS).  \n\n**Assessment:**  \nAbnormal uterine bleeding (AUB) in a premenopausal patient. Differential includes:  \n1. Hormonal imbalance (e.g., anovulatory cycles).  \n2. Structural causes (e.g., fibroids, polyps—though not confirmed without imaging).  \n3. Less likely: Coagulopathy or thyroid dysfunction (no testing yet).  \n\n**Plan:**  \n1. **Investigations:**  \n   - CBC to assess for anemia.  \n   - TSH to rule out thyroid dysfunction.  \n   - Pelvic ultrasound to evaluate for structural abnormalities.  \n   - *Omitted:* Coagulation studies (despite heavy bleeding), endometrial biopsy (given age >35 and prolonged symptoms).  \n\n2. **Management:**  \n   - Start tranexamic acid 1g TID during heavy bleeding days.  \n   - Consider trial of combined oral contraceptive pill for cycle regulation if no contraindications found.  \n   - *Omitted:* Discussion of progesterone-only options or referral to gynecology if symptoms persist.  \n\n3. **Follow-up:**  \n   - Return in 4 weeks to review lab/imaging results and symptom progression.  \n   - *Omitted:* Clear instructions for urgent review if worsening anemia or severe pain.  \n\n**Patient Counseling:**  \nDiscussed likely benign causes but emphasized need for further evaluation. Advised to track bleeding patterns using a diary. No questions asked about patient’s reproductive goals or desire for future contraception.  \n\n*Note: This dictation is fictional for testing purposes only. No real medical advice is implied.*  \n\n---  \n**Testing Notes:**  \n- Intentional gaps include incomplete menstrual history, lack of pelvic exam details, and omitted differentials (e.g., endometrial hyperplasia).  \n- Management includes initial steps but lacks contingency planning for abnormal results.  \n- Patient counseling is minimal to simulate a time-constrained encounter.\n\n--- Token Usage Report ---\nPrompt tokens: 158\nCompletion tokens: 731\nTotal tokens: 889\nEstimated cost: $0.000445",
  "ai_provider": "DeepSeek",
  "ai_model": "deepseek-chat",
  "token_usage": {
    "prompt_tokens": 158,
    "completion_tokens": 731,
    "total_tokens": 889,
    "estimated_cost_usd": 0.0004445
  }
}