{
  "prompt": {
    "prompt": "Create a fictional dictation of a clinical interaction between a healthcare professional and a patient. \nThis dictation is for testing purposes only and should include various topics that might be discussed in a healthcare setting. \nPlease ensure the material is entirely fictional and does not provide any real medical advice or information. \nPlease ensure variables such as age, weight and history are varied.\nThe clinician should ensure the history and examination findings are incomplete, leaving out some pertinent questions.\nIn response to their history and examination findings, the clinician should  provide management advice and guidance.\nThe clinical scenario should be the following: \n\nMake the age 44, the BMI 35.8 and the number of prior pregnancies 4\n\nBase the clinical scenario on the following gynecology issue: Abnormal uterine bleeding",
    "system_prompt": "Create a fictional dictation of a clinical interaction between a healthcare professional and a patient. \nThis dictation is for testing purposes only and should include various topics that might be discussed in a healthcare setting. \nPlease ensure the material is entirely fictional and does not provide any real medical advice or information. \nPlease ensure variables such as age, weight and history are varied.\nThe clinician should ensure the history and examination findings are incomplete, leaving out some pertinent questions.\nIn response to their history and examination findings, the clinician should  provide management advice and guidance.\nThe clinical scenario should be the following: \n\nMake the age 44, the BMI 35.8 and the number of prior pregnancies 4\n\nBase the clinical scenario on the following gynecology issue: Abnormal uterine bleeding"
  },
  "response": "**Clinical Dictation – Fictional Example**  \n\n**Patient Name:** Jane Doe  \n**Age:** 44  \n**BMI:** 35.8  \n**Gravida:** 4, Para: 4  \n**Date of Encounter:** [Fictional Date]  \n**Clinician:** Dr. Smith  \n\n### **Subjective:**  \nMs. Doe presents today for evaluation of abnormal uterine bleeding. She reports heavy, irregular menstrual bleeding for the past six months, with episodes lasting 10–14 days and requiring frequent pad changes (soaking 6–8 pads per day). She denies intermenstrual bleeding but notes occasional clots. She reports associated fatigue but denies dizziness, syncope, or significant pain.  \n\nShe has a history of four uncomplicated vaginal deliveries. She has no known medical conditions and takes no medications. She denies a family history of bleeding disorders or gynecologic malignancies. She has no known drug allergies.  \n\n*Social History:* Non-smoker, occasional alcohol use. Sexually active with one partner, using condoms inconsistently for contraception.  \n\n*Review of Systems:* Positive for fatigue. Denies weight changes, hair loss, or skin changes. No urinary or bowel symptoms.  \n\n(*Note: Clinician did not inquire about recent weight changes, symptoms of thyroid dysfunction, or history of fibroids/Polycystic Ovary Syndrome (PCOS).*)  \n\n### **Objective:**  \n*Vitals:* BP 128/82, HR 78, Temp 98.4°F, Weight 98 kg, Height 165 cm.  \n*General:* Well-appearing, no acute distress.  \n*Abdomen:* Soft, non-tender, obese, no palpable masses.  \n*Pelvic Exam:* External genitalia normal. Speculum exam reveals blood in the vault; cervix appears normal. Bimanual exam: Uterus slightly enlarged, mobile, non-tender. No adnexal masses noted.  \n\n(*Note: No transvaginal ultrasound or endometrial biopsy performed at this visit. No hemoglobin/hematocrit checked.*)  \n\n### **Assessment:**  \n**Abnormal Uterine Bleeding (AUB)** in a 44-year-old woman with obesity (BMI 35.8) and parity 4. Differential includes:  \n- Dysfunctional uterine bleeding (anovulatory)  \n- Endometrial hyperplasia  \n- Fibroids (though not palpated on exam)  \n- Less likely: Coagulopathy, malignancy  \n\n### **Plan:**  \n1. **Initial Workup:**  \n   - Order CBC to assess for anemia.  \n   - TSH to evaluate for thyroid dysfunction.  \n   - Pelvic ultrasound (transvaginal preferred) to assess endometrial thickness and rule out structural causes.  \n   - Consider endometrial biopsy if ultrasound shows thickened endometrium (>4 mm) or if bleeding persists.  \n\n2. **Management Options Discussed:**  \n   - **Hormonal Therapy:** Trial of combined oral contraceptive pills (if no contraindications) or progestin-only therapy to regulate cycles.  \n   - **Non-Hormonal Option:** Tranexamic acid for heavy bleeding episodes.  \n   - **Lifestyle:** Weight loss counseling given obesity as a potential contributing factor.  \n\n3. **Follow-Up:**  \n   - Return in 4 weeks for review of lab/imaging results.  \n   - If bleeding worsens or signs of anemia develop (lightheadedness, palpitations), seek urgent evaluation.  \n\n(*Note: Did not discuss risks/benefits of hormonal therapy in detail or screen for diabetes/hypertension given obesity.*)  \n\n**End of Note**  \n\n*This dictation is for fictional testing purposes only and does not constitute real medical advice.*",
  "endpoint": "newFunctionName",
  "timestamp": "2025-05-11T06-31-20",
  "textContent": "AI: DeepSeek (deepseek-chat)\n\nQ: {\n  \"prompt\": \"Create a fictional dictation of a clinical interaction between a healthcare professional and a patient. \\nThis dictation is for testing purposes only and should include various topics that might be discussed in a healthcare setting. \\nPlease ensure the material is entirely fictional and does not provide any real medical advice or information. \\nPlease ensure variables such as age, weight and history are varied.\\nThe clinician should ensure the history and examination findings are incomplete, leaving out some pertinent questions.\\nIn response to their history and examination findings, the clinician should  provide management advice and guidance.\\nThe clinical scenario should be the following: \\n\\nMake the age 44, the BMI 35.8 and the number of prior pregnancies 4\\n\\nBase the clinical scenario on the following gynecology issue: Abnormal uterine bleeding\",\n  \"system_prompt\": \"Create a fictional dictation of a clinical interaction between a healthcare professional and a patient. \\nThis dictation is for testing purposes only and should include various topics that might be discussed in a healthcare setting. \\nPlease ensure the material is entirely fictional and does not provide any real medical advice or information. \\nPlease ensure variables such as age, weight and history are varied.\\nThe clinician should ensure the history and examination findings are incomplete, leaving out some pertinent questions.\\nIn response to their history and examination findings, the clinician should  provide management advice and guidance.\\nThe clinical scenario should be the following: \\n\\nMake the age 44, the BMI 35.8 and the number of prior pregnancies 4\\n\\nBase the clinical scenario on the following gynecology issue: Abnormal uterine bleeding\"\n}\n\nA: **Clinical Dictation – Fictional Example**  \n\n**Patient Name:** Jane Doe  \n**Age:** 44  \n**BMI:** 35.8  \n**Gravida:** 4, Para: 4  \n**Date of Encounter:** [Fictional Date]  \n**Clinician:** Dr. Smith  \n\n### **Subjective:**  \nMs. Doe presents today for evaluation of abnormal uterine bleeding. She reports heavy, irregular menstrual bleeding for the past six months, with episodes lasting 10–14 days and requiring frequent pad changes (soaking 6–8 pads per day). She denies intermenstrual bleeding but notes occasional clots. She reports associated fatigue but denies dizziness, syncope, or significant pain.  \n\nShe has a history of four uncomplicated vaginal deliveries. She has no known medical conditions and takes no medications. She denies a family history of bleeding disorders or gynecologic malignancies. She has no known drug allergies.  \n\n*Social History:* Non-smoker, occasional alcohol use. Sexually active with one partner, using condoms inconsistently for contraception.  \n\n*Review of Systems:* Positive for fatigue. Denies weight changes, hair loss, or skin changes. No urinary or bowel symptoms.  \n\n(*Note: Clinician did not inquire about recent weight changes, symptoms of thyroid dysfunction, or history of fibroids/Polycystic Ovary Syndrome (PCOS).*)  \n\n### **Objective:**  \n*Vitals:* BP 128/82, HR 78, Temp 98.4°F, Weight 98 kg, Height 165 cm.  \n*General:* Well-appearing, no acute distress.  \n*Abdomen:* Soft, non-tender, obese, no palpable masses.  \n*Pelvic Exam:* External genitalia normal. Speculum exam reveals blood in the vault; cervix appears normal. Bimanual exam: Uterus slightly enlarged, mobile, non-tender. No adnexal masses noted.  \n\n(*Note: No transvaginal ultrasound or endometrial biopsy performed at this visit. No hemoglobin/hematocrit checked.*)  \n\n### **Assessment:**  \n**Abnormal Uterine Bleeding (AUB)** in a 44-year-old woman with obesity (BMI 35.8) and parity 4. Differential includes:  \n- Dysfunctional uterine bleeding (anovulatory)  \n- Endometrial hyperplasia  \n- Fibroids (though not palpated on exam)  \n- Less likely: Coagulopathy, malignancy  \n\n### **Plan:**  \n1. **Initial Workup:**  \n   - Order CBC to assess for anemia.  \n   - TSH to evaluate for thyroid dysfunction.  \n   - Pelvic ultrasound (transvaginal preferred) to assess endometrial thickness and rule out structural causes.  \n   - Consider endometrial biopsy if ultrasound shows thickened endometrium (>4 mm) or if bleeding persists.  \n\n2. **Management Options Discussed:**  \n   - **Hormonal Therapy:** Trial of combined oral contraceptive pills (if no contraindications) or progestin-only therapy to regulate cycles.  \n   - **Non-Hormonal Option:** Tranexamic acid for heavy bleeding episodes.  \n   - **Lifestyle:** Weight loss counseling given obesity as a potential contributing factor.  \n\n3. **Follow-Up:**  \n   - Return in 4 weeks for review of lab/imaging results.  \n   - If bleeding worsens or signs of anemia develop (lightheadedness, palpitations), seek urgent evaluation.  \n\n(*Note: Did not discuss risks/benefits of hormonal therapy in detail or screen for diabetes/hypertension given obesity.*)  \n\n**End of Note**  \n\n*This dictation is for fictional testing purposes only and does not constitute real medical advice.*\n\n--- Token Usage Report ---\nPrompt tokens: 158\nCompletion tokens: 756\nTotal tokens: 914\nEstimated cost: $0.000457",
  "ai_provider": "DeepSeek",
  "ai_model": "deepseek-chat",
  "token_usage": {
    "prompt_tokens": 158,
    "completion_tokens": 756,
    "total_tokens": 914,
    "estimated_cost_usd": 0.00045700000000000005
  }
}