{
  "prompt": {
    "prompt": "Create a fictional dictation of a clinical interaction between a healthcare professional and a patient. \nThis dictation is for testing purposes only and should include various topics that might be discussed in a healthcare setting. \nPlease ensure the material is entirely fictional and does not provide any real medical advice or information. \nPlease ensure variables such as age, weight and history are varied.\nThe clinician should ensure the history and examination findings are incomplete, leaving out some pertinent questions.\nIn response to their history and examination findings, the clinician should  provide management advice and guidance.\nThe clinical scenario should be the following: \n\nMake the age 18, the BMI 18.7 and the number of prior pregnancies 1\n\nBase the clinical scenario on the following obstetrics issue: Intrapartum fetal heart rate concerns",
    "system_prompt": "Create a fictional dictation of a clinical interaction between a healthcare professional and a patient. \nThis dictation is for testing purposes only and should include various topics that might be discussed in a healthcare setting. \nPlease ensure the material is entirely fictional and does not provide any real medical advice or information. \nPlease ensure variables such as age, weight and history are varied.\nThe clinician should ensure the history and examination findings are incomplete, leaving out some pertinent questions.\nIn response to their history and examination findings, the clinician should  provide management advice and guidance.\nThe clinical scenario should be the following: \n\nMake the age 18, the BMI 18.7 and the number of prior pregnancies 1\n\nBase the clinical scenario on the following obstetrics issue: Intrapartum fetal heart rate concerns"
  },
  "response": "**Dictation: Clinical Interaction – Intrapartum Fetal Heart Rate Concerns**  \n*For Testing Purposes Only – Fictional Scenario*  \n\n**Patient Details:**  \n- Name: Jane Doe (fictional)  \n- Age: 18  \n- BMI: 18.7  \n- Gravida: 1, Para: 0 (1 prior pregnancy, no live births)  \n- Gestational Age: 39 weeks  \n- Last Menstrual Period: [Not documented]  \n- Allergies: NKDA (No known drug allergies)  \n\n**History of Presenting Complaint:**  \nPatient presented to labor and delivery with spontaneous onset of labor at 39 weeks gestation. Contractions began 6 hours prior, increasing in intensity. Membranes ruptured spontaneously 2 hours ago with clear fluid. Patient reports normal fetal movements prior to labor but notes decreased perception of movement in the last hour.  \n\n*Incomplete History:*  \n- No documentation of prenatal care attendance or prior ultrasound findings.  \n- Social history (e.g., smoking, substance use) not elicited.  \n- Family history of obstetric complications not asked.  \n\n**Examination Findings:**  \n- *Vitals:* BP 120/78, HR 88, Temp 37.1°C  \n- *Abdomen:* Fundal height 38 cm, vertex presentation, longitudinal lie.  \n- *Contractions:* Regular, every 3 minutes, lasting 60 seconds, moderate intensity.  \n- *Cervical Exam:* 5 cm dilated, 80% effaced, -1 station.  \n- *Fetal Heart Rate (FHR):*  \n  - Baseline 150 bpm.  \n  - Recurrent late decelerations noted over 30-minute tracing.  \n  - Variability: Minimal (absent accelerations).  \n  - No documentation of tocodynamometer placement or contraction correlation.  \n\n*Incomplete Examination:*  \n- No Leopold’s maneuvers performed to confirm presentation.  \n- No documentation of amniotic fluid volume or meconium presence.  \n- Maternal pulse not checked to rule out superimposition on FHR tracing.  \n\n**Impression:**  \n- Intrapartum fetal heart rate tracing concerning for recurrent late decelerations with minimal variability in an 18-year-old primigravida at 39 weeks.  \n- Differential includes uteroplacental insufficiency, cord compression, or maternal hemodynamic instability (e.g., dehydration, hypotension).  \n\n**Management Plan:**  \n1. **Immediate Actions:**  \n   - Maternal repositioning (left lateral tilt).  \n   - IV fluid bolus (500 mL normal saline) to optimize perfusion.  \n   - Supplemental O2 via non-rebreather mask at 10 L/min.  \n   - Discontinue oxytocin if infusing (not documented in history).  \n\n2. **Monitoring:**  \n   - Continuous FHR monitoring; consider fetal scalp electrode for direct assessment if tracing remains indeterminate.  \n   - Repeat cervical exam in 1 hour to assess labor progress.  \n\n3. **Escalation:**  \n   - Notify obstetric team for potential expedited delivery (e.g., operative vaginal or cesarean delivery) if tracing does not improve.  \n   - Anesthesia consult for epidural placement (if not already in place) or surgical prep.  \n\n4. **Patient Counseling:**  \n   - Explained concerns regarding fetal tolerance of labor.  \n   - Patient verbalized understanding and consented to possible interventions.  \n\n**Plan for Follow-Up:**  \n- Reassess FHR tracing after interventions.  \n- Document decision-to-delivery interval if intervention required.  \n\n*Dictated by: Dr. Smith (fictional)*  \n*Date: [Fictional]*  \n\n---  \n**Note for Testing:** This dictation intentionally omits key details (e.g., prenatal records, contraction pattern documentation) to simulate incomplete clinical documentation. Management advice is fictional and not for real-world use.",
  "endpoint": "newFunctionName",
  "timestamp": "2025-04-28T10-51-17",
  "textContent": "AI: DeepSeek (deepseek-chat)\n\nQ: {\n  \"prompt\": \"Create a fictional dictation of a clinical interaction between a healthcare professional and a patient. \\nThis dictation is for testing purposes only and should include various topics that might be discussed in a healthcare setting. \\nPlease ensure the material is entirely fictional and does not provide any real medical advice or information. \\nPlease ensure variables such as age, weight and history are varied.\\nThe clinician should ensure the history and examination findings are incomplete, leaving out some pertinent questions.\\nIn response to their history and examination findings, the clinician should  provide management advice and guidance.\\nThe clinical scenario should be the following: \\n\\nMake the age 18, the BMI 18.7 and the number of prior pregnancies 1\\n\\nBase the clinical scenario on the following obstetrics issue: Intrapartum fetal heart rate concerns\",\n  \"system_prompt\": \"Create a fictional dictation of a clinical interaction between a healthcare professional and a patient. \\nThis dictation is for testing purposes only and should include various topics that might be discussed in a healthcare setting. \\nPlease ensure the material is entirely fictional and does not provide any real medical advice or information. \\nPlease ensure variables such as age, weight and history are varied.\\nThe clinician should ensure the history and examination findings are incomplete, leaving out some pertinent questions.\\nIn response to their history and examination findings, the clinician should  provide management advice and guidance.\\nThe clinical scenario should be the following: \\n\\nMake the age 18, the BMI 18.7 and the number of prior pregnancies 1\\n\\nBase the clinical scenario on the following obstetrics issue: Intrapartum fetal heart rate concerns\"\n}\n\nA: **Dictation: Clinical Interaction – Intrapartum Fetal Heart Rate Concerns**  \n*For Testing Purposes Only – Fictional Scenario*  \n\n**Patient Details:**  \n- Name: Jane Doe (fictional)  \n- Age: 18  \n- BMI: 18.7  \n- Gravida: 1, Para: 0 (1 prior pregnancy, no live births)  \n- Gestational Age: 39 weeks  \n- Last Menstrual Period: [Not documented]  \n- Allergies: NKDA (No known drug allergies)  \n\n**History of Presenting Complaint:**  \nPatient presented to labor and delivery with spontaneous onset of labor at 39 weeks gestation. Contractions began 6 hours prior, increasing in intensity. Membranes ruptured spontaneously 2 hours ago with clear fluid. Patient reports normal fetal movements prior to labor but notes decreased perception of movement in the last hour.  \n\n*Incomplete History:*  \n- No documentation of prenatal care attendance or prior ultrasound findings.  \n- Social history (e.g., smoking, substance use) not elicited.  \n- Family history of obstetric complications not asked.  \n\n**Examination Findings:**  \n- *Vitals:* BP 120/78, HR 88, Temp 37.1°C  \n- *Abdomen:* Fundal height 38 cm, vertex presentation, longitudinal lie.  \n- *Contractions:* Regular, every 3 minutes, lasting 60 seconds, moderate intensity.  \n- *Cervical Exam:* 5 cm dilated, 80% effaced, -1 station.  \n- *Fetal Heart Rate (FHR):*  \n  - Baseline 150 bpm.  \n  - Recurrent late decelerations noted over 30-minute tracing.  \n  - Variability: Minimal (absent accelerations).  \n  - No documentation of tocodynamometer placement or contraction correlation.  \n\n*Incomplete Examination:*  \n- No Leopold’s maneuvers performed to confirm presentation.  \n- No documentation of amniotic fluid volume or meconium presence.  \n- Maternal pulse not checked to rule out superimposition on FHR tracing.  \n\n**Impression:**  \n- Intrapartum fetal heart rate tracing concerning for recurrent late decelerations with minimal variability in an 18-year-old primigravida at 39 weeks.  \n- Differential includes uteroplacental insufficiency, cord compression, or maternal hemodynamic instability (e.g., dehydration, hypotension).  \n\n**Management Plan:**  \n1. **Immediate Actions:**  \n   - Maternal repositioning (left lateral tilt).  \n   - IV fluid bolus (500 mL normal saline) to optimize perfusion.  \n   - Supplemental O2 via non-rebreather mask at 10 L/min.  \n   - Discontinue oxytocin if infusing (not documented in history).  \n\n2. **Monitoring:**  \n   - Continuous FHR monitoring; consider fetal scalp electrode for direct assessment if tracing remains indeterminate.  \n   - Repeat cervical exam in 1 hour to assess labor progress.  \n\n3. **Escalation:**  \n   - Notify obstetric team for potential expedited delivery (e.g., operative vaginal or cesarean delivery) if tracing does not improve.  \n   - Anesthesia consult for epidural placement (if not already in place) or surgical prep.  \n\n4. **Patient Counseling:**  \n   - Explained concerns regarding fetal tolerance of labor.  \n   - Patient verbalized understanding and consented to possible interventions.  \n\n**Plan for Follow-Up:**  \n- Reassess FHR tracing after interventions.  \n- Document decision-to-delivery interval if intervention required.  \n\n*Dictated by: Dr. Smith (fictional)*  \n*Date: [Fictional]*  \n\n---  \n**Note for Testing:** This dictation intentionally omits key details (e.g., prenatal records, contraction pattern documentation) to simulate incomplete clinical documentation. Management advice is fictional and not for real-world use.\n\n--- Token Usage Report ---\nPrompt tokens: 162\nCompletion tokens: 800\nTotal tokens: 962\nEstimated cost: $0.000481",
  "ai_provider": "DeepSeek",
  "ai_model": "deepseek-chat",
  "token_usage": {
    "prompt_tokens": 162,
    "completion_tokens": 800,
    "total_tokens": 962,
    "estimated_cost_usd": 0.00048100000000000004
  }
}