{
  "prompt": {
    "prompt": "Create a fictional dictation of a clinical interaction between a healthcare professional and a patient. \nThis dictation is for testing purposes only and should include various topics that might be discussed in a healthcare setting. \nPlease ensure the material is entirely fictional and does not provide any real medical advice or information. \nPlease ensure variables such as age, weight and history are varied.\nThe clinician should ensure the history and examination findings are incomplete, leaving out some pertinent questions.\nIn response to their history and examination findings, the clinician should  provide management advice and guidance.\nThe clinical scenario should be the following:  \n      \nThe clinical scenario should focus on a patient with Bacterial vaginosis.",
    "system_prompt": "Create a fictional dictation of a clinical interaction between a healthcare professional and a patient. \nThis dictation is for testing purposes only and should include various topics that might be discussed in a healthcare setting. \nPlease ensure the material is entirely fictional and does not provide any real medical advice or information. \nPlease ensure variables such as age, weight and history are varied.\nThe clinician should ensure the history and examination findings are incomplete, leaving out some pertinent questions.\nIn response to their history and examination findings, the clinician should  provide management advice and guidance.\nThe clinical scenario should be the following:  \n      \nThe clinical scenario should focus on a patient with Bacterial vaginosis."
  },
  "response": "**Dictation: Clinical Interaction – Fictional Patient with Bacterial Vaginosis**  \n\n**Patient Details:**  \n- Name: Jane Doe (fictional)  \n- Age: 32 years  \n- Sex: Female  \n- Weight: 68 kg  \n- Occupation: Office administrator  \n\n**Presenting Complaint:**  \nThe patient reports a 1-week history of abnormal vaginal discharge, which she describes as thin, grayish-white, and with a noticeable \"fishy\" odor, particularly after intercourse. She denies itching, burning, or dysuria but notes mild discomfort.  \n\n**History of Presenting Complaint:**  \n- Onset: Symptoms began approximately 7 days ago.  \n- Discharge: Increased volume, malodorous, no blood.  \n- Associated symptoms: None reported (no pruritus, dyspareunia, or abdominal pain).  \n- Sexual history: Sexually active with one male partner in the last 6 months. Uses condoms inconsistently. No history of STIs.  \n- Last menstrual period: 2 weeks ago (regular cycles).  \n- Recent antibiotics: Completed a course of amoxicillin for sinusitis 3 weeks ago.  \n- Contraception: Combined oral contraceptive pill.  \n\n**Past Medical History:**  \n- Recurrent UTIs (last episode 6 months ago).  \n- No known allergies.  \n- No chronic medical conditions.  \n\n**Medications:**  \n- Combined oral contraceptive pill (Microgynon 30).  \n- No recent antifungals or vaginal treatments.  \n\n**Examination Findings (Incomplete):**  \n- General appearance: Well, no distress.  \n- Abdominal exam: Soft, non-tender, no masses.  \n- Pelvic exam (external): No erythema or lesions.  \n- Speculum exam: Thin, homogenous grayish discharge coating vaginal walls. No cervical friability or pus.  \n- pH testing: Not performed.  \n- Whiff test: Not performed.  \n- Microscopy: Not available at this visit.  \n\n**Assessment:**  \nGiven the history of malodorous, thin discharge and lack of significant irritation, bacterial vaginosis (BV) is the most likely diagnosis. No evidence of candidiasis or trichomoniasis based on history alone.  \n\n**Management Plan (Incomplete – Pertinent Questions Omitted):**  \n1. **Empirical treatment for BV:**  \n   - Metronidazole 500 mg orally twice daily for 7 days.  \n   - Alternative: Clindamycin cream 2% intravaginally at bedtime for 7 days.  \n2. **Advice:**  \n   - Avoid douching or scented hygiene products.  \n   - Use condoms consistently to reduce recurrence risk.  \n   - Follow up if symptoms persist or worsen.  \n3. **Omissions:**  \n   - Did not inquire about recent new sexual partners or partner symptoms.  \n   - Did not perform confirmatory pH/whiff test or microscopy.  \n   - Did not discuss probiotic use or long-term prevention strategies.  \n\n**Follow-Up:**  \nAdvise to return if no improvement after treatment or if symptoms recur. Consider STI screening if recurrent BV.  \n\n**Dictated by:** Dr. Smith (fictional)  \n**Date:** [Fictional date]  \n\n**Note:** This is a fictional dictation for testing purposes only. No real medical advice is intended or provided.",
  "endpoint": "generateFakeClinicalInteraction",
  "timestamp": "2025-05-17T20-31-36",
  "textContent": "AI: DeepSeek (deepseek-chat)\n\nQ: {\n  \"prompt\": \"Create a fictional dictation of a clinical interaction between a healthcare professional and a patient. \\nThis dictation is for testing purposes only and should include various topics that might be discussed in a healthcare setting. \\nPlease ensure the material is entirely fictional and does not provide any real medical advice or information. \\nPlease ensure variables such as age, weight and history are varied.\\nThe clinician should ensure the history and examination findings are incomplete, leaving out some pertinent questions.\\nIn response to their history and examination findings, the clinician should  provide management advice and guidance.\\nThe clinical scenario should be the following:  \\n      \\nThe clinical scenario should focus on a patient with Bacterial vaginosis.\",\n  \"system_prompt\": \"Create a fictional dictation of a clinical interaction between a healthcare professional and a patient. \\nThis dictation is for testing purposes only and should include various topics that might be discussed in a healthcare setting. \\nPlease ensure the material is entirely fictional and does not provide any real medical advice or information. \\nPlease ensure variables such as age, weight and history are varied.\\nThe clinician should ensure the history and examination findings are incomplete, leaving out some pertinent questions.\\nIn response to their history and examination findings, the clinician should  provide management advice and guidance.\\nThe clinical scenario should be the following:  \\n      \\nThe clinical scenario should focus on a patient with Bacterial vaginosis.\"\n}\n\nA: **Dictation: Clinical Interaction – Fictional Patient with Bacterial Vaginosis**  \n\n**Patient Details:**  \n- Name: Jane Doe (fictional)  \n- Age: 32 years  \n- Sex: Female  \n- Weight: 68 kg  \n- Occupation: Office administrator  \n\n**Presenting Complaint:**  \nThe patient reports a 1-week history of abnormal vaginal discharge, which she describes as thin, grayish-white, and with a noticeable \"fishy\" odor, particularly after intercourse. She denies itching, burning, or dysuria but notes mild discomfort.  \n\n**History of Presenting Complaint:**  \n- Onset: Symptoms began approximately 7 days ago.  \n- Discharge: Increased volume, malodorous, no blood.  \n- Associated symptoms: None reported (no pruritus, dyspareunia, or abdominal pain).  \n- Sexual history: Sexually active with one male partner in the last 6 months. Uses condoms inconsistently. No history of STIs.  \n- Last menstrual period: 2 weeks ago (regular cycles).  \n- Recent antibiotics: Completed a course of amoxicillin for sinusitis 3 weeks ago.  \n- Contraception: Combined oral contraceptive pill.  \n\n**Past Medical History:**  \n- Recurrent UTIs (last episode 6 months ago).  \n- No known allergies.  \n- No chronic medical conditions.  \n\n**Medications:**  \n- Combined oral contraceptive pill (Microgynon 30).  \n- No recent antifungals or vaginal treatments.  \n\n**Examination Findings (Incomplete):**  \n- General appearance: Well, no distress.  \n- Abdominal exam: Soft, non-tender, no masses.  \n- Pelvic exam (external): No erythema or lesions.  \n- Speculum exam: Thin, homogenous grayish discharge coating vaginal walls. No cervical friability or pus.  \n- pH testing: Not performed.  \n- Whiff test: Not performed.  \n- Microscopy: Not available at this visit.  \n\n**Assessment:**  \nGiven the history of malodorous, thin discharge and lack of significant irritation, bacterial vaginosis (BV) is the most likely diagnosis. No evidence of candidiasis or trichomoniasis based on history alone.  \n\n**Management Plan (Incomplete – Pertinent Questions Omitted):**  \n1. **Empirical treatment for BV:**  \n   - Metronidazole 500 mg orally twice daily for 7 days.  \n   - Alternative: Clindamycin cream 2% intravaginally at bedtime for 7 days.  \n2. **Advice:**  \n   - Avoid douching or scented hygiene products.  \n   - Use condoms consistently to reduce recurrence risk.  \n   - Follow up if symptoms persist or worsen.  \n3. **Omissions:**  \n   - Did not inquire about recent new sexual partners or partner symptoms.  \n   - Did not perform confirmatory pH/whiff test or microscopy.  \n   - Did not discuss probiotic use or long-term prevention strategies.  \n\n**Follow-Up:**  \nAdvise to return if no improvement after treatment or if symptoms recur. Consider STI screening if recurrent BV.  \n\n**Dictated by:** Dr. Smith (fictional)  \n**Date:** [Fictional date]  \n\n**Note:** This is a fictional dictation for testing purposes only. No real medical advice is intended or provided.\n\n--- Token Usage Report ---\nPrompt tokens: 137\nCompletion tokens: 691\nTotal tokens: 828\nEstimated cost: $0.000414",
  "ai_provider": "DeepSeek",
  "ai_model": "deepseek-chat",
  "token_usage": {
    "prompt_tokens": 137,
    "completion_tokens": 691,
    "total_tokens": 828,
    "estimated_cost_usd": 0.000414
  }
}