{
  "prompt": {
    "prompt": "Create a fictional dictation of a clinical interaction between a healthcare professional and a patient. \nThis dictation is for testing purposes only and should include various topics that might be discussed in a healthcare setting. \nPlease ensure the material is entirely fictional and does not provide any real medical advice or information. \nPlease ensure variables such as age, weight and history are varied.\nThe clinician should ensure the history and examination findings are incomplete, leaving out some pertinent questions.\nIn response to their history and examination findings, the clinician should  provide management advice and guidance.\nThe clinical scenario should be the following: \n\nMake the age 64, the BMI 32.1 and the number of prior pregnancies 3\n\nBase the clinical scenario on the following gynecology issue: Abnormal uterine bleeding",
    "system_prompt": "Create a fictional dictation of a clinical interaction between a healthcare professional and a patient. \nThis dictation is for testing purposes only and should include various topics that might be discussed in a healthcare setting. \nPlease ensure the material is entirely fictional and does not provide any real medical advice or information. \nPlease ensure variables such as age, weight and history are varied.\nThe clinician should ensure the history and examination findings are incomplete, leaving out some pertinent questions.\nIn response to their history and examination findings, the clinician should  provide management advice and guidance.\nThe clinical scenario should be the following: \n\nMake the age 64, the BMI 32.1 and the number of prior pregnancies 3\n\nBase the clinical scenario on the following gynecology issue: Abnormal uterine bleeding"
  },
  "response": "**Clinical Dictation: Fictional Patient Encounter**  \n\n**Patient Name:** Jane Doe (fictional)  \n**Age:** 64  \n**BMI:** 32.1  \n**Gravida/Parity:** G3P3  \n**Date of Encounter:** [Fictional Date]  \n**Clinician:** Dr. Smith (fictional)  \n\n### **Subjective:**  \nMs. Doe presents today reporting a 6-month history of abnormal uterine bleeding. She describes intermittent heavy bleeding, sometimes with clots, occurring unpredictably. She denies associated pain but reports fatigue, which she attributes to blood loss. She has no history of gynecologic malignancies. Her last menstrual period was approximately 8 months ago, but she has since experienced irregular spotting and episodes of heavier bleeding.  \n\nShe has a history of hypertension (well-controlled on lisinopril) and type 2 diabetes (on metformin). She denies any personal or family history of bleeding disorders. She has had three prior vaginal deliveries without complications. She is sexually active with one partner and uses barrier contraception inconsistently. She has never had an abnormal Pap smear.  \n\n*[Note: Clinician did not inquire about recent weight changes, medication adherence, or family history of gynecologic cancers.]*  \n\n### **Objective:**  \n**Vitals:** BP 128/78, HR 76, Temp 98.4°F, SpO2 98% RA  \n**General:** Well-appearing, no acute distress  \n**Abdomen:** Soft, non-tender, obese, no palpable masses  \n**Pelvic Exam:** External genitalia normal. Speculum exam reveals a small amount of dark blood in the vaginal vault. Cervix appears normal. Bimanual exam demonstrates a mildly enlarged, non-tender uterus without adnexal masses.  \n\n*[Note: Clinician did not perform an endometrial biopsy or transvaginal ultrasound at this visit.]*  \n\n### **Assessment:**  \n**Primary Concern:** Abnormal uterine bleeding (likely postmenopausal given prior amenorrhea)  \n**Differential Diagnosis:**  \n1. Endometrial hyperplasia  \n2. Endometrial polyp  \n3. Hormonal imbalance (e.g., unopposed estrogen effect)  \n4. Less likely: Endometrial carcinoma (risk factors include age, obesity)  \n\n### **Plan:**  \n1. **Diagnostics:**  \n   - Order transvaginal ultrasound to assess endometrial thickness.  \n   - Schedule outpatient endometrial biopsy for further evaluation.  \n   - Basic labs: CBC (to evaluate for anemia), HbA1c (given diabetes history).  \n   - *[Note: Clinician did not order coagulation studies or thyroid function tests.]*  \n\n2. **Management:**  \n   - If bleeding becomes heavy or symptomatic, consider short-course progestin therapy pending biopsy results.  \n   - Recommend iron supplementation if anemia is confirmed.  \n   - Advise patient to track bleeding episodes and return if worsening symptoms occur.  \n\n3. **Follow-Up:**  \n   - Return in 2 weeks for biopsy results and further management.  \n   - If endometrial thickness >4mm on ultrasound, biopsy is strongly indicated.  \n\n*[Note: Clinician did not discuss weight management or long-term risks of unopposed estrogen exposure.]*  \n\n**Impression:** Abnormal uterine bleeding in a postmenopausal patient with obesity—requires further workup to rule out malignancy or hyperplasia.  \n\n**End of Dictation.**  \n\n*This is a fictional dictation for testing purposes only. No real medical advice is given or implied.*",
  "endpoint": "generateFakeClinicalInteraction",
  "timestamp": "2025-05-27T14-09-37",
  "textContent": "AI: DeepSeek (deepseek-chat)\n\nQ: {\n  \"prompt\": \"Create a fictional dictation of a clinical interaction between a healthcare professional and a patient. \\nThis dictation is for testing purposes only and should include various topics that might be discussed in a healthcare setting. \\nPlease ensure the material is entirely fictional and does not provide any real medical advice or information. \\nPlease ensure variables such as age, weight and history are varied.\\nThe clinician should ensure the history and examination findings are incomplete, leaving out some pertinent questions.\\nIn response to their history and examination findings, the clinician should  provide management advice and guidance.\\nThe clinical scenario should be the following: \\n\\nMake the age 64, the BMI 32.1 and the number of prior pregnancies 3\\n\\nBase the clinical scenario on the following gynecology issue: Abnormal uterine bleeding\",\n  \"system_prompt\": \"Create a fictional dictation of a clinical interaction between a healthcare professional and a patient. \\nThis dictation is for testing purposes only and should include various topics that might be discussed in a healthcare setting. \\nPlease ensure the material is entirely fictional and does not provide any real medical advice or information. \\nPlease ensure variables such as age, weight and history are varied.\\nThe clinician should ensure the history and examination findings are incomplete, leaving out some pertinent questions.\\nIn response to their history and examination findings, the clinician should  provide management advice and guidance.\\nThe clinical scenario should be the following: \\n\\nMake the age 64, the BMI 32.1 and the number of prior pregnancies 3\\n\\nBase the clinical scenario on the following gynecology issue: Abnormal uterine bleeding\"\n}\n\nA: **Clinical Dictation: Fictional Patient Encounter**  \n\n**Patient Name:** Jane Doe (fictional)  \n**Age:** 64  \n**BMI:** 32.1  \n**Gravida/Parity:** G3P3  \n**Date of Encounter:** [Fictional Date]  \n**Clinician:** Dr. Smith (fictional)  \n\n### **Subjective:**  \nMs. Doe presents today reporting a 6-month history of abnormal uterine bleeding. She describes intermittent heavy bleeding, sometimes with clots, occurring unpredictably. She denies associated pain but reports fatigue, which she attributes to blood loss. She has no history of gynecologic malignancies. Her last menstrual period was approximately 8 months ago, but she has since experienced irregular spotting and episodes of heavier bleeding.  \n\nShe has a history of hypertension (well-controlled on lisinopril) and type 2 diabetes (on metformin). She denies any personal or family history of bleeding disorders. She has had three prior vaginal deliveries without complications. She is sexually active with one partner and uses barrier contraception inconsistently. She has never had an abnormal Pap smear.  \n\n*[Note: Clinician did not inquire about recent weight changes, medication adherence, or family history of gynecologic cancers.]*  \n\n### **Objective:**  \n**Vitals:** BP 128/78, HR 76, Temp 98.4°F, SpO2 98% RA  \n**General:** Well-appearing, no acute distress  \n**Abdomen:** Soft, non-tender, obese, no palpable masses  \n**Pelvic Exam:** External genitalia normal. Speculum exam reveals a small amount of dark blood in the vaginal vault. Cervix appears normal. Bimanual exam demonstrates a mildly enlarged, non-tender uterus without adnexal masses.  \n\n*[Note: Clinician did not perform an endometrial biopsy or transvaginal ultrasound at this visit.]*  \n\n### **Assessment:**  \n**Primary Concern:** Abnormal uterine bleeding (likely postmenopausal given prior amenorrhea)  \n**Differential Diagnosis:**  \n1. Endometrial hyperplasia  \n2. Endometrial polyp  \n3. Hormonal imbalance (e.g., unopposed estrogen effect)  \n4. Less likely: Endometrial carcinoma (risk factors include age, obesity)  \n\n### **Plan:**  \n1. **Diagnostics:**  \n   - Order transvaginal ultrasound to assess endometrial thickness.  \n   - Schedule outpatient endometrial biopsy for further evaluation.  \n   - Basic labs: CBC (to evaluate for anemia), HbA1c (given diabetes history).  \n   - *[Note: Clinician did not order coagulation studies or thyroid function tests.]*  \n\n2. **Management:**  \n   - If bleeding becomes heavy or symptomatic, consider short-course progestin therapy pending biopsy results.  \n   - Recommend iron supplementation if anemia is confirmed.  \n   - Advise patient to track bleeding episodes and return if worsening symptoms occur.  \n\n3. **Follow-Up:**  \n   - Return in 2 weeks for biopsy results and further management.  \n   - If endometrial thickness >4mm on ultrasound, biopsy is strongly indicated.  \n\n*[Note: Clinician did not discuss weight management or long-term risks of unopposed estrogen exposure.]*  \n\n**Impression:** Abnormal uterine bleeding in a postmenopausal patient with obesity—requires further workup to rule out malignancy or hyperplasia.  \n\n**End of Dictation.**  \n\n*This is a fictional dictation for testing purposes only. No real medical advice is given or implied.*\n\n--- Token Usage Report ---\nPrompt tokens: 158\nCompletion tokens: 720\nTotal tokens: 878\nEstimated cost: $0.000439",
  "ai_provider": "DeepSeek",
  "ai_model": "deepseek-chat",
  "token_usage": {
    "prompt_tokens": 158,
    "completion_tokens": 720,
    "total_tokens": 878,
    "estimated_cost_usd": 0.00043899999999999994
  }
}