{
  "prompt": {
    "prompt": "Create a fictional dictation of a clinical interaction between a healthcare professional and a patient. \nThis dictation is for testing purposes only and should include various topics that might be discussed in a healthcare setting. \nPlease ensure the material is entirely fictional and does not provide any real medical advice or information. \nPlease ensure variables such as age, weight and history are varied.\nThe clinician should ensure the history and examination findings are incomplete, leaving out some pertinent questions.\nIn response to their history and examination findings, the clinician should  provide management advice and guidance.\nThe clinical scenario should be the following: \n\nMake the age 36, the BMI 19.4 and the number of prior pregnancies 2\n\nBase the clinical scenario on the following obstetrics issue: Advanced maternal age pregnancy",
    "system_prompt": "Create a fictional dictation of a clinical interaction between a healthcare professional and a patient. \nThis dictation is for testing purposes only and should include various topics that might be discussed in a healthcare setting. \nPlease ensure the material is entirely fictional and does not provide any real medical advice or information. \nPlease ensure variables such as age, weight and history are varied.\nThe clinician should ensure the history and examination findings are incomplete, leaving out some pertinent questions.\nIn response to their history and examination findings, the clinician should  provide management advice and guidance.\nThe clinical scenario should be the following: \n\nMake the age 36, the BMI 19.4 and the number of prior pregnancies 2\n\nBase the clinical scenario on the following obstetrics issue: Advanced maternal age pregnancy"
  },
  "response": "**Clinical Dictation: Fictional Obstetrics Consultation**  \n\n**Patient Name:** Jane Doe  \n**Age:** 36  \n**BMI:** 19.4  \n**Gravida:** 2, Para: 1 (prior full-term delivery, no complications)  \n**Last Menstrual Period (LMP):** Estimated 8 weeks ago  \n**Chief Complaint:** Positive home pregnancy test, requesting prenatal counseling due to concerns about advanced maternal age.  \n\n### **History of Present Illness:**  \nMs. Doe is a 36-year-old woman with one prior uncomplicated vaginal delivery at age 32. She reports a positive home pregnancy test two days ago and has mild nausea but no vomiting. She denies vaginal bleeding, pelvic pain, or dizziness. She has no known chronic medical conditions and takes no medications. She does not smoke, drinks alcohol socially (last drink two weeks ago), and denies recreational drug use.  \n\n*[Missing Pertinent Information: Family history of genetic disorders, prior pregnancy complications, detailed menstrual history, or prior contraceptive use.]*  \n\n### **Examination Findings:**  \n- **Vitals:** BP 118/72, HR 72, afebrile  \n- **General:** Well-appearing, no distress  \n- **Cardiovascular:** Regular rate and rhythm, no murmurs  \n- **Respiratory:** Clear to auscultation bilaterally  \n- **Abdomen:** Soft, non-tender, no palpable masses  \n- **Pelvic Exam:** Deferred at this visit (patient declined)  \n\n*[Missing Pertinent Information: No fundal height assessment, no documentation of fetal heart tones, no cervical exam findings.)*  \n\n### **Assessment:**  \n- **Advanced Maternal Age Pregnancy (AMA):** Given patient’s age (36), she is at increased risk for chromosomal abnormalities (e.g., trisomy 21), gestational diabetes, and hypertensive disorders.  \n- **Low BMI (19.4):** May require nutritional counseling to ensure adequate weight gain.  \n- **Incomplete History:** Lack of detailed genetic/family history limits risk stratification.  \n\n### **Plan:**  \n1. **Confirm Pregnancy:** Order quantitative beta-hCG and pelvic ultrasound for dating and viability.  \n2. **Genetic Counseling:** Offer first-trimester screening (NIPT or combined screening) given AMA.  \n3. **Nutritional Guidance:** Recommend prenatal vitamins and dietary assessment to support healthy weight gain.  \n4. **Follow-Up:** Schedule OB intake visit in 1–2 weeks for full prenatal labs, BP monitoring, and further counseling.  \n5. **Patient Education:** Advised to report any bleeding, severe nausea/vomiting, or pelvic pain.  \n\n*[Missing Management Considerations: No discussion of exercise recommendations, caffeine limits, or detailed preconception health optimization.]*  \n\n**Dictated by:** Dr. Smith, OB/GYN (Fictional for Testing Purposes Only)  \n**Date:** [Today’s Date]  \n\n---  \n*Note: This is a fictional dictation for testing purposes only. No real medical advice is given or implied.*",
  "endpoint": "newFunctionName",
  "timestamp": "2025-04-22T14-08-37",
  "textContent": "AI: DeepSeek (deepseek-chat)\n\nQ: {\n  \"prompt\": \"Create a fictional dictation of a clinical interaction between a healthcare professional and a patient. \\nThis dictation is for testing purposes only and should include various topics that might be discussed in a healthcare setting. \\nPlease ensure the material is entirely fictional and does not provide any real medical advice or information. \\nPlease ensure variables such as age, weight and history are varied.\\nThe clinician should ensure the history and examination findings are incomplete, leaving out some pertinent questions.\\nIn response to their history and examination findings, the clinician should  provide management advice and guidance.\\nThe clinical scenario should be the following: \\n\\nMake the age 36, the BMI 19.4 and the number of prior pregnancies 2\\n\\nBase the clinical scenario on the following obstetrics issue: Advanced maternal age pregnancy\",\n  \"system_prompt\": \"Create a fictional dictation of a clinical interaction between a healthcare professional and a patient. \\nThis dictation is for testing purposes only and should include various topics that might be discussed in a healthcare setting. \\nPlease ensure the material is entirely fictional and does not provide any real medical advice or information. \\nPlease ensure variables such as age, weight and history are varied.\\nThe clinician should ensure the history and examination findings are incomplete, leaving out some pertinent questions.\\nIn response to their history and examination findings, the clinician should  provide management advice and guidance.\\nThe clinical scenario should be the following: \\n\\nMake the age 36, the BMI 19.4 and the number of prior pregnancies 2\\n\\nBase the clinical scenario on the following obstetrics issue: Advanced maternal age pregnancy\"\n}\n\nA: **Clinical Dictation: Fictional Obstetrics Consultation**  \n\n**Patient Name:** Jane Doe  \n**Age:** 36  \n**BMI:** 19.4  \n**Gravida:** 2, Para: 1 (prior full-term delivery, no complications)  \n**Last Menstrual Period (LMP):** Estimated 8 weeks ago  \n**Chief Complaint:** Positive home pregnancy test, requesting prenatal counseling due to concerns about advanced maternal age.  \n\n### **History of Present Illness:**  \nMs. Doe is a 36-year-old woman with one prior uncomplicated vaginal delivery at age 32. She reports a positive home pregnancy test two days ago and has mild nausea but no vomiting. She denies vaginal bleeding, pelvic pain, or dizziness. She has no known chronic medical conditions and takes no medications. She does not smoke, drinks alcohol socially (last drink two weeks ago), and denies recreational drug use.  \n\n*[Missing Pertinent Information: Family history of genetic disorders, prior pregnancy complications, detailed menstrual history, or prior contraceptive use.]*  \n\n### **Examination Findings:**  \n- **Vitals:** BP 118/72, HR 72, afebrile  \n- **General:** Well-appearing, no distress  \n- **Cardiovascular:** Regular rate and rhythm, no murmurs  \n- **Respiratory:** Clear to auscultation bilaterally  \n- **Abdomen:** Soft, non-tender, no palpable masses  \n- **Pelvic Exam:** Deferred at this visit (patient declined)  \n\n*[Missing Pertinent Information: No fundal height assessment, no documentation of fetal heart tones, no cervical exam findings.)*  \n\n### **Assessment:**  \n- **Advanced Maternal Age Pregnancy (AMA):** Given patient’s age (36), she is at increased risk for chromosomal abnormalities (e.g., trisomy 21), gestational diabetes, and hypertensive disorders.  \n- **Low BMI (19.4):** May require nutritional counseling to ensure adequate weight gain.  \n- **Incomplete History:** Lack of detailed genetic/family history limits risk stratification.  \n\n### **Plan:**  \n1. **Confirm Pregnancy:** Order quantitative beta-hCG and pelvic ultrasound for dating and viability.  \n2. **Genetic Counseling:** Offer first-trimester screening (NIPT or combined screening) given AMA.  \n3. **Nutritional Guidance:** Recommend prenatal vitamins and dietary assessment to support healthy weight gain.  \n4. **Follow-Up:** Schedule OB intake visit in 1–2 weeks for full prenatal labs, BP monitoring, and further counseling.  \n5. **Patient Education:** Advised to report any bleeding, severe nausea/vomiting, or pelvic pain.  \n\n*[Missing Management Considerations: No discussion of exercise recommendations, caffeine limits, or detailed preconception health optimization.]*  \n\n**Dictated by:** Dr. Smith, OB/GYN (Fictional for Testing Purposes Only)  \n**Date:** [Today’s Date]  \n\n---  \n*Note: This is a fictional dictation for testing purposes only. No real medical advice is given or implied.*\n\n--- Token Usage Report ---\nPrompt tokens: 158\nCompletion tokens: 626\nTotal tokens: 784\nEstimated cost: $0.000392",
  "ai_provider": "DeepSeek",
  "ai_model": "deepseek-chat",
  "token_usage": {
    "prompt_tokens": 158,
    "completion_tokens": 626,
    "total_tokens": 784,
    "estimated_cost_usd": 0.000392
  }
}