{
  "prompt": {
    "prompt": "Please write a concise clinical note using medical terminology, based solely on the clinical transcript provided below. Do not invent or assume any details that are not explicitly mentioned in the transcript.\n\nThe output should be in 3 sectiions.\nThe first section should be a simple summary of the presentation in bullet points, each point on a new line, including age, presenting complaint(s), and if relevant things like previous pregnancies (or lack thereof) and BMI. \nThen there should be a newline, then the middle section should be describe each issue in detail with the appropriate context and the associated advice from the doctor.\nThen there should be a newline, then the plan: first write &#x27;Plan:&#x27; and then, from a new line, a numbered list of the management steps anticipated\n\nRules:\n- Use professional medical terminology.\n- Use one sentence per line.\n- Only include details that are directly mentioned in the transcript\n\nClinical transcript:\n{{text}}",
    "system_prompt": "Please write a concise clinical note using medical terminology, based solely on the clinical transcript provided below. Do not invent or assume any details that are not explicitly mentioned in the transcript.\n\nThe output should be in 3 sectiions.\nThe first section should be a simple summary of the presentation in bullet points, each point on a new line, including age, presenting complaint(s), and if relevant things like previous pregnancies (or lack thereof) and BMI. \nThen there should be a newline, then the middle section should be describe each issue in detail with the appropriate context and the associated advice from the doctor.\nThen there should be a newline, then the plan: first write &#x27;Plan:&#x27; and then, from a new line, a numbered list of the management steps anticipated\n\nRules:\n- Use professional medical terminology.\n- Use one sentence per line.\n- Only include details that are directly mentioned in the transcript\n\nClinical transcript:\n{{text}}"
  },
  "response": "Since no clinical transcript was provided (the placeholder `{{text}}` was not replaced with actual content), I cannot generate a clinical note.  \n\nPlease provide the clinical transcript, and I will create a structured note following your requested format.  \n\nFor reference, here is how the output would be structured if the transcript were provided:  \n\n---  \n**Summary:**  \n- Age: [if mentioned]  \n- Presenting complaint(s): [e.g., \"abdominal pain, nausea\"]  \n- Relevant history: [e.g., \"nulliparous, BMI 28\"]  \n\n**Details:**  \n- [First issue]: [Description with context and doctor's advice]  \n- [Second issue]: [Description with context and doctor's advice]  \n\n**Plan:**  \n1. [First management step]  \n2. [Second management step]  \n---  \n\nLet me know the clinical details, and I will draft the note accordingly.",
  "endpoint": "generateFakeClinicalInteraction",
  "timestamp": "2025-05-30T08-06-06",
  "textContent": "AI: DeepSeek (deepseek-chat)\n\nQ: {\n  \"prompt\": \"Please write a concise clinical note using medical terminology, based solely on the clinical transcript provided below. Do not invent or assume any details that are not explicitly mentioned in the transcript.\\n\\nThe output should be in 3 sectiions.\\nThe first section should be a simple summary of the presentation in bullet points, each point on a new line, including age, presenting complaint(s), and if relevant things like previous pregnancies (or lack thereof) and BMI. \\nThen there should be a newline, then the middle section should be describe each issue in detail with the appropriate context and the associated advice from the doctor.\\nThen there should be a newline, then the plan: first write &#x27;Plan:&#x27; and then, from a new line, a numbered list of the management steps anticipated\\n\\nRules:\\n- Use professional medical terminology.\\n- Use one sentence per line.\\n- Only include details that are directly mentioned in the transcript\\n\\nClinical transcript:\\n{{text}}\",\n  \"system_prompt\": \"Please write a concise clinical note using medical terminology, based solely on the clinical transcript provided below. Do not invent or assume any details that are not explicitly mentioned in the transcript.\\n\\nThe output should be in 3 sectiions.\\nThe first section should be a simple summary of the presentation in bullet points, each point on a new line, including age, presenting complaint(s), and if relevant things like previous pregnancies (or lack thereof) and BMI. \\nThen there should be a newline, then the middle section should be describe each issue in detail with the appropriate context and the associated advice from the doctor.\\nThen there should be a newline, then the plan: first write &#x27;Plan:&#x27; and then, from a new line, a numbered list of the management steps anticipated\\n\\nRules:\\n- Use professional medical terminology.\\n- Use one sentence per line.\\n- Only include details that are directly mentioned in the transcript\\n\\nClinical transcript:\\n{{text}}\"\n}\n\nA: Since no clinical transcript was provided (the placeholder `{{text}}` was not replaced with actual content), I cannot generate a clinical note.  \n\nPlease provide the clinical transcript, and I will create a structured note following your requested format.  \n\nFor reference, here is how the output would be structured if the transcript were provided:  \n\n---  \n**Summary:**  \n- Age: [if mentioned]  \n- Presenting complaint(s): [e.g., \"abdominal pain, nausea\"]  \n- Relevant history: [e.g., \"nulliparous, BMI 28\"]  \n\n**Details:**  \n- [First issue]: [Description with context and doctor's advice]  \n- [Second issue]: [Description with context and doctor's advice]  \n\n**Plan:**  \n1. [First management step]  \n2. [Second management step]  \n---  \n\nLet me know the clinical details, and I will draft the note accordingly.\n\n--- Token Usage Report ---\nPrompt tokens: 199\nCompletion tokens: 187\nTotal tokens: 386\nEstimated cost: $0.000193",
  "ai_provider": "DeepSeek",
  "ai_model": "deepseek-chat",
  "token_usage": {
    "prompt_tokens": 199,
    "completion_tokens": 187,
    "total_tokens": 386,
    "estimated_cost_usd": 0.000193
  }
}