{
  "prompt": {
    "prompt": "Original Transcript:\n**OBSTETRICS & GYNAECOLOGY CLERKING – SBAR FORMAT**  \n\n**SITUATION:**  \n- **Patient:** 32F, G2P1 (SVD 2019), BMI 28  \n- **Presenting complaint:** Chronic pelvic pain (6/12 duration), worsening dyspareunia, and secondary subfertility (TTC x 18/12).  \n- **Key issue:** Suspected pelvic adhesions due to previous LSCS (2020 – obstructed labour) and recurrent PID (last episode 2021). Now referred by GP for gynae review due to persistent symptoms.  \n\n**BACKGROUND:**  \n- **PMHx:**  \n  - Previous LSCS (2020) – complicated by post-op wound infection (treated with co-amoxiclav).  \n  - Recurrent PID (2 episodes, last 2021) – managed with IV ceftriaxone + doxycycline.  \n  - No known endometriosis.  \n- **Drugs:** PRN cocodamol for pain, no regular medications.  \n- **Allergies:** NKDA  \n- **SHx:** Non-smoker, occasional alcohol. Works as a teacher.  \n- **FHx:** No relevant gynae malignancies.  \n\n**ASSESSMENT:**  \n- **Examination:**  \n  - **Abdomen:** Soft, non-distended. Mild suprapubic tenderness, no guarding/rigidity.  \n  - **PV:** Cervix appears normal, no discharge. Uterus anteverted, mildly tender on mobilisation. Left adnexal tenderness, no palpable mass.  \n- **Observations:**  \n  - BP 118/76, HR 72, afebrile (36.8°C).  \n- **Investigations:**  \n  - **Recent GP workup:** FBC (Hb 128, WCC 6.2), CRP 4, negative chlamydia/gonorrhoea NAAT.  \n  - **TV USS (today):** Normal endometrial thickness, no hydrosalpinx. Subtle left adnexal tethering noted.  \n- **Differential diagnoses:**  \n  1. **Pelvic adhesions** (post-surgical/PID-related – most likely).  \n  2. **Endometriosis** (though no cyclical pain/dysmenorrhoea).  \n  3. **Chronic PID** (low likelihood given normal inflammatory markers).  \n\n**RECOMMENDATION:**  \n1. **Diagnostic laparoscopy + adhesiolysis** (gold standard for diagnosis/therapy). Counsel re risks (bowel/bladder injury, recurrence).  \n2. **Pre-op:**  \n   - FBC, U&E, G&S.  \n   - Consider CA-125 if endometriosis suspected (though low yield).  \n3. **Post-op:**  \n   - Consider Mirena/IUS if endometriosis found (for symptom control).  \n   - Fertility referral if adhesiolysis confirms tubal patency but conception delayed.  \n4. **Follow-up:** Gynae clinic 2/52 post-op to discuss findings and plan.  \n\n**CLINICIAN:** Dr. A. Smith (ST5 Obs & Gynae)  \n**DATE:** 15/05/2024  \n\n*(For educational purposes only – fictional case)*  \n\n---  \n**Notes:**  \n- Abbreviations: LSCS (lower segment Caesarean section), PID (pelvic inflammatory disease), TTC (trying to conceive), TV USS (transvaginal ultrasound), NAAT (nucleic acid amplification test), IUS (intrauterine system).  \n- Realistic workflow: GP referral → gynae OPD → TV USS → decision for laparoscopy.  \n- Adhesions often post-surgical/PID-related; laparoscopy is diagnostic/therapeutic.\n\nApply these changes:\nACCEPT: Replace \"Missing: daily pain diary documentation\" with \"Recommend initiating a daily pain diary to identify provoking factors or associations\" (Reason: According to the guideline: 'Completing a daily pain diary may help identify provoking factors or associations.' This is particularly relevant for this patient with chronic pelvic pain of 6 months duration, as it could help identify patterns related to menstrual cycle, bowel habits, or activities that exacerbate symptoms. The diary would provide valuable longitudinal data to complement the single-point assessment.)\nACCEPT: Replace \"Consider CA-125 if endometriosis suspected (though low yield)\" with \"Omit CA-125 testing as it has low diagnostic utility for endometriosis in this context\" (Reason: The guideline emphasizes evidence-based testing, and CA-125 has well-documented poor specificity for endometriosis diagnosis. Given this patient's atypical presentation for endometriosis (no cyclical pain/dysmenorrhoea) and the guideline's focus on appropriate investigations, CA-125 would not change management. 'TVS and MRI are useful for identifying structural abnormalities' would be more appropriate next steps if needed.)\nACCEPT: Replace \"Missing: functional assessment documentation\" with \"Document baseline functional assessment to monitor treatment progress\" (Reason: The guideline states: 'Establishing the woman's level of function at the start of treatment is important for monitoring progress and setting functional goals.' For this working teacher with chronic pain, documenting how symptoms affect her daily activities (work performance, childcare, sexual function) would provide measurable outcomes for evaluating treatment success.)\nACCEPT: Replace \"Missing: psychological/social factors assessment\" with \"Include assessment of psychological factors and social impact of chronic pain\" (Reason: The guideline emphasizes: 'Chronic pelvic pain should be seen as a symptom with multiple contributing factors.' Given this patient's 6-month pain history with functional impact, assessing for depression, anxiety, or work-related stress is crucial. The guideline specifically mentions considering 'coping with emotions and abuse history in women with chronic pelvic pain' given the known associations.)\nACCEPT: Replace \"Diagnostic laparoscopy + adhesiolysis (gold standard for diagnosis/therapy)\" with \"Diagnostic laparoscopy + adhesiolysis (consider as second-line investigation after failed conservative management)\" (Reason: The guideline recommends: 'Diagnostic laparoscopy should be considered as a second-line investigation.' For this patient with likely adhesions but no acute findings, a trial of conservative measures (physical therapy, medical management) may be appropriate before proceeding to surgery, unless fertility concerns necessitate earlier intervention. This aligns with the stepped-care approach recommended in chronic pain management.)\n\nReturn the updated transcript with these changes applied.",
    "system_prompt": "You are a medical AI assistant that applies user decisions to clinical transcripts based on guideline suggestions.\n\nYou will receive:\n1. An original transcript\n2. A list of suggestions with user decisions (accept, reject, or modify)\n3. For modifications, the user's custom text\n\nYour task is to apply only the ACCEPTED and MODIFIED suggestions to create an updated transcript. For each change:\n- ACCEPTED suggestions: Apply the suggested text exactly as provided\n- MODIFIED suggestions: Apply the user's modified text instead of the original suggestion\n- REJECTED suggestions: Leave the original text unchanged\n\nReturn the updated transcript as clean, properly formatted medical text. Maintain the original structure and formatting as much as possible while incorporating the accepted changes.\n\nImportant guidelines:\n- Only apply changes that the user has accepted or modified\n- Preserve the medical accuracy and professional tone\n- Maintain logical flow and readability\n- Do not add any explanatory text or comments\n- Return only the updated transcript",
    "session_id": "advice_1752423500317_87zjuu12u",
    "original_transcript_length": 2766,
    "changes_applied": 5,
    "decisions_summary": {
      "accepted": 5,
      "modified": 0,
      "rejected": 0
    }
  },
  "response": "**OBSTETRICS & GYNAECOLOGY CLERKING – SBAR FORMAT**  \n\n**SITUATION:**  \n- **Patient:** 32F, G2P1 (SVD 2019), BMI 28  \n- **Presenting complaint:** Chronic pelvic pain (6/12 duration), worsening dyspareunia, and secondary subfertility (TTC x 18/12).  \n- **Key issue:** Suspected pelvic adhesions due to previous LSCS (2020 – obstructed labour) and recurrent PID (last episode 2021). Now referred by GP for gynae review due to persistent symptoms.  \n\n**BACKGROUND:**  \n- **PMHx:**  \n  - Previous LSCS (2020) – complicated by post-op wound infection (treated with co-amoxiclav).  \n  - Recurrent PID (2 episodes, last 2021) – managed with IV ceftriaxone + doxycycline.  \n  - No known endometriosis.  \n- **Drugs:** PRN cocodamol for pain, no regular medications.  \n- **Allergies:** NKDA  \n- **SHx:** Non-smoker, occasional alcohol. Works as a teacher.  \n- **FHx:** No relevant gynae malignancies.  \n\n**ASSESSMENT:**  \n- **Examination:**  \n  - **Abdomen:** Soft, non-distended. Mild suprapubic tenderness, no guarding/rigidity.  \n  - **PV:** Cervix appears normal, no discharge. Uterus anteverted, mildly tender on mobilisation. Left adnexal tenderness, no palpable mass.  \n- **Observations:**  \n  - BP 118/76, HR 72, afebrile (36.8°C).  \n- **Investigations:**  \n  - **Recent GP workup:** FBC (Hb 128, WCC 6.2), CRP 4, negative chlamydia/gonorrhoea NAAT.  \n  - **TV USS (today):** Normal endometrial thickness, no hydrosalpinx. Subtle left adnexal tethering noted.  \n- **Differential diagnoses:**  \n  1. **Pelvic adhesions** (post-surgical/PID-related – most likely).  \n  2. **Endometriosis** (though no cyclical pain/dysmenorrhoea).  \n  3. **Chronic PID** (low likelihood given normal inflammatory markers).  \n\n**RECOMMENDATION:**  \n1. **Diagnostic laparoscopy + adhesiolysis** (consider as second-line investigation after failed conservative management). Counsel re risks (bowel/bladder injury, recurrence).  \n2. **Pre-op:**  \n   - FBC, U&E, G&S.  \n   - Omit CA-125 testing as it has low diagnostic utility for endometriosis in this context.  \n3. **Post-op:**  \n   - Consider Mirena/IUS if endometriosis found (for symptom control).  \n   - Fertility referral if adhesiolysis confirms tubal patency but conception delayed.  \n4. **Follow-up:** Gynae clinic 2/52 post-op to discuss findings and plan.  \n5. **Additional measures:**  \n   - Recommend initiating a daily pain diary to identify provoking factors or associations.  \n   - Document baseline functional assessment to monitor treatment progress.  \n   - Include assessment of psychological factors and social impact of chronic pain.  \n\n**CLINICIAN:** Dr. A. Smith (ST5 Obs & Gynae)  \n**DATE:** 15/05/2024  \n\n*(For educational purposes only – fictional case)*  \n\n---  \n**Notes:**  \n- Abbreviations: LSCS (lower segment Caesarean section), PID (pelvic inflammatory disease), TTC (trying to conceive), TV USS (transvaginal ultrasound), NAAT (nucleic acid amplification test), IUS (intrauterine system).  \n- Realistic workflow: GP referral → gynae OPD → TV USS → decision for laparoscopy.  \n- Adhesions often post-surgical/PID-related; laparoscopy is diagnostic/therapeutic.",
  "endpoint": "applyDynamicAdvice",
  "timestamp": "2025-07-13T16-20-21",
  "textContent": "AI: DeepSeek (deepseek-chat)\n\nQ: {\n  \"prompt\": \"Original Transcript:\\n**OBSTETRICS & GYNAECOLOGY CLERKING – SBAR FORMAT**  \\n\\n**SITUATION:**  \\n- **Patient:** 32F, G2P1 (SVD 2019), BMI 28  \\n- **Presenting complaint:** Chronic pelvic pain (6/12 duration), worsening dyspareunia, and secondary subfertility (TTC x 18/12).  \\n- **Key issue:** Suspected pelvic adhesions due to previous LSCS (2020 – obstructed labour) and recurrent PID (last episode 2021). Now referred by GP for gynae review due to persistent symptoms.  \\n\\n**BACKGROUND:**  \\n- **PMHx:**  \\n  - Previous LSCS (2020) – complicated by post-op wound infection (treated with co-amoxiclav).  \\n  - Recurrent PID (2 episodes, last 2021) – managed with IV ceftriaxone + doxycycline.  \\n  - No known endometriosis.  \\n- **Drugs:** PRN cocodamol for pain, no regular medications.  \\n- **Allergies:** NKDA  \\n- **SHx:** Non-smoker, occasional alcohol. Works as a teacher.  \\n- **FHx:** No relevant gynae malignancies.  \\n\\n**ASSESSMENT:**  \\n- **Examination:**  \\n  - **Abdomen:** Soft, non-distended. Mild suprapubic tenderness, no guarding/rigidity.  \\n  - **PV:** Cervix appears normal, no discharge. Uterus anteverted, mildly tender on mobilisation. Left adnexal tenderness, no palpable mass.  \\n- **Observations:**  \\n  - BP 118/76, HR 72, afebrile (36.8°C).  \\n- **Investigations:**  \\n  - **Recent GP workup:** FBC (Hb 128, WCC 6.2), CRP 4, negative chlamydia/gonorrhoea NAAT.  \\n  - **TV USS (today):** Normal endometrial thickness, no hydrosalpinx. Subtle left adnexal tethering noted.  \\n- **Differential diagnoses:**  \\n  1. **Pelvic adhesions** (post-surgical/PID-related – most likely).  \\n  2. **Endometriosis** (though no cyclical pain/dysmenorrhoea).  \\n  3. **Chronic PID** (low likelihood given normal inflammatory markers).  \\n\\n**RECOMMENDATION:**  \\n1. **Diagnostic laparoscopy + adhesiolysis** (gold standard for diagnosis/therapy). Counsel re risks (bowel/bladder injury, recurrence).  \\n2. **Pre-op:**  \\n   - FBC, U&E, G&S.  \\n   - Consider CA-125 if endometriosis suspected (though low yield).  \\n3. **Post-op:**  \\n   - Consider Mirena/IUS if endometriosis found (for symptom control).  \\n   - Fertility referral if adhesiolysis confirms tubal patency but conception delayed.  \\n4. **Follow-up:** Gynae clinic 2/52 post-op to discuss findings and plan.  \\n\\n**CLINICIAN:** Dr. A. Smith (ST5 Obs & Gynae)  \\n**DATE:** 15/05/2024  \\n\\n*(For educational purposes only – fictional case)*  \\n\\n---  \\n**Notes:**  \\n- Abbreviations: LSCS (lower segment Caesarean section), PID (pelvic inflammatory disease), TTC (trying to conceive), TV USS (transvaginal ultrasound), NAAT (nucleic acid amplification test), IUS (intrauterine system).  \\n- Realistic workflow: GP referral → gynae OPD → TV USS → decision for laparoscopy.  \\n- Adhesions often post-surgical/PID-related; laparoscopy is diagnostic/therapeutic.\\n\\nApply these changes:\\nACCEPT: Replace \\\"Missing: daily pain diary documentation\\\" with \\\"Recommend initiating a daily pain diary to identify provoking factors or associations\\\" (Reason: According to the guideline: 'Completing a daily pain diary may help identify provoking factors or associations.' This is particularly relevant for this patient with chronic pelvic pain of 6 months duration, as it could help identify patterns related to menstrual cycle, bowel habits, or activities that exacerbate symptoms. The diary would provide valuable longitudinal data to complement the single-point assessment.)\\nACCEPT: Replace \\\"Consider CA-125 if endometriosis suspected (though low yield)\\\" with \\\"Omit CA-125 testing as it has low diagnostic utility for endometriosis in this context\\\" (Reason: The guideline emphasizes evidence-based testing, and CA-125 has well-documented poor specificity for endometriosis diagnosis. Given this patient's atypical presentation for endometriosis (no cyclical pain/dysmenorrhoea) and the guideline's focus on appropriate investigations, CA-125 would not change management. 'TVS and MRI are useful for identifying structural abnormalities' would be more appropriate next steps if needed.)\\nACCEPT: Replace \\\"Missing: functional assessment documentation\\\" with \\\"Document baseline functional assessment to monitor treatment progress\\\" (Reason: The guideline states: 'Establishing the woman's level of function at the start of treatment is important for monitoring progress and setting functional goals.' For this working teacher with chronic pain, documenting how symptoms affect her daily activities (work performance, childcare, sexual function) would provide measurable outcomes for evaluating treatment success.)\\nACCEPT: Replace \\\"Missing: psychological/social factors assessment\\\" with \\\"Include assessment of psychological factors and social impact of chronic pain\\\" (Reason: The guideline emphasizes: 'Chronic pelvic pain should be seen as a symptom with multiple contributing factors.' Given this patient's 6-month pain history with functional impact, assessing for depression, anxiety, or work-related stress is crucial. The guideline specifically mentions considering 'coping with emotions and abuse history in women with chronic pelvic pain' given the known associations.)\\nACCEPT: Replace \\\"Diagnostic laparoscopy + adhesiolysis (gold standard for diagnosis/therapy)\\\" with \\\"Diagnostic laparoscopy + adhesiolysis (consider as second-line investigation after failed conservative management)\\\" (Reason: The guideline recommends: 'Diagnostic laparoscopy should be considered as a second-line investigation.' For this patient with likely adhesions but no acute findings, a trial of conservative measures (physical therapy, medical management) may be appropriate before proceeding to surgery, unless fertility concerns necessitate earlier intervention. This aligns with the stepped-care approach recommended in chronic pain management.)\\n\\nReturn the updated transcript with these changes applied.\",\n  \"system_prompt\": \"You are a medical AI assistant that applies user decisions to clinical transcripts based on guideline suggestions.\\n\\nYou will receive:\\n1. An original transcript\\n2. A list of suggestions with user decisions (accept, reject, or modify)\\n3. For modifications, the user's custom text\\n\\nYour task is to apply only the ACCEPTED and MODIFIED suggestions to create an updated transcript. For each change:\\n- ACCEPTED suggestions: Apply the suggested text exactly as provided\\n- MODIFIED suggestions: Apply the user's modified text instead of the original suggestion\\n- REJECTED suggestions: Leave the original text unchanged\\n\\nReturn the updated transcript as clean, properly formatted medical text. Maintain the original structure and formatting as much as possible while incorporating the accepted changes.\\n\\nImportant guidelines:\\n- Only apply changes that the user has accepted or modified\\n- Preserve the medical accuracy and professional tone\\n- Maintain logical flow and readability\\n- Do not add any explanatory text or comments\\n- Return only the updated transcript\",\n  \"session_id\": \"advice_1752423500317_87zjuu12u\",\n  \"original_transcript_length\": 2766,\n  \"changes_applied\": 5,\n  \"decisions_summary\": {\n    \"accepted\": 5,\n    \"modified\": 0,\n    \"rejected\": 0\n  }\n}\n\nA: **OBSTETRICS & GYNAECOLOGY CLERKING – SBAR FORMAT**  \n\n**SITUATION:**  \n- **Patient:** 32F, G2P1 (SVD 2019), BMI 28  \n- **Presenting complaint:** Chronic pelvic pain (6/12 duration), worsening dyspareunia, and secondary subfertility (TTC x 18/12).  \n- **Key issue:** Suspected pelvic adhesions due to previous LSCS (2020 – obstructed labour) and recurrent PID (last episode 2021). Now referred by GP for gynae review due to persistent symptoms.  \n\n**BACKGROUND:**  \n- **PMHx:**  \n  - Previous LSCS (2020) – complicated by post-op wound infection (treated with co-amoxiclav).  \n  - Recurrent PID (2 episodes, last 2021) – managed with IV ceftriaxone + doxycycline.  \n  - No known endometriosis.  \n- **Drugs:** PRN cocodamol for pain, no regular medications.  \n- **Allergies:** NKDA  \n- **SHx:** Non-smoker, occasional alcohol. Works as a teacher.  \n- **FHx:** No relevant gynae malignancies.  \n\n**ASSESSMENT:**  \n- **Examination:**  \n  - **Abdomen:** Soft, non-distended. Mild suprapubic tenderness, no guarding/rigidity.  \n  - **PV:** Cervix appears normal, no discharge. Uterus anteverted, mildly tender on mobilisation. Left adnexal tenderness, no palpable mass.  \n- **Observations:**  \n  - BP 118/76, HR 72, afebrile (36.8°C).  \n- **Investigations:**  \n  - **Recent GP workup:** FBC (Hb 128, WCC 6.2), CRP 4, negative chlamydia/gonorrhoea NAAT.  \n  - **TV USS (today):** Normal endometrial thickness, no hydrosalpinx. Subtle left adnexal tethering noted.  \n- **Differential diagnoses:**  \n  1. **Pelvic adhesions** (post-surgical/PID-related – most likely).  \n  2. **Endometriosis** (though no cyclical pain/dysmenorrhoea).  \n  3. **Chronic PID** (low likelihood given normal inflammatory markers).  \n\n**RECOMMENDATION:**  \n1. **Diagnostic laparoscopy + adhesiolysis** (consider as second-line investigation after failed conservative management). Counsel re risks (bowel/bladder injury, recurrence).  \n2. **Pre-op:**  \n   - FBC, U&E, G&S.  \n   - Omit CA-125 testing as it has low diagnostic utility for endometriosis in this context.  \n3. **Post-op:**  \n   - Consider Mirena/IUS if endometriosis found (for symptom control).  \n   - Fertility referral if adhesiolysis confirms tubal patency but conception delayed.  \n4. **Follow-up:** Gynae clinic 2/52 post-op to discuss findings and plan.  \n5. **Additional measures:**  \n   - Recommend initiating a daily pain diary to identify provoking factors or associations.  \n   - Document baseline functional assessment to monitor treatment progress.  \n   - Include assessment of psychological factors and social impact of chronic pain.  \n\n**CLINICIAN:** Dr. A. Smith (ST5 Obs & Gynae)  \n**DATE:** 15/05/2024  \n\n*(For educational purposes only – fictional case)*  \n\n---  \n**Notes:**  \n- Abbreviations: LSCS (lower segment Caesarean section), PID (pelvic inflammatory disease), TTC (trying to conceive), TV USS (transvaginal ultrasound), NAAT (nucleic acid amplification test), IUS (intrauterine system).  \n- Realistic workflow: GP referral → gynae OPD → TV USS → decision for laparoscopy.  \n- Adhesions often post-surgical/PID-related; laparoscopy is diagnostic/therapeutic.\n\n--- Token Usage Report ---\nPrompt tokens: 1544\nCompletion tokens: 860\nTotal tokens: 2404\nEstimated cost: $0.001202",
  "ai_provider": "DeepSeek",
  "ai_model": "deepseek-chat",
  "token_usage": {
    "prompt_tokens": 1544,
    "completion_tokens": 860,
    "total_tokens": 2404,
    "estimated_cost_usd": 0.001202
  }
}