{
  "prompt": {
    "prompt": "Create a fictional dictation of a clinical interaction between a healthcare professional and a patient. \nThis dictation is for testing purposes only and should include various topics that might be discussed in a healthcare setting. \nPlease ensure the material is entirely fictional and does not provide any real medical advice or information. \nPlease ensure variables such as age, weight and history are varied.\nThe clinician should ensure the history and examination findings are incomplete, leaving out some pertinent questions.\nIn response to their history and examination findings, the clinician should  provide management advice and guidance.\nThe clinical scenario should be the following: \n\nMake the age 40, the BMI 20.8 and the number of prior pregnancies 0\n\nBase the clinical scenario on the following gynecology issue: Lichen sclerosus",
    "system_prompt": "Create a fictional dictation of a clinical interaction between a healthcare professional and a patient. \nThis dictation is for testing purposes only and should include various topics that might be discussed in a healthcare setting. \nPlease ensure the material is entirely fictional and does not provide any real medical advice or information. \nPlease ensure variables such as age, weight and history are varied.\nThe clinician should ensure the history and examination findings are incomplete, leaving out some pertinent questions.\nIn response to their history and examination findings, the clinician should  provide management advice and guidance.\nThe clinical scenario should be the following: \n\nMake the age 40, the BMI 20.8 and the number of prior pregnancies 0\n\nBase the clinical scenario on the following gynecology issue: Lichen sclerosus"
  },
  "response": "**Dictation: Clinical Interaction – Gynecology Consultation**  \n\n**Patient Name:** Jane Doe  \n**Age:** 40  \n**BMI:** 20.8  \n**Gravida:** 0  \n**Date of Encounter:** [Fictional Date]  \n**Clinician:** Dr. Smith  \n\n### **Subjective:**  \nMs. Doe presents today reporting a 6-month history of persistent vulvar itching and discomfort. She describes the sensation as intense, often worse at night, and notes occasional sharp pain with intercourse. She denies any vaginal discharge, bleeding, or urinary symptoms. She has tried over-the-counter antifungal creams without relief.  \n\n**Relevant History:**  \n- No prior pregnancies.  \n- No history of sexually transmitted infections.  \n- No chronic medical conditions.  \n- No known allergies.  \n- No prior vulvar biopsies or procedures.  \n\n*Incomplete aspects:*  \n- Family history of autoimmune or dermatologic conditions not explored.  \n- Sexual history (e.g., recent partners, contraception) not fully assessed.  \n- Impact on daily activities or emotional well-being not discussed.  \n\n### **Objective:**  \n**Physical Examination:**  \n- **General:** Well-appearing, no acute distress.  \n- **Vulvar Inspection:** Thin, pale, parchment-like skin with areas of whitish plaques noted on labia minora and perineum. Fissuring present near the posterior fourchette. No active bleeding or ulcerations.  \n- **Speculum Exam:** Vaginal mucosa appears normal; cervix without lesions.  \n- **Bimanual Exam:** Uterus anteverted, non-tender; adnexa without masses.  \n\n*Incomplete aspects:*  \n- No documentation of lymph node assessment.  \n- No mention of anal involvement (common in lichen sclerosus).  \n\n### **Assessment:**  \n**Working Diagnosis:** Likely lichen sclerosus given classic appearance of vulvar skin changes and symptoms. Differential includes lichen planus or vulvar dysplasia, though less likely.  \n\n### **Plan:**  \n1. **Topical Therapy:** Prescribe high-potency corticosteroid ointment (e.g., clobetasol 0.05%) applied thinly to affected areas once daily for 4 weeks, then taper.  \n2. **Symptom Management:** Recommend emollients (e.g., plain petroleum jelly) to reduce friction and soothe skin.  \n3. **Follow-Up:** Re-evaluate in 6 weeks to assess response. If no improvement, consider biopsy to confirm diagnosis.  \n4. **Counseling:** Advised to avoid irritants (e.g., scented soaps, tight clothing). Discussed chronic nature of condition but reassured about benign course with treatment.  \n\n*Omissions in Guidance:*  \n- No discussion of long-term monitoring for malignancy risk (rare but increased in lichen sclerosus).  \n- No referral to dermatology or vulvar specialty clinic considered.  \n\n**Next Steps:** Patient instructed to call if worsening symptoms or new lesions arise.  \n\n**Dictated by:** Dr. Smith  \n**For Testing Purposes Only – Fictional Documentation**  \n\n---  \n*Note: This is a simulated clinical note for educational/testing use. No real patient data or medical advice is represented.*",
  "endpoint": "newFunctionName",
  "timestamp": "2025-04-22T05-30-09",
  "textContent": "AI: DeepSeek (deepseek-chat)\n\nQ: {\n  \"prompt\": \"Create a fictional dictation of a clinical interaction between a healthcare professional and a patient. \\nThis dictation is for testing purposes only and should include various topics that might be discussed in a healthcare setting. \\nPlease ensure the material is entirely fictional and does not provide any real medical advice or information. \\nPlease ensure variables such as age, weight and history are varied.\\nThe clinician should ensure the history and examination findings are incomplete, leaving out some pertinent questions.\\nIn response to their history and examination findings, the clinician should  provide management advice and guidance.\\nThe clinical scenario should be the following: \\n\\nMake the age 40, the BMI 20.8 and the number of prior pregnancies 0\\n\\nBase the clinical scenario on the following gynecology issue: Lichen sclerosus\",\n  \"system_prompt\": \"Create a fictional dictation of a clinical interaction between a healthcare professional and a patient. \\nThis dictation is for testing purposes only and should include various topics that might be discussed in a healthcare setting. \\nPlease ensure the material is entirely fictional and does not provide any real medical advice or information. \\nPlease ensure variables such as age, weight and history are varied.\\nThe clinician should ensure the history and examination findings are incomplete, leaving out some pertinent questions.\\nIn response to their history and examination findings, the clinician should  provide management advice and guidance.\\nThe clinical scenario should be the following: \\n\\nMake the age 40, the BMI 20.8 and the number of prior pregnancies 0\\n\\nBase the clinical scenario on the following gynecology issue: Lichen sclerosus\"\n}\n\nA: **Dictation: Clinical Interaction – Gynecology Consultation**  \n\n**Patient Name:** Jane Doe  \n**Age:** 40  \n**BMI:** 20.8  \n**Gravida:** 0  \n**Date of Encounter:** [Fictional Date]  \n**Clinician:** Dr. Smith  \n\n### **Subjective:**  \nMs. Doe presents today reporting a 6-month history of persistent vulvar itching and discomfort. She describes the sensation as intense, often worse at night, and notes occasional sharp pain with intercourse. She denies any vaginal discharge, bleeding, or urinary symptoms. She has tried over-the-counter antifungal creams without relief.  \n\n**Relevant History:**  \n- No prior pregnancies.  \n- No history of sexually transmitted infections.  \n- No chronic medical conditions.  \n- No known allergies.  \n- No prior vulvar biopsies or procedures.  \n\n*Incomplete aspects:*  \n- Family history of autoimmune or dermatologic conditions not explored.  \n- Sexual history (e.g., recent partners, contraception) not fully assessed.  \n- Impact on daily activities or emotional well-being not discussed.  \n\n### **Objective:**  \n**Physical Examination:**  \n- **General:** Well-appearing, no acute distress.  \n- **Vulvar Inspection:** Thin, pale, parchment-like skin with areas of whitish plaques noted on labia minora and perineum. Fissuring present near the posterior fourchette. No active bleeding or ulcerations.  \n- **Speculum Exam:** Vaginal mucosa appears normal; cervix without lesions.  \n- **Bimanual Exam:** Uterus anteverted, non-tender; adnexa without masses.  \n\n*Incomplete aspects:*  \n- No documentation of lymph node assessment.  \n- No mention of anal involvement (common in lichen sclerosus).  \n\n### **Assessment:**  \n**Working Diagnosis:** Likely lichen sclerosus given classic appearance of vulvar skin changes and symptoms. Differential includes lichen planus or vulvar dysplasia, though less likely.  \n\n### **Plan:**  \n1. **Topical Therapy:** Prescribe high-potency corticosteroid ointment (e.g., clobetasol 0.05%) applied thinly to affected areas once daily for 4 weeks, then taper.  \n2. **Symptom Management:** Recommend emollients (e.g., plain petroleum jelly) to reduce friction and soothe skin.  \n3. **Follow-Up:** Re-evaluate in 6 weeks to assess response. If no improvement, consider biopsy to confirm diagnosis.  \n4. **Counseling:** Advised to avoid irritants (e.g., scented soaps, tight clothing). Discussed chronic nature of condition but reassured about benign course with treatment.  \n\n*Omissions in Guidance:*  \n- No discussion of long-term monitoring for malignancy risk (rare but increased in lichen sclerosus).  \n- No referral to dermatology or vulvar specialty clinic considered.  \n\n**Next Steps:** Patient instructed to call if worsening symptoms or new lesions arise.  \n\n**Dictated by:** Dr. Smith  \n**For Testing Purposes Only – Fictional Documentation**  \n\n---  \n*Note: This is a simulated clinical note for educational/testing use. No real patient data or medical advice is represented.*\n\n--- Token Usage Report ---\nPrompt tokens: 161\nCompletion tokens: 667\nTotal tokens: 828\nEstimated cost: $0.000414",
  "ai_provider": "DeepSeek",
  "ai_model": "deepseek-chat",
  "token_usage": {
    "prompt_tokens": 161,
    "completion_tokens": 667,
    "total_tokens": 828,
    "estimated_cost_usd": 0.00041400000000000003
  }
}