{
  "prompt": {
    "prompt": "Original Transcript:\n29 years old 39 weeks plus zero days  parano in my 33 recess positive  spontaneous sunset of labor aggressive over the last 24 to 48 hours on 20th rupture membranes at approximately 7 pm today clearly core clinically feeling well no symptoms of infection good fetal movements felt  CTG normal observations normal  benedicta and a partner Delhi Dei are awaken their baby celesta  he appears well and contracting  up to one in every five minutes  and contractions are palpable moderate and abortion of 30 seconds long  we had to discussion about  spontaneous structure of membranes pre labor and term and after 24 hours the obstetric device would be for augmentation of labor  the option exists prior to that to  offer augmentation or induction  the benefit is that there's a progressive increase in risk of chordia notice it neonatal infection with time that wrist doubles from one and 200 to 1 and 100 after 24 hours posture membranes  the method in her case would be by oxytocin drip adjusted to increase the contraction frequency to three to four and 10 with the risk system is contained associated for her to the stress associated for baby use of an epidural would be increased there's no significant increase that you interventions Associates the alternative will be either more time or is there in section  on the reflection benedicta and her partner would like a few more hours in order to see if labor establishes and if so shoulders spontaneously and if not to augmentation  therefore the plan is  to  reassess in an hour or two and offer tunnel examination of labor is not obviously arising and if there's no significant survival change to  CTG and start\n\nApply these changes:\nACCEPT: Replace \"the benefit is that there's a progressive increase in risk of chordia notice it neonatal infection with time that wrist doubles from one and 200 to 1 and 100 after 24 hours posture membranes\" with \"the benefit is that there's a progressive increase in risk of chorioamnionitis and neonatal infection with time - the risk doubles from 1 in 200 to 1 in 100 after 24 hours post membrane rupture\" (Reason: Clearer risk communication improves shared decision-making)\nACCEPT: Replace \"Missing: criteria for intervention during waiting period\" with \"Document specific criteria that would prompt intervention (e.g., abnormal CTG, maternal fever, prolonged rupture >24 hours)\" (Reason: Clear action thresholds improve safety)\n\nReturn the updated transcript with these changes applied.",
    "system_prompt": "You are a medical AI assistant that applies user decisions to clinical transcripts based on guideline suggestions.\n\nYou will receive:\n1. An original transcript\n2. A list of suggestions with user decisions (accept, reject, or modify)\n3. For modifications, the user's custom text\n\nYour task is to apply only the ACCEPTED and MODIFIED suggestions to create an updated transcript. For each change:\n- ACCEPTED suggestions: Apply the suggested text exactly as provided\n- MODIFIED suggestions: Apply the user's modified text instead of the original suggestion\n- REJECTED suggestions: Leave the original text unchanged\n\nReturn the updated transcript as clean, properly formatted medical text. Maintain the original structure and formatting as much as possible while incorporating the accepted changes.\n\nImportant guidelines:\n- Only apply changes that the user has accepted or modified\n- Preserve the medical accuracy and professional tone\n- Maintain logical flow and readability\n- Do not add any explanatory text or comments\n- Return only the updated transcript",
    "session_id": "advice_1750019144985_35h89i0g2",
    "original_transcript_length": 1663,
    "changes_applied": 2,
    "decisions_summary": {
      "accepted": 2,
      "modified": 0,
      "rejected": 3
    }
  },
  "response": "29 years old 39 weeks plus zero days parano in my 33 recess positive spontaneous sunset of labor aggressive over the last 24 to 48 hours on 20th rupture membranes at approximately 7 pm today clearly core clinically feeling well no symptoms of infection good fetal movements felt CTG normal observations normal benedicta and a partner Delhi Dei are awaken their baby celesta he appears well and contracting up to one in every five minutes and contractions are palpable moderate and abortion of 30 seconds long we had to discussion about spontaneous structure of membranes pre labor and term and after 24 hours the obstetric device would be for augmentation of labor the option exists prior to that to offer augmentation or induction the benefit is that there's a progressive increase in risk of chorioamnionitis and neonatal infection with time - the risk doubles from 1 in 200 to 1 in 100 after 24 hours post membrane rupture the method in her case would be by oxytocin drip adjusted to increase the contraction frequency to three to four and 10 with the risk system is contained associated for her to the stress associated for baby use of an epidural would be increased there's no significant increase that you interventions Associates the alternative will be either more time or is there in section on the reflection benedicta and her partner would like a few more hours in order to see if labor establishes and if so shoulders spontaneously and if not to augmentation therefore the plan is to reassess in an hour or two and offer tunnel examination of labor is not obviously arising and if there's no significant survival change to CTG and start. Document specific criteria that would prompt intervention (e.g., abnormal CTG, maternal fever, prolonged rupture >24 hours).",
  "endpoint": "applyDynamicAdvice",
  "timestamp": "2025-06-15T20-27-02",
  "textContent": "AI: DeepSeek (deepseek-chat)\n\nQ: {\n  \"prompt\": \"Original Transcript:\\n29 years old 39 weeks plus zero days  parano in my 33 recess positive  spontaneous sunset of labor aggressive over the last 24 to 48 hours on 20th rupture membranes at approximately 7 pm today clearly core clinically feeling well no symptoms of infection good fetal movements felt  CTG normal observations normal  benedicta and a partner Delhi Dei are awaken their baby celesta  he appears well and contracting  up to one in every five minutes  and contractions are palpable moderate and abortion of 30 seconds long  we had to discussion about  spontaneous structure of membranes pre labor and term and after 24 hours the obstetric device would be for augmentation of labor  the option exists prior to that to  offer augmentation or induction  the benefit is that there's a progressive increase in risk of chordia notice it neonatal infection with time that wrist doubles from one and 200 to 1 and 100 after 24 hours posture membranes  the method in her case would be by oxytocin drip adjusted to increase the contraction frequency to three to four and 10 with the risk system is contained associated for her to the stress associated for baby use of an epidural would be increased there's no significant increase that you interventions Associates the alternative will be either more time or is there in section  on the reflection benedicta and her partner would like a few more hours in order to see if labor establishes and if so shoulders spontaneously and if not to augmentation  therefore the plan is  to  reassess in an hour or two and offer tunnel examination of labor is not obviously arising and if there's no significant survival change to  CTG and start\\n\\nApply these changes:\\nACCEPT: Replace \\\"the benefit is that there's a progressive increase in risk of chordia notice it neonatal infection with time that wrist doubles from one and 200 to 1 and 100 after 24 hours posture membranes\\\" with \\\"the benefit is that there's a progressive increase in risk of chorioamnionitis and neonatal infection with time - the risk doubles from 1 in 200 to 1 in 100 after 24 hours post membrane rupture\\\" (Reason: Clearer risk communication improves shared decision-making)\\nACCEPT: Replace \\\"Missing: criteria for intervention during waiting period\\\" with \\\"Document specific criteria that would prompt intervention (e.g., abnormal CTG, maternal fever, prolonged rupture >24 hours)\\\" (Reason: Clear action thresholds improve safety)\\n\\nReturn the updated transcript with these changes applied.\",\n  \"system_prompt\": \"You are a medical AI assistant that applies user decisions to clinical transcripts based on guideline suggestions.\\n\\nYou will receive:\\n1. An original transcript\\n2. A list of suggestions with user decisions (accept, reject, or modify)\\n3. For modifications, the user's custom text\\n\\nYour task is to apply only the ACCEPTED and MODIFIED suggestions to create an updated transcript. For each change:\\n- ACCEPTED suggestions: Apply the suggested text exactly as provided\\n- MODIFIED suggestions: Apply the user's modified text instead of the original suggestion\\n- REJECTED suggestions: Leave the original text unchanged\\n\\nReturn the updated transcript as clean, properly formatted medical text. Maintain the original structure and formatting as much as possible while incorporating the accepted changes.\\n\\nImportant guidelines:\\n- Only apply changes that the user has accepted or modified\\n- Preserve the medical accuracy and professional tone\\n- Maintain logical flow and readability\\n- Do not add any explanatory text or comments\\n- Return only the updated transcript\",\n  \"session_id\": \"advice_1750019144985_35h89i0g2\",\n  \"original_transcript_length\": 1663,\n  \"changes_applied\": 2,\n  \"decisions_summary\": {\n    \"accepted\": 2,\n    \"modified\": 0,\n    \"rejected\": 3\n  }\n}\n\nA: 29 years old 39 weeks plus zero days parano in my 33 recess positive spontaneous sunset of labor aggressive over the last 24 to 48 hours on 20th rupture membranes at approximately 7 pm today clearly core clinically feeling well no symptoms of infection good fetal movements felt CTG normal observations normal benedicta and a partner Delhi Dei are awaken their baby celesta he appears well and contracting up to one in every five minutes and contractions are palpable moderate and abortion of 30 seconds long we had to discussion about spontaneous structure of membranes pre labor and term and after 24 hours the obstetric device would be for augmentation of labor the option exists prior to that to offer augmentation or induction the benefit is that there's a progressive increase in risk of chorioamnionitis and neonatal infection with time - the risk doubles from 1 in 200 to 1 in 100 after 24 hours post membrane rupture the method in her case would be by oxytocin drip adjusted to increase the contraction frequency to three to four and 10 with the risk system is contained associated for her to the stress associated for baby use of an epidural would be increased there's no significant increase that you interventions Associates the alternative will be either more time or is there in section on the reflection benedicta and her partner would like a few more hours in order to see if labor establishes and if so shoulders spontaneously and if not to augmentation therefore the plan is to reassess in an hour or two and offer tunnel examination of labor is not obviously arising and if there's no significant survival change to CTG and start. Document specific criteria that would prompt intervention (e.g., abnormal CTG, maternal fever, prolonged rupture >24 hours).\n\n--- Token Usage Report ---\nPrompt tokens: 706\nCompletion tokens: 344\nTotal tokens: 1050\nEstimated cost: $0.000525",
  "ai_provider": "DeepSeek",
  "ai_model": "deepseek-chat",
  "token_usage": {
    "prompt_tokens": 706,
    "completion_tokens": 344,
    "total_tokens": 1050,
    "estimated_cost_usd": 0.000525
  }
}