{
  "prompt": {
    "prompt": "Create a fictional dictation of a clinical interaction between a healthcare professional and a patient. \nThis dictation is for testing purposes only and should include various topics that might be discussed in a healthcare setting. \nPlease ensure the material is entirely fictional and does not provide any real medical advice or information. \nPlease ensure variables such as age, weight and history are varied.\nThe clinician should ensure the history and examination findings are incomplete, leaving out some pertinent questions.\nIn response to their history and examination findings, the clinician should  provide management advice and guidance.\nThe clinical scenario should be the following: \n\nMake the age 64, the BMI 31.3 and the number of prior pregnancies 3\n\nBase the clinical scenario on the following gynecology issue: Abnormal uterine bleeding",
    "system_prompt": "Create a fictional dictation of a clinical interaction between a healthcare professional and a patient. \nThis dictation is for testing purposes only and should include various topics that might be discussed in a healthcare setting. \nPlease ensure the material is entirely fictional and does not provide any real medical advice or information. \nPlease ensure variables such as age, weight and history are varied.\nThe clinician should ensure the history and examination findings are incomplete, leaving out some pertinent questions.\nIn response to their history and examination findings, the clinician should  provide management advice and guidance.\nThe clinical scenario should be the following: \n\nMake the age 64, the BMI 31.3 and the number of prior pregnancies 3\n\nBase the clinical scenario on the following gynecology issue: Abnormal uterine bleeding"
  },
  "response": "**Dictation: Clinical Interaction – Abnormal Uterine Bleeding**  \n*Date: [Fictional Date]*  \n*Clinician: Dr. [Fictional Name], OB/GYN*  \n*Patient: Ms. [Fictional Name], 64-year-old female*  \n\n---\n\n### **Subjective History**  \nMs. [Fictional Name], a 64-year-old female with a BMI of 31.3 (obesity class I), presents with a 4-month history of abnormal uterine bleeding. She reports intermittent heavy bleeding with occasional passage of clots, occurring unpredictably every 2–6 weeks. She denies associated pelvic pain but notes mild fatigue, which she attributes to the bleeding.  \n\n**Menstrual History:**  \n- Menarche at age 12.  \n- Prior regular cycles (28–30 days) before menopause at age 52.  \n- No bleeding for 12 years until symptoms began 4 months ago.  \n\n**Obstetric History:**  \n- G3P3 (3 prior pregnancies, all vaginal deliveries).  \n- No history of miscarriages or pregnancy complications.  \n\n**Medical/Surgical History:**  \n- Hypertension (on lisinopril).  \n- No prior gynecologic surgeries.  \n- No known bleeding disorders.  \n\n**Medications:**  \n- Lisinopril 10 mg daily.  \n- Denies hormonal therapy or anticoagulants.  \n\n**Family History:**  \n- Mother with breast cancer (age 70).  \n- No known endometrial/colon cancers.  \n\n**Social History:**  \n- Non-smoker, occasional alcohol.  \n- Sedentary lifestyle.  \n\n**Incomplete Aspects:**  \n- No documentation of sexual activity or postmenopausal bleeding triggers (e.g., weight loss, new medications).  \n- No inquiry about associated symptoms (dysuria, bowel changes).  \n- Family history of Lynch syndrome or other hereditary cancers not explored.  \n\n---\n\n### **Objective Findings**  \n**Vitals:**  \n- BP: 138/86 mmHg, HR: 82 bpm, afebrile.  \n\n**Physical Exam:**  \n- Abdomen: Soft, non-tender, obese. No palpable masses.  \n- Pelvic: External genitalia normal. Speculum exam reveals minimal blood in vault. Cervix appears normal.  \n- Bimanual: Uterus slightly enlarged, mobile, non-tender. Adnexa not palpably enlarged.  \n\n**Incomplete Aspects:**  \n- No documentation of cervical motion tenderness.  \n- No breast exam performed.  \n- No rectal exam or assessment for occult bleeding.  \n\n---\n\n### **Assessment & Plan**  \n**Working Diagnosis:**  \n- Postmenopausal bleeding (PMB), likely due to endometrial hyperplasia or malignancy until proven otherwise.  \n- Differential includes atrophy, polyps, or hormonal influence.  \n\n**Next Steps:**  \n1. **Diagnostics:**  \n   - Transvaginal ultrasound (TVUS) to assess endometrial thickness.  \n   - Endometrial biopsy in office (given high suspicion for pathology).  \n   - CBC to evaluate for anemia.  \n\n2. **Counseling:**  \n   - Emphasized urgency of workup due to cancer risk.  \n   - Advised to track bleeding patterns but did not provide a bleeding diary.  \n   - No discussion of weight management’s role in reducing risk.  \n\n3. **Follow-Up:**  \n   - Return in 1 week for biopsy results.  \n   - If biopsy is inconclusive, will schedule hysteroscopy/D&C.  \n\n**Gaps in Guidance:**  \n- No mention of genetic counseling given family history of breast cancer.  \n- No discussion of anticoagulant risks (if applicable).  \n- No referral to nutrition/endocrinology for obesity comanagement.  \n\n---  \n*Note: This dictation is fictional for testing purposes only. No real medical advice is implied.*  \n\n**End of Report**  \n\n---  \n**Key Testing Features:**  \n- Intentional omissions (e.g., incomplete review of systems, missed screenings).  \n- Varied demographics (age, BMI, parity).  \n- Management includes diagnostic urgency but lacks holistic counseling.",
  "endpoint": "newFunctionName",
  "timestamp": "2025-05-11T06-49-11",
  "textContent": "AI: DeepSeek (deepseek-chat)\n\nQ: {\n  \"prompt\": \"Create a fictional dictation of a clinical interaction between a healthcare professional and a patient. \\nThis dictation is for testing purposes only and should include various topics that might be discussed in a healthcare setting. \\nPlease ensure the material is entirely fictional and does not provide any real medical advice or information. \\nPlease ensure variables such as age, weight and history are varied.\\nThe clinician should ensure the history and examination findings are incomplete, leaving out some pertinent questions.\\nIn response to their history and examination findings, the clinician should  provide management advice and guidance.\\nThe clinical scenario should be the following: \\n\\nMake the age 64, the BMI 31.3 and the number of prior pregnancies 3\\n\\nBase the clinical scenario on the following gynecology issue: Abnormal uterine bleeding\",\n  \"system_prompt\": \"Create a fictional dictation of a clinical interaction between a healthcare professional and a patient. \\nThis dictation is for testing purposes only and should include various topics that might be discussed in a healthcare setting. \\nPlease ensure the material is entirely fictional and does not provide any real medical advice or information. \\nPlease ensure variables such as age, weight and history are varied.\\nThe clinician should ensure the history and examination findings are incomplete, leaving out some pertinent questions.\\nIn response to their history and examination findings, the clinician should  provide management advice and guidance.\\nThe clinical scenario should be the following: \\n\\nMake the age 64, the BMI 31.3 and the number of prior pregnancies 3\\n\\nBase the clinical scenario on the following gynecology issue: Abnormal uterine bleeding\"\n}\n\nA: **Dictation: Clinical Interaction – Abnormal Uterine Bleeding**  \n*Date: [Fictional Date]*  \n*Clinician: Dr. [Fictional Name], OB/GYN*  \n*Patient: Ms. [Fictional Name], 64-year-old female*  \n\n---\n\n### **Subjective History**  \nMs. [Fictional Name], a 64-year-old female with a BMI of 31.3 (obesity class I), presents with a 4-month history of abnormal uterine bleeding. She reports intermittent heavy bleeding with occasional passage of clots, occurring unpredictably every 2–6 weeks. She denies associated pelvic pain but notes mild fatigue, which she attributes to the bleeding.  \n\n**Menstrual History:**  \n- Menarche at age 12.  \n- Prior regular cycles (28–30 days) before menopause at age 52.  \n- No bleeding for 12 years until symptoms began 4 months ago.  \n\n**Obstetric History:**  \n- G3P3 (3 prior pregnancies, all vaginal deliveries).  \n- No history of miscarriages or pregnancy complications.  \n\n**Medical/Surgical History:**  \n- Hypertension (on lisinopril).  \n- No prior gynecologic surgeries.  \n- No known bleeding disorders.  \n\n**Medications:**  \n- Lisinopril 10 mg daily.  \n- Denies hormonal therapy or anticoagulants.  \n\n**Family History:**  \n- Mother with breast cancer (age 70).  \n- No known endometrial/colon cancers.  \n\n**Social History:**  \n- Non-smoker, occasional alcohol.  \n- Sedentary lifestyle.  \n\n**Incomplete Aspects:**  \n- No documentation of sexual activity or postmenopausal bleeding triggers (e.g., weight loss, new medications).  \n- No inquiry about associated symptoms (dysuria, bowel changes).  \n- Family history of Lynch syndrome or other hereditary cancers not explored.  \n\n---\n\n### **Objective Findings**  \n**Vitals:**  \n- BP: 138/86 mmHg, HR: 82 bpm, afebrile.  \n\n**Physical Exam:**  \n- Abdomen: Soft, non-tender, obese. No palpable masses.  \n- Pelvic: External genitalia normal. Speculum exam reveals minimal blood in vault. Cervix appears normal.  \n- Bimanual: Uterus slightly enlarged, mobile, non-tender. Adnexa not palpably enlarged.  \n\n**Incomplete Aspects:**  \n- No documentation of cervical motion tenderness.  \n- No breast exam performed.  \n- No rectal exam or assessment for occult bleeding.  \n\n---\n\n### **Assessment & Plan**  \n**Working Diagnosis:**  \n- Postmenopausal bleeding (PMB), likely due to endometrial hyperplasia or malignancy until proven otherwise.  \n- Differential includes atrophy, polyps, or hormonal influence.  \n\n**Next Steps:**  \n1. **Diagnostics:**  \n   - Transvaginal ultrasound (TVUS) to assess endometrial thickness.  \n   - Endometrial biopsy in office (given high suspicion for pathology).  \n   - CBC to evaluate for anemia.  \n\n2. **Counseling:**  \n   - Emphasized urgency of workup due to cancer risk.  \n   - Advised to track bleeding patterns but did not provide a bleeding diary.  \n   - No discussion of weight management’s role in reducing risk.  \n\n3. **Follow-Up:**  \n   - Return in 1 week for biopsy results.  \n   - If biopsy is inconclusive, will schedule hysteroscopy/D&C.  \n\n**Gaps in Guidance:**  \n- No mention of genetic counseling given family history of breast cancer.  \n- No discussion of anticoagulant risks (if applicable).  \n- No referral to nutrition/endocrinology for obesity comanagement.  \n\n---  \n*Note: This dictation is fictional for testing purposes only. No real medical advice is implied.*  \n\n**End of Report**  \n\n---  \n**Key Testing Features:**  \n- Intentional omissions (e.g., incomplete review of systems, missed screenings).  \n- Varied demographics (age, BMI, parity).  \n- Management includes diagnostic urgency but lacks holistic counseling.\n\n--- Token Usage Report ---\nPrompt tokens: 158\nCompletion tokens: 842\nTotal tokens: 1000\nEstimated cost: $0.000500",
  "ai_provider": "DeepSeek",
  "ai_model": "deepseek-chat",
  "token_usage": {
    "prompt_tokens": 158,
    "completion_tokens": 842,
    "total_tokens": 1000,
    "estimated_cost_usd": 0.0005
  }
}