{
  "prompt": {
    "prompt": "Create a fictional dictation of a clinical interaction between a healthcare professional and a patient. \nThis dictation is for testing purposes only and should include various topics that might be discussed in a healthcare setting. \nPlease ensure the material is entirely fictional and does not provide any real medical advice or information. \nPlease ensure variables such as age, weight and history are varied.\nThe clinician should ensure the history and examination findings are incomplete, leaving out some pertinent questions.\nIn response to their history and examination findings, the clinician should  provide management advice and guidance.\nThe clinical scenario should be the following: Abnormal uterine bleeding",
    "system_prompt": "Create a fictional dictation of a clinical interaction between a healthcare professional and a patient. \nThis dictation is for testing purposes only and should include various topics that might be discussed in a healthcare setting. \nPlease ensure the material is entirely fictional and does not provide any real medical advice or information. \nPlease ensure variables such as age, weight and history are varied.\nThe clinician should ensure the history and examination findings are incomplete, leaving out some pertinent questions.\nIn response to their history and examination findings, the clinician should  provide management advice and guidance.\nThe clinical scenario should be the following: Abnormal uterine bleeding"
  },
  "response": "**Clinical Dictation: Fictional Patient Encounter**  \n**Date:** [Fictional Date]  \n**Clinician:** Dr. A. Smith, OB/GYN  \n**Patient:** Ms. J. Doe (Fictitious Name)  \n**Age:** 38  \n**Weight:** 72 kg  \n**Chief Complaint:** Abnormal uterine bleeding (AUB) for 3 months  \n\n---\n\n### **Subjective History:**  \nMs. Doe reports a 3-month history of irregular, heavy menstrual bleeding, with episodes lasting up to 10 days and requiring frequent pad changes (every 1–2 hours). She notes occasional intermenstrual spotting. She denies associated fever, severe pain, or syncopal episodes.  \n\n**Relevant Medical History:**  \n- Hypothyroidism (on levothyroxine 50 mcg daily, last TSH check unknown).  \n- No prior surgeries.  \n- No known bleeding disorders.  \n- Family history: Mother with \"fibroids\" (details unclear).  \n\n**Social History:**  \n- Non-smoker, occasional alcohol.  \n- Sexually active with one partner, using condoms inconsistently.  \n\n**Medications:**  \n- Levothyroxine 50 mcg daily.  \n- No NSAIDs or hormonal contraception.  \n\n**Allergies:** None reported.  \n\n**Pertinent Omissions (Intentional for Testing):**  \n- Last menstrual period (LMP) not documented.  \n- Gravidity/parity status not asked.  \n- No inquiry about weight changes, hirsutism, or galactorrhea.  \n- Contraceptive goals not explored.  \n\n---\n\n### **Objective Findings:**  \n**Vitals:** BP 118/76, HR 78, BMI 26.  \n**General:** Well-appearing, no pallor.  \n**Abdominal Exam:** Soft, non-tender, no masses palpated.  \n**Pelvic Exam (Limited):** Cervix appears normal; no active bleeding at time of exam. Uterus slightly enlarged, mobile, non-tender. Adnexa not palpated.  \n\n**Omissions:**  \n- No speculum exam performed.  \n- No cervical motion tenderness assessed.  \n- Thyroid exam not documented.  \n\n---\n\n### **Assessment:**  \n**Working Diagnosis:** Abnormal uterine bleeding (AUB) – likely structural etiology (e.g., fibroids) vs. ovulatory dysfunction (e.g., hypothyroidism). Other causes (endometrial pathology, coagulopathy) less likely but not excluded.  \n\n---\n\n### **Plan:**  \n1. **Diagnostics:**  \n   - Pelvic ultrasound to evaluate for fibroids, polyps, or endometrial thickening.  \n   - TSH, CBC, ferritin, and coagulation panel (PT/INR, PTT) to assess for anemia/bleeding disorders.  \n   - *Omission:* No endometrial biopsy ordered despite age >35 and prolonged bleeding.  \n\n2. **Management:**  \n   - Start tranexamic acid 1 g TID during heavy bleeding days (if no contraindications).  \n   - Consider trial of combined oral contraceptive pill (after ultrasound) if no structural abnormalities.  \n   - Re-evaluate thyroid control (order TSH).  \n\n3. **Follow-Up:**  \n   - Return in 4 weeks with results.  \n   - Counsel on seeking urgent care if syncope, severe anemia symptoms, or bleeding worsens.  \n\n**Patient Instructions:**  \n- Keep a menstrual diary.  \n- Avoid NSAIDs until coag workup complete.  \n\n**Disposition:** Stable for outpatient management.  \n\n---  \n**Note for Testing:** This dictation intentionally lacks key elements (e.g., LMP, full contraceptive history, endometrial biopsy consideration) to evaluate documentation accuracy. No real medical advice is implied.  \n\n---  \n**End of Dictation**",
  "endpoint": "generateFakeClinicalInteraction",
  "timestamp": "2025-05-27T12-01-11",
  "textContent": "AI: DeepSeek (deepseek-chat)\n\nQ: {\n  \"prompt\": \"Create a fictional dictation of a clinical interaction between a healthcare professional and a patient. \\nThis dictation is for testing purposes only and should include various topics that might be discussed in a healthcare setting. \\nPlease ensure the material is entirely fictional and does not provide any real medical advice or information. \\nPlease ensure variables such as age, weight and history are varied.\\nThe clinician should ensure the history and examination findings are incomplete, leaving out some pertinent questions.\\nIn response to their history and examination findings, the clinician should  provide management advice and guidance.\\nThe clinical scenario should be the following: Abnormal uterine bleeding\",\n  \"system_prompt\": \"Create a fictional dictation of a clinical interaction between a healthcare professional and a patient. \\nThis dictation is for testing purposes only and should include various topics that might be discussed in a healthcare setting. \\nPlease ensure the material is entirely fictional and does not provide any real medical advice or information. \\nPlease ensure variables such as age, weight and history are varied.\\nThe clinician should ensure the history and examination findings are incomplete, leaving out some pertinent questions.\\nIn response to their history and examination findings, the clinician should  provide management advice and guidance.\\nThe clinical scenario should be the following: Abnormal uterine bleeding\"\n}\n\nA: **Clinical Dictation: Fictional Patient Encounter**  \n**Date:** [Fictional Date]  \n**Clinician:** Dr. A. Smith, OB/GYN  \n**Patient:** Ms. J. Doe (Fictitious Name)  \n**Age:** 38  \n**Weight:** 72 kg  \n**Chief Complaint:** Abnormal uterine bleeding (AUB) for 3 months  \n\n---\n\n### **Subjective History:**  \nMs. Doe reports a 3-month history of irregular, heavy menstrual bleeding, with episodes lasting up to 10 days and requiring frequent pad changes (every 1–2 hours). She notes occasional intermenstrual spotting. She denies associated fever, severe pain, or syncopal episodes.  \n\n**Relevant Medical History:**  \n- Hypothyroidism (on levothyroxine 50 mcg daily, last TSH check unknown).  \n- No prior surgeries.  \n- No known bleeding disorders.  \n- Family history: Mother with \"fibroids\" (details unclear).  \n\n**Social History:**  \n- Non-smoker, occasional alcohol.  \n- Sexually active with one partner, using condoms inconsistently.  \n\n**Medications:**  \n- Levothyroxine 50 mcg daily.  \n- No NSAIDs or hormonal contraception.  \n\n**Allergies:** None reported.  \n\n**Pertinent Omissions (Intentional for Testing):**  \n- Last menstrual period (LMP) not documented.  \n- Gravidity/parity status not asked.  \n- No inquiry about weight changes, hirsutism, or galactorrhea.  \n- Contraceptive goals not explored.  \n\n---\n\n### **Objective Findings:**  \n**Vitals:** BP 118/76, HR 78, BMI 26.  \n**General:** Well-appearing, no pallor.  \n**Abdominal Exam:** Soft, non-tender, no masses palpated.  \n**Pelvic Exam (Limited):** Cervix appears normal; no active bleeding at time of exam. Uterus slightly enlarged, mobile, non-tender. Adnexa not palpated.  \n\n**Omissions:**  \n- No speculum exam performed.  \n- No cervical motion tenderness assessed.  \n- Thyroid exam not documented.  \n\n---\n\n### **Assessment:**  \n**Working Diagnosis:** Abnormal uterine bleeding (AUB) – likely structural etiology (e.g., fibroids) vs. ovulatory dysfunction (e.g., hypothyroidism). Other causes (endometrial pathology, coagulopathy) less likely but not excluded.  \n\n---\n\n### **Plan:**  \n1. **Diagnostics:**  \n   - Pelvic ultrasound to evaluate for fibroids, polyps, or endometrial thickening.  \n   - TSH, CBC, ferritin, and coagulation panel (PT/INR, PTT) to assess for anemia/bleeding disorders.  \n   - *Omission:* No endometrial biopsy ordered despite age >35 and prolonged bleeding.  \n\n2. **Management:**  \n   - Start tranexamic acid 1 g TID during heavy bleeding days (if no contraindications).  \n   - Consider trial of combined oral contraceptive pill (after ultrasound) if no structural abnormalities.  \n   - Re-evaluate thyroid control (order TSH).  \n\n3. **Follow-Up:**  \n   - Return in 4 weeks with results.  \n   - Counsel on seeking urgent care if syncope, severe anemia symptoms, or bleeding worsens.  \n\n**Patient Instructions:**  \n- Keep a menstrual diary.  \n- Avoid NSAIDs until coag workup complete.  \n\n**Disposition:** Stable for outpatient management.  \n\n---  \n**Note for Testing:** This dictation intentionally lacks key elements (e.g., LMP, full contraceptive history, endometrial biopsy consideration) to evaluate documentation accuracy. No real medical advice is implied.  \n\n---  \n**End of Dictation**\n\n--- Token Usage Report ---\nPrompt tokens: 124\nCompletion tokens: 776\nTotal tokens: 900\nEstimated cost: $0.000450",
  "ai_provider": "DeepSeek",
  "ai_model": "deepseek-chat",
  "token_usage": {
    "prompt_tokens": 124,
    "completion_tokens": 776,
    "total_tokens": 900,
    "estimated_cost_usd": 0.00045
  }
}