{
  "prompt": {
    "prompt": "Create a fictional dictation of a clinical interaction between a healthcare professional and a patient. \nThis dictation is for testing purposes only and should include various topics that might be discussed in a healthcare setting. \nPlease ensure the material is entirely fictional and does not provide any real medical advice or information. \nPlease ensure variables such as age, weight and history are varied.\nThe clinician should ensure the history and examination findings are incomplete, leaving out some pertinent questions.\nIn response to their history and examination findings, the clinician should  provide management advice and guidance.\nThe clinical scenario should be the following: \n\nMake the age 41, the BMI 25.2 and the number of prior pregnancies 2\n\nBase the clinical scenario on the following gynecology issue: Abnormal uterine bleeding",
    "system_prompt": "Create a fictional dictation of a clinical interaction between a healthcare professional and a patient. \nThis dictation is for testing purposes only and should include various topics that might be discussed in a healthcare setting. \nPlease ensure the material is entirely fictional and does not provide any real medical advice or information. \nPlease ensure variables such as age, weight and history are varied.\nThe clinician should ensure the history and examination findings are incomplete, leaving out some pertinent questions.\nIn response to their history and examination findings, the clinician should  provide management advice and guidance.\nThe clinical scenario should be the following: \n\nMake the age 41, the BMI 25.2 and the number of prior pregnancies 2\n\nBase the clinical scenario on the following gynecology issue: Abnormal uterine bleeding"
  },
  "response": "**Dictation: Clinical Interaction – Abnormal Uterine Bleeding**  \n*Date: [Fictional Date] | Clinician: Dr. [Fictional Name] | Patient: Ms. [Fictional Name]*  \n\n**Subjective:**  \nMs. X, a 41-year-old female (BMI 25.2, G2P2), presents with a 4-month history of abnormal uterine bleeding. She reports intermittent heavy menstrual bleeding (changing pads every 2 hours on heavy days) and intermenstrual spotting. Bleeding is occasionally associated with mild pelvic cramping but no fever, dizziness, or syncope. She denies dyspareunia or postcoital bleeding. Her last Pap smear was 2 years ago (reported as normal). She has no personal or family history of bleeding disorders or gynecologic malignancies.  \n\n*Incomplete history:*  \n- No documentation of contraceptive use (e.g., hormonal IUD, pills).  \n- Menstrual cycle regularity prior to symptoms not explored.  \n- Thyroid symptoms (fatigue, weight changes) not asked.  \n- Medications (e.g., NSAIDs, anticoagulants) not reviewed.  \n\n**Objective:**  \n- Vitals: BP 118/76, HR 78, afebrile.  \n- Abdomen: Soft, non-tender, no palpable masses.  \n- Pelvic exam (limited): Cervix appears normal; no active bleeding at time of exam. Uterus midline, non-tender. Adnexa not palpated due to patient discomfort.  \n*Incomplete exam:*  \n- No speculum exam performed to visualize cervical os.  \n- Uterine size not assessed (e.g., fibroids).  \n- No labs drawn (e.g., CBC, TSH, pregnancy test).  \n\n**Assessment:**  \nAbnormal uterine bleeding (AUB) in a perimenopausal patient. Differential includes:  \n1. Hormonal imbalance (anovulatory cycles).  \n2. Structural causes (e.g., fibroids, polyps – not ruled out).  \n3. Endometrial pathology (e.g., hyperplasia – risk factors like obesity not fully explored).  \n\n**Plan:**  \n1. *Diagnostics:*  \n   - Order CBC, TSH, and serum hCG to rule out anemia, thyroid dysfunction, pregnancy.  \n   - Schedule pelvic ultrasound to evaluate for structural abnormalities.  \n   - Endometrial biopsy deferred pending ultrasound results (incomplete risk stratification).  \n2. *Symptomatic management:*  \n   - Trial of tranexamic acid for heavy bleeding (no contraindications reviewed).  \n   - Consider progesterone therapy if bleeding persists (not discussed in detail).  \n3. *Follow-up:*  \n   - Return in 4 weeks for results and reassessment. Counseled to seek care sooner if bleeding worsens (e.g., syncope, severe anemia).  \n\n*Omissions:*  \n- No discussion of lifestyle impact (e.g., work limitations).  \n- Contraceptive needs/preferences not addressed.  \n- Family planning goals not explored.  \n\n**Impression:**  \nInitial evaluation incomplete but initiated workup for AUB. Patient advised to monitor symptoms.  \n\n*--End of Dictation--*  \n\n**Note for Testing:** This fictional scenario includes intentional gaps in history/exam and management decisions for educational purposes only. No real clinical guidance is implied.",
  "endpoint": "generateFakeClinicalInteraction",
  "timestamp": "2025-05-27T14-43-39",
  "textContent": "AI: DeepSeek (deepseek-chat)\n\nQ: {\n  \"prompt\": \"Create a fictional dictation of a clinical interaction between a healthcare professional and a patient. \\nThis dictation is for testing purposes only and should include various topics that might be discussed in a healthcare setting. \\nPlease ensure the material is entirely fictional and does not provide any real medical advice or information. \\nPlease ensure variables such as age, weight and history are varied.\\nThe clinician should ensure the history and examination findings are incomplete, leaving out some pertinent questions.\\nIn response to their history and examination findings, the clinician should  provide management advice and guidance.\\nThe clinical scenario should be the following: \\n\\nMake the age 41, the BMI 25.2 and the number of prior pregnancies 2\\n\\nBase the clinical scenario on the following gynecology issue: Abnormal uterine bleeding\",\n  \"system_prompt\": \"Create a fictional dictation of a clinical interaction between a healthcare professional and a patient. \\nThis dictation is for testing purposes only and should include various topics that might be discussed in a healthcare setting. \\nPlease ensure the material is entirely fictional and does not provide any real medical advice or information. \\nPlease ensure variables such as age, weight and history are varied.\\nThe clinician should ensure the history and examination findings are incomplete, leaving out some pertinent questions.\\nIn response to their history and examination findings, the clinician should  provide management advice and guidance.\\nThe clinical scenario should be the following: \\n\\nMake the age 41, the BMI 25.2 and the number of prior pregnancies 2\\n\\nBase the clinical scenario on the following gynecology issue: Abnormal uterine bleeding\"\n}\n\nA: **Dictation: Clinical Interaction – Abnormal Uterine Bleeding**  \n*Date: [Fictional Date] | Clinician: Dr. [Fictional Name] | Patient: Ms. [Fictional Name]*  \n\n**Subjective:**  \nMs. X, a 41-year-old female (BMI 25.2, G2P2), presents with a 4-month history of abnormal uterine bleeding. She reports intermittent heavy menstrual bleeding (changing pads every 2 hours on heavy days) and intermenstrual spotting. Bleeding is occasionally associated with mild pelvic cramping but no fever, dizziness, or syncope. She denies dyspareunia or postcoital bleeding. Her last Pap smear was 2 years ago (reported as normal). She has no personal or family history of bleeding disorders or gynecologic malignancies.  \n\n*Incomplete history:*  \n- No documentation of contraceptive use (e.g., hormonal IUD, pills).  \n- Menstrual cycle regularity prior to symptoms not explored.  \n- Thyroid symptoms (fatigue, weight changes) not asked.  \n- Medications (e.g., NSAIDs, anticoagulants) not reviewed.  \n\n**Objective:**  \n- Vitals: BP 118/76, HR 78, afebrile.  \n- Abdomen: Soft, non-tender, no palpable masses.  \n- Pelvic exam (limited): Cervix appears normal; no active bleeding at time of exam. Uterus midline, non-tender. Adnexa not palpated due to patient discomfort.  \n*Incomplete exam:*  \n- No speculum exam performed to visualize cervical os.  \n- Uterine size not assessed (e.g., fibroids).  \n- No labs drawn (e.g., CBC, TSH, pregnancy test).  \n\n**Assessment:**  \nAbnormal uterine bleeding (AUB) in a perimenopausal patient. Differential includes:  \n1. Hormonal imbalance (anovulatory cycles).  \n2. Structural causes (e.g., fibroids, polyps – not ruled out).  \n3. Endometrial pathology (e.g., hyperplasia – risk factors like obesity not fully explored).  \n\n**Plan:**  \n1. *Diagnostics:*  \n   - Order CBC, TSH, and serum hCG to rule out anemia, thyroid dysfunction, pregnancy.  \n   - Schedule pelvic ultrasound to evaluate for structural abnormalities.  \n   - Endometrial biopsy deferred pending ultrasound results (incomplete risk stratification).  \n2. *Symptomatic management:*  \n   - Trial of tranexamic acid for heavy bleeding (no contraindications reviewed).  \n   - Consider progesterone therapy if bleeding persists (not discussed in detail).  \n3. *Follow-up:*  \n   - Return in 4 weeks for results and reassessment. Counseled to seek care sooner if bleeding worsens (e.g., syncope, severe anemia).  \n\n*Omissions:*  \n- No discussion of lifestyle impact (e.g., work limitations).  \n- Contraceptive needs/preferences not addressed.  \n- Family planning goals not explored.  \n\n**Impression:**  \nInitial evaluation incomplete but initiated workup for AUB. Patient advised to monitor symptoms.  \n\n*--End of Dictation--*  \n\n**Note for Testing:** This fictional scenario includes intentional gaps in history/exam and management decisions for educational purposes only. No real clinical guidance is implied.\n\n--- Token Usage Report ---\nPrompt tokens: 158\nCompletion tokens: 684\nTotal tokens: 842\nEstimated cost: $0.000421",
  "ai_provider": "DeepSeek",
  "ai_model": "deepseek-chat",
  "token_usage": {
    "prompt_tokens": 158,
    "completion_tokens": 684,
    "total_tokens": 842,
    "estimated_cost_usd": 0.00042100000000000004
  }
}