{
  "prompt": {
    "prompt": "Create a fictional dictation of a clinical interaction between a healthcare professional and a patient. \nThis dictation is for testing purposes only and should include various topics that might be discussed in a healthcare setting. \nPlease ensure the material is entirely fictional and does not provide any real medical advice or information. \nPlease ensure variables such as age, weight and history are varied.\nThe clinician should ensure the history and examination findings are incomplete, leaving out some pertinent questions.\nIn response to their history and examination findings, the clinician should  provide management advice and guidance.\nThe clinical scenario should be the following: \n\nMake the age 36, the BMI 18.9 and the number of prior pregnancies 1\n\nBase the clinical scenario on the following gynecology issue: Abnormal uterine bleeding",
    "system_prompt": "Create a fictional dictation of a clinical interaction between a healthcare professional and a patient. \nThis dictation is for testing purposes only and should include various topics that might be discussed in a healthcare setting. \nPlease ensure the material is entirely fictional and does not provide any real medical advice or information. \nPlease ensure variables such as age, weight and history are varied.\nThe clinician should ensure the history and examination findings are incomplete, leaving out some pertinent questions.\nIn response to their history and examination findings, the clinician should  provide management advice and guidance.\nThe clinical scenario should be the following: \n\nMake the age 36, the BMI 18.9 and the number of prior pregnancies 1\n\nBase the clinical scenario on the following gynecology issue: Abnormal uterine bleeding"
  },
  "response": "**Dictation: Clinical Interaction – Abnormal Uterine Bleeding**  \n\n**Patient Details:**  \n- Name: [Fictional Name] Jane Doe  \n- Age: 36  \n- BMI: 18.9 (weight 52 kg, height 1.65 m)  \n- Gravida: 1, Para: 1 (prior full-term vaginal delivery)  \n- Last Menstrual Period (LMP): 2 weeks ago (currently mid-cycle)  \n- Contraception: None currently  \n\n**History of Presenting Complaint:**  \nMs. Doe presents with a 4-month history of irregular menstrual bleeding. She reports episodes of heavy bleeding lasting 7–10 days, occurring every 2–3 weeks, with associated fatigue. She denies intermenstrual spotting but admits to occasional cramping. No history of post-coital bleeding. She has not been sexually active in the past year.  \n\n**Relevant Medical History:**  \n- No known bleeding disorders or thyroid dysfunction.  \n- No prior gynecological procedures (e.g., hysteroscopy, D&C).  \n- No history of fibroids or endometriosis.  \n- No chronic medical conditions.  \n\n**Medications & Allergies:**  \n- Occasional ibuprofen for cramps (no regular medications).  \n- No known drug allergies.  \n\n**Social History:**  \n- Non-smoker, occasional alcohol (1–2 units/week).  \n- Works as a teacher; moderate stress levels reported.  \n\n**Examination Findings:**  \n- General appearance: Pale conjunctivae (possible anemia).  \n- Abdomen: Soft, non-tender, no palpable masses.  \n- Speculum exam: Cervix appears normal, no visible lesions.  \n- Bimanual exam: Uterus anteverted, normal size, no adnexal tenderness.  \n\n**Notable Omissions (for testing purposes):**  \n- No documented assessment of iron studies or hemoglobin.  \n- No inquiry about family history of gynecological malignancies.  \n- No discussion of prior Pap smear history or HPV vaccination status.  \n- Pelvic ultrasound not yet performed.  \n\n**Impression:**  \nAbnormal uterine bleeding (AUB) in a premenopausal patient—differential includes ovulatory dysfunction (e.g., PCOS, thyroid disorder), endometrial polyp, or early perimenopausal changes.  \n\n**Management Plan:**  \n1. **Investigations:**  \n   - Full blood count (FBC) to assess for anemia.  \n   - TSH and prolactin to evaluate endocrine causes.  \n   - Pelvic ultrasound to rule out structural pathology.  \n   - (No endometrial biopsy arranged at this stage.)  \n\n2. **Symptomatic Relief:**  \n   - Trial of tranexamic acid during heavy bleeding.  \n   - Consider combined oral contraceptive pill (COCP) for cycle regulation if no contraindications.  \n\n3. **Follow-Up:**  \n   - Review in 6 weeks with investigation results.  \n   - If bleeding worsens or anemia confirmed, escalate to gynecology referral.  \n\n**Counseling Provided:**  \n- Reassured that AUB is common but requires evaluation.  \n- Advised to monitor bleeding patterns and report syncope or severe fatigue.  \n\n**Dictated by:** Dr. [Fictional Name] Smith  \n**Date:** [Fictional Date]  \n\n---  \n*Note: This is a fictional dictation for testing purposes only. No real patient data or medical advice is contained herein.*",
  "endpoint": "generateFakeClinicalInteraction",
  "timestamp": "2025-05-27T14-26-48",
  "textContent": "AI: DeepSeek (deepseek-chat)\n\nQ: {\n  \"prompt\": \"Create a fictional dictation of a clinical interaction between a healthcare professional and a patient. \\nThis dictation is for testing purposes only and should include various topics that might be discussed in a healthcare setting. \\nPlease ensure the material is entirely fictional and does not provide any real medical advice or information. \\nPlease ensure variables such as age, weight and history are varied.\\nThe clinician should ensure the history and examination findings are incomplete, leaving out some pertinent questions.\\nIn response to their history and examination findings, the clinician should  provide management advice and guidance.\\nThe clinical scenario should be the following: \\n\\nMake the age 36, the BMI 18.9 and the number of prior pregnancies 1\\n\\nBase the clinical scenario on the following gynecology issue: Abnormal uterine bleeding\",\n  \"system_prompt\": \"Create a fictional dictation of a clinical interaction between a healthcare professional and a patient. \\nThis dictation is for testing purposes only and should include various topics that might be discussed in a healthcare setting. \\nPlease ensure the material is entirely fictional and does not provide any real medical advice or information. \\nPlease ensure variables such as age, weight and history are varied.\\nThe clinician should ensure the history and examination findings are incomplete, leaving out some pertinent questions.\\nIn response to their history and examination findings, the clinician should  provide management advice and guidance.\\nThe clinical scenario should be the following: \\n\\nMake the age 36, the BMI 18.9 and the number of prior pregnancies 1\\n\\nBase the clinical scenario on the following gynecology issue: Abnormal uterine bleeding\"\n}\n\nA: **Dictation: Clinical Interaction – Abnormal Uterine Bleeding**  \n\n**Patient Details:**  \n- Name: [Fictional Name] Jane Doe  \n- Age: 36  \n- BMI: 18.9 (weight 52 kg, height 1.65 m)  \n- Gravida: 1, Para: 1 (prior full-term vaginal delivery)  \n- Last Menstrual Period (LMP): 2 weeks ago (currently mid-cycle)  \n- Contraception: None currently  \n\n**History of Presenting Complaint:**  \nMs. Doe presents with a 4-month history of irregular menstrual bleeding. She reports episodes of heavy bleeding lasting 7–10 days, occurring every 2–3 weeks, with associated fatigue. She denies intermenstrual spotting but admits to occasional cramping. No history of post-coital bleeding. She has not been sexually active in the past year.  \n\n**Relevant Medical History:**  \n- No known bleeding disorders or thyroid dysfunction.  \n- No prior gynecological procedures (e.g., hysteroscopy, D&C).  \n- No history of fibroids or endometriosis.  \n- No chronic medical conditions.  \n\n**Medications & Allergies:**  \n- Occasional ibuprofen for cramps (no regular medications).  \n- No known drug allergies.  \n\n**Social History:**  \n- Non-smoker, occasional alcohol (1–2 units/week).  \n- Works as a teacher; moderate stress levels reported.  \n\n**Examination Findings:**  \n- General appearance: Pale conjunctivae (possible anemia).  \n- Abdomen: Soft, non-tender, no palpable masses.  \n- Speculum exam: Cervix appears normal, no visible lesions.  \n- Bimanual exam: Uterus anteverted, normal size, no adnexal tenderness.  \n\n**Notable Omissions (for testing purposes):**  \n- No documented assessment of iron studies or hemoglobin.  \n- No inquiry about family history of gynecological malignancies.  \n- No discussion of prior Pap smear history or HPV vaccination status.  \n- Pelvic ultrasound not yet performed.  \n\n**Impression:**  \nAbnormal uterine bleeding (AUB) in a premenopausal patient—differential includes ovulatory dysfunction (e.g., PCOS, thyroid disorder), endometrial polyp, or early perimenopausal changes.  \n\n**Management Plan:**  \n1. **Investigations:**  \n   - Full blood count (FBC) to assess for anemia.  \n   - TSH and prolactin to evaluate endocrine causes.  \n   - Pelvic ultrasound to rule out structural pathology.  \n   - (No endometrial biopsy arranged at this stage.)  \n\n2. **Symptomatic Relief:**  \n   - Trial of tranexamic acid during heavy bleeding.  \n   - Consider combined oral contraceptive pill (COCP) for cycle regulation if no contraindications.  \n\n3. **Follow-Up:**  \n   - Review in 6 weeks with investigation results.  \n   - If bleeding worsens or anemia confirmed, escalate to gynecology referral.  \n\n**Counseling Provided:**  \n- Reassured that AUB is common but requires evaluation.  \n- Advised to monitor bleeding patterns and report syncope or severe fatigue.  \n\n**Dictated by:** Dr. [Fictional Name] Smith  \n**Date:** [Fictional Date]  \n\n---  \n*Note: This is a fictional dictation for testing purposes only. No real patient data or medical advice is contained herein.*\n\n--- Token Usage Report ---\nPrompt tokens: 158\nCompletion tokens: 704\nTotal tokens: 862\nEstimated cost: $0.000431",
  "ai_provider": "DeepSeek",
  "ai_model": "deepseek-chat",
  "token_usage": {
    "prompt_tokens": 158,
    "completion_tokens": 704,
    "total_tokens": 862,
    "estimated_cost_usd": 0.00043099999999999996
  }
}