{
  "prompt": {
    "prompt": "Create a fictional dictation of a clinical interaction between a healthcare professional and a patient. \nThis dictation is for testing purposes only and should include various topics that might be discussed in a healthcare setting. \nPlease ensure the material is entirely fictional and does not provide any real medical advice or information. \nPlease ensure variables such as age, weight and history are varied.\nThe clinician should ensure the history and examination findings are incomplete, leaving out some pertinent questions.\nIn response to their history and examination findings, the clinician should  provide management advice and guidance.\nThe clinical scenario should be the following:  \n            \nThe clinical scenario should focus on a patient with Abnormal uterine bleeding.",
    "system_prompt": "Create a fictional dictation of a clinical interaction between a healthcare professional and a patient. \nThis dictation is for testing purposes only and should include various topics that might be discussed in a healthcare setting. \nPlease ensure the material is entirely fictional and does not provide any real medical advice or information. \nPlease ensure variables such as age, weight and history are varied.\nThe clinician should ensure the history and examination findings are incomplete, leaving out some pertinent questions.\nIn response to their history and examination findings, the clinician should  provide management advice and guidance.\nThe clinical scenario should be the following:  \n            \nThe clinical scenario should focus on a patient with Abnormal uterine bleeding."
  },
  "response": "**Fictional Clinical Dictation: Abnormal Uterine Bleeding**  \n\n**Patient Name:** Jane Doe  \n**Age:** 42 years  \n**Gender:** Female  \n**Date of Visit:** October 10, 2023  \n**Clinician:** Dr. Smith, OB/GYN  \n\n**Subjective:**  \nMs. Doe presents today reporting abnormal uterine bleeding for the past 3 months. She describes her periods as heavy, lasting 7–10 days, with frequent passage of large clots. She reports intermenstrual spotting but denies postcoital bleeding. She has no associated pelvic pain or dyspareunia.  \n\nShe has a history of obesity (BMI 32), hypertension (on lisinopril), and a remote history of iron deficiency anemia. She is gravida 3, para 3, with all deliveries via cesarean section. She denies any personal or family history of bleeding disorders or gynecologic malignancies. She is sexually active with one partner and uses condoms inconsistently for contraception.  \n\n*[Missing Pertinent Questions:]*  \n- Last menstrual period (LMP) not documented.  \n- No inquiry about weight changes, fatigue, or symptoms of hypothyroidism/hyperthyroidism.  \n- No detailed family history of fibroids, endometriosis, or coagulopathies.  \n- No assessment of NSAID or anticoagulant use.  \n\n**Objective:**  \n- **Vitals:** BP 138/86, HR 78, BMI 32.  \n- **General:** Well-appearing, no pallor.  \n- **Abdominal Exam:** Soft, non-tender, obese, no palpable masses.  \n- **Pelvic Exam:** Cervix appears normal, no active bleeding at time of exam. Uterus slightly enlarged, mobile, non-tender. Adnexa without masses.  \n- *[Missing Exam Components:]*  \n  - No speculum exam documented.  \n  - No bimanual exam findings on uterine size consistency (e.g., fibroids).  \n  - No assessment for cervical motion tenderness.  \n\n**Assessment:**  \n42-year-old female with abnormal uterine bleeding, likely secondary to perimenopausal hormonal changes or structural etiology (e.g., fibroids). Differential includes endometrial hyperplasia, coagulopathy (less likely given history), or anovulatory bleeding.  \n\n*[Missing Considerations:]*  \n- No transvaginal ultrasound ordered to assess endometrial thickness or fibroids.  \n- No labs (CBC, TSH, coagulation studies) performed to evaluate anemia or underlying disorders.  \n\n**Plan:**  \n1. **Initial Management:**  \n   - Start empiric progesterone therapy (medroxyprogesterone acetate 10 mg daily for 10 days) to regulate bleeding.  \n   - Recommend iron supplementation given likely menorrhagia-related anemia (ferrous sulfate 325 mg daily).  \n   - Advise NSAIDs (e.g., ibuprofen) during heavy bleeding for symptom relief.  \n\n2. **Follow-Up:**  \n   - Return in 4 weeks for reassessment. If bleeding persists or worsens, will proceed with pelvic ultrasound and endometrial biopsy.  \n   - Counsel on importance of tracking bleeding patterns and symptoms.  \n\n3. **Contingencies:**  \n   - If hemodynamically unstable (e.g., syncope, severe fatigue), proceed to ER for further evaluation.  \n\n*[Missing Guidance:]*  \n- No discussion of long-term contraception needs.  \n- No counseling on weight management’s role in hormonal regulation.  \n\n**Impression:** Abnormal uterine bleeding, etiology unclear. Initial conservative management with close follow-up.  \n\n---  \n*This dictation is entirely fictional for testing purposes only. No real medical advice is implied or provided.*",
  "endpoint": "generateFakeClinicalInteraction",
  "timestamp": "2025-05-26T16-25-09",
  "textContent": "AI: DeepSeek (deepseek-chat)\n\nQ: {\n  \"prompt\": \"Create a fictional dictation of a clinical interaction between a healthcare professional and a patient. \\nThis dictation is for testing purposes only and should include various topics that might be discussed in a healthcare setting. \\nPlease ensure the material is entirely fictional and does not provide any real medical advice or information. \\nPlease ensure variables such as age, weight and history are varied.\\nThe clinician should ensure the history and examination findings are incomplete, leaving out some pertinent questions.\\nIn response to their history and examination findings, the clinician should  provide management advice and guidance.\\nThe clinical scenario should be the following:  \\n            \\nThe clinical scenario should focus on a patient with Abnormal uterine bleeding.\",\n  \"system_prompt\": \"Create a fictional dictation of a clinical interaction between a healthcare professional and a patient. \\nThis dictation is for testing purposes only and should include various topics that might be discussed in a healthcare setting. \\nPlease ensure the material is entirely fictional and does not provide any real medical advice or information. \\nPlease ensure variables such as age, weight and history are varied.\\nThe clinician should ensure the history and examination findings are incomplete, leaving out some pertinent questions.\\nIn response to their history and examination findings, the clinician should  provide management advice and guidance.\\nThe clinical scenario should be the following:  \\n            \\nThe clinical scenario should focus on a patient with Abnormal uterine bleeding.\"\n}\n\nA: **Fictional Clinical Dictation: Abnormal Uterine Bleeding**  \n\n**Patient Name:** Jane Doe  \n**Age:** 42 years  \n**Gender:** Female  \n**Date of Visit:** October 10, 2023  \n**Clinician:** Dr. Smith, OB/GYN  \n\n**Subjective:**  \nMs. Doe presents today reporting abnormal uterine bleeding for the past 3 months. She describes her periods as heavy, lasting 7–10 days, with frequent passage of large clots. She reports intermenstrual spotting but denies postcoital bleeding. She has no associated pelvic pain or dyspareunia.  \n\nShe has a history of obesity (BMI 32), hypertension (on lisinopril), and a remote history of iron deficiency anemia. She is gravida 3, para 3, with all deliveries via cesarean section. She denies any personal or family history of bleeding disorders or gynecologic malignancies. She is sexually active with one partner and uses condoms inconsistently for contraception.  \n\n*[Missing Pertinent Questions:]*  \n- Last menstrual period (LMP) not documented.  \n- No inquiry about weight changes, fatigue, or symptoms of hypothyroidism/hyperthyroidism.  \n- No detailed family history of fibroids, endometriosis, or coagulopathies.  \n- No assessment of NSAID or anticoagulant use.  \n\n**Objective:**  \n- **Vitals:** BP 138/86, HR 78, BMI 32.  \n- **General:** Well-appearing, no pallor.  \n- **Abdominal Exam:** Soft, non-tender, obese, no palpable masses.  \n- **Pelvic Exam:** Cervix appears normal, no active bleeding at time of exam. Uterus slightly enlarged, mobile, non-tender. Adnexa without masses.  \n- *[Missing Exam Components:]*  \n  - No speculum exam documented.  \n  - No bimanual exam findings on uterine size consistency (e.g., fibroids).  \n  - No assessment for cervical motion tenderness.  \n\n**Assessment:**  \n42-year-old female with abnormal uterine bleeding, likely secondary to perimenopausal hormonal changes or structural etiology (e.g., fibroids). Differential includes endometrial hyperplasia, coagulopathy (less likely given history), or anovulatory bleeding.  \n\n*[Missing Considerations:]*  \n- No transvaginal ultrasound ordered to assess endometrial thickness or fibroids.  \n- No labs (CBC, TSH, coagulation studies) performed to evaluate anemia or underlying disorders.  \n\n**Plan:**  \n1. **Initial Management:**  \n   - Start empiric progesterone therapy (medroxyprogesterone acetate 10 mg daily for 10 days) to regulate bleeding.  \n   - Recommend iron supplementation given likely menorrhagia-related anemia (ferrous sulfate 325 mg daily).  \n   - Advise NSAIDs (e.g., ibuprofen) during heavy bleeding for symptom relief.  \n\n2. **Follow-Up:**  \n   - Return in 4 weeks for reassessment. If bleeding persists or worsens, will proceed with pelvic ultrasound and endometrial biopsy.  \n   - Counsel on importance of tracking bleeding patterns and symptoms.  \n\n3. **Contingencies:**  \n   - If hemodynamically unstable (e.g., syncope, severe fatigue), proceed to ER for further evaluation.  \n\n*[Missing Guidance:]*  \n- No discussion of long-term contraception needs.  \n- No counseling on weight management’s role in hormonal regulation.  \n\n**Impression:** Abnormal uterine bleeding, etiology unclear. Initial conservative management with close follow-up.  \n\n---  \n*This dictation is entirely fictional for testing purposes only. No real medical advice is implied or provided.*\n\n--- Token Usage Report ---\nPrompt tokens: 136\nCompletion tokens: 754\nTotal tokens: 890\nEstimated cost: $0.000445",
  "ai_provider": "DeepSeek",
  "ai_model": "deepseek-chat",
  "token_usage": {
    "prompt_tokens": 136,
    "completion_tokens": 754,
    "total_tokens": 890,
    "estimated_cost_usd": 0.00044500000000000003
  }
}