{
  "prompt": {
    "prompt": "Please analyze the clinical note against the provided guideline and suggest improvements to better align with the guideline recommendations.\n\nFor each recommendation, specify:\n1. The type of recommendation:\n   - Additional information needed (history/examination/investigations)\n   - Improved patient advice (options/statistics/patient information)\n   - Different management plan\n2. The specific recommendation\n3. The reason for the recommendation (referencing the guideline)\n\nCategorize each recommendation by importance:\n- Very Important: Critical for patient safety or guideline compliance\n- Somewhat Important: Significant for optimal care but not critical\n- Less Important: Would improve care but not essential\n- Unimportant: Minor suggestions that could be considered\n\nFormat the response as follows:\n\n### Very Important Recommendations\n[Type] - [Specific recommendation]\nReason: [Reference to guideline ID and relevant section]\n\n### Somewhat Important Recommendations\n[Type] - [Specific recommendation]\nReason: [Reference to guideline ID and relevant section]\n\n### Less Important Recommendations\n[Type] - [Specific recommendation]\nReason: [Reference to guideline ID and relevant section]\n\n### Unimportant Recommendations\n[Type] - [Specific recommendation]\nReason: [Reference to guideline ID and relevant section]\n\nClinical Note:\nSITUATION: 30-year-old G1P0 with dichorionic diamniotic twin pregnancy at 32+2 weeks presenting with preterm labor and growth discordance\n\nBACKGROUND: Mrs Liu conceived via IVF after 2 years of unexplained infertility, single embryo transfer resulted in spontaneous splitting to monozygotic twins. Pregnancy has been closely monitored with fortnightly scans. Recent growth scans show developing growth discordance between twins - Twin A estimated 1.8kg (50th centile), Twin B estimated 1.4kg (10th centile), representing 22% weight difference. She presented today with regular uterine contractions every 4-5 minutes for past 3 hours, accompanied by lower back ache and pelvic pressure. No bleeding, no rupture of membranes, both babies moving well. Previous antenatal care has been uncomplicated apart from gestational diabetes diagnosed at 26 weeks, well controlled with diet. She works as a teacher, supportive partner, anxious about early delivery.\n\nASSESSMENT: Maternal vital signs stable: BP 132/84 mmHg, HR 92 bpm, temp 36.8Â°C. Abdomen shows regular contractions palpable every 4-5 minutes, both twins in longitudinal lie, Twin A cephalic presentation, Twin B breech. CTG monitoring shows both twins with reassuring patterns - Twin A baseline 140 bpm, Twin B baseline 155 bpm, both with good variability. Cervical assessment reveals 3cm dilatation, 60% effacement, soft consistency. Ultrasound confirms presentations and estimated fetal weights as above. Twin-to-twin transfusion syndrome excluded - both twins have adequate liquor volume. Bloods normal including FBC and inflammatory markers.\n\nRECOMMENDATION: Preterm labor in twin pregnancy with growth discordance requiring immediate management. Tocolysis with nifedipine commenced to delay delivery. Antenatal corticosteroids (betamethasone) administered for fetal lung maturation. Magnesium sulfate given for neuroprotection. Pediatric team alerted for twin delivery. Anesthetic consultation for potential operative delivery. Given growth discordance, immediate delivery not indicated unless fetal compromise develops. Plan for cesarean section if further cervical change or if Twin B becomes compromised. Continuous monitoring of both twins. Growth discordance investigation post-delivery to exclude underlying causes.\n\nGuideline:\n[ID] bjog-2022-stock-antenatal-corticosteroids-to-reduce-neonatal-morbidity-and-mortality-pdf\nTitle: BJOG - 2022 - Stock - Antenatal corticosteroids to reduce neonatal morbidity and mortality.pdf\nContent: Antenatal corticosteroids given within seven days prior to preterm birth reduce perinatal and neonatal death and respiratory distress syndrome. For women undergoing planned caesarean birth between 37+0 and 38+6 weeks, an informed discussion should take place about the potential risks and benefits of corticosteroids. Corticosteroids should be offered to women between 24+0 and 34+6 weeks' gestation in whom imminent preterm birth is anticipated. Women with twins and triplets should also be offered corticosteroids. Birth should not be delayed for corticosteroids if it impacts the health of the woman or baby. Antenatal corticosteroids should be offered to women with preterm prelabour rupture of membranes. Corticosteroids reduce neonatal death when given within 48 hours prior to birth, and benefits are still seen if given within 24 hours of birth.\n\nAntenatal corticosteroids should be considered for women at risk of preterm birth between 35+0 to 36+6 weeks gestation. Steroids have short-term respiratory benefits for the neonate but may increase the risk of neonatal hypoglycemia. The use of corticosteroids in late preterm birth should be carefully weighed for its risks and benefits. In multiple pregnancies, targeted corticosteroids for early birth should be considered, as there is little evidence of benefit in twins compared to singletons. Women with diabetes should not be excluded from receiving corticosteroids, but additional insulin and close monitoring are recommended. Antenatal corticosteroids should not delay birth if it is necessary for the health of the woman or baby. In pregnancies complicated by fetal growth restriction, pre-eclampsia, or antepartum hemorrhage, corticosteroids may be considered if imminent preterm birth is likely. Women should be informed about the lack of evidence for the use of corticosteroids in small-for-gestational-age babies.\n\nAntenatal corticosteroids should be offered to women with PPROM who are at increased risk of preterm birth. There is limited evidence to recommend repeat courses of antenatal corticosteroids if a woman remains at imminent risk of preterm birth seven days after administration. The optimum dose and route of administration for a course of antenatal corticosteroids recommend 24mg dexamethasone phosphate or 24 mg betamethasone sodium phosphate/acetate mix given intramuscularly. Antenatal corticosteroids are most effective when given within 48 hours prior to birth, with benefits seen within 24 hours of birth. They are most effective in reducing RDS in pregnancies that birth between 24 hours and 7 days of administration of the second dose.\n\nAntenatal corticosteroids have shown significant reductions in cases of RDS and cerebroventricular hemorrhage among infants born within specific time frames after administration. There is a reduction in fetal and neonatal death for births within 24 hours to seven days after administration. However, caution is advised in interpreting the data due to limitations in subgroup analyses. Population-based cohort studies support the early effects of antenatal corticosteroids, with the largest effect seen 24 hours to seven days after the first injection. Concerns about potential risks to both women and babies include effects on maternal blood glucose levels, fetal growth, neonatal hypoglycemia, long-term metabolic and neurological consequences, and potential impacts on brain development. WHO recommends offering antenatal corticosteroids only when minimum standards of maternal and neonatal hospital services are available.\n\nAntenatal corticosteroids should not be delayed in serious maternal or fetal conditions. In the presence of systemic infection, the use of corticosteroids should be carefully balanced due to the risk of exacerbating the infection. Repeat courses of corticosteroids may not reduce serious morbidity but can lead to smaller babies. The maximum number of corticosteroid courses in pregnancy should not exceed three. Research is needed to determine the effectiveness of corticosteroids in various conditions and to investigate potential off-target effects. Recommendations for future research include determining the effectiveness of corticosteroids in reducing neonatal morbidity in elective caesarean births at term and investigating the safety and effectiveness of steroids in multiple pregnancies and women with diabetes. Auditable topics include discussions about corticosteroids in planned caesarean births and the proportion of women offered corticosteroids for preterm birth. Support groups and useful links are provided for further information.\n\nAntenatal corticosteroids for reducing adverse maternal and child outcomes in special populations of women at risk of imminent preterm birth: a systematic review and meta-analysis. Managing hyperglycaemia during antenatal steroid administration, labour, and birth in pregnant women with diabetes. Should antenatal corticosteroids be considered in women with gestational diabetes before planned late gestation caesarean section. Effects of antenatal corticosteroid administration on mortality and long-term morbidity in early preterm, growth-restricted infants. Antenatal corticosteroids in preterm small-for-gestational age infants: a systematic review and meta-analysis. Use of antenatal corticosteroids in special circumstances: a comprehensive review. Single versus weekly courses of antenatal corticosteroids in preterm premature rupture of membranes. Multiple courses of antenatal corticosteroid therapy in patients with preterm premature rupture of membranes. Neonatal sepsis after betamethasone administration to patients with preterm premature rupture of membranes. Length of latency with preterm premature rupture of membranes before 32 weeks' gestation. Duration of the latency period in preterm premature rupture of the membranes. Preterm premature rupture of the membranes. Length of latency with preterm premature rupture of membranes. Association of fetal growth restriction with neurocognitive function after repeated antenatal betamethasone treatment vs placebo. Antenatal corticosteroids for preterm premature rupture of membranes: single or repeat course. The clinical use of corticosteroids in pregnancy. Antenatal corticosteroids: an assessment of anticipated benefits and potential risks. Antenatal corticosteroids for accelerating fetal lung maturation for women at risk of preterm birth. Maternal intramuscular dexamethasone versus betamethasone before preterm birth. Transplacental versus direct fetal corticosteroid treatment for accelerating fetal lung maturation where there is a risk of preterm birth. Antenatal dexamethasone for early preterm birth in low-resource countries. Antenatal corticosteroid therapy for prevention of respiratory distress syndrome in severe preeclampsia. Antenatal corticosteroid therapy and blood pressure at 14 years of age in preterm children. Neurodevelopmental disorders among term infants exposed to antenatal corticosteroids during pregnancy. Impact of antenatal synthetic glucocorticoid exposure on endocrine stress reactivity in term-born children. Persistent effects of antenatal synthetic glucocorticoids on endocrine stress reactivity from childhood to adolescence. Long-term impacts of prenatal synthetic glucocorticoids exposure on functional brain correlates of cognitive monitoring in adolescence. Prenatal betamethasone exposure and psychopathology risk in extremely low birth weight survivors in the third and fourth decades of life. A population-based, multifaceted strategy to implement antenatal corticosteroid treatment versus standard care for the reduction of neonatal mortality due to preterm birth in low-income and middle-income countries.",
    "system_prompt": "You are a medical guidelines compliance checker. Your task is to analyze if the given clinical note follows the specified guideline and suggest improvements.",
    "guideline_id": "bjog-2022-stock-antenatal-corticosteroids-to-reduce-neonatal-morbidity-and-mortality-pdf",
    "guideline_title": "BJOG - 2022 - Stock - Antenatal corticosteroids to reduce neonatal morbidity and mortality.pdf"
  },
  "response": "Here is the analysis of the clinical note against the provided guideline, with recommendations for improvement:\n\n### Very Important Recommendations  \n1. **Additional information needed** - Document the timing of betamethasone administration relative to anticipated delivery.  \n   Reason: The guideline states corticosteroids are most effective when given within 48 hours prior to birth, with benefits seen within 24 hours (BJOG-2022-Stock guideline, \"Antenatal corticosteroids are most effective when given within 48 hours prior to birth\"). The note should clarify whether delivery is expected within this window.  \n\n2. **Improved patient advice** - Discuss the risks/benefits of corticosteroids with the patient, including potential neonatal hypoglycemia (given her gestational diabetes).  \n   Reason: The guideline emphasizes informed discussions, especially in diabetic patients, and highlights the risk of neonatal hypoglycemia (BJOG-2022-Stock, \"Women with diabetes should not be excluded... but additional insulin and close monitoring are recommended\").  \n\n### Somewhat Important Recommendations  \n1. **Different management plan** - Consider repeating corticosteroids if delivery does not occur within 7 days and she remains at risk.  \n   Reason: The guideline notes limited evidence for repeat courses but suggests consideration if the risk persists (BJOG-2022-Stock, \"limited evidence to recommend repeat courses... if a woman remains at imminent risk seven days after administration\").  \n\n2. **Additional information needed** - Monitor maternal blood glucose closely post-corticosteroids due to gestational diabetes.  \n   Reason: The guideline recommends additional monitoring for diabetic patients (BJOG-2022-Stock, \"additional insulin and close monitoring are recommended\").  \n\n### Less Important Recommendations  \n1. **Improved patient advice** - Provide resources/support groups for preterm birth anxiety.  \n   Reason: The guideline mentions support groups as part of holistic care (BJOG-2022-Stock, \"Support groups and useful links are provided\").  \n\n### Unimportant Recommendations  \n1. **Additional information needed** - Document the specific betamethasone formulation used (sodium phosphate/acetate mix).  \n   Reason: The guideline specifies preferred formulations but does not mandate documentation (BJOG-2022-Stock, \"24 mg betamethasone sodium phosphate/acetate mix\").  \n\n### Key Omissions Addressed:  \n- The note aligns well with the guidelineâs core recommendations (e.g., offering corticosteroids for twins at 32+2 weeks, not delaying delivery for steroids). However, explicit documentation of timing, diabetic monitoring, and patient counseling would strengthen compliance.  \n\n*Note: No critical deviations from the guideline were identified.*",
  "endpoint": "analyzeNoteAgainstGuideline",
  "timestamp": "2025-06-26T10-34-48",
  "textContent": "AI: DeepSeek (deepseek-chat)\n\nQ: {\n  \"prompt\": \"Please analyze the clinical note against the provided guideline and suggest improvements to better align with the guideline recommendations.\\n\\nFor each recommendation, specify:\\n1. The type of recommendation:\\n   - Additional information needed (history/examination/investigations)\\n   - Improved patient advice (options/statistics/patient information)\\n   - Different management plan\\n2. The specific recommendation\\n3. The reason for the recommendation (referencing the guideline)\\n\\nCategorize each recommendation by importance:\\n- Very Important: Critical for patient safety or guideline compliance\\n- Somewhat Important: Significant for optimal care but not critical\\n- Less Important: Would improve care but not essential\\n- Unimportant: Minor suggestions that could be considered\\n\\nFormat the response as follows:\\n\\n### Very Important Recommendations\\n[Type] - [Specific recommendation]\\nReason: [Reference to guideline ID and relevant section]\\n\\n### Somewhat Important Recommendations\\n[Type] - [Specific recommendation]\\nReason: [Reference to guideline ID and relevant section]\\n\\n### Less Important Recommendations\\n[Type] - [Specific recommendation]\\nReason: [Reference to guideline ID and relevant section]\\n\\n### Unimportant Recommendations\\n[Type] - [Specific recommendation]\\nReason: [Reference to guideline ID and relevant section]\\n\\nClinical Note:\\nSITUATION: 30-year-old G1P0 with dichorionic diamniotic twin pregnancy at 32+2 weeks presenting with preterm labor and growth discordance\\n\\nBACKGROUND: Mrs Liu conceived via IVF after 2 years of unexplained infertility, single embryo transfer resulted in spontaneous splitting to monozygotic twins. Pregnancy has been closely monitored with fortnightly scans. Recent growth scans show developing growth discordance between twins - Twin A estimated 1.8kg (50th centile), Twin B estimated 1.4kg (10th centile), representing 22% weight difference. She presented today with regular uterine contractions every 4-5 minutes for past 3 hours, accompanied by lower back ache and pelvic pressure. No bleeding, no rupture of membranes, both babies moving well. Previous antenatal care has been uncomplicated apart from gestational diabetes diagnosed at 26 weeks, well controlled with diet. She works as a teacher, supportive partner, anxious about early delivery.\\n\\nASSESSMENT: Maternal vital signs stable: BP 132/84 mmHg, HR 92 bpm, temp 36.8Â°C. Abdomen shows regular contractions palpable every 4-5 minutes, both twins in longitudinal lie, Twin A cephalic presentation, Twin B breech. CTG monitoring shows both twins with reassuring patterns - Twin A baseline 140 bpm, Twin B baseline 155 bpm, both with good variability. Cervical assessment reveals 3cm dilatation, 60% effacement, soft consistency. Ultrasound confirms presentations and estimated fetal weights as above. Twin-to-twin transfusion syndrome excluded - both twins have adequate liquor volume. Bloods normal including FBC and inflammatory markers.\\n\\nRECOMMENDATION: Preterm labor in twin pregnancy with growth discordance requiring immediate management. Tocolysis with nifedipine commenced to delay delivery. Antenatal corticosteroids (betamethasone) administered for fetal lung maturation. Magnesium sulfate given for neuroprotection. Pediatric team alerted for twin delivery. Anesthetic consultation for potential operative delivery. Given growth discordance, immediate delivery not indicated unless fetal compromise develops. Plan for cesarean section if further cervical change or if Twin B becomes compromised. Continuous monitoring of both twins. Growth discordance investigation post-delivery to exclude underlying causes.\\n\\nGuideline:\\n[ID] bjog-2022-stock-antenatal-corticosteroids-to-reduce-neonatal-morbidity-and-mortality-pdf\\nTitle: BJOG - 2022 - Stock - Antenatal corticosteroids to reduce neonatal morbidity and mortality.pdf\\nContent: Antenatal corticosteroids given within seven days prior to preterm birth reduce perinatal and neonatal death and respiratory distress syndrome. For women undergoing planned caesarean birth between 37+0 and 38+6 weeks, an informed discussion should take place about the potential risks and benefits of corticosteroids. Corticosteroids should be offered to women between 24+0 and 34+6 weeks' gestation in whom imminent preterm birth is anticipated. Women with twins and triplets should also be offered corticosteroids. Birth should not be delayed for corticosteroids if it impacts the health of the woman or baby. Antenatal corticosteroids should be offered to women with preterm prelabour rupture of membranes. Corticosteroids reduce neonatal death when given within 48 hours prior to birth, and benefits are still seen if given within 24 hours of birth.\\n\\nAntenatal corticosteroids should be considered for women at risk of preterm birth between 35+0 to 36+6 weeks gestation. Steroids have short-term respiratory benefits for the neonate but may increase the risk of neonatal hypoglycemia. The use of corticosteroids in late preterm birth should be carefully weighed for its risks and benefits. In multiple pregnancies, targeted corticosteroids for early birth should be considered, as there is little evidence of benefit in twins compared to singletons. Women with diabetes should not be excluded from receiving corticosteroids, but additional insulin and close monitoring are recommended. Antenatal corticosteroids should not delay birth if it is necessary for the health of the woman or baby. In pregnancies complicated by fetal growth restriction, pre-eclampsia, or antepartum hemorrhage, corticosteroids may be considered if imminent preterm birth is likely. Women should be informed about the lack of evidence for the use of corticosteroids in small-for-gestational-age babies.\\n\\nAntenatal corticosteroids should be offered to women with PPROM who are at increased risk of preterm birth. There is limited evidence to recommend repeat courses of antenatal corticosteroids if a woman remains at imminent risk of preterm birth seven days after administration. The optimum dose and route of administration for a course of antenatal corticosteroids recommend 24mg dexamethasone phosphate or 24 mg betamethasone sodium phosphate/acetate mix given intramuscularly. Antenatal corticosteroids are most effective when given within 48 hours prior to birth, with benefits seen within 24 hours of birth. They are most effective in reducing RDS in pregnancies that birth between 24 hours and 7 days of administration of the second dose.\\n\\nAntenatal corticosteroids have shown significant reductions in cases of RDS and cerebroventricular hemorrhage among infants born within specific time frames after administration. There is a reduction in fetal and neonatal death for births within 24 hours to seven days after administration. However, caution is advised in interpreting the data due to limitations in subgroup analyses. Population-based cohort studies support the early effects of antenatal corticosteroids, with the largest effect seen 24 hours to seven days after the first injection. Concerns about potential risks to both women and babies include effects on maternal blood glucose levels, fetal growth, neonatal hypoglycemia, long-term metabolic and neurological consequences, and potential impacts on brain development. WHO recommends offering antenatal corticosteroids only when minimum standards of maternal and neonatal hospital services are available.\\n\\nAntenatal corticosteroids should not be delayed in serious maternal or fetal conditions. In the presence of systemic infection, the use of corticosteroids should be carefully balanced due to the risk of exacerbating the infection. Repeat courses of corticosteroids may not reduce serious morbidity but can lead to smaller babies. The maximum number of corticosteroid courses in pregnancy should not exceed three. Research is needed to determine the effectiveness of corticosteroids in various conditions and to investigate potential off-target effects. Recommendations for future research include determining the effectiveness of corticosteroids in reducing neonatal morbidity in elective caesarean births at term and investigating the safety and effectiveness of steroids in multiple pregnancies and women with diabetes. Auditable topics include discussions about corticosteroids in planned caesarean births and the proportion of women offered corticosteroids for preterm birth. Support groups and useful links are provided for further information.\\n\\nAntenatal corticosteroids for reducing adverse maternal and child outcomes in special populations of women at risk of imminent preterm birth: a systematic review and meta-analysis. Managing hyperglycaemia during antenatal steroid administration, labour, and birth in pregnant women with diabetes. Should antenatal corticosteroids be considered in women with gestational diabetes before planned late gestation caesarean section. Effects of antenatal corticosteroid administration on mortality and long-term morbidity in early preterm, growth-restricted infants. Antenatal corticosteroids in preterm small-for-gestational age infants: a systematic review and meta-analysis. Use of antenatal corticosteroids in special circumstances: a comprehensive review. Single versus weekly courses of antenatal corticosteroids in preterm premature rupture of membranes. Multiple courses of antenatal corticosteroid therapy in patients with preterm premature rupture of membranes. Neonatal sepsis after betamethasone administration to patients with preterm premature rupture of membranes. Length of latency with preterm premature rupture of membranes before 32 weeks' gestation. Duration of the latency period in preterm premature rupture of the membranes. Preterm premature rupture of the membranes. Length of latency with preterm premature rupture of membranes. Association of fetal growth restriction with neurocognitive function after repeated antenatal betamethasone treatment vs placebo. Antenatal corticosteroids for preterm premature rupture of membranes: single or repeat course. The clinical use of corticosteroids in pregnancy. Antenatal corticosteroids: an assessment of anticipated benefits and potential risks. Antenatal corticosteroids for accelerating fetal lung maturation for women at risk of preterm birth. Maternal intramuscular dexamethasone versus betamethasone before preterm birth. Transplacental versus direct fetal corticosteroid treatment for accelerating fetal lung maturation where there is a risk of preterm birth. Antenatal dexamethasone for early preterm birth in low-resource countries. Antenatal corticosteroid therapy for prevention of respiratory distress syndrome in severe preeclampsia. Antenatal corticosteroid therapy and blood pressure at 14 years of age in preterm children. Neurodevelopmental disorders among term infants exposed to antenatal corticosteroids during pregnancy. Impact of antenatal synthetic glucocorticoid exposure on endocrine stress reactivity in term-born children. Persistent effects of antenatal synthetic glucocorticoids on endocrine stress reactivity from childhood to adolescence. Long-term impacts of prenatal synthetic glucocorticoids exposure on functional brain correlates of cognitive monitoring in adolescence. Prenatal betamethasone exposure and psychopathology risk in extremely low birth weight survivors in the third and fourth decades of life. A population-based, multifaceted strategy to implement antenatal corticosteroid treatment versus standard care for the reduction of neonatal mortality due to preterm birth in low-income and middle-income countries.\",\n  \"system_prompt\": \"You are a medical guidelines compliance checker. Your task is to analyze if the given clinical note follows the specified guideline and suggest improvements.\",\n  \"guideline_id\": \"bjog-2022-stock-antenatal-corticosteroids-to-reduce-neonatal-morbidity-and-mortality-pdf\",\n  \"guideline_title\": \"BJOG - 2022 - Stock - Antenatal corticosteroids to reduce neonatal morbidity and mortality.pdf\"\n}\n\nA: Here is the analysis of the clinical note against the provided guideline, with recommendations for improvement:\n\n### Very Important Recommendations  \n1. **Additional information needed** - Document the timing of betamethasone administration relative to anticipated delivery.  \n   Reason: The guideline states corticosteroids are most effective when given within 48 hours prior to birth, with benefits seen within 24 hours (BJOG-2022-Stock guideline, \"Antenatal corticosteroids are most effective when given within 48 hours prior to birth\"). The note should clarify whether delivery is expected within this window.  \n\n2. **Improved patient advice** - Discuss the risks/benefits of corticosteroids with the patient, including potential neonatal hypoglycemia (given her gestational diabetes).  \n   Reason: The guideline emphasizes informed discussions, especially in diabetic patients, and highlights the risk of neonatal hypoglycemia (BJOG-2022-Stock, \"Women with diabetes should not be excluded... but additional insulin and close monitoring are recommended\").  \n\n### Somewhat Important Recommendations  \n1. **Different management plan** - Consider repeating corticosteroids if delivery does not occur within 7 days and she remains at risk.  \n   Reason: The guideline notes limited evidence for repeat courses but suggests consideration if the risk persists (BJOG-2022-Stock, \"limited evidence to recommend repeat courses... if a woman remains at imminent risk seven days after administration\").  \n\n2. **Additional information needed** - Monitor maternal blood glucose closely post-corticosteroids due to gestational diabetes.  \n   Reason: The guideline recommends additional monitoring for diabetic patients (BJOG-2022-Stock, \"additional insulin and close monitoring are recommended\").  \n\n### Less Important Recommendations  \n1. **Improved patient advice** - Provide resources/support groups for preterm birth anxiety.  \n   Reason: The guideline mentions support groups as part of holistic care (BJOG-2022-Stock, \"Support groups and useful links are provided\").  \n\n### Unimportant Recommendations  \n1. **Additional information needed** - Document the specific betamethasone formulation used (sodium phosphate/acetate mix).  \n   Reason: The guideline specifies preferred formulations but does not mandate documentation (BJOG-2022-Stock, \"24 mg betamethasone sodium phosphate/acetate mix\").  \n\n### Key Omissions Addressed:  \n- The note aligns well with the guidelineâs core recommendations (e.g., offering corticosteroids for twins at 32+2 weeks, not delaying delivery for steroids). However, explicit documentation of timing, diabetic monitoring, and patient counseling would strengthen compliance.  \n\n*Note: No critical deviations from the guideline were identified.*\n\n--- Token Usage Report ---\nPrompt tokens: 2110\nCompletion tokens: 521\nTotal tokens: 2631\nEstimated cost: $0.001315",
  "ai_provider": "DeepSeek",
  "ai_model": "deepseek-chat",
  "token_usage": {
    "prompt_tokens": 2110,
    "completion_tokens": 521,
    "total_tokens": 2631,
    "estimated_cost_usd": 0.0013154999999999998
  }
}